Workbook
Name _??: BlankMacro1
Name _??????1: BlankMacro1
Name _??????2: BlankMacro1
Name _??????3: BlankMacro1
Name _??????4: BlankMacro1
Name _??????5: BlankMacro1
Name _??????6: BlankMacro1
Name __: #REF!
Name __??: BlankMacro1
Name __??????1: BlankMacro1
Name __??????2: BlankMacro1
Name __??????3: BlankMacro1
Name __??????4: BlankMacro1
Name __??????5: BlankMacro1
Name __??????6: BlankMacro1
Name ___??: BlankMacro1
Name ___??????1: BlankMacro1
Name ___??????2: BlankMacro1
Name ___??????3: BlankMacro1
Name ___??????4: BlankMacro1
Name ___??????5: BlankMacro1
Name ___??????6: BlankMacro1
Name ____??: BlankMacro1
Name ____??????1: BlankMacro1
Name ____??????2: BlankMacro1
Name ____??????3: BlankMacro1
Name ____??????4: BlankMacro1
Name ____??????5: BlankMacro1
Name ____??????6: BlankMacro1
Name ________________________________________PPP3: #REF!
Name ________________________________________PPP33: #REF!
Name ________________________________________ppp34: #REF!
Name ________________________________________ppp3444: #REF!
Name ______________________________________P3: #REF!
Name ____________________________a1: {"'Sheet1'!$L$16"}
Name ____________________________PPP3: #REF!
Name ____________________________PPP33: #REF!
Name ____________________________ppp34: #REF!
Name ____________________________ppp3444: #REF!
Name __________________________a1: {"'Sheet1'!$L$16"}
Name __________________________P3: #REF!
Name __________________________PPP3: #REF!
Name __________________________PPP33: #REF!
Name __________________________ppp34: #REF!
Name __________________________ppp3444: #REF!
Name _________________________a1: {"'Sheet1'!$L$16"}
Name _________________________PPP3: #REF!
Name _________________________PPP33: #REF!
Name _________________________ppp34: #REF!
Name _________________________ppp3444: #REF!
Name ________________________a1: {"'Sheet1'!$L$16"}
Name ________________________Goi8: {"'Sheet1'!$L$16"}
Name ________________________P3: #REF!
Name ________________________SCL4: {"'Sheet1'!$L$16"}
Name _______________________a1: {"'Sheet1'!$L$16"}
Name _______________________Goi8: {"'Sheet1'!$L$16"}
Name _______________________P3: #REF!
Name _______________________SCL4: {"'Sheet1'!$L$16"}
Name ______________________a1: {"'Sheet1'!$L$16"}
Name ______________________Goi8: {"'Sheet1'!$L$16"}

Sheet TH
A1: STT | B1: CỤM/BLOCK | C1: GIÁ TRỊ TRƯỚC VAT | D1: VAT | E1: GIÁ TRỊ SAU VAT | F1: THaCo
A2: 1 | B2: A22 | C2: ='A22'!O73 -> 2.1982406e+09 | D2: =C2*0.08 -> 1.7585925e+08 | E2: =C2+D2 -> 2.3740998e+09 | F2: ='A22'!S73 -> 2578591000 | G2: =F2*0.08 -> 206287280 | H2: =G2+F2 -> 2784878280
A3: =A2+1 -> 2 | B3: A05 | C3: ='A05'!O69 -> 2.0603566e+09 | D3: =C3*0.08 -> 1.6482853e+08 | E3: =C3+D3 -> 2.2251851e+09 | F3: ='A05'!R69 -> 2249620000 | G3: =F3*0.08 -> 179969600 | H3: =G3+F3 -> 2429589600
A4: =A3+1 -> 3 | B4: A06 | C4: ='A06'!O82 -> 2.3053299e+09 | D4: =C4*0.08 -> 1.8442639e+08 | E4: =C4+D4 -> 2.4897563e+09 | F4: ='A06'!R82 -> 1692590000 | G4: =F4*0.08 -> 135407200 | H4: =G4+F4 -> 1827997200
A5: =A4+1 -> 4 | B5: A07 | C5: ='A07'!O86 -> 2.4069867e+09 | D5: =C5*0.08 -> 1.9255894e+08 | E5: =C5+D5 -> 2.5995457e+09 | F5: ='A07'!R86 -> 2478842000 | G5: =F5*0.08 -> 198307360 | H5: =G5+F5 -> 2677149360
A6: CỘNG | C6: =SUM(C2:C5) -> 8.9709138e+09 | D6: =SUM(D2:D5) -> 7.176731e+08 | E6: =SUM(E2:E5) -> 9.6885869e+09 | H6: =SUM(H2:H5) -> 9719614440
H7: =H6-E6 -> 31027547

Sheet A22
C2: CÔNG TY CỔ PHẦN TẬP ĐOÀN QUỐC TẾ SLAND
C3: VPGD: SỐ 49, Ngõ 1295 Giải Phóng, Phường Hoàng Mai, TP Hà Nội
C4: Nhà máy: Thôn Nhân Hiền- xã Thường Tín - TP Hà Nội
C5: Hotline: 082 5577 999
A6: BẢNG BÁO GIÁ
A7: Khách hàng : CÔNG TY CỔ PHẦN XÂY DỰNG & KỸ THUẬT KD VIỆT NAM | M7: Seri number Số hiệu | P7: BG1_SLAND_KDVN_PCCC NHA A22
A8: Địa chỉ : | M8: Sales executive PT Kinh doanh | P8: Ms Nhài
A9: Người nhận : | M9: Mobile Điện thoại | P9: 0945588248
A10: Email: | C10: Số điện thoại : | M10: Dự án | N10: NHÀ A22
A11: STT | B11: Danh mục sản phẩm | C11: Model | D11: Thương hiệu | E11: Kích thước (mm) | I11: Modul | J11: L | K11: Độ dày (m) | L11: Unit Đơn vị | M11: Q'ty Số lượng | N11: Price Đơn giá | O11: Total price Thành tiền | P11: Remarks Ghi chú
D12: Thương hiệu | E12: A1 | F12: A2 | G12: B1 | H12: B2
E13: Face size | G13: Neck size
A15: =+[23]l7!A15 -> 1 | B15: 棟強排煙系統 Hút khói sự cố
A16: =+[23]l7!A16 -> 2 | B16: 百叶风口 Cửa Louver KT 4500x1000 尺寸50x50箱钢门框、Z形条系，75mm宽铝合金，各条均匀间隔 40mm，同步配件，浅灰色面漆 khung cửa thép hộp KT50x50, hệ nan chữ Z hợp kim nhôm rộng 75mm, các nan cách đều 40mm, phụ kiện đồng bộ, sơn dầu hoàn thiện màu xám nhạt | C16: WL+LCCT | D16: SWIND | E16: 4500 | F16: 1000 | G16: =+E16-50 -> 4450 | H16: =+F16-50 -> 950 | L16: 個 Cái | M16: 54 | N16: 5396600 | O16: =+N16*M16 -> 291416400 | P16: Louver nan Z cố định chia modul khi sản xuất+ LCCT | Q16: 5600000 | R16: 百叶风口 Cửa Louver KT 4500x1000 尺寸50x50箱钢门框、Z形条系，75mm宽铝合金，各条均匀间隔 40mm，同步配件，浅灰色面漆 khung cửa thép hộp KT50x50, hệ nan chữ Z hợp kim nhôm rộng 75mm, các nan cách đều 40mm, phụ kiện đồng bộ, sơn dầu hoàn thiện màu xám nhạt | S16: =Q16*M16 -> 302400000
A17: =+[23]l7!A17 -> 3 | B17: 百叶风口 Cửa Louver KT 4000x1500 尺寸50x50箱钢门框、Z形条系，75mm宽铝合金，各条均匀间隔 40mm，同步配件，浅灰色面漆 khung cửa thép hộp KT50x50, hệ nan chữ Z hợp kim nhôm rộng 75mm, các nan cách đều 40mm, phụ kiện đồng bộ, sơn dầu hoàn thiện màu xám nhạt | C17: WL+LCCT | D17: SWIND | E17: 4000 | F17: 1500 | G17: =+E17-50 -> 3950 | H17: =+F17-50 -> 1450 | L17: 個 Cái | M17: 45 | N17: 7069700 | O17: =+N17*M17 -> 3.181365e+08 | P17: Louver nan Z cố định chia modul khi sản xuất+ LCCT | Q17: 7300000 | R17: 百叶风口 Cửa Louver KT 4000x1500 尺寸50x50箱钢门框、Z形条系，75mm宽铝合金，各条均匀间隔 40mm，同步配件，浅灰色面漆 khung cửa thép hộp KT50x50, hệ nan chữ Z hợp kim nhôm rộng 75mm, các nan cách đều 40mm, phụ kiện đồng bộ, sơn dầu hoàn thiện màu xám nhạt | S17: =Q17*M17 -> 328500000
A18: =+[23]l7!A18 -> 4 | B18: 百叶风口 Cửa Louver KT 4000x1000 尺寸50x50箱钢门框、Z形条系，75mm宽铝合金，各条均匀间隔 40mm，同步配件，浅灰色面漆 khung cửa thép hộp KT50x50, hệ nan chữ Z hợp kim nhôm rộng 75mm, các nan cách đều 40mm, phụ kiện đồng bộ, sơn dầu hoàn thiện màu xám nhạt | C18: WL+LCCT | D18: SWIND | E18: 4000 | F18: 1000 | G18: =+E18-50 -> 3950 | H18: =+F18-50 -> 950 | L18: 個 Cái | M18: 8 | N18: 4803700 | O18: =+N18*M18 -> 38429600 | P18: Louver nan Z cố định chia modul khi sản xuất+ LCCT | Q18: 4910000 | R18: 百叶风口 Cửa Louver KT 4000x1000 尺寸50x50箱钢门框、Z形条系，75mm宽铝合金，各条均匀间隔 40mm，同步配件，浅灰色面漆 khung cửa thép hộp KT50x50, hệ nan chữ Z hợp kim nhôm rộng 75mm, các nan cách đều 40mm, phụ kiện đồng bộ, sơn dầu hoàn thiện màu xám nhạt | S18: =Q18*M18 -> 39280000
A19: =+[23]l7!A19 -> 5 | B19: 百叶风口 Cửa Louver KT 3500x500 尺寸50x50箱钢门框、Z形条系，75mm宽铝合金，各条均匀间隔 40mm，同步配件，浅灰色面漆 khung cửa thép hộp KT50x50, hệ nan chữ Z hợp kim nhôm rộng 75mm, các nan cách đều 40mm, phụ kiện đồng bộ, sơn dầu hoàn thiện màu xám nhạt | C19: WL+LCCT | D19: SWIND | E19: 3500 | F19: 500 | G19: =+E19-50 -> 3450 | H19: =+F19-50 -> 450 | L19: 個 Cái | M19: 1 | N19: 2226400 | O19: =+N19*M19 -> 2226400 | P19: Louver nan Z cố định chia modul khi sản xuất+ LCCT | Q19: 2250000 | R19: 百叶风口 Cửa Louver KT 3500x500 尺寸50x50箱钢门框、Z形条系，75mm宽铝合金，各条均匀间隔 40mm，同步配件，浅灰色面漆 khung cửa thép hộp KT50x50, hệ nan chữ Z hợp kim nhôm rộng 75mm, các nan cách đều 40mm, phụ kiện đồng bộ, sơn dầu hoàn thiện màu xám nhạt | S19: =Q19*M19 -> 2250000
A20: =+[23]l7!A20 -> 6 | B20: 百叶风口 Cửa Louver KT 3000x2000 尺寸50x50箱钢门框、Z形条系，75mm宽铝合金，各条均匀间隔 40mm，同步配件，浅灰色面漆 khung cửa thép hộp KT50x50, hệ nan chữ Z hợp kim nhôm rộng 75mm, các nan cách đều 40mm, phụ kiện đồng bộ, sơn dầu hoàn thiện màu xám nhạt | C20: WL+LCCT | D20: SWIND | E20: 3000 | F20: 2000 | G20: =+E20-50 -> 2950 | H20: =+F20-50 -> 1950 | L20: 個 Cái | M20: 0 | N20: 7030100 | O20: =+N20*M20 -> 0 | P20: Louver nan Z cố định chia modul khi sản xuất+ LCCT | Q20: 7020000 | R20: 百叶风口 Cửa Louver KT 3000x2000 尺寸50x50箱钢门框、Z形条系，75mm宽铝合金，各条均匀间隔 40mm，同步配件，浅灰色面漆 khung cửa thép hộp KT50x50, hệ nan chữ Z hợp kim nhôm rộng 75mm, các nan cách đều 40mm, phụ kiện đồng bộ, sơn dầu hoàn thiện màu xám nhạt | S20: =Q20*M20 -> 0
A21: =+[23]l7!A21 -> 7 | B21: 百叶风口 Cửa Louver KT 2400x1600 尺寸50x50箱钢门框、Z形条系，75mm宽铝合金，各条均匀间隔 40mm，同步配件，浅灰色面漆 khung cửa thép hộp KT50x50, hệ nan chữ Z hợp kim nhôm rộng 75mm, các nan cách đều 40mm, phụ kiện đồng bộ, sơn dầu hoàn thiện màu xám nhạt | C21: WL+LCCT | D21: SWIND | E21: 2400 | F21: 1600 | G21: =+E21-50 -> 2350 | H21: =+F21-50 -> 1550 | L21: 個 Cái | M21: 24 | N21: 4528700 | O21: =+N21*M21 -> 108688800 | P21: Louver nan Z cố định + LCCT | Q21: 4890000 | R21: 百叶风口 Cửa Louver KT 2400x1600 尺寸50x50箱钢门框、Z形条系，75mm宽铝合金，各条均匀间隔 40mm，同步配件，浅灰色面漆 khung cửa thép hộp KT50x50, hệ nan chữ Z hợp kim nhôm rộng 75mm, các nan cách đều 40mm, phụ kiện đồng bộ, sơn dầu hoàn thiện màu xám nhạt | S21: =Q21*M21 -> 117360000
A22: =+[23]l7!A22 -> 8 | B22: 百叶风口 Cửa Louver KT 2000x1300 尺寸50x50箱钢门框、Z形条系，75mm宽铝合金，各条均匀间隔 40mm，同步配件，浅灰色面漆 khung cửa thép hộp KT50x50, hệ nan chữ Z hợp kim nhôm rộng 75mm, các nan cách đều 40mm, phụ kiện đồng bộ, sơn dầu hoàn thiện màu xám nhạt | C22: WL+LCCT | D22: SWIND | E22: 2000 | F22: 1300 | G22: =+E22-50 -> 1950 | H22: =+F22-50 -> 1250 | L22: 個 Cái | M22: 1 | N22: 3161400 | O22: =+N22*M22 -> 3161400 | P22: Louver nan Z cố định + LCCT | Q22: 3210000 | R22: 百叶风口 Cửa Louver KT 2000x1300 尺寸50x50箱钢门框、Z形条系，75mm宽铝合金，各条均匀间隔 40mm，同步配件，浅灰色面漆 khung cửa thép hộp KT50x50, hệ nan chữ Z hợp kim nhôm rộng 75mm, các nan cách đều 40mm, phụ kiện đồng bộ, sơn dầu hoàn thiện màu xám nhạt | S22: =Q22*M22 -> 3210000
A23: =+[23]l7!A23 -> 9 | B23: 百叶风口 Cửa Louver KT 2000x1000 尺寸50x50箱钢门框、Z形条系，75mm宽铝合金，各条均匀间隔 40mm，同步配件，浅灰色面漆 khung cửa thép hộp KT50x50, hệ nan chữ Z hợp kim nhôm rộng 75mm, các nan cách đều 40mm, phụ kiện đồng bộ, sơn dầu hoàn thiện màu xám nhạt | C23: WL+LCCT | D23: SWIND | E23: 2000 | F23: 1000 | G23: =+E23-50 -> 1950 | H23: =+F23-50 -> 950 | L23: 個 Cái | M23: 10 | N23: 2435400 | O23: =+N23*M23 -> 24354000 | P23: Louver nan Z cố định + LCCT | Q23: 2450000 | R23: 百叶风口 Cửa Louver KT 2000x1000 尺寸50x50箱钢门框、Z形条系，75mm宽铝合金，各条均匀间隔 40mm，同步配件，浅灰色面漆 khung cửa thép hộp KT50x50, hệ nan chữ Z hợp kim nhôm rộng 75mm, các nan cách đều 40mm, phụ kiện đồng bộ, sơn dầu hoàn thiện màu xám nhạt | S23: =Q23*M23 -> 24500000
A24: =+[23]l7!A24 -> 10 | B24: 百叶风口 Cửa Louver KT 2000x800 尺寸50x50箱钢门框、Z形条系，75mm宽铝合金，各条均匀间隔 40mm，同步配件，浅灰色面漆 khung cửa thép hộp KT50x50, hệ nan chữ Z hợp kim nhôm rộng 75mm, các nan cách đều 40mm, phụ kiện đồng bộ, sơn dầu hoàn thiện màu xám nhạt | C24: WL+LCCT | D24: SWIND | E24: 2000 | F24: 800 | G24: =+E24-50 -> 1950 | H24: =+F24-50 -> 750 | L24: 個 Cái | M24: 12 | N24: 2016300 | O24: =+N24*M24 -> 24195600 | P24: Louver nan Z cố định + LCCT | Q24: 2000000 | R24: 百叶风口 Cửa Louver KT 2000x800 尺寸50x50箱钢门框、Z形条系，75mm宽铝合金，各条均匀间隔 40mm，同步配件，浅灰色面漆 khung cửa thép hộp KT50x50, hệ nan chữ Z hợp kim nhôm rộng 75mm, các nan cách đều 40mm, phụ kiện đồng bộ, sơn dầu hoàn thiện màu xám nhạt | S24: =Q24*M24 -> 24000000
A25: =+[23]l7!A25 -> 11 | B25: 百叶风口 Cửa Louver KT 1500x1500 尺寸50x50箱钢门框、Z形条系，75mm宽铝合金，各条均匀间隔 40mm，同步配件，浅灰色面漆 khung cửa thép hộp KT50x50, hệ nan chữ Z hợp kim nhôm rộng 75mm, các nan cách đều 40mm, phụ kiện đồng bộ, sơn dầu hoàn thiện màu xám nhạt | C25: WL+LCCT | D25: SWIND | E25: 1500 | F25: 1500 | G25: =+E25-50 -> 1450 | H25: =+F25-50 -> 1450 | L25: 個 Cái | M25: 10 | N25: 2708200 | O25: =+N25*M25 -> 27082000 | P25: Louver nan Z cố định + LCCT | Q25: 2860000 | R25: 百叶风口 Cửa Louver KT 1500x1500 尺寸50x50箱钢门框、Z形条系，75mm宽铝合金，各条均匀间隔 40mm，同步配件，浅灰色面漆 khung cửa thép hộp KT50x50, hệ nan chữ Z hợp kim nhôm rộng 75mm, các nan cách đều 40mm, phụ kiện đồng bộ, sơn dầu hoàn thiện màu xám nhạt | S25: =Q25*M25 -> 28600000
A26: =+[23]l7!A26 -> 12 | B26: 百叶风口 Cửa Louver KT 1000x1500 尺寸50x50箱钢门框、Z形条系，75mm宽铝合金，各条均匀间隔 40mm，同步配件，浅灰色面漆 khung cửa thép hộp KT50x50, hệ nan chữ Z hợp kim nhôm rộng 75mm, các nan cách đều 40mm, phụ kiện đồng bộ, sơn dầu hoàn thiện màu xám nhạt | C26: WL+LCCT | D26: SWIND | E26: 1000 | F26: 1500 | G26: =+E26-50 -> 950 | H26: =+F26-50 -> 1450 | L26: 個 Cái | M26: 1 | N26: 1835900 | O26: =+N26*M26 -> 1835900 | P26: Louver nan Z cố định + LCCT | Q26: 2000000 | R26: 百叶风口 Cửa Louver KT 1000x1500 尺寸50x50箱钢门框、Z形条系，75mm宽铝合金，各条均匀间隔 40mm，同步配件，浅灰色面漆 khung cửa thép hộp KT50x50, hệ nan chữ Z hợp kim nhôm rộng 75mm, các nan cách đều 40mm, phụ kiện đồng bộ, sơn dầu hoàn thiện màu xám nhạt | S26: =Q26*M26 -> 2000000
A27: =+[23]l7!A27 -> 13 | B27: 百叶风口 Cửa Louver KT 1200x1000 尺寸50x50箱钢门框、Z形条系，75mm宽铝合金，各条均匀间隔 40mm，同步配件，浅灰色面漆 khung cửa thép hộp KT50x50, hệ nan chữ Z hợp kim nhôm rộng 75mm, các nan cách đều 40mm, phụ kiện đồng bộ, sơn dầu hoàn thiện màu xám nhạt | C27: WL+LCCT | D27: SWIND | E27: 1200 | F27: 1000 | G27: =+E27-50 -> 1150 | H27: =+F27-50 -> 950 | L27: 個 Cái | M27: 10 | N27: 1487200 | O27: =+N27*M27 -> 14872000 | P27: Louver nan Z cố định + LCCT | Q27: 1540000 | R27: 百叶风口 Cửa Louver KT 1200x1000 尺寸50x50箱钢门框、Z形条系，75mm宽铝合金，各条均匀间隔 40mm，同步配件，浅灰色面漆 khung cửa thép hộp KT50x50, hệ nan chữ Z hợp kim nhôm rộng 75mm, các nan cách đều 40mm, phụ kiện đồng bộ, sơn dầu hoàn thiện màu xám nhạt | S27: =Q27*M27 -> 15400000
... A30: =+[23]l7!A30 -> 16 | B30: 風門含SEG 1200x600+OBD 流量調節閥含配件及安裝Cửa gió kèm van điều chỉnh lưu lượng SEG 1200x600+OBD Bao gồm nhân công phụ kiện lắp đặt | C30: SDG+OBD | D30: SWIND | E30: 1200 | F30: 600 | G30: =+E30-50 -> 1150 | H30: =+F30-50 -> 550 | L30: 個 Cái | M30: 32 | N30: 1051600 | O30: =+N30*M30 -> 33651200 | P30: Cửa gió 1 lớp nan thẳng bầu dục + van OBD | Q30: 1230000 | R30: 風門含SEG 1200x600+OBD 流量調節閥含配件及安裝Cửa gió kèm van điều chỉnh lưu lượng SEG 1200x600+OBD Bao gồm nhân công phụ kiện lắp đặt | S30: =Q30*M30 -> 39360000
B31: 風門含SEG 600x600+OBD 流量調節閥含配件及安裝Cửa gió kèm van điều chỉnh lưu lượng SEG 600x600+OBD Bao gồm nhân công phụ kiện lắp đặt | C31: SDG+OBD | D31: SWIND | E31: 600 | F31: 600 | G31: =+E31-50 -> 550 | H31: =+F31-50 -> 550 | L31: 個 Cái | M31: 10 | N31: 556600 | O31: =+N31*M31 -> 5566000 | P31: Cửa gió 1 lớp nan thẳng bầu dục + van OBD | Q31: 590000 | R31: 風門含SEG 600x600+OBD 流量調節閥含配件及安裝Cửa gió kèm van điều chỉnh lưu lượng SEG 600x600+OBD Bao gồm nhân công phụ kiện lắp đặt | S31: =Q31*M31 -> 5900000
A32: =+[23]l7!A32 -> 1 | B32: 空調鍍鋅鐵皮排風管 1400x700mm, δ=1.15mm 含製作及安裝 Ống thoát gió bằng tôn mạ kẽm 1400x700mm , δ=1.15mm bao gồm gia công chế tạo và lắp đặt. | L32: m2 | M32: 742 | O32: =+N32*M32 -> 0 | R32: 空調鍍鋅鐵皮排風管 1400x700mm, δ=1.15mm 含製作及安裝 Ống thoát gió bằng tôn mạ kẽm 1400x700mm , δ=1.15mm bao gồm gia công chế tạo và lắp đặt. | S32: =Q32*M32 -> 0
A33: =+[23]l7!A33 -> 2 | B33: 空調鍍鋅鐵皮排風管 1000x350mm, δ=1.15mm 含製作及安裝 Ống thoát gió bằng tôn mạ kẽm 1000x350mm , δ=1.15mm bao gồm gia công chế tạo và lắp đặt. | L33: m2 | M33: 319 | O33: =+N33*M33 -> 0 | R33: 空調鍍鋅鐵皮排風管 1000x350mm, δ=1.15mm 含製作及安裝 Ống thoát gió bằng tôn mạ kẽm 1000x350mm , δ=1.15mm bao gồm gia công chế tạo và lắp đặt. | S33: =Q33*M33 -> 0
A34: =+[23]l7!A34 -> 3 | B34: 空調鍍鋅鐵皮排風管1200x400mm EI45, 含製作及安裝 （含越南消防及救護-救難警察局檢定費用） Ống thoát gió bằng tôn mạ kẽm 1200x400mm, EI45, bao gồm gia công chế tạo và lắp đặt. （Bao gồm chi phí kiểm định của cục cảnh sát pccc & CNCH Việt Nam) | L34: m2 | M34: 821 | O34: =+N34*M34 -> 0 | R34: 空調鍍鋅鐵皮排風管1200x400mm EI45, 含製作及安裝 （含越南消防及救護-救難警察局檢定費用） Ống thoát gió bằng tôn mạ kẽm 1200x400mm, EI45, bao gồm gia công chế tạo và lắp đặt. （Bao gồm chi phí kiểm định của cục cảnh sát pccc & CNCH Việt Nam) | S34: =Q34*M34 -> 0
A35: =+[23]l7!A35 -> 3 | B35: 空調鍍鋅鐵皮排風管1600x400mm EI45, 含製作及安裝 （含越南消防及救護-救難警察局檢定費用） Ống thoát gió bằng tôn mạ kẽm 1600x400mm, EI45, bao gồm gia công chế tạo và lắp đặt. （Bao gồm chi phí kiểm định của cục cảnh sát pccc & CNCH Việt Nam) | L35: m2 | M35: 151 | O35: =+N35*M35 -> 0 | R35: 空調鍍鋅鐵皮排風管1600x400mm EI45, 含製作及安裝 （含越南消防及救護-救難警察局檢定費用） Ống thoát gió bằng tôn mạ kẽm 1600x400mm, EI45, bao gồm gia công chế tạo và lắp đặt. （Bao gồm chi phí kiểm định của cục cảnh sát pccc & CNCH Việt Nam) | S35: =Q35*M35 -> 0
A36: =+[23]l7!A36 -> 4 | B36: 空調鍍鋅鐵皮排風管1800x400mm EI45, 含製作及安裝 （含越南消防及救護-救難警察局檢定費用） Ống thoát gió bằng tôn mạ kẽm 1800x400mm, EI45, bao gồm gia công chế tạo và lắp đặt. （Bao gồm chi phí kiểm định của cục cảnh sát pccc & CNCH Việt Nam) | L36: m2 | M36: 671 | O36: =+N36*M36 -> 0 | R36: 空調鍍鋅鐵皮排風管1800x400mm EI45, 含製作及安裝 （含越南消防及救護-救難警察局檢定費用） Ống thoát gió bằng tôn mạ kẽm 1800x400mm, EI45, bao gồm gia công chế tạo và lắp đặt. （Bao gồm chi phí kiểm định của cục cảnh sát pccc & CNCH Việt Nam) | S36: =Q36*M36 -> 0
A37: =+[23]l7!A37 -> 5 | B37: 空調鍍鋅鐵皮排風管2000x400mm EI45, 含製作及安裝 （含越南消防及救護-救難警察局檢定費用） Ống thoát gió bằng tôn mạ kẽm 2000x400mm, EI45, bao gồm gia công chế tạo và lắp đặt. （Bao gồm chi phí kiểm định của cục cảnh sát pccc & CNCH Việt Nam) | L37: m2 | M37: 808 | O37: =+N37*M37 -> 0 | R37: 空調鍍鋅鐵皮排風管2000x400mm EI45, 含製作及安裝 （含越南消防及救護-救難警察局檢定費用） Ống thoát gió bằng tôn mạ kẽm 2000x400mm, EI45, bao gồm gia công chế tạo và lắp đặt. （Bao gồm chi phí kiểm định của cục cảnh sát pccc & CNCH Việt Nam) | S37: =Q37*M37 -> 0
A38: =+[23]l7!A38 -> 6 | B38: 空調鍍鋅鐵皮排風管2000x400mm EI120, 含製作及安裝 （含越南消防及救護-救難警察局檢定費用） Ống thoát gió bằng tôn mạ kẽm 2000x400mm, EI120, bao gồm gia công chế tạo và lắp đặt. （Bao gồm chi phí kiểm định của cục cảnh sát pccc & CNCH Việt Nam) | L38: m2 | M38: 140 | O38: =+N38*M38 -> 0 | R38: 空調鍍鋅鐵皮排風管2000x400mm EI120, 含製作及安裝 （含越南消防及救護-救難警察局檢定費用） Ống thoát gió bằng tôn mạ kẽm 2000x400mm, EI120, bao gồm gia công chế tạo và lắp đặt. （Bao gồm chi phí kiểm định của cục cảnh sát pccc & CNCH Việt Nam) | S38: =Q38*M38 -> 0
A39: =+[23]l7!A39 -> 7 | B39: 空調鍍鋅鐵皮排風管700x350mm EI30, 含製作及安裝 （含越南消防及救護-救難警察局檢定費用） Ống thoát gió bằng tôn mạ kẽm 700x350mm, EI30,bao gồm gia công chế tạo và lắp đặt. （Bao gồm chi phí kiểm định của cục cảnh sát pccc & CNCH Việt Nam) | L39: m2 | M39: 276 | O39: =+N39*M39 -> 0 | R39: 空調鍍鋅鐵皮排風管700x350mm EI30, 含製作及安裝 （含越南消防及救護-救難警察局檢定費用） Ống thoát gió bằng tôn mạ kẽm 700x350mm, EI30,bao gồm gia công chế tạo và lắp đặt. （Bao gồm chi phí kiểm định của cục cảnh sát pccc & CNCH Việt Nam) | S39: =Q39*M39 -> 0
A40: =+[23]l7!A40 -> 8 | B40: 空調鍍鋅鐵皮排風管1000x350mm EI30, 含製作及安裝 （含越南消防及救護-救難警察局檢定費用） Ống thoát gió bằng tôn mạ kẽm 1000x350mm, EI30, bao gồm gia công chế tạo và lắp đặt. （Bao gồm chi phí kiểm định của cục cảnh sát pccc & CNCH Việt Nam) | L40: m2 | M40: 138 | O40: =+N40*M40 -> 0 | R40: 空調鍍鋅鐵皮排風管1000x350mm EI30, 含製作及安裝 （含越南消防及救護-救難警察局檢定費用） Ống thoát gió bằng tôn mạ kẽm 1000x350mm, EI30, bao gồm gia công chế tạo và lắp đặt. （Bao gồm chi phí kiểm định của cục cảnh sát pccc & CNCH Việt Nam) | S40: =Q40*M40 -> 0
A41: =+[23]l7!A41 -> 9 | B41: 大小頭、彎頭、三通等連接配件，含安裝Phụ kiện kết nối côn, cút, tê…. bao gồm lắp đặt | L41: Khoản 式 | M41: 1 | O41: =+N41*M41 -> 0 | R41: 大小頭、彎頭、三通等連接配件，含安裝Phụ kiện kết nối côn, cút, tê…. bao gồm lắp đặt | S41: =Q41*M41 -> 0
A42: =+[23]l7!A42 -> 10 | B42: MFD單葉閥2000x400 ，on/off DC 24v電動機, EI45 Van MFD 1 lá 2000x400, động cơ điện on/off DC 24v, EI45 | C42: SWIND-1.03- MFD-EI90 | D42: SWIND | E42: 2000 | F42: 400 | I42: 2 | J42: 200 | K42: 1.15 | L42: Cái 個 | M42: 11 | N42: 9387821.2 | O42: =+N42*M42 -> 1.0326603e+08 | P42: - Van ngăn cháy động cơ - Tiêu chuẩn EI 90 - 2 đầu bích TDC - Gắn kèm động cơ ON-OFF 5Nm, Hãng KLB - Sản xuất theo BCTN số 4651/VLXD-TBMT | Q42: 7920000 | R42: MFD單葉閥2000x400 ，on/off DC 24v電動機, EI45 Van MFD 1 lá 2000x400, động cơ điện on/off DC 24v, EI45 | S42: =Q42*M42 -> 87120000
A43: =+[23]l7!A43 -> 11 | B43: MFD單葉閥1800x400 ，on/off DC 24v電動機, EI45 Van MFD 1 lá 1800x400, động cơ điện on/off DC 24v, EI45 | C43: SWIND-1.03- MFD-EI90 | D43: SWIND | E43: 1800 | F43: 400 | I43: 2 | J43: 200 | K43: 1.15 | L43: Cái 個 | M43: 5 | N43: 8957893.3 | O43: =+N43*M43 -> 44789467 | P43: - Van ngăn cháy động cơ - Tiêu chuẩn EI 90 - 2 đầu bích TDC - Gắn kèm động cơ ON-OFF 5Nm, Hãng KLB - Sản xuất theo BCTN số 4651/VLXD-TBMT | Q43: 7700000 | R43: MFD單葉閥1800x400 ，on/off DC 24v電動機, EI45 Van MFD 1 lá 1800x400, động cơ điện on/off DC 24v, EI45 | S43: =Q43*M43 -> 38500000
A44: =+[23]l7!A44 -> 12 | B44: MFD單葉閥1000x350 ，on/off DC 24v電動機, EI45 Van MFD 1 lá 1000x350, động cơ điện on/off DC 24v, EI45 | C44: SWIND-1.03- MFD-EI90 | D44: SWIND | E44: 1000 | F44: 350 | J44: 200 | K44: 1.15 | L44: Cái 個 | M44: 6 | N44: 4531029 | O44: =+N44*M44 -> 27186174 | P44: - Van ngăn cháy động cơ - Tiêu chuẩn EI 90 - 2 đầu bích TDC - Gắn kèm động cơ ON-OFF 5Nm, Hãng KLB - Sản xuất theo BCTN số 4651/VLXD-TBMT | Q44: 4030000 | R44: MFD單葉閥1000x350 ，on/off DC 24v電動機, EI45 Van MFD 1 lá 1000x350, động cơ điện on/off DC 24v, EI45 | S44: =Q44*M44 -> 24180000
A45: =+[23]l7!A45 -> 13 | B45: MD單葉閥4500x1000 ，on/off DC 24v電動機 Van MD 1 lá 4500x1000, động cơ điện on/off DC 24v | C45: MD | D45: SWIND | E45: 4500 | F45: 1000 | J45: 200 | K45: 1.15 | L45: Cái 個 | M45: 54 | N45: 7523250 | O45: =+N45*M45 -> 406255500 | P45: Van MD chia 4 modul, 4 động cơ KLB/VIWECO 24V -10N | Q45: 10260000 | R45: MD單葉閥4500x1000 ，on/off DC 24v電動機 Van MD 1 lá 4500x1000, động cơ điện on/off DC 24v | S45: =Q45*M45 -> 554040000
A46: =+[23]l7!A46 -> 14 | B46: MD單葉閥4000x2000 ，on/off DC 24v電動機 Van MD 1 lá 4000x2000, động cơ điện on/off DC 24v | C46: MD | D46: SWIND | E46: 4000 | F46: 2000 | J46: 200 | K46: 1.15 | L46: 個 Cái | M46: 0 | N46: 12866438 | O46: =+N46*M46 -> 0 | P46: Van MD chia 8 modul, 8 động cơ KLB/VIWECO 24V -10N | Q46: 19400000 | R46: MD單葉閥4000x2000 ，on/off DC 24v電動機 Van MD 1 lá 4000x2000, động cơ điện on/off DC 24v | S46: =Q46*M46 -> 0
A47: =+[23]l7!A47 -> 15 | B47: MD單葉閥4000x1500 ，on/off DC 24v電動機 Van MD 1 lá 4000x1500, động cơ điện on/off DC 24v | C47: MD | D47: SWIND | E47: 4000 | F47: 1500 | J47: 200 | K47: 1.15 | L47: 個 Cái | M47: 45 | N47: 8250375 | O47: =+N47*M47 -> 371266875 | P47: Van MD chia 4 modul, 4 động cơ KLB/VIWECO 24V -10N | Q47: 11310000 | R47: MD單葉閥4000x1500 ，on/off DC 24v電動機 Van MD 1 lá 4000x1500, động cơ điện on/off DC 24v | S47: =Q47*M47 -> 508950000
A48: =+[23]l7!A48 -> 16 | B48: MD單葉閥4000x1000 ，on/off DC 24v電動機 Van MD 1 lá 4000x1000, động cơ điện on/off DC 24v | C48: MD | D48: SWIND | E48: 4000 | F48: 1000 | J48: 200 | K48: 1.15 | L48: 個 Cái | M48: 8 | N48: 7134750 | O48: =+N48*M48 -> 57078000 | P48: Van MD chia 4 modul, 4 động cơ KLB/VIWECO 24V -10N | Q48: 9700000 | R48: MD單葉閥4000x1000 ，on/off DC 24v電動機 Van MD 1 lá 4000x1000, động cơ điện on/off DC 24v | S48: =Q48*M48 -> 77600000
A49: =+[23]l7!A49 -> 17 | B49: MD單葉閥3500x500 ，on/off DC 24v電動機 Van MD 1 lá 3500x500, động cơ điện on/off DC 24v | C49: MD | D49: SWIND | E49: 3500 | F49: 500 | J49: 200 | K49: 1.15 | L49: 個 Cái | M49: 1 | N49: 4072687.5 | O49: =+N49*M49 -> 4072687.5 | P49: Van MD chia 2 modul, 2 động cơ KLB/VIWECO 24V -10N | Q49: 5305000 | R49: MD單葉閥3500x500 ，on/off DC 24v電動機 Van MD 1 lá 3500x500, động cơ điện on/off DC 24v | S49: =Q49*M49 -> 5305000
A50: =+[23]l7!A50 -> 18 | B50: MD單葉閥2000x1000 ，on/off DC 24v電動機 Van MD 1 lá 2000x1000, động cơ điện on/off DC 24v | C50: MD | D50: SWIND | E50: 2000 | F50: 1000 | J50: 200 | K50: 1.15 | L50: 個 Cái | M50: 10 | N50: 3903375 | O50: =+N50*M50 -> 39033750 | P50: Van MD chia 2 modul, 2 động cơ KLB/VIWECO 24V -10N | Q50: 5060000 | R50: MD單葉閥2000x1000 ，on/off DC 24v電動機 Van MD 1 lá 2000x1000, động cơ điện on/off DC 24v | S50: =Q50*M50 -> 50600000
A51: =+[23]l7!A51 -> 19 | B51: MD單葉閥2000x800 ，on/off DC 24v電動機 Van MD 1 lá 2000x800, động cơ điện on/off DC 24v | C51: MD | D51: SWIND | E51: 2000 | F51: 800 | J51: 200 | K51: 1.15 | L51: 個 Cái | M51: 12 | N51: 3651375 | O51: =+N51*M51 -> 43816500 | P51: Van MD chia 2 modul, 2 động cơ KLB/VIWECO 24V -10N | Q51: 4696000 | R51: MD單葉閥2000x800 ，on/off DC 24v電動機 Van MD 1 lá 2000x800, động cơ điện on/off DC 24v | S51: =Q51*M51 -> 56352000
A52: =+[23]l7!A52 -> 20 | B52: MD單葉閥1500x1500 ，on/off DC 24v電動機 Van MD 1 lá 1500x1500, động cơ điện on/off DC 24v | C52: MD | D52: SWIND | E52: 1500 | F52: 1500 | J52: 200 | K52: 1.15 | L52: 個 Cái | M52: 10 | N52: 4024125 | O52: =+N52*M52 -> 40241250 | P52: Van MD chia 2 modul, 2 động cơ KLB/VIWECO 24V -10N | Q52: 4035000 | R52: MD單葉閥1500x1500 ，on/off DC 24v電動機 Van MD 1 lá 1500x1500, động cơ điện on/off DC 24v | S52: =Q52*M52 -> 40350000
A53: =+[23]l7!A53 -> 21 | B53: MD單葉閥1200x1000 ，on/off DC 24v電動機 Van MD 1 lá 1200x1000, động cơ điện on/off DC 24v | C53: MD | D53: SWIND | E53: 1200 | F53: 1000 | J53: 200 | K53: 1.15 | L53: 個 Cái | M53: 10 | N53: 3282562.5 | O53: =+N53*M53 -> 32825625 | P53: Van MD chia 2 modul, 2 động cơ KLB/VIWECO 24V -10N | Q53: 2964000 | R53: MD單葉閥1200x1000 ，on/off DC 24v電動機 Van MD 1 lá 1200x1000, động cơ điện on/off DC 24v | S53: =Q53*M53 -> 29640000
A54: =+[23]l7!A54 -> 22 | B54: MD單葉閥1000x1000 ，on/off DC 24v電動機 Van MD 1 lá 1000x1000, động cơ điện on/off DC 24v | C54: MD | D54: SWIND | E54: 1000 | F54: 1000 | J54: 200 | K54: 1.15 | L54: 個 Cái | M54: 1 | N54: 2287687.5 | O54: =+N54*M54 -> 2287687.5 | P54: Van MD, động cơ KLB/VIWECO 24v-10N | Q54: 2740000 | R54: MD單葉閥1000x1000 ，on/off DC 24v電動機 Van MD 1 lá 1000x1000, động cơ điện on/off DC 24v | S54: =Q54*M54 -> 2740000
A55: =+[23]l7!A55 -> 23 | B55: MD單葉閥800x1500 ，on/off DC 24v電動機 Van MD 1 lá 800x1500, động cơ điện on/off DC 24v | C55: MD | D55: SWIND | E55: 800 | F55: 1500 | J55: 200 | K55: 1.15 | L55: 個 Cái | M55: 2 | N55: 2471437.5 | O55: =+N55*M55 -> 4942875 | P55: Van MD, động cơ KLB/VIWECO 24v-10N | Q55: 3006000 | R55: MD單葉閥800x1500 ，on/off DC 24v電動機 Van MD 1 lá 800x1500, động cơ điện on/off DC 24v | S55: =Q55*M55 -> 6012000
... A58: =+[23]l7!A58 -> 26 | B58: MD單葉閥1000x1500 ，on/off DC 24v電動機 Van MD 1 lá 1000x1500, động cơ điện on/off DC 24v | C58: MD | D58: SWIND | E58: 1000 | F58: 1500 | J58: 200 | K58: 1.15 | L58: 個 Cái | M58: 1 | N58: 2674875 | O58: =+N58*M58 -> 2674875 | P58: Van MD, động cơ KLB/VIWECO 24v-10N | Q58: 3300000 | R58: MD單葉閥1000x1500 ，on/off DC 24v電動機 Van MD 1 lá 1000x1500, động cơ điện on/off DC 24v | S58: =Q58*M58 -> 3300000
A59: =+[23]l7!A59 -> 27 | B59: 1800×1000止回阀安装 Van 1 chiều 1800x1000 | C59: NRD | D59: SWIND | E59: 1800 | F59: 1000 | J59: 200 | K59: 1.15 | L59: Cái 個 | M59: 4 | N59: 1970000 | O59: =+N59*M59 -> 7880000 | Q59: 2436000 | R59: 1800×1000止回阀安装 Van 1 chiều 1800x1000 | S59: =Q59*M59 -> 9744000
B60: 1400×500止回阀安装 Van 1 chiều 1400x500 | C60: NRD | D60: SWIND | E60: 1400 | F60: 500 | J60: 200 | K60: 1.15 | L60: Cái 個 | M60: 3 | N60: 1212500 | O60: =+N60*M60 -> 3637500 | Q60: 1288000 | R60: 1400×500止回阀安装 Van 1 chiều 1400x500 | S60: =Q60*M60 -> 3864000
A61: =+[23]l7!A61 -> 1 | B61: Cửa gió louver thải khói + lưới chắn côn trùng 1800x1000 louver風門排煙+擋昆蟲網1800x1000 | C61: WL+LCCT | D61: SWIND | E61: 1800 | F61: 1000 | L61: 個 Cái | M61: 0 | N61: 2472140 | O61: =+N61*M61 -> 0 | P61: Louver nan Z cố định + LCCT | Q61: 2770000 | S61: =Q61*M61 -> 0
A62: =+[23]l7!A62 -> 2 | B62: Cửa gió louver thải khói + lưới chắn côn trùng 1000x500 louver風門排煙+擋昆蟲網1000x500 | C62: WL+LCCT | D62: SWIND | E62: 1000 | F62: 500 | L62: 個 Cái | M62: 0 | N62: 736010 | O62: =+N62*M62 -> 0 | P62: Louver nan Z cố định + LCCT | Q62: 665000 | S62: =Q62*M62 -> 0
A63: =+[23]l7!A63 -> 3 | B63: Côn thu đầu quạt 1400x700/DQ-L800. Bao gồm nhân công lắp đặt, phụ kiện bích nối, zoăng làm kín, kẹp C, bulong+ốc+long đen 1400x700/DQ-L800抽煙機頭變徑。含安裝及鏈接法蘭、墊圈、C夾、螺栓螺絲等 | L63: 個 Cái | M63: 4 | O63: =+N63*M63 -> 0 | S63: =Q63*M63 -> 0
A64: =+[23]l7!A64 -> 4 | B64: Côn thu đầu quạt 1000x350/DQ. Bao gồm nhân công lắp đặt, phụ kiện bích nối, zoăng làm kín, kẹp C, bulong+ốc+long đen 1000x350/DQ抽煙機頭變徑。含安裝及鏈接法蘭、墊圈、C夾、螺栓螺絲等 | L64: 個 Cái | M64: 3 | O64: =+N64*M64 -> 0 | S64: =Q64*M64 -> 0
A65: =+[23]l7!A65 -> 5 | B65: D820排风帽（带防虫网）制作与安装. Chụp thải gió kèm lưới chắn côn trùng D820 | L65: 個 Cái | M65: 0 | O65: =+N65*M65 -> 0 | S65: =Q65*M65 -> 0
A66: =+[23]l7!A66 -> 6 | B66: Cút 90 độ 1800x1000R1000. Bao gồm nhân công lắp đặt, phụ kiện bích nối, zoăng làm kín, kẹp C, bulong+ốc+long đen 1800x1000R1000 90度彎頭含安裝及鏈接法蘭、墊圈、C夾、螺栓螺絲等 | L66: 個 Cái | M66: 4 | O66: =+N66*M66 -> 0 | S66: =Q66*M66 -> 0
A67: =+[23]l7!A67 -> 7 | B67: 45°弯头（1800×1000，TDC法兰）+ 304不锈钢防虫网（4–6mm），板厚0.95mm. Cút 45 độ KT: 1800x1000 - TDC+Lưới chắn côn trùng inox 304 (mắt lưới 4-6mm), chiều dày tôn 0,95mm | L67: 個 Cái | M67: 4 | O67: =+N67*M67 -> 0 | S67: =Q67*M67 -> 0
A68: =+[23]l7!A68 -> 8 | B68: Cút 90 độ 1400x500R1000. Bao gồm nhân công lắp đặt, phụ kiện bích nối, zoăng làm kín, kẹp C, bulong+ốc+long đen 1800x1000R1000 90度彎頭含安裝及鏈接法蘭、墊圈、C夾、螺栓螺絲等 | L68: 個 Cái | M68: 3 | O68: =+N68*M68 -> 0 | S68: =Q68*M68 -> 0
A69: =+[23]l7!A69 -> 9 | B69: 45°弯头（1400×500，TDC法兰）+ 304不锈钢防虫网（4–6mm），板厚0.95mm Cút 45 độ KT: 1400x500 - TDC+Lưới chắn côn trùng inox 304 (mắt lưới 4-6mm), chiều dày tôn 0,95mm | L69: 個 Cái | M69: 3 | O69: =+N69*M69 -> 0 | S69: =Q69*M69 -> 0
A70: =+[23]l7!A70 -> 10 | B70: 軟接法蘭Bích nối mềm | L70: 個 Cái | M70: 44 | O70: =+N70*M70 -> 0 | S70: =Q70*M70 -> 0
A71: =+[23]l7!A71 -> 11 | B71: Chi phí vận chuyển | L71: lô | M71: 1 | O71: =+N71*M71 -> 0 | P71: Chưa bao gồm, dự kiến 3% | S71: =Q71*M71 -> 0
B72: Chi phí kiểm dịnh | L72: lô | M72: 1 | N72: 0 | P72: Đã bao gồm | S72: =Q72*M72 -> 0
A73: Total/ Tổng Trước thuế | O73: =SUM(O15:O72) -> 2.1982406e+09 | S73: =SUM(S16:S72) -> 2578591000
A74: VAT 8% | O74: =O73*0.08 -> 1.7585925e+08 | S74: =S73*10% -> 257859100
A75: Total Amount (including VAT 8%)/ Tổng sau thuế | O75: =SUM(O73:O74) -> 2.3740998e+09 | S75: =S73+S74 -> 2836450100
B77: - Ghi chú :
B78: * Thời hạn báo giá: Báo giá có giá trị trong vòng 07 ngày kể từ ngày báo. | N78: XÁC NHẬN ĐẶT HÀNG
B79: * Thời gian giao hàng: theo thực tế từng đơn hàng
B80: - Van gió & Phụ kiện : Tôn Hoa Sen Z08/Z18
B81: - Cửa gió và Phụ kiện : Nhôm A6063 T5 - Sơn Tĩnh điện mầu trắng .
B82: ĐIỀU KHOẢN THANH TOÁN VÀ GIAO HÀNG
B83: * Điều kiện thanh toán: Tạm ứng 30%, Thanh toán bằng bảo lãnh thanh toán thời hạn 35 ngày
B84: Xin vui lòng liên hệ với chúng tôi nếu quý khách có cần thêm các yêu cầu nào khác.
B85: Đơn vị thụ hưởng :
B86: Công ty Cổ phần tập đoàn quốc tế Sland
B87: Trụ sở: Thôn 1B, xã Nam Phù, TP Hà Nội
B88: - Số tài khoản : 1359 666 888
B89: - Mở tại : Ngân hàng TMCP Á Châu ( ACB ) chi nhánh Hà Nội

Sheet A05
C2: CÔNG TY CỔ PHẦN TẬP ĐOÀN QUỐC TẾ SLAND
C3: VPGD: SỐ 49, Ngõ 1295 Giải Phóng, Phường Hoàng Mai, TP Hà Nội
C4: Nhà máy: Thôn Nhân Hiền- xã Thường Tín - TP Hà Nội
C5: Hotline: 082 5577 999
A6: BẢNG BÁO GIÁ
A7: Khách hàng : CÔNG TY CỔ PHẦN XÂY DỰNG & KỸ THUẬT KD VIỆT NAM | M7: Seri number Số hiệu | P7: BG2_SLAND_KDVN_PCCC NHA A05
A8: Địa chỉ : | M8: Sales executive PT Kinh doanh | P8: Ms Nhài
A9: Người nhận : | M9: Mobile Điện thoại | P9: 0945588248
A10: Email: | C10: Số điện thoại : | M10: Dự án | N10: NHÀ A05
A11: STT | B11: Danh mục sản phẩm | C11: Model | D11: Thương hiệu | E11: Kích thước (mm) | I11: Modul | J11: L | K11: Độ dày (m) | L11: Unit Đơn vị | M11: Q'ty Số lượng | N11: Price Đơn giá | O11: Total price Thành tiền | P11: Remarks Ghi chú
D12: Thương hiệu | E12: A1 | F12: A2 | G12: B1 | H12: B2
E13: Face size | G13: Neck size
A15: WL | B15: 百叶风口 4500x800 Cửa Louver KT 4500x800 尺寸50x50箱钢门框、Z形条系，75mm宽铝合金，各条均匀间隔 40mm，同步配件，浅灰色面漆 khung cửa thép hộp KT50x50, hệ nan chữ Z hợp kim nhôm rộng 75mm, các nan cách đều 40mm, phụ kiện đồng bộ, sơn dầu hoàn thiện màu xám nhạt | C15: WL | D15: SWIND | E15: 4500 | F15: 800 | G15: 4450 | H15: 750 | L15: 個 Cái | M15: 57 | N15: 4468200 | O15: =N15*M15 -> 254687400 | P15: Louver nan Z khung nan nhôm sơn tĩnh điện Chia modul khi sản xuất | Q15: 4490000 | R15: =Q15*M15 -> 255930000
A16: WL | B16: 百叶风口 2000x2000 Cửa Louver 2000x2000 尺寸50x50箱钢门框、Z形条系，75mm宽铝合金，各条均匀间隔 40mm，同步配件，浅灰色面漆 khung cửa thép hộp KT50x50, hệ nan chữ Z hợp kim nhôm rộng 75mm, các nan cách đều 40mm, phụ kiện đồng bộ, sơn dầu hoàn thiện màu xám nhạt | C16: WL | D16: SWIND | E16: 2000 | F16: 2000 | G16: =E16-50 -> 1950 | H16: =F16-50 -> 1950 | L16: 個 Cái | M16: 11 | N16: 4725600 | O16: =N16*M16 -> 51981600 | P16: Louver nan Z khung nan nhôm sơn tĩnh điện | Q16: 4890000 | R16: =Q16*M16 -> 53790000
A17: WL | B17: 百叶风口 2000x1000 Cửa Louver 2000x1000 尺寸50x50箱钢门框、Z形条系，75mm宽铝合金，各条均匀间隔 40mm，同步配件，浅灰色面漆 khung cửa thép hộp KT50x50, hệ nan chữ Z hợp kim nhôm rộng 75mm, các nan cách đều 40mm, phụ kiện đồng bộ, sơn dầu hoàn thiện màu xám nhạt | C17: WL | D17: SWIND | E17: 2000 | F17: 1000 | G17: 1950 | H17: 950 | L17: 個 Cái | M17: 7 | N17: 2435400 | O17: =N17*M17 -> 17047800 | P17: Louver nan Z khung nan nhôm sơn tĩnh điện | Q17: 2450000 | R17: =Q17*M17 -> 17150000
A18: WL | B18: 百叶风口 1500x1500 Cửa Louver 1500x1500 尺寸50x50箱钢门框、Z形条系，75mm宽铝合金，各条均匀间隔 40mm，同步配件，浅灰色面漆 khung cửa thép hộp KT50x50, hệ nan chữ Z hợp kim nhôm rộng 75mm, các nan cách đều 40mm, phụ kiện đồng bộ, sơn dầu hoàn thiện màu xám nhạt | C18: WL | D18: SWIND | E18: 1500 | F18: 1500 | G18: 1450 | H18: 1450 | L18: 個 Cái | M18: 54 | N18: 2708200 | O18: =N18*M18 -> 146242800 | P18: Louver nan Z khung nan nhôm sơn tĩnh điện | Q18: 2860000 | R18: =Q18*M18 -> 154440000
A19: WL | B19: 百叶风口 1000x1000 Cửa Louver 1000x1000 尺寸50x50箱钢门框、Z形条系，75mm宽铝合金，各条均匀间隔 40mm，同步配件，浅灰色面漆 khung cửa thép hộp KT50x50, hệ nan chữ Z hợp kim nhôm rộng 75mm, các nan cách đều 40mm, phụ kiện đồng bộ, sơn dầu hoàn thiện màu xám nhạt | C19: WL | D19: SWIND | E19: 1000 | F19: 1000 | G19: 950 | H19: 950 | L19: 個 Cái | M19: 12 | N19: 1250700 | O19: =N19*M19 -> 15008400 | P19: Louver nan Z khung nan nhôm sơn tĩnh điện | Q19: 1320000 | R19: =Q19*M19 -> 15840000
A20: WL | B20: 百叶风口 1000x700 Cửa Louver 1000x700 尺寸50x50箱钢门框、Z形条系，75mm宽铝合金，各条均匀间隔 40mm，同步配件，浅灰色面漆 khung cửa thép hộp KT50x50, hệ nan chữ Z hợp kim nhôm rộng 75mm, các nan cách đều 40mm, phụ kiện đồng bộ, sơn dầu hoàn thiện màu xám nhạt | C20: WL | D20: SWIND | E20: 1000 | F20: 700 | G20: =E20-50 -> 950 | H20: =F20-50 -> 650 | L20: 個 Cái | M20: 2 | N20: 880000 | O20: =N20*M20 -> 1760000 | P20: Louver nan Z khung nan nhôm sơn tĩnh điện | Q20: 920000 | R20: =Q20*M20 -> 1840000
A21: SDG | B21: 風門含SEG 1200x600+OBD 流量調節閥含配件及安裝Cửa gió kèm van điều chỉnh lưu lượng SEG 1200x600+OBD Bao gồm nhân công phụ kiện lắp đặt | C21: SDG+OBD | D21: SWIND | E21: 1200 | F21: 600 | G21: 1150 | H21: 550 | L21: 個 Cái | M21: 140 | N21: 1051600 | O21: =N21*M21 -> 147224000 | P21: Cửa gió 1 lớp nan thẳng bầu dục + van OBD | Q21: 1230000 | R21: =Q21*M21 -> 172200000
A22: SDG | B22: 風門含SEG 600x600+OBD 流量調節閥含配件及安裝Cửa gió kèm van điều chỉnh lưu lượng SEG 600x600+OBD Bao gồm nhân công phụ kiện lắp đặt | C22: SDG+OBD | D22: SWIND | E22: 600 | F22: 600 | G22: 550 | H22: 550 | L22: 個 Cái | M22: 14 | N22: 556600 | O22: =N22*M22 -> 7792400 | P22: Cửa gió 1 lớp nan thẳng bầu dục + van OBD | Q22: 590000 | R22: =Q22*M22 -> 8260000
A23: SDG | B23: 風門含PAG 500x500 流量調節閥含配件及安裝 Cửa gió kèm van điều chỉnh lưu lượng PAG 500x500 Bao gồm nhân công phụ kiện lắp đặt | C23: SDG+OBD | D23: SWIND | E23: 500 | F23: 500 | G23: 450 | H23: 450 | L23: Cái 個 | M23: 32 | N23: 408100 | O23: =N23*M23 -> 13059200 | P23: Cửa gió 1 lớp nan thẳng bầu dục + van OBD | Q23: 530000 | R23: =Q23*M23 -> 16960000
A24: Ống chữ nhật | B24: 空調鍍鋅鐵皮排風管 1400x700mm, δ=1.15mm 含製作及安裝 Ống thoát gió bằng tôn mạ kẽm 1400x700mm , δ=1.15mm bao gồm gia công chế tạo và lắp đặt. | L24: m2 | M24: 1696 | O24: =N24*M24 -> 0 | R24: =Q24*M24 -> 0
A25: Ống chữ nhật | B25: 空調鍍鋅鐵皮排風管 1000x600mm, δ=1.15mm 含製作及安裝 Ống thoát gió bằng tôn mạ kẽm 1000x600mm , δ=1.15mm bao gồm gia công chế tạo và lắp đặt. | L25: m2 | M25: 791 | O25: =N25*M25 -> 0 | R25: =Q25*M25 -> 0
A26: Ống chữ nhật | B26: 空調鍍鋅鐵皮排風管 1000x350mm, δ=1.15mm 含製作及安裝 Ống thoát gió bằng tôn mạ kẽm 1000x350mm , δ=1.15mm bao gồm gia công chế tạo và lắp đặt. | L26: m2 | M26: 118 | O26: =N26*M26 -> 0 | R26: =Q26*M26 -> 0
A27: Ống chữ nhật | B27: 空調鍍鋅鐵皮排風管 600x600mm, δ=0.75mm 含製作及安裝 Ống thoát gió bằng tôn mạ kẽm 600x600mm , δ=0.75mm bao gồm gia công chế tạo và lắp đặt. | L27: m2 | M27: 523 | O27: =N27*M27 -> 0 | R27: =Q27*M27 -> 0
A28: Ống chữ nhật | B28: 空調鍍鋅鐵皮排風管1200x400mm EI45, δ=0.75mm含製作及安裝 （含越南消防及救護-救難警察局檢定費用） Ống thoát gió bằng tôn mạ kẽm 1200x400mm, EI45, δ=0.75mm bao gồm gia công chế tạo và lắp đặt. （Bao gồm chi phí kiểm định của cục cảnh sát pccc & CNCH Việt Nam) | L28: m2 | M28: 4369 | O28: =N28*M28 -> 0 | R28: =Q28*M28 -> 0
A29: Ống chữ nhật | B29: 空調鍍鋅鐵皮排風管1600x400mm EI45 含製作及安裝 （含越南消防及救護-救難警察局檢定費用） Ống thoát gió bằng tôn mạ kẽm 1600x400mm, EI45 bao gồm gia công chế tạo và lắp đặt. （Bao gồm chi phí kiểm định của cục cảnh sát pccc & CNCH Việt Nam) | L29: m2 | M29: 275 | O29: =N29*M29 -> 0 | R29: =Q29*M29 -> 0
A30: Ống chữ nhật | B30: 空調鍍鋅鐵皮排風管1800x400mm EI45 含製作及安裝 （含越南消防及救護-救難警察局檢定費用） Ống thoát gió bằng tôn mạ kẽm 1800x400mm, EI45 bao gồm gia công chế tạo và lắp đặt. （Bao gồm chi phí kiểm định của cục cảnh sát pccc & CNCH Việt Nam) | L30: m2 | M30: 3185 | O30: =N30*M30 -> 0 | R30: =Q30*M30 -> 0
A31: Ống chữ nhật | B31: 空調鍍鋅鐵皮排風管2000x400mm EI45 含製作及安裝 （含越南消防及救護-救難警察局檢定費用） Ống thoát gió bằng tôn mạ kẽm 2000x400mm, EI45 bao gồm gia công chế tạo và lắp đặt. （Bao gồm chi phí kiểm định của cục cảnh sát pccc & CNCH Việt Nam) | L31: m2 | M31: 4557 | O31: =N31*M31 -> 0 | R31: =Q31*M31 -> 0
A32: Ống chữ nhật | B32: 空調鍍鋅鐵皮排風管500x500mm EI30 含製作及安裝 （含越南消防及救護-救難警察局檢定費用） Ống thoát gió bằng tôn mạ kẽm 500x500mm, EI30 bao gồm gia công chế tạo và lắp đặt. （Bao gồm chi phí kiểm định của cục cảnh sát pccc & CNCH Việt Nam) | L32: m2 | M32: 31 | O32: =N32*M32 -> 0 | R32: =Q32*M32 -> 0
A33: Ống chữ nhật | B33: 空調鍍鋅鐵皮排風管700x300mm EI30 含製作及安裝 （含越南消防及救護-救難警察局檢定費用） Ống thoát gió bằng tôn mạ kẽm 700x300mm, EI30 bao gồm gia công chế tạo và lắp đặt. （Bao gồm chi phí kiểm định của cục cảnh sát pccc & CNCH Việt Nam) | L33: m2 | M33: 102 | O33: =N33*M33 -> 0 | R33: =Q33*M33 -> 0
A34: Ống chữ nhật | B34: 空調鍍鋅鐵皮排風管700x350mm EI30 含製作及安裝 （含越南消防及救護-救難警察局檢定費用） Ống thoát gió bằng tôn mạ kẽm 700x350mm, EI30 bao gồm gia công chế tạo và lắp đặt. （Bao gồm chi phí kiểm định của cục cảnh sát pccc & CNCH Việt Nam) | L34: m2 | M34: 571 | O34: =N34*M34 -> 0 | R34: =Q34*M34 -> 0
A35: Ống chữ nhật | B35: 空調鍍鋅鐵皮排風管1000x350mm EI30 含製作及安裝 （含越南消防及救護-救難警察局檢定費用） Ống thoát gió bằng tôn mạ kẽm 1000x350mm, EI30 bao gồm gia công chế tạo và lắp đặt. （Bao gồm chi phí kiểm định của cục cảnh sát pccc & CNCH Việt Nam) | L35: m2 | M35: 208 | O35: =N35*M35 -> 0 | R35: =Q35*M35 -> 0
A36: Ống chữ nhật | B36: 空調鍍鋅鐵皮排風管1500x50mm EI30 含製作及安裝 （含越南消防及救護-救難警察局檢定費用） Ống thoát gió bằng tôn mạ kẽm 1500x500mm, EI30 bao gồm gia công chế tạo và lắp đặt. （Bao gồm chi phí kiểm định của cục cảnh sát pccc & CNCH Việt Nam) | L36: m2 | M36: 900 | O36: =N36*M36 -> 0 | R36: =Q36*M36 -> 0
B37: 大小頭、彎頭、三通等連接配件，含安裝Phụ kiện kết nối côn, cút, tê…. bao gồm lắp đặt | L37: Khoản 式 | M37: 1 | O37: =N37*M37 -> 0 | R37: =Q37*M37 -> 0
A38: MFD - EI | B38: MFD單葉閥2000x400 ，on/off DC 24v電動機, EI45 Van MFD 1 lá 2000x400, động cơ điện on/off DC 24v, EI45 | C38: SWIND-1.03- MFD-EI90 | D38: SWIND | E38: 2000 | F38: 400 | G38: 1000 | H38: 400 | I38: 2 | J38: 200 | K38: 1.15 | L38: Cái 個 | M38: 48 | N38: 9387821.2 | O38: =N38*M38 -> 4.5061542e+08 | P38: - Van ngăn cháy động cơ - Tiêu chuẩn EI 90 - 2 đầu bích TDC - Gắn kèm động cơ ON-OFF 5Nm, Hãng KLB - Sản xuất theo BCTN số 4651/VLXD-TBMT | Q38: 7920000 | R38: =Q38*M38 -> 380160000
A39: MFD - EI | B39: MFD單葉閥1200x400 ，on/off DC 24v電動機, EI45 Van MFD 1 lá 1200x400, động cơ điện on/off DC 24v, EI45 | C39: SWIND-1.03- MFD-EI90 | D39: SWIND | E39: 1200 | F39: 400 | J39: 200 | K39: 1.15 | L39: Cái 個 | M39: 8 | N39: 5123838.5 | O39: =N39*M39 -> 40990708 | P39: - Van ngăn cháy động cơ - Tiêu chuẩn EI 90 - 2 đầu bích TDC - Gắn kèm động cơ ON-OFF 5Nm, Hãng KLB - Sản xuất theo BCTN số 4651/VLXD-TBMT | Q39: 4300000 | R39: =Q39*M39 -> 34400000
A40: MFD - EI | B40: MFD單葉閥1000x350 ，on/off DC 24v電動機, EI45 Van MFD 1 lá 1000x350, động cơ điện on/off DC 24v, EI45 | C40: SWIND-1.03- MFD-EI90 | D40: SWIND | E40: 1000 | F40: 350 | J40: 200 | K40: 1.15 | L40: Cái 個 | M40: 7 | N40: 4531029 | O40: =N40*M40 -> 31717203 | P40: - Van ngăn cháy động cơ - Tiêu chuẩn EI 90 - 2 đầu bích TDC - Gắn kèm động cơ ON-OFF 5Nm, Hãng KLB - Sản xuất theo BCTN số 4651/VLXD-TBMT | Q40: 4030000 | R40: =Q40*M40 -> 28210000
A41: MFD - EI | B41: MFD單葉閥700x300 ，on/off DC 24v電動機, EI45 Van MFD 1 lá 700x300, động cơ điện on/off DC 24v, EI45 | C41: SWIND-1.03- MFD-EI90 | D41: SWIND | E41: 700 | F41: 300 | J41: 200 | K41: 1.15 | L41: Cái 個 | M41: 2 | N41: 3678194.3 | O41: =N41*M41 -> 7356388.6 | P41: - Van ngăn cháy động cơ - Tiêu chuẩn EI 90 - 2 đầu bích TDC - Gắn kèm động cơ ON-OFF 5Nm, Hãng KLB - Sản xuất theo BCTN số 4651/VLXD-TBMT | Q41: 3680000 | R41: =Q41*M41 -> 7360000
A42: MD | B42: MD單葉閥4500x800 ，on/off DC 24v電動機 Van MD 1 lá 4500x800, động cơ điện on/off DC 24v | C42: MD | D42: SWIND | E42: 4500 | F42: 800 | J42: 200 | K42: 1.15 | L42: Cái 個 | M42: 57 | N42: 7168875 | O42: =N42*M42 -> 408625875 | P42: Van MD chia 4 modul, 4 động cơ KLB/VIWECO 24V -10N | Q42: 9546000 | R42: =Q42*M42 -> 544122000
A43: MD | B43: MD單葉閥2000x2000 ，on/off DC 24v電動機 Van MD 1 lá 2000x2000, động cơ điện on/off DC 24v | C43: MD | D43: SWIND | E43: 2000 | F43: 2000 | J43: 200 | K43: 1.15 | L43: Cái 個 | M43: 11 | N43: 6985125 | O43: =N43*M43 -> 76836375 | P43: Van MD chia 4 modul, 4 động cơ KLB/VIWECO 24V -10N | Q43: 9280000 | R43: =Q43*M43 -> 102080000
A44: MD | B44: MD單葉閥2000x1000 ，on/off DC 24v電動機 Van MD 1 lá 2000x2000, động cơ điện on/off DC 24v | C44: MD | D44: SWIND | E44: 2000 | F44: 1000 | J44: 200 | K44: 1.15 | L44: Cái 個 | M44: 7 | N44: 3903375 | O44: =N44*M44 -> 27323625 | P44: Van MD chia 2 modul, 2 động cơ KLB/VIWECO 24V -10N | Q44: 5060000 | R44: =Q44*M44 -> 35420000
A45: MD | B45: MD單葉閥1500x1500 ，on/off DC 24v電動機 Van MD 1 lá 1500x1500, động cơ điện on/off DC 24v | C45: MD | D45: SWIND | E45: 1500 | F45: 1500 | J45: 200 | K45: 1.15 | L45: Cái 個 | M45: 54 | N45: 4024125 | O45: =N45*M45 -> 217302750 | P45: Van MD chia 2 modul, 2 động cơ KLB/VIWECO 24V -10N | Q45: 5235000 | R45: =Q45*M45 -> 282690000
A46: MD | B46: MD單葉閥1000x1000 ，on/off DC 24v電動機 Van MD 1 lá 1000x1000, động cơ điện on/off DC 24v | C46: MD | D46: SWIND | E46: 1000 | F46: 1000 | J46: 200 | K46: 1.15 | L46: Cái 個 | M46: 12 | N46: 2287687.5 | O46: =N46*M46 -> 27452250 | P46: Van MD, động cơ KLB/VIWECO 24v-10N | Q46: 2740000 | R46: =Q46*M46 -> 32880000
A47: MD | B47: MD單葉閥1000x700 ，on/off DC 24v電動機 Van MD 1 lá 1000x700, động cơ điện on/off DC 24v | C47: MD | D47: SWIND | E47: 1000 | F47: 700 | I47: khung thì s | J47: 200 | K47: 1.15 | L47: Cái 個 | M47: 2 | N47: 2054062.5 | O47: =N47*M47 -> 4108125 | P47: Van MD, động cơ KLB/VIWECO 24v-10N | Q47: 2404000 | R47: =Q47*M47 -> 4808000
A48: NRD | B48: 1800×1000止回阀安装 Van 1 chiều 1800x1000 | C48: NRD | D48: SWIND | E48: 1800 | F48: 1500 | J48: 200 | K48: 1.15 | L48: Cái 個 | M48: 9 | N48: 2523750 | O48: =N48*M48 -> 22713750 | P48: Van 1 chiều | Q48: 2436000 | R48: =Q48*M48 -> 21924000
A49: NRD | B49: 1400×500止回阀安装 Van 1 chiều 1400x500 | C49: NRD | D49: SWIND | E49: 1400 | F49: 500 | J49: 200 | K49: 1.15 | L49: Cái 個 | M49: 7 | N49: 1212500 | O49: =N49*M49 -> 8487500 | P49: Van 1 chiều | Q49: 1288000 | R49: =Q49*M49 -> 9016000
A50: PRD | B50: 1000×500配重式泄压阀安装 Van xả áp kiểu đối trọng KT:1000x500 | C50: PRD | D50: SWIND | E50: 1000 | F50: 500 | J50: 200 | K50: 1.15 | L50: Cái 個 | M50: 32 | N50: 1153450 | O50: =N50*M50 -> 36910400 | P50: Van xả áp | Q50: 980000 | R50: =Q50*M50 -> 31360000
B51: 手動抽煙啟動按鈕。含安裝及與監控模塊鏈接配件 Nút ấn khởi động hút khói bằng tay (testing). Bao gồm nhân công lắp đặt, phụ kiện liên kết | L51: 個 Cái | M51: 22 | O51: =N51*M51 -> 0 | R51: =Q51*M51 -> 0
B52: L50x50x5mm吊架，含製造與施工（含一道底漆，及兩道乳白色面漆） Giá treo L50x50x5mm bao gồm chế tạo và thi công ( gồm sơn 1 lớp sơn lót và 2 lớp sơn phủ màu sữa) | L52: 套 Bộ | M52: 2330 | O52: =N52*M52 -> 0 | R52: =Q52*M52 -> 0
A53: FXC | B53: Khớp nối mềm kèm bích đầu quạt Bao gồm nhân công phụ kiện lắp đặt 軟接頭含抽煙機頭法蘭。含配件及安裝 | L53: 個 Cái | M53: 44 | O53: =N53*M53 -> 0 | R53: =Q53*M53 -> 0
A54: WL | B54: Cửa gió louver thải khói + lưới chắn côn trùng 1800x1000 louver風門排煙+擋昆蟲網1800x1000 | C54: WL+LCCT | D54: SWIND | E54: 1800 | F54: 1500 | G54: =E54-50 -> 1750 | H54: =F54-50 -> 1450 | L54: 個 Cái | M54: 9 | N54: 3650460 | O54: =N54*M54 -> 32854140 | P54: Louver nan Z cố định + LCCT | Q54: 2770000 | R54: =Q54*M54 -> 24930000
A55: WL | B55: Cửa gió louver thải khói + lưới chắn côn trùng 1400x500 louver風門排煙+擋昆蟲網1400x500 | C55: WL+LCCT | D55: SWIND | E55: 1400 | F55: 500 | G55: 1350 | H55: 450 | L55: 個 Cái | M55: 7 | N55: 1015410 | O55: =N55*M55 -> 7107870 | P55: Louver nan Z cố định + LCCT | Q55: 1130000 | R55: =Q55*M55 -> 7910000
A56: WL | B56: Cửa gió louver thải khói + lưới chắn côn trùng 1000x600 louver風門排煙+擋昆蟲網1000x600 | C56: WL+LCCT | D56: SWIND | E56: 1000 | F56: 600 | G56: 950 | H56: 550 | L56: 個 Cái | M56: 6 | N56: 858440 | O56: =N56*M56 -> 5150640 | P56: Louver nan Z cố định + LCCT | Q56: 990000 | R56: =Q56*M56 -> 5940000
A57: Côn VT | B57: Côn thu đầu quạt 1400x700/DQ-L800. Bao gồm nhân công lắp đặt, phụ kiện bích nối, zoăng làm kín, kẹp C, bulong+ốc+long đen 1400x700/DQ-L800抽煙機頭變徑。含安裝及鏈接法蘭、墊圈、C夾、螺栓螺絲等 | L57: 個 Cái | M57: 9 | O57: =N57*M57 -> 0 | R57: =Q57*M57 -> 0
A58: Côn VT | B58: Côn thu đầu quạt 1000x350/DQ. Bao gồm nhân công lắp đặt, phụ kiện bích nối, zoăng làm kín, kẹp C, bulong+ốc+long đen 1000x350/DQ抽煙機頭變徑。含安裝及鏈接法蘭、墊圈、C夾、螺栓螺絲等 | L58: 個 Cái | M58: 7 | O58: =N58*M58 -> 0 | R58: =Q58*M58 -> 0
A59: Côn VT | B59: Côn thu đầu quạt 1000x600/DQ. Bao gồm nhân công lắp đặt, phụ kiện bích nối, zoăng làm kín, kẹp C, bulong+ốc+long đen 1000x600/DQ抽煙機頭變徑。含安裝及鏈接法蘭、墊圈、C夾、螺栓螺絲等 | L59: 個 Cái | M59: 6 | O59: =N59*M59 -> 0 | R59: =Q59*M59 -> 0
A60: Cút tròn | B60: D820排风帽（带防虫网）制作与安装. Chụp thải gió kèm lưới chắn côn trùng D820 | L60: 個 Cái | M60: 22 | O60: =N60*M60 -> 0 | R60: =Q60*M60 -> 0
A61: Cút | B61: Cút 90 độ 1800x1000R1000. Bao gồm nhân công lắp đặt, phụ kiện bích nối, zoăng làm kín, kẹp C, bulong+ốc+long đen 1800x1000R1000 90度彎頭含安裝及鏈接法蘭、墊圈、C夾、螺栓螺絲等 | L61: 個 Cái | M61: 9 | O61: =N61*M61 -> 0 | R61: =Q61*M61 -> 0
A62: Cút | B62: 45°弯头（1800×1000，TDC法兰）+ 304不锈钢防虫网（4–6mm），板厚0.95mm. Cút 45 độ KT: 1800x1000 - TDC+Lưới chắn côn trùng inox 304 (mắt lưới 4-6mm), chiều dày tôn 0,95mm | L62: 個 Cái | M62: 9 | O62: =N62*M62 -> 0 | R62: =Q62*M62 -> 0
A63: Cút | B63: Cút 90 độ 1400x500R1000. Bao gồm nhân công lắp đặt, phụ kiện bích nối, zoăng làm kín, kẹp C, bulong+ốc+long đen 1400x500R1000 90度彎頭含安裝及鏈接法蘭、墊圈、C夾、螺栓螺絲等 | L63: 個 Cái | M63: 6 | O63: =N63*M63 -> 0 | R63: =Q63*M63 -> 0
A64: Cút | B64: 45°弯头（1400×500，TDC法兰）+ 304不锈钢防虫网（4–6mm），板厚0.95mm Cút 45 độ KT: 1400x500 - TDC+Lưới chắn côn trùng inox 304 (mắt lưới 4-6mm), chiều dày tôn 0,95mm | L64: 個 Cái | M64: 6 | O64: =N64*M64 -> 0 | R64: =Q64*M64 -> 0
B65: 軟接法蘭Bích nối mềm | L65: 個 Cái | M65: 44 | O65: =N65*M65 -> 0 | R65: =Q65*M65 -> 0
B66: Chi phí vận chuyển | L66: lô | M66: 1 | O66: =N66*M66 -> 0 | P66: Chưa bao gồm, dự kiến 3% | R66: =Q66*M66 -> 0
B67: Chi phí kiểm định | L67: lô | M67: 1 | P67: Đã bao gồm | R67: =Q67*M67 -> 0
A69: Total/ Tổng Trước thuế | O69: =SUM(O15:O68) -> 2.0603566e+09 | R69: =SUM(R15:R68) -> 2249620000
A70: VAT 8% | O70: =O69*0.08 -> 1.6482853e+08
A71: Total Amount (including VAT 8%)/ Tổng sau thuế | O71: =SUM(O69:O70) -> 2.2251851e+09
B73: - Ghi chú : | N73: XÁC NHẬN ĐẶT HÀNG
B74: * Thời hạn báo giá: Báo giá có giá trị trong vòng 07 ngày kể từ ngày báo.
B75: * Thời gian giao hàng: theo thực tế từng đơn hàng
B76: - Van gió & Phụ kiện : Tôn Hoa Sen Z08/Z18
B77: - Cửa gió và Phụ kiện : Nhôm A6063 T5 - Sơn Tĩnh điện mầu trắng .
B78: ĐIỀU KHOẢN THANH TOÁN VÀ GIAO HÀNG
B79: * Điều kiện thanh toán: Tạm ứng 30%, Thanh toán bằng bảo lãnh thanh toán thời hạn 35 ngày
B80: Xin vui lòng liên hệ với chúng tôi nếu quý khách có cần thêm các yêu cầu nào khác.
B81: Đơn vị thụ hưởng :
B82: Công ty Cổ phần tập đoàn quốc tế Sland
B83: Trụ sở: Thôn 1B, xã Nam Phù, TP Hà Nội
B84: - Số tài khoản : 1359 666 888
B85: - Mở tại : Ngân hàng TMCP Á Châu ( ACB ) chi nhánh Hà Nội

Sheet A06
C2: CÔNG TY CỔ PHẦN TẬP ĐOÀN QUỐC TẾ SLAND
C3: VPGD: SỐ 49, Ngõ 1295 Giải Phóng, Phường Hoàng Mai, TP Hà Nội
C4: Nhà máy: Thôn Nhân Hiền- xã Thường Tín - TP Hà Nội
C5: Hotline: 082 5577 999
A6: BẢNG BÁO GIÁ
A7: Khách hàng : CÔNG TY CỔ PHẦN XÂY DỰNG & KỸ THUẬT KD VIỆT NAM | M7: Seri number Số hiệu | P7: BG3_SLAND_KDVN_PCCC NHA A06
A8: Địa chỉ : | M8: Sales executive PT Kinh doanh | P8: Ms Nhài
A9: Người nhận : | M9: Mobile Điện thoại | P9: 0945588248
A10: Email: | C10: Số điện thoại : | M10: Dự án | N10: NHÀ A06
A11: STT | B11: Danh mục sản phẩm | C11: Model | D11: Thương hiệu | E11: Kích thước (mm) | I11: Modul | J11: L | K11: Độ dày (m) | L11: Unit Đơn vị | M11: Q'ty Số lượng | N11: Price Đơn giá | O11: Total price Thành tiền | P11: Remarks Ghi chú
D12: Thương hiệu | E12: A1 | F12: A2 | G12: B1 | H12: B2
E13: Face size | G13: Neck size
A15: =+[23]l7!A15 -> 1 | B15: =+[24]BG!C13 -> Cửa gió nan KT 4500x1000 尺寸50x50箱钢门框、Z形条系，75mm宽铝合金，各条均匀间隔 40mm，同步配件，浅灰色面漆 khung cửa thép hộp KT50x50, hệ nan chữ Z hợp kim nhôm rộng 75mm, các nan cách đều 40mm, phụ kiện đồng bộ, sơn dầu hoàn thiện màu xám nhạt | C15: WL+LCCT | D15: SWIND | E15: 4500 | F15: 1000 | G15: =+E15-50 -> 4450 | H15: =+F15-50 -> 950 | L15: =+[24]BG!L13 -> 個 Cái | M15: =+[24]BG!M13 -> 61 | N15: 5396600 | O15: =+N15*M15 -> 329192600 | P15: Louver nan Z cố định+ LCCT | Q15: 5600000
A16: =+[23]l7!A16 -> 2 | B16: =+[24]BG!C14 -> Cửa gió nan KT 4500x800 尺寸50x50箱钢门框、Z形条系，75mm宽铝合金，各条均匀间隔 40mm，同步配件，浅灰色面漆 khung cửa thép hộp KT50x50, hệ nan chữ Z hợp kim nhôm rộng 75mm, các nan cách đều 40mm, phụ kiện đồng bộ, sơn dầu hoàn thiện màu xám nhạt | C16: WL+LCCT | D16: SWIND | E16: 4500 | F16: 800 | G16: =+E16-50 -> 4450 | H16: =+F16-50 -> 750 | L16: =+[24]BG!L14 -> 個 Cái | M16: =+[24]BG!M14 -> 0 | N16: 4468200 | O16: =+N16*M16 -> 0 | P16: Louver nan Z cố định+ LCCT | Q16: 4490000
A17: =+[23]l7!A17 -> 3 | B17: =+[24]BG!C15 -> Cửa gió nan KT 4500x700 尺寸50x50箱钢门框、Z形条系，75mm宽铝合金，各条均匀间隔 40mm，同步配件，浅灰色面漆 khung cửa thép hộp KT50x50, hệ nan chữ Z hợp kim nhôm rộng 75mm, các nan cách đều 40mm, phụ kiện đồng bộ, sơn dầu hoàn thiện màu xám nhạt | C17: WL+LCCT | D17: SWIND | E17: 4500 | F17: 700 | G17: =+E17-50 -> 4450 | H17: =+F17-50 -> 650 | L17: =+[24]BG!L15 -> 個 Cái | M17: =+[24]BG!M15 -> 11 | N17: 3778500 | O17: =+N17*M17 -> 41563500 | P17: Louver nan Z cố định+ LCCT | Q17: 3980000
A18: =+[23]l7!A18 -> 4 | B18: =+[24]BG!C16 -> Cửa gió nan KT 2500x1800 尺寸50x50箱钢门框、Z形条系，75mm宽铝合金，各条均匀间隔 40mm，同步配件，浅灰色面漆 khung cửa thép hộp KT50x50, hệ nan chữ Z hợp kim nhôm rộng 75mm, các nan cách đều 40mm, phụ kiện đồng bộ, sơn dầu hoàn thiện màu xám nhạt | C18: WL+LCCT | D18: SWIND | E18: 2500 | F18: 1800 | G18: =+E18-50 -> 2450 | H18: =+F18-50 -> 1750 | L18: =+[24]BG!L16 -> 個 Cái | M18: =+[24]BG!M16 -> 10 | N18: 5358100 | O18: =+N18*M18 -> 53581000 | P18: Louver nan Z cố định+ LCCT | Q18: 5480000
A19: =+[23]l7!A19 -> 5 | B19: =+[24]BG!C17 -> Cửa gió nan KT 2000x2000 尺寸50x50箱钢门框、Z形条系，75mm宽铝合金，各条均匀间隔 40mm，同步配件，浅灰色面漆 khung cửa thép hộp KT50x50, hệ nan chữ Z hợp kim nhôm rộng 75mm, các nan cách đều 40mm, phụ kiện đồng bộ, sơn dầu hoàn thiện màu xám nhạt | C19: WL+LCCT | D19: SWIND | E19: 2000 | F19: 2000 | G19: =+E19-50 -> 1950 | H19: =+F19-50 -> 1950 | L19: =+[24]BG!L17 -> 個 Cái | M19: =+[24]BG!M17 -> 5 | N19: 4725600 | O19: =+N19*M19 -> 23628000 | P19: Louver nan Z cố định+ LCCT | Q19: 4890000
A20: =+[23]l7!A20 -> 6 | B20: =+[24]BG!C18 -> Cửa gió nan KT 2000x1800 尺寸50x50箱钢门框、Z形条系，75mm宽铝合金，各条均匀间隔 40mm，同步配件，浅灰色面漆 khung cửa thép hộp KT50x50, hệ nan chữ Z hợp kim nhôm rộng 75mm, các nan cách đều 40mm, phụ kiện đồng bộ, sơn dầu hoàn thiện màu xám nhạt | C20: WL+LCCT | D20: SWIND | E20: 2000 | F20: 1800 | G20: =+E20-50 -> 1950 | H20: =+F20-50 -> 1750 | L20: =+[24]BG!L18 -> 個 Cái | M20: =+[24]BG!M18 -> 2 | N20: 4307600 | O20: =+N20*M20 -> 8615200 | P20: Louver nan Z cố định+ LCCT | Q20: 4490000
A21: =+[23]l7!A21 -> 7 | B21: =+[24]BG!C19 -> Cửa gió nan KT 2000x1000 尺寸50x50箱钢门框、Z形条系，75mm宽铝合金，各条均匀间隔 40mm，同步配件，浅灰色面漆 khung cửa thép hộp KT50x50, hệ nan chữ Z hợp kim nhôm rộng 75mm, các nan cách đều 40mm, phụ kiện đồng bộ, sơn dầu hoàn thiện màu xám nhạt | C21: WL+LCCT | D21: SWIND | E21: 2000 | F21: 1000 | G21: =+E21-50 -> 1950 | H21: =+F21-50 -> 950 | L21: =+[24]BG!L19 -> 個 Cái | M21: =+[24]BG!M19 -> 7 | N21: 2435400 | O21: =+N21*M21 -> 17047800 | P21: Louver nan Z cố định+ LCCT | Q21: 2450000
A22: =+[23]l7!A22 -> 8 | B22: =+[24]BG!C20 -> Cửa gió nan KT 1500x1500 尺寸50x50箱钢门框、Z形条系，75mm宽铝合金，各条均匀间隔 40mm，同步配件，浅灰色面漆 khung cửa thép hộp KT50x50, hệ nan chữ Z hợp kim nhôm rộng 75mm, các nan cách đều 40mm, phụ kiện đồng bộ, sơn dầu hoàn thiện màu xám nhạt | C22: WL+LCCT | D22: SWIND | E22: 1500 | F22: 1500 | G22: =+E22-50 -> 1450 | H22: =+F22-50 -> 1450 | L22: =+[24]BG!L20 -> 個 Cái | M22: =+[24]BG!M20 -> 26 | N22: 2708200 | O22: =+N22*M22 -> 70413200 | P22: Louver nan Z cố định+ LCCT | Q22: 2860000
A23: =+[23]l7!A23 -> 9 | B23: =+[24]BG!C21 -> Cửa gió nan KT 1000x1000 尺寸50x50箱钢门框、Z形条系，75mm宽铝合金，各条均匀间隔 40mm，同步配件，浅灰色面漆 khung cửa thép hộp KT50x50, hệ nan chữ Z hợp kim nhôm rộng 75mm, các nan cách đều 40mm, phụ kiện đồng bộ, sơn dầu hoàn thiện màu xám nhạt | C23: WL+LCCT | D23: SWIND | E23: 1000 | F23: 1000 | G23: =+E23-50 -> 950 | H23: =+F23-50 -> 950 | L23: =+[24]BG!L21 -> 個 Cái | M23: =+[24]BG!M21 -> 12 | N23: 1250700 | O23: =+N23*M23 -> 15008400 | P23: Louver nan Z cố định+ LCCT | Q23: 1320000
A24: =+[23]l7!A24 -> 10 | B24: =+[24]BG!C22 -> Cửa gió nan KT 1000x700 尺寸50x50箱钢门框、Z形条系，75mm宽铝合金，各条均匀间隔 40mm，同步配件，浅灰色面漆 khung cửa thép hộp KT50x50, hệ nan chữ Z hợp kim nhôm rộng 75mm, các nan cách đều 40mm, phụ kiện đồng bộ, sơn dầu hoàn thiện màu xám nhạt | C24: WL+LCCT | D24: SWIND | E24: 1000 | F24: 700 | G24: =+E24-50 -> 950 | H24: =+F24-50 -> 650 | L24: =+[24]BG!L22 -> 個 Cái | M24: =+[24]BG!M22 -> 37 | N24: 880000 | O24: =+N24*M24 -> 32560000 | P24: Louver nan Z cố định+ LCCT | Q24: 920000
A25: =+[23]l7!A25 -> 11 | B25: =+[24]BG!C23 -> Cửa gió nan KT 800x1500 尺寸50x50箱钢门框、Z形条系，75mm宽铝合金，各条均匀间隔 40mm，同步配件，浅灰色面漆 khung cửa thép hộp KT50x50, hệ nan chữ Z hợp kim nhôm rộng 75mm, các nan cách đều 40mm, phụ kiện đồng bộ, sơn dầu hoàn thiện màu xám nhạt | C25: WL+LCCT | D25: SWIND | E25: 800 | F25: 1500 | G25: =+E25-50 -> 750 | H25: =+F25-50 -> 1450 | L25: =+[24]BG!L23 -> 個 Cái | M25: =+[24]BG!M23 -> 1 | N25: 1338480 | O25: =+N25*M25 -> 1338480 | P25: Louver nan Z cố định+ LCCT | Q25: 1520000
A26: =+[23]l7!A26 -> 12 | B26: =+[24]BG!C24 -> 風門含SEG 1200x600+OBD 流量調節閥含配件及安裝Cửa gió kèm van điều chỉnh lưu lượng SEG 1200x600+OBD Bao gồm nhân công phụ kiện lắp đặt | C26: SDG+OBD | D26: SWIND | E26: 1200 | F26: 600 | G26: =+E26-50 -> 1150 | H26: =+F26-50 -> 550 | L26: =+[24]BG!L24 -> 個 Cái | M26: =+[24]BG!M24 -> 164 | N26: 1051600 | O26: =+N26*M26 -> 172462400 | P26: Cửa gió 1 lớp nan bầu dục cố định kèm van OBD | Q26: 1230000
... A28: =+[23]l7!A28 -> 14 | B28: =+[24]BG!C26 -> 風門含PAG 500x500 流量調節閥含配件及安裝 Cửa gió kèm van điều chỉnh lưu lượng PAG 500x500 Bao gồm nhân công phụ kiện lắp đặt | C28: SDG+OBD | D28: SWIND | E28: 500 | F28: 500 | G28: =+E28-50 -> 450 | H28: =+F28-50 -> 450 | L28: =+[24]BG!L26 -> Cái 個 | M28: =+[24]BG!M26 -> 42 | N28: 408100 | O28: =+N28*M28 -> 17140200 | P28: Cửa gió 1 lớp nan bầu dục cố định kèm van OBD | Q28: 530000
A29: =+[23]l7!A29 -> 15 | B29: =+[24]BG!C27 -> 空調鍍鋅鐵皮排風管 1400x700mm, δ=1.15mm 含製作及安裝 Ống thoát gió bằng tôn mạ kẽm 1400x700mm , δ=1.15mm bao gồm gia công chế tạo và lắp đặt. | L29: =+[24]BG!L27 -> m2 | M29: =+[24]BG!M27 -> 1560 | O29: =+N29*M29 -> 0
A30: =+[23]l7!A30 -> 16 | B30: =+[24]BG!C28 -> 空調鍍鋅鐵皮排風管 1400x500mm, δ=1.15mm 含製作及安裝 Ống thoát gió bằng tôn mạ kẽm 1400x500mm , δ=1.15mm bao gồm gia công chế tạo và lắp đặt. | L30: =+[24]BG!L28 -> m2 | M30: =+[24]BG!M28 -> 32 | O30: =+N30*M30 -> 0
B31: =+[24]BG!C29 -> 空調鍍鋅鐵皮排風管 1000x600mm, δ=1.15mm 含製作及安裝 Ống thoát gió bằng tôn mạ kẽm 1000x600mm , δ=1.15mm bao gồm gia công chế tạo và lắp đặt. | L31: =+[24]BG!L29 -> m2 | M31: =+[24]BG!M29 -> 863 | O31: =+N31*M31 -> 0
A32: =+[23]l7!A32 -> 1 | B32: =+[24]BG!C30 -> 空調鍍鋅鐵皮排風管 1000x500mm, δ=1.15mm 含製作及安裝 Ống thoát gió bằng tôn mạ kẽm 1000x500mm , δ=1.15mm bao gồm gia công chế tạo và lắp đặt. | L32: =+[24]BG!L30 -> m2 | M32: =+[24]BG!M30 -> 144 | O32: =+N32*M32 -> 0
A33: =+[23]l7!A33 -> 2 | B33: =+[24]BG!C31 -> 空調鍍鋅鐵皮排風管 1000x350mm, δ=1.15mm 含製作及安裝 Ống thoát gió bằng tôn mạ kẽm 1000x350mm , δ=1.15mm bao gồm gia công chế tạo và lắp đặt. | L33: =+[24]BG!L31 -> m2 | M33: =+[24]BG!M31 -> 116 | O33: =+N33*M33 -> 0
A34: =+[23]l7!A34 -> 3 | B34: =+[24]BG!C32 -> 空調鍍鋅鐵皮排風管 600x600mm, δ=0.75mm 含製作及安裝 Ống thoát gió bằng tôn mạ kẽm 600x600mm , δ=0.75mm bao gồm gia công chế tạo và lắp đặt. | L34: =+[24]BG!L32 -> m2 | M34: =+[24]BG!M32 -> 539 | O34: =+N34*M34 -> 0
A35: =+[23]l7!A35 -> 3 | B35: =+[24]BG!C33 -> 空調鍍鋅鐵皮排風管 500x500mm, δ=0.75mm 含製作及安裝 Ống thoát gió bằng tôn mạ kẽm 500x500mm , δ=0.75mm bao gồm gia công chế tạo và lắp đặt. | L35: =+[24]BG!L33 -> m2 | M35: =+[24]BG!M33 -> 54 | O35: =+N35*M35 -> 0
A36: =+[23]l7!A36 -> 4 | B36: =+[24]BG!C34 -> 空調鍍鋅鐵皮排風管1200x400mm EI45, 含製作及安裝 （含越南消防及救護-救難警察局檢定費用） Ống thoát gió bằng tôn mạ kẽm 1200x400mm, EI45,bao gồm gia công chế tạo và lắp đặt. （Bao gồm chi phí kiểm định của cục cảnh sát pccc & CNCH Việt Nam) | L36: =+[24]BG!L34 -> m2 | M36: =+[24]BG!M34 -> 6703 | O36: =+N36*M36 -> 0
A37: =+[23]l7!A37 -> 5 | B37: =+[24]BG!C35 -> 空調鍍鋅鐵皮排風管1600x400mm ,EI45, 含製作及安裝 （含越南消防及救護-救難警察局檢定費用） Ống thoát gió bằng tôn mạ kẽm 1600x400mm, EI45, bao gồm gia công chế tạo và lắp đặt. （Bao gồm chi phí kiểm định của cục cảnh sát pccc & CNCH Việt Nam) | L37: =+[24]BG!L35 -> m2 | M37: =+[24]BG!M35 -> 88 | O37: =+N37*M37 -> 0
A38: =+[23]l7!A38 -> 6 | B38: =+[24]BG!C36 -> 空調鍍鋅鐵皮排風管1800x400mm EI45, 含製作及安裝 （含越南消防及救護-救難警察局檢定費用） Ống thoát gió bằng tôn mạ kẽm 1800x400mm, EI45, bao gồm gia công chế tạo và lắp đặt. （Bao gồm chi phí kiểm định của cục cảnh sát pccc & CNCH Việt Nam) | L38: =+[24]BG!L36 -> m2 | M38: =+[24]BG!M36 -> 1235 | O38: =+N38*M38 -> 0
A39: =+[23]l7!A39 -> 7 | B39: =+[24]BG!C37 -> 空調鍍鋅鐵皮排風管2000x400mm EI45, 含製作及安裝 （含越南消防及救護-救難警察局檢定費用） Ống thoát gió bằng tôn mạ kẽm 2000x400mm, EI45, bao gồm gia công chế tạo và lắp đặt. （Bao gồm chi phí kiểm định của cục cảnh sát pccc & CNCH Việt Nam) | L39: =+[24]BG!L37 -> m2 | M39: =+[24]BG!M37 -> 5200 | O39: =+N39*M39 -> 0
A40: =+[23]l7!A40 -> 8 | B40: =+[24]BG!C38 -> 空調鍍鋅鐵皮排風管1500x500mm EI30, 含製作及安裝 （含越南消防及救護-救難警察局檢定費用） Ống thoát gió bằng tôn mạ kẽm 1500x500mm, EI30, bao gồm gia công chế tạo và lắp đặt. （Bao gồm chi phí kiểm định của cục cảnh sát pccc & CNCH Việt Nam) | L40: =+[24]BG!L38 -> m2 | M40: =+[24]BG!M38 -> 570 | O40: =+N40*M40 -> 0
A41: =+[23]l7!A41 -> 9 | B41: =+[24]BG!C39 -> 空調鍍鋅鐵皮排風管500x500mm EI30, 含製作及安裝 （含越南消防及救護-救難警察局檢定費用） Ống thoát gió bằng tôn mạ kẽm 500x500mm, EI30, bao gồm gia công chế tạo và lắp đặt. （Bao gồm chi phí kiểm định của cục cảnh sát pccc & CNCH Việt Nam) | L41: =+[24]BG!L39 -> m2 | M41: =+[24]BG!M39 -> 39 | O41: =+N41*M41 -> 0
A42: =+[23]l7!A42 -> 10 | B42: =+[24]BG!C40 -> 空調鍍鋅鐵皮排風管700x350mm EI30, 含製作及安裝 （含越南消防及救護-救難警察局檢定費用） Ống thoát gió bằng tôn mạ kẽm 700x350mm, EI30, bao gồm gia công chế tạo và lắp đặt. （Bao gồm chi phí kiểm định của cục cảnh sát pccc & CNCH Việt Nam) | L42: =+[24]BG!L40 -> m2 | M42: =+[24]BG!M40 -> 476 | O42: =+N42*M42 -> 0
A43: =+[23]l7!A43 -> 11 | B43: =+[24]BG!C41 -> 空調鍍鋅鐵皮排風管1000x350mm EI30, 含製作及安裝 （含越南消防及救護-救難警察局檢定費用） Ống thoát gió bằng tôn mạ kẽm 1000x350mm, EI30, bao gồm gia công chế tạo và lắp đặt. （Bao gồm chi phí kiểm định của cục cảnh sát pccc & CNCH Việt Nam) | L43: =+[24]BG!L41 -> m2 | M43: =+[24]BG!M41 -> 232 | O43: =+N43*M43 -> 0
A44: =+[23]l7!A44 -> 12 | B44: =+[24]BG!C42 -> 大小頭、彎頭、三通等連接配件，含安裝Phụ kiện kết nối côn, cút, tê…. bao gồm lắp đặt | L44: =+[24]BG!L42 -> Khoản 式 | M44: =+[24]BG!M42 -> 1 | O44: =+N44*M44 -> 0
A45: =+[23]l7!A45 -> 13 | B45: =+[24]BG!C43 -> MFD單葉閥2000x400 ，on/off DC 24v電動機, EI45 Van MFD 1 lá 2000x400, động cơ điện on/off DC 24v, EI45 | C45: SWIND-1.03- MFD-EI90 | D45: SWIND | E45: 2000 | F45: 400 | I45: 2 | J45: 200 | K45: 1.15 | L45: =+[24]BG!L43 -> Cái 個 | M45: =+[24]BG!M43 -> 49 | N45: 9387821.2 | O45: =+N45*M45 -> 4.6000324e+08 | P45: - Van ngăn cháy động cơ - Tiêu chuẩn EI 90 - 2 đầu bích TDC - Gắn kèm động cơ ON-OFF 5Nm, Hãng KLB - Sản xuất theo BCTN số 4651/VLXD-TBMT | Q45: 7920000 | R45: =Q45*M45 -> 388080000
A46: =+[23]l7!A46 -> 14 | B46: =+[24]BG!C44 -> MFD單葉閥1200x400 ，on/off DC 24v電動機, EI45 Van MFD 1 lá 1200x400, động cơ điện on/off DC 24v, EI45 | C46: SWIND-1.03- MFD-EI90 | D46: SWIND | E46: 1200 | F46: 400 | J46: 200 | K46: 1.15 | L46: =+[24]BG!L44 -> Cái 個 | M46: =+[24]BG!M44 -> 8 | N46: 5123838.5 | O46: =+N46*M46 -> 40990708 | P46: - Van ngăn cháy động cơ - Tiêu chuẩn EI 90 - 2 đầu bích TDC - Gắn kèm động cơ ON-OFF 5Nm, Hãng KLB - Sản xuất theo BCTN số 4651/VLXD-TBMT | Q46: 4300000 | R46: =Q46*M46 -> 34400000
A47: =+[23]l7!A47 -> 15 | B47: =+[24]BG!C45 -> MFD單葉閥1000x350 ，on/off DC 24v電動機, EI45 Van MFD 1 lá 1000x350, động cơ điện on/off DC 24v, EI45 | C47: SWIND-1.03- MFD-EI90 | D47: SWIND | E47: 1000 | F47: 350 | J47: 200 | K47: 1.15 | L47: =+[24]BG!L45 -> Cái 個 | M47: =+[24]BG!M45 -> 7 | N47: 4531029 | O47: =+N47*M47 -> 31717203 | P47: - Van ngăn cháy động cơ - Tiêu chuẩn EI 90 - 2 đầu bích TDC - Gắn kèm động cơ ON-OFF 5Nm, Hãng KLB - Sản xuất theo BCTN số 4651/VLXD-TBMT | Q47: 4030000 | R47: =Q47*M47 -> 28210000
A48: =+[23]l7!A48 -> 16 | B48: =+[24]BG!C46 -> MD單葉閥4500x1000 ，on/off DC 24v電動機 Van MD 1 lá 4500x1000, động cơ điện on/off DC 24v | C48: MD | D48: SWIND | E48: 4500 | F48: 1000 | J48: 200 | K48: 1.15 | L48: =+[24]BG!L46 -> Cái 個 | M48: =+[24]BG!M46 -> 61 | N48: 7523250 | O48: =+N48*M48 -> 458918250 | P48: Van MD chia 4 modul, 4 động cơ KLB/VIWECO 24V -10N | Q48: 10260000 | R48: =Q48*M48 -> 625860000
A49: =+[23]l7!A49 -> 17 | B49: =+[24]BG!C47 -> MD單葉閥4500x900 ，on/off DC 24v電動機 Van MD 1 lá 4500x900, động cơ điện on/off DC 24v | C49: MD | D49: SWIND | E49: 4500 | F49: 900 | J49: 200 | K49: 1.15 | L49: =+[24]BG!L47 -> Cái 個 | M49: =+[24]BG!M47 -> 0 | N49: 7275187.5 | O49: =+N49*M49 -> 0 | P49: Van MD chia 4 modul, 4 động cơ KLB/VIWECO 24V -10N | R49: =Q49*M49 -> 0
A50: =+[23]l7!A50 -> 18 | B50: =+[24]BG!C48 -> MD單葉閥4500x700 ，on/off DC 24v電動機 Van MD 1 lá 4500x700, động cơ điện on/off DC 24v | C50: MD | D50: SWIND | E50: 4500 | F50: 700 | J50: 200 | K50: 1.15 | L50: =+[24]BG!L48 -> Cái 個 | M50: =+[24]BG!M48 -> 11 | N50: 6781687.5 | O50: =+N50*M50 -> 74598562 | P50: Van MD chia 4 modul, 4 động cơ KLB/VIWECO 24V -10N | Q50: 7989000 | R50: =Q50*M50 -> 87879000
A51: =+[23]l7!A51 -> 19 | B51: =+[24]BG!C49 -> MD單葉閥2500x1800 ，on/off DC 24v電動機 Van MD 1 lá 2500x1800, động cơ điện on/off DC 24v | C51: MD | D51: SWIND | E51: 2500 | F51: 1800 | J51: 200 | K51: 1.15 | L51: =+[24]BG!L49 -> Cái 個 | M51: =+[24]BG!M49 -> 10 | N51: 7174125 | O51: =+N51*M51 -> 71741250 | P51: Van MD chia 4 modul, 4 động cơ KLB/VIWECO 24V -10N | Q51: 9756000 | R51: =Q51*M51 -> 97560000
A52: =+[23]l7!A52 -> 20 | B52: =+[24]BG!C50 -> MD單葉閥2000x2000 ，on/off DC 24v電動機 Van MD 1 lá 2000x2000, động cơ điện on/off DC 24v | C52: MD | D52: SWIND | E52: 2000 | F52: 2000 | J52: 200 | K52: 1.15 | L52: =+[24]BG!L50 -> Cái 個 | M52: =+[24]BG!M50 -> 5 | N52: 6844687.5 | O52: =+N52*M52 -> 34223438 | P52: Van MD chia 4 modul, 4 động cơ KLB/VIWECO 24V -10N | Q52: 9280000 | R52: =Q52*M52 -> 46400000
A53: =+[23]l7!A53 -> 21 | B53: =+[24]BG!C51 -> MD單葉閥2000x1800 ，on/off DC 24v電動機 Van MD 1 lá 2000x1800, động cơ điện on/off DC 24v | C53: MD | D53: SWIND | E53: 2000 | F53: 1800 | J53: 200 | K53: 1.15 | L53: =+[24]BG!L51 -> Cái 個 | M53: =+[24]BG!M51 -> 2 | N53: 6591375 | O53: =+N53*M53 -> 13182750 | P53: Van MD chia 4 modul, 4 động cơ KLB/VIWECO 24V -10N | Q53: 8916000 | R53: =Q53*M53 -> 17832000
A54: =+[23]l7!A54 -> 22 | B54: =+[24]BG!C52 -> MD單葉閥2000x1000 ，on/off DC 24v電動機 Van MD 1 lá 2000x1000, động cơ điện on/off DC 24v | C54: MD | D54: SWIND | E54: 2000 | F54: 1000 | J54: 200 | K54: 1.15 | L54: =+[24]BG!L52 -> Cái 個 | M54: =+[24]BG!M52 -> 7 | N54: 3903375 | O54: =+N54*M54 -> 27323625 | P54: Van MD chia 2 modul, 2 động cơ KLB/VIWECO 24V -10N | Q54: 5060000 | R54: =Q54*M54 -> 35420000
A55: =+[23]l7!A55 -> 23 | B55: =+[24]BG!C53 -> MD單葉閥1500x1500 ，on/off DC 24v電動機 Van MD 1 lá 1500x1500, động cơ điện on/off DC 24v | C55: MD | D55: SWIND | E55: 1500 | F55: 1500 | J55: 200 | K55: 1.15 | L55: =+[24]BG!L53 -> Cái 個 | M55: =+[24]BG!M53 -> 26 | N55: 4024125 | O55: =+N55*M55 -> 104627250 | P55: Van MD chia 2 modul, 2 động cơ KLB/VIWECO 24V -10N | Q55: 4035000 | R55: =Q55*M55 -> 104910000
A56: =+[23]l7!A56 -> 24 | B56: =+[24]BG!C54 -> MD單葉閥1000x1000 ，on/off DC 24v電動機 Van MD 1 lá 1000x1000, động cơ điện on/off DC 24v | C56: MD | D56: SWIND | E56: 1000 | F56: 1000 | J56: 200 | K56: 1.15 | L56: =+[24]BG!L54 -> Cái 個 | M56: =+[24]BG!M54 -> 12 | N56: 2287687.5 | O56: =+N56*M56 -> 27452250 | P56: Van MD, động cơ KLB/VIWECO 24v-10N | Q56: 2740000 | R56: =Q56*M56 -> 32880000
A57: =+[23]l7!A57 -> 25 | B57: =+[24]BG!C55 -> MD單葉閥1000x700 ，on/off DC 24v電動機 Van MD 1 lá 1000x700, động cơ điện on/off DC 24v | C57: MD | D57: SWIND | E57: 1000 | F57: 700 | J57: 200 | K57: 1.15 | L57: =+[24]BG!L55 -> Cái 個 | M57: =+[24]BG!M55 -> 37 | N57: 2054062.5 | O57: =+N57*M57 -> 76000312 | P57: Van MD, động cơ KLB/VIWECO 24v-10N | Q57: 2404000 | R57: =Q57*M57 -> 88948000
A58: =+[23]l7!A58 -> 26 | B58: =+[24]BG!C56 -> MD單葉閥800x1500 ，on/off DC 24v電動機 Van MD 1 lá 800x1500, động cơ điện on/off DC 24v | C58: MD | D58: SWIND | E58: 800 | F58: 1500 | J58: 200 | K58: 1.15 | L58: =+[24]BG!L56 -> Cái 個 | M58: =+[24]BG!M56 -> 1 | N58: 2471437.5 | O58: =+N58*M58 -> 2471437.5 | P58: Van MD, động cơ KLB/VIWECO 24v-10N | Q58: 3006000 | R58: =Q58*M58 -> 3006000
A59: =+[23]l7!A59 -> 27 | B59: =+[24]BG!C57 -> 1800×1000止回阀安装 Van 1 chiều 1800x1000 | C59: NRD | D59: SWIND | E59: 1800 | F59: 1000 | J59: 200 | K59: 1.15 | L59: =+[24]BG!L57 -> Cái 個 | M59: =+[24]BG!M57 -> 9 | N59: 1970000 | O59: =+N59*M59 -> 17730000 | Q59: 2436000 | R59: =Q59*M59 -> 21924000
B60: =+[24]BG!C58 -> 单向止回风阀（NRD）1400×500 mm Van 1 chiều NRD 1400x500 | C60: NRD | D60: SWIND | E60: 1400 | F60: 500 | J60: 200 | K60: 1.15 | L60: =+[24]BG!L58 -> Cái 個 | M60: =+[24]BG!M58 -> 7 | N60: 1212500 | O60: =+N60*M60 -> 8487500 | Q60: 1288000 | R60: =Q60*M60 -> 9016000
A61: =+[23]l7!A61 -> 1 | B61: =+[24]BG!C59 -> 1000×500配重式泄压阀安装 Van xả áp kiểu đối trọng KT:1000x500 | C61: PRD | D61: SWIND | E61: 1000 | F61: 500 | J61: 200 | K61: 1.15 | L61: =+[24]BG!L59 -> Cái 個 | M61: =+[24]BG!M59 -> 21 | N61: 1153450 | O61: =+N61*M61 -> 24222450 | Q61: 980000 | R61: =Q61*M61 -> 20580000
A62: =+[23]l7!A62 -> 2 | B62: =+[24]BG!C60 -> 手動抽煙啟動按鈕。含安裝及與監控模塊鏈接配件 Nút ấn khởi động hút khói bằng tay (testing). Bao gồm nhân công lắp đặt, phụ kiện liên kết | L62: =+[24]BG!L60 -> 個 Cái | M62: =+[24]BG!M60 -> 37 | O62: =+N62*M62 -> 0 | R62: =Q62*M62 -> 0
A63: =+[23]l7!A63 -> 3 | B63: =+[24]BG!C61 -> L50x50x5mm吊架，含製造與施工（含一道底漆，及兩道乳白色面漆） Giá treo L50x50x5mm bao gồm chế tạo và thi công ( gồm sơn 1 lớp sơn lót và 2 lớp sơn phủ màu sữa) | L63: =+[24]BG!L61 -> 套 Bộ | M63: =+[24]BG!M61 -> 2577 | O63: =+N63*M63 -> 0 | R63: =Q63*M63 -> 0
A64: =+[23]l7!A64 -> 4 | B64: =+[24]BG!C62 -> Khớp nối mềm kèm bích đầu quạt Bao gồm nhân công phụ kiện lắp đặt 軟接頭含抽煙機頭法蘭。含配件及安裝 | L64: =+[24]BG!L62 -> 個 Cái | M64: =+[24]BG!M62 -> 58 | O64: =+N64*M64 -> 0 | R64: =Q64*M64 -> 0
A65: =+[23]l7!A65 -> 5 | B65: =+[24]BG!C63 -> Cửa gió louver thải khói + lưới chắn côn trùng 1800x1000 louver風門排煙+擋昆蟲網1800x1000 | C65: WL+LCCT | D65: SWIND | E65: 1800 | F65: 1000 | G65: =+E65-50 -> 1750 | H65: =+F65-50 -> 950 | L65: =+[24]BG!L63 -> 個 Cái | M65: =+[24]BG!M63 -> 9 | N65: 2202750 | O65: =+N65*M65 -> 19824750 | P65: Louver nan Z cố định + LCCT | Q65: 2770000 | R65: =Q65*M65 -> 24930000
A66: =+[23]l7!A66 -> 6 | B66: =+[24]BG!C64 -> Cửa gió louver thải khói + lưới chắn côn trùng 1400x500 louver風門排煙+擋昆蟲網1400x500 | C66: WL+LCCT | D66: SWIND | E66: 1400 | F66: 500 | G66: =+E66-50 -> 1350 | H66: =+F66-50 -> 450 | L66: =+[24]BG!L64 -> 個 Cái | M66: =+[24]BG!M64 -> 9 | N66: 913869 | O66: =+N66*M66 -> 8224821 | P66: Louver nan Z cố định + LCCT | Q66: 1130000 | R66: =Q66*M66 -> 10170000
A67: =+[23]l7!A67 -> 7 | B67: =+[24]BG!C65 -> Cửa gió louver thải khói + lưới chắn côn trùng 1000x600 louver風門排煙+擋昆蟲網1000x600 | C67: WL+LCCT | D67: SWIND | E67: 1000 | F67: 600 | G67: =+E67-50 -> 950 | H67: =+F67-50 -> 550 | L67: =+[24]BG!L65 -> 個 Cái | M67: =+[24]BG!M65 -> 6 | N67: 772596 | O67: =+N67*M67 -> 4635576 | P67: Louver nan Z cố định + LCCT | Q67: 990000 | R67: =Q67*M67 -> 5940000
A68: =+[23]l7!A68 -> 8 | B68: =+[24]BG!C66 -> Cửa gió louver thải khói + lưới chắn côn trùng 1000x500 louver風門排煙+擋昆蟲網1000x500 | C68: WL+LCCT | D68: SWIND | E68: 1000 | F68: 500 | G68: =+E68-50 -> 950 | H68: =+F68-50 -> 450 | L68: =+[24]BG!L66 -> 個 Cái | M68: =+[24]BG!M66 -> 13 | N68: 662409 | O68: =+N68*M68 -> 8611317 | P68: Louver nan Z cố định + LCCT | Q68: 665000 | R68: =Q68*M68 -> 8645000
A69: =+[23]l7!A69 -> 9 | B69: =+[24]BG!C67 -> Côn thu đầu quạt 1400x700/DQ-L800. Bao gồm nhân công lắp đặt, phụ kiện bích nối, zoăng làm kín, kẹp C, bulong+ốc+long đen 1400x700/DQ-L800抽煙機頭變徑。含安裝及鏈接法蘭、墊圈、C夾、螺栓螺絲等 | L69: =+[24]BG!L67 -> 個 Cái | M69: =+[24]BG!M67 -> 9 | O69: =+N69*M69 -> 0 | R69: =Q69*M69 -> 0
A70: =+[23]l7!A70 -> 10 | B70: =+[24]BG!C68 -> Côn thu đầu quạt 1400x500/DQ-L800. Bao gồm nhân công lắp đặt, phụ kiện bích nối, zoăng làm kín, kẹp C, bulong+ốc+long đen 1400x500/DQ-L800抽煙機頭變徑。含安裝及鏈接法蘭、墊圈、C夾、螺栓螺絲等 | L70: =+[24]BG!L68 -> 個 Cái | M70: =+[24]BG!M68 -> 4 | O70: =+N70*M70 -> 0 | R70: =Q70*M70 -> 0
B71: =+[24]BG!C69 -> Côn thu đầu quạt 1000x350/DQ-L800. Bao gồm nhân công lắp đặt, phụ kiện bích nối, zoăng làm kín, kẹp C, bulong+ốc+long đen 1000x350/DQ-L800抽煙機頭變徑。含安裝及鏈接法蘭、墊圈、C夾、螺栓螺絲等 | L71: =+[24]BG!L69 -> 個 Cái | M71: =+[24]BG!M69 -> 7 | O71: =+N71*M71 -> 0 | R71: =Q71*M71 -> 0
B72: =+[24]BG!C70 -> Côn thu đầu quạt 1000x600/DQ-L800. Bao gồm nhân công lắp đặt, phụ kiện bích nối, zoăng làm kín, kẹp C, bulong+ốc+long đen 1000x600/DQ-L800抽煙機頭變徑。含安裝及鏈接法蘭、墊圈、C夾、螺栓螺絲等 | L72: =+[24]BG!L70 -> 個 Cái | M72: =+[24]BG!M70 -> 12 | O72: =+N72*M72 -> 0 | R72: =Q72*M72 -> 0
B73: =+[24]BG!C71 -> Côn thu đầu quạt 1000x500/DQ-L800. Bao gồm nhân công lắp đặt, phụ kiện bích nối, zoăng làm kín, kẹp C, bulong+ốc+long đen 1000x500/DQ-L800抽煙機頭變徑。含安裝及鏈接法蘭、墊圈、C夾、螺栓螺絲等 | L73: =+[24]BG!L71 -> 個 Cái | M73: =+[24]BG!M71 -> 26 | O73: =+N73*M73 -> 0 | R73: =Q73*M73 -> 0
B74: =+[24]BG!C72 -> D820排风帽（带防虫网）制作与安装. Chụp thải gió kèm lưới chắn côn trùng D820 | L74: =+[24]BG!L72 -> 個 Cái | M74: =+[24]BG!M72 -> 12 | O74: =+N74*M74 -> 0 | R74: =Q74*M74 -> 0
B75: =+[24]BG!C73 -> Cút 90 độ 1800x1000R1000. Bao gồm nhân công lắp đặt, phụ kiện bích nối, zoăng làm kín, kẹp C, bulong+ốc+long đen 1800x1000R1000 90度彎頭含安裝及鏈接法蘭、墊圈、C夾、螺栓螺絲等 | L75: =+[24]BG!L73 -> 個 Cái | M75: =+[24]BG!M73 -> 9 | O75: =+N75*M75 -> 0 | R75: =Q75*M75 -> 0
B76: =+[24]BG!C74 -> 45°弯头（1800×1000，TDC法兰）+ 304不锈钢防虫网（4–6mm），板厚0.95mm. Cút 45 độ KT: 1800x1000 - TDC+Lưới chắn côn trùng inox 304 (mắt lưới 4-6mm), chiều dày tôn 0,95mm | L76: =+[24]BG!L74 -> 個 Cái | M76: =+[24]BG!M74 -> 9 | O76: =+N76*M76 -> 0 | R76: =Q76*M76 -> 0
B77: =+[24]BG!C75 -> Cút 90 độ 1400x500R500. Bao gồm nhân công lắp đặt, phụ kiện bích nối, zoăng làm kín, kẹp C, bulong+ốc+long đen 1400x500R500 90度彎頭含安裝及鏈接法蘭、墊圈、C夾、螺栓螺絲等 | L77: =+[24]BG!L75 -> 個 Cái | M77: =+[24]BG!M75 -> 7 | O77: =+N77*M77 -> 0 | R77: =Q77*M77 -> 0
B78: =+[24]BG!C76 -> 45°弯头（1400x500，TDC法兰）+ 304不锈钢防虫网（4–6mm），板厚0.95mm. Cút 45 độ KT: 1400x500 - TDC+Lưới chắn côn trùng inox 304 (mắt lưới 4-6mm), chiều dày tôn 0,95mm | L78: =+[24]BG!L76 -> 個 Cái | M78: =+[24]BG!M76 -> 7 | O78: =+N78*M78 -> 0 | R78: =Q78*M78 -> 0
B79: =+[24]BG!C77 -> Cút 90 độ 1000x500R500. Bao gồm nhân công lắp đặt, phụ kiện bích nối, zoăng làm kín, kẹp C, bulong+ốc+long đen 1000x500R500 90度彎頭含安裝及鏈接法蘭、墊圈、C夾、螺栓螺絲等 | L79: =+[24]BG!L77 -> 個 Cái | M79: =+[24]BG!M77 -> 0 | O79: =+N79*M79 -> 0 | R79: =Q79*M79 -> 0
B80: Chi phí vận chuyển | L80: gói | M80: 1 | O80: =+N80*M80 -> 0 | P80: chưa bao gồm, dự kiến 3% | R80: =Q80*M80 -> 0
B81: Chi phí kiểm định | L81: gói | M81: 1 | P81: đã bao gồm | R81: =Q81*M81 -> 0
A82: Total/ Tổng Trước thuế | O82: =SUM(O15:O81) -> 2.3053299e+09 | R82: =SUM(R45:R81) -> 1692590000
A83: VAT 8% | O83: =O82*0.08 -> 1.8442639e+08
A84: Total Amount (including VAT 8%)/ Tổng sau thuế | O84: =SUM(O82:O83) -> 2.4897563e+09
B86: - Ghi chú : | N86: XÁC NHẬN ĐẶT HÀNG
B87: * Thời hạn báo giá: Báo giá có giá trị trong vòng 07 ngày kể từ ngày báo.
B88: * Thời gian giao hàng: theo thực tế từng đơn hàng
B89: - Van gió & Phụ kiện : Tôn Hoa Sen Z08/Z18
B90: - Cửa gió và Phụ kiện : Nhôm A6063 T5 - Sơn Tĩnh điện mầu trắng .
B91: ĐIỀU KHOẢN THANH TOÁN VÀ GIAO HÀNG
B92: * Điều kiện thanh toán: Tạm ứng 30%, Thanh toán bằng bảo lãnh thanh toán thời hạn 35 ngày
B93: Xin vui lòng liên hệ với chúng tôi nếu quý khách có cần thêm các yêu cầu nào khác.
B94: Đơn vị thụ hưởng :
B95: Công ty Cổ phần tập đoàn quốc tế Sland
B96: Trụ sở: Thôn 1B, xã Nam Phù, TP Hà Nội
B97: - Số tài khoản : 1359 666 888
B98: - Mở tại : Ngân hàng TMCP Á Châu ( ACB ) chi nhánh Hà Nội

Sheet A07
C2: CÔNG TY CỔ PHẦN TẬP ĐOÀN QUỐC TẾ SLAND
C3: VPGD: SỐ 49, Ngõ 1295 Giải Phóng, Phường Hoàng Mai, TP Hà Nội
C4: Nhà máy: Thôn Nhân Hiền- xã Thường Tín - TP Hà Nội
C5: Hotline: 082 5577 999
A6: BẢNG BÁO GIÁ
A7: Khách hàng : CÔNG TY CỔ PHẦN XÂY DỰNG & KỸ THUẬT KD VIỆT NAM | M7: Seri number Số hiệu | P7: BG4_SLAND_KDVN_PCCC NHA A07
A8: Địa chỉ : | M8: Sales executive PT Kinh doanh | P8: Ms Nhài
A9: Người nhận : | M9: Mobile Điện thoại | P9: 0945588248
A10: Email: | C10: Số điện thoại : | M10: Dự án | N10: NHÀ A07
A11: STT | B11: Danh mục sản phẩm | C11: Model | D11: Thương hiệu | E11: Kích thước (mm) | I11: Modul | J11: L | K11: Độ dày (m) | L11: Unit Đơn vị | M11: Q'ty Số lượng | N11: Price Đơn giá | O11: Total price Thành tiền | P11: Remarks Ghi chú
D12: Thương hiệu | E12: A1 | F12: A2 | G12: B1 | H12: B2
E13: Face size | G13: Neck size
A15: =+[23]l7!A15 -> 1 | B15: =+[25]BG!C13 -> 百叶风口 4700x1500 Cửa Louver KT 4700x1500 尺寸50x50箱钢门框、Z形条系，75mm宽铝合金，各条均匀间隔 40mm，同步配件，浅灰色面漆 khung cửa thép hộp KT50x50, hệ nan chữ Z hợp kim nhôm rộng 75mm, các nan cách đều 40mm, phụ kiện đồng bộ, sơn dầu hoàn thiện màu xám nhạt | C15: WL+LCCT | D15: SWIND | E15: 4700 | F15: 1500 | G15: =+E15-50 -> 4650 | H15: =+F15-50 -> 1450 | L15: =+[25]BG!L13 -> 個 Cái | M15: =+[25]BG!M13 -> 2 | N15: 8290700 | O15: =+N15*M15 -> 16581400 | P15: Louver nan Z cố định+ LCCT | Q15: 8840000 | R15: =Q15*M15 -> 17680000
A16: =+[23]l7!A16 -> 2 | B16: =+[25]BG!C14 -> 百叶风口 4500x1000 Cửa Louver KT 4500x1000 尺寸50x50箱钢门框、Z形条系，75mm宽铝合金，各条均匀间隔 40mm，同步配件，浅灰色面漆 khung cửa thép hộp KT50x50, hệ nan chữ Z hợp kim nhôm rộng 75mm, các nan cách đều 40mm, phụ kiện đồng bộ, sơn dầu hoàn thiện màu xám nhạt | C16: WL+LCCT | D16: SWIND | E16: 4500 | F16: 1000 | G16: =+E16-50 -> 4450 | H16: =+F16-50 -> 950 | L16: =+[25]BG!L14 -> 個 Cái | M16: =+[25]BG!M14 -> 26 | N16: 5396600 | O16: =+N16*M16 -> 140311600 | P16: Louver nan Z cố định+ LCCT | Q16: 5600000 | R16: =Q16*M16 -> 145600000
A17: =+[23]l7!A17 -> 3 | B17: =+[25]BG!C15 -> 百叶风口 4500x800 Cửa Louver KT 4500x800 尺寸50x50箱钢门框、Z形条系，75mm宽铝合金，各条均匀间隔 40mm，同步配件，浅灰色面漆 khung cửa thép hộp KT50x50, hệ nan chữ Z hợp kim nhôm rộng 75mm, các nan cách đều 40mm, phụ kiện đồng bộ, sơn dầu hoàn thiện màu xám nhạt | C17: WL+LCCT | D17: SWIND | E17: 4500 | F17: 800 | G17: =+E17-50 -> 4450 | H17: =+F17-50 -> 750 | L17: =+[25]BG!L15 -> 個 Cái | M17: =+[25]BG!M15 -> 16 | N17: 4468200 | O17: =+N17*M17 -> 71491200 | P17: Louver nan Z cố định+ LCCT | Q17: 4490000 | R17: =Q17*M17 -> 71840000
A18: =+[23]l7!A18 -> 4 | B18: =+[25]BG!C16 -> 百叶风口 3500x1600 Cửa Louver KT 3500x1600 尺寸50x50箱钢门框、Z形条系，75mm宽铝合金，各条均匀间隔 40mm，同步配件，浅灰色面漆 khung cửa thép hộp KT50x50, hệ nan chữ Z hợp kim nhôm rộng 75mm, các nan cách đều 40mm, phụ kiện đồng bộ, sơn dầu hoàn thiện màu xám nhạt | C18: WL+LCCT | D18: SWIND | E18: 3500 | F18: 1600 | G18: =+E18-50 -> 3450 | H18: =+F18-50 -> 1550 | L18: =+[25]BG!L16 -> 個 Cái | M18: =+[25]BG!M16 -> 2 | N18: 6559300 | O18: =+N18*M18 -> 13118600 | P18: Louver nan Z cố định+ LCCT | Q18: 7200000 | R18: =Q18*M18 -> 14400000
A19: =+[23]l7!A19 -> 5 | B19: =+[25]BG!C17 -> 百叶风口 2500x1500 Cửa Louver KT 2500x1500 尺寸50x50箱钢门框、Z形条系，75mm宽铝合金，各条均匀间隔 40mm，同步配件，浅灰色面漆 khung cửa thép hộp KT50x50, hệ nan chữ Z hợp kim nhôm rộng 75mm, các nan cách đều 40mm, phụ kiện đồng bộ, sơn dầu hoàn thiện màu xám nhạt | C19: WL+LCCT | D19: SWIND | E19: 2500 | F19: 1500 | G19: =+E19-50 -> 2450 | H19: =+F19-50 -> 1450 | L19: =+[25]BG!L17 -> 個 Cái | M19: =+[25]BG!M17 -> 2 | N19: 4452800 | O19: =+N19*M19 -> 8905600 | P19: Louver nan Z cố định+ LCCT | Q19: 4740000 | R19: =Q19*M19 -> 9480000
A20: =+[23]l7!A20 -> 6 | B20: =+[25]BG!C18 -> 百叶风口 2300x1500 Cửa Louver KT 2300x1500 尺寸50x50箱钢门框、Z形条系，75mm宽铝合金，各条均匀间隔 40mm，同步配件，浅灰色面漆 khung cửa thép hộp KT50x50, hệ nan chữ Z hợp kim nhôm rộng 75mm, các nan cách đều 40mm, phụ kiện đồng bộ, sơn dầu hoàn thiện màu xám nhạt | C20: WL+LCCT | D20: SWIND | E20: 2300 | F20: 1500 | G20: =+E20-50 -> 2250 | H20: =+F20-50 -> 1450 | L20: =+[25]BG!L18 -> 個 Cái | M20: =+[25]BG!M18 -> 2 | N20: 4104100 | O20: =+N20*M20 -> 8208200 | P20: Louver nan Z cố định+ LCCT | Q20: 4310000 | R20: =Q20*M20 -> 8620000
A21: =+[23]l7!A21 -> 7 | B21: =+[25]BG!C19 -> 百叶风口 2000x1500 Cửa Louver KT 2000x1500 尺寸50x50箱钢门框、Z形条系，75mm宽铝合金，各条均匀间隔 40mm，同步配件，浅灰色面漆 khung cửa thép hộp KT50x50, hệ nan chữ Z hợp kim nhôm rộng 75mm, các nan cách đều 40mm, phụ kiện đồng bộ, sơn dầu hoàn thiện màu xám nhạt | C21: WL+LCCT | D21: SWIND | E21: 2000 | F21: 1500 | G21: =+E21-50 -> 1950 | H21: =+F21-50 -> 1450 | L21: =+[25]BG!L19 -> 個 Cái | M21: =+[25]BG!M19 -> 4 | N21: 3580500 | O21: =+N21*M21 -> 14322000 | P21: Louver nan Z cố định+ LCCT | Q21: 3650000 | R21: =Q21*M21 -> 14600000
A22: =+[23]l7!A22 -> 8 | B22: =+[25]BG!C20 -> 百叶风口 1500x1500 Cửa Louver KT 1500x1500 尺寸50x50箱钢门框、Z形条系，75mm宽铝合金，各条均匀间隔 40mm，同步配件，浅灰色面漆 khung cửa thép hộp KT50x50, hệ nan chữ Z hợp kim nhôm rộng 75mm, các nan cách đều 40mm, phụ kiện đồng bộ, sơn dầu hoàn thiện màu xám nhạt | C22: WL+LCCT | D22: SWIND | E22: 1500 | F22: 1500 | G22: =+E22-50 -> 1450 | H22: =+F22-50 -> 1450 | L22: =+[25]BG!L20 -> 個 Cái | M22: =+[25]BG!M20 -> 33 | N22: 2708200 | O22: =+N22*M22 -> 89370600 | P22: Louver nan Z cố định+ LCCT | Q22: 2860000 | R22: =Q22*M22 -> 94380000
A23: =+[23]l7!A23 -> 9 | B23: =+[25]BG!C21 -> 百叶风口 1300x700 Cửa Louver KT 1300x700 尺寸50x50箱钢门框、Z形条系，75mm宽铝合金，各条均匀间隔 40mm，同步配件，浅灰色面漆 khung cửa thép hộp KT50x50, hệ nan chữ Z hợp kim nhôm rộng 75mm, các nan cách đều 40mm, phụ kiện đồng bộ, sơn dầu hoàn thiện màu xám nhạt | C23: WL+LCCT | D23: SWIND | E23: 1300 | F23: 700 | G23: =+E23-50 -> 1250 | H23: =+F23-50 -> 650 | L23: =+[25]BG!L21 -> 個 Cái | M23: =+[25]BG!M21 -> 8 | N23: 1128600 | O23: =+N23*M23 -> 9028800 | P23: Louver nan Z cố định+ LCCT | Q23: 1170000 | R23: =Q23*M23 -> 9360000
A24: =+[23]l7!A24 -> 10 | B24: =+[25]BG!C22 -> 百叶风口 1000x1000 Cửa Louver KT 1000x1000 尺寸50x50箱钢门框、Z形条系，75mm宽铝合金，各条均匀间隔 40mm，同步配件，浅灰色面漆 khung cửa thép hộp KT50x50, hệ nan chữ Z hợp kim nhôm rộng 75mm, các nan cách đều 40mm, phụ kiện đồng bộ, sơn dầu hoàn thiện màu xám nhạt | C24: WL+LCCT | D24: SWIND | E24: 1000 | F24: 1000 | G24: =+E24-50 -> 950 | H24: =+F24-50 -> 950 | L24: =+[25]BG!L22 -> 個 Cái | M24: =+[25]BG!M22 -> 12 | N24: 1250700 | O24: =+N24*M24 -> 15008400 | P24: Louver nan Z cố định+ LCCT | Q24: 1320000 | R24: =Q24*M24 -> 15840000
A25: =+[23]l7!A25 -> 11 | B25: =+[25]BG!C23 -> 百叶风口 1000x700 Cửa Louver KT 1000x700 尺寸50x50箱钢门框、Z形条系，75mm宽铝合金，各条均匀间隔 40mm，同步配件，浅灰色面漆 khung cửa thép hộp KT50x50, hệ nan chữ Z hợp kim nhôm rộng 75mm, các nan cách đều 40mm, phụ kiện đồng bộ, sơn dầu hoàn thiện màu xám nhạt | C25: WL+LCCT | D25: SWIND | E25: 1000 | F25: 700 | G25: =+E25-50 -> 950 | H25: =+F25-50 -> 650 | L25: =+[25]BG!L23 -> 個 Cái | M25: =+[25]BG!M23 -> 16 | N25: 880000 | O25: =+N25*M25 -> 14080000 | P25: Louver nan Z cố định+ LCCT | Q25: 920000 | R25: =Q25*M25 -> 14720000
A26: =+[23]l7!A26 -> 12 | B26: =+[25]BG!C24 -> 風門含SEG 1200x600+OBD 流量調節閥含配件及安裝Cửa gió kèm van điều chỉnh lưu lượng SEG 1200x600+OBD Bao gồm nhân công phụ kiện lắp đặt | C26: SDG+OBD | D26: SWIND | E26: 1200 | F26: 600 | G26: =+E26-50 -> 1150 | H26: =+F26-50 -> 550 | L26: =+[25]BG!L24 -> 個 Cái | M26: =+[25]BG!M24 -> 168 | N26: 1051600 | O26: =+N26*M26 -> 176668800 | P26: Cửa gió 1 lớp nan thẳng bầu dục + van OBD | Q26: 1230000 | R26: =Q26*M26 -> 206640000
... A28: =+[23]l7!A28 -> 14 | B28: =+[25]BG!C26 -> 風門含PAG 500x500 流量調節閥含配件及安裝 Cửa gió kèm van điều chỉnh lưu lượng PAG 500x500 Bao gồm nhân công phụ kiện lắp đặt | C28: SDG+OBD | D28: SWIND | E28: 500 | F28: 500 | G28: =+E28-50 -> 450 | H28: =+F28-50 -> 450 | L28: =+[25]BG!L26 -> Cái 個 | M28: =+[25]BG!M26 -> 42 | N28: 408100 | O28: =+N28*M28 -> 17140200 | P28: Cửa gió 1 lớp nan thẳng bầu dục + van OBD | Q28: 530000 | R28: =Q28*M28 -> 22260000
A29: =+[23]l7!A29 -> 15 | B29: =+[25]BG!C27 -> 空調鍍鋅鐵皮排風管 4000x500mm, δ=1.15mm 含製作及安裝 Ống thoát gió bằng tôn mạ kẽm 4000x500mm , δ=1.15mm bao gồm gia công chế tạo và lắp đặt. | L29: =+[25]BG!L27 -> m2 | M29: =+[25]BG!M27 -> 70 | O29: =+N29*M29 -> 0 | R29: =Q29*M29 -> 0
A30: =+[23]l7!A30 -> 16 | B30: =+[25]BG!C28 -> 空調鍍鋅鐵皮排風管 3000x300mm, δ=1.15mm 含製作及安裝 Ống thoát gió bằng tôn mạ kẽm 3000x300mm , δ=1.15mm bao gồm gia công chế tạo và lắp đặt. | L30: =+[25]BG!L28 -> m2 | M30: =+[25]BG!M28 -> 0 | O30: =+N30*M30 -> 0 | R30: =Q30*M30 -> 0
B31: =+[25]BG!C29 -> 空調鍍鋅鐵皮排風管 2000x500mm, δ=1.15mm 含製作及安裝 Ống thoát gió bằng tôn mạ kẽm 2000x500mm , δ=1.15mm bao gồm gia công chế tạo và lắp đặt. | L31: =+[25]BG!L29 -> m2 | M31: =+[25]BG!M29 -> 248 | O31: =+N31*M31 -> 0 | R31: =Q31*M31 -> 0
A32: =+[23]l7!A32 -> 1 | B32: =+[25]BG!C30 -> 空調鍍鋅鐵皮排風管 1200x500mm, δ=0.95mm 含製作及安裝 Ống thoát gió bằng tôn mạ kẽm 1200x500mm , δ=0.95mm bao gồm gia công chế tạo và lắp đặt. | L32: =+[25]BG!L30 -> m2 | M32: =+[25]BG!M30 -> 94 | O32: =+N32*M32 -> 0 | R32: =Q32*M32 -> 0
A33: =+[23]l7!A33 -> 2 | B33: =+[25]BG!C31 -> 空調鍍鋅鐵皮排風管 1050x1200mm, δ=0.95mm 含製作及安裝 Ống thoát gió bằng tôn mạ kẽm 1050x1200mm , δ=0.95mm bao gồm gia công chế tạo và lắp đặt. | L33: =+[25]BG!L31 -> m2 | M33: =+[25]BG!M31 -> 1597 | O33: =+N33*M33 -> 0 | R33: =Q33*M33 -> 0
A34: =+[23]l7!A34 -> 3 | B34: =+[25]BG!C32 -> 空調鍍鋅鐵皮排風管 550x1200mm, δ=0.95mm 含製作及安裝 Ống thoát gió bằng tôn mạ kẽm 550x1200mm , δ=0.95mm bao gồm gia công chế tạo và lắp đặt. | L34: =+[25]BG!L32 -> m2 | M34: =+[25]BG!M32 -> 1363 | O34: =+N34*M34 -> 0 | R34: =Q34*M34 -> 0
A35: =+[23]l7!A35 -> 3 | B35: =+[25]BG!C33 -> 空調鍍鋅鐵皮排風管 400x1200mm, δ=0.95mm 含製作及安裝 Ống thoát gió bằng tôn mạ kẽm 400x1200mm , δ=0.95mm bao gồm gia công chế tạo và lắp đặt. | L35: =+[25]BG!L33 -> m2 | M35: =+[25]BG!M33 -> 132 | O35: =+N35*M35 -> 0 | R35: =Q35*M35 -> 0
A36: =+[23]l7!A36 -> 4 | B36: =+[25]BG!C34 -> 空調鍍鋅鐵皮排風管 800x500mm, δ=0.95mm 含製作及安裝 Ống thoát gió bằng tôn mạ kẽm 800x500mm , δ=0.95mm bao gồm gia công chế tạo và lắp đặt. | L36: =+[25]BG!L34 -> m2 | M36: =+[25]BG!M34 -> 72 | O36: =+N36*M36 -> 0 | R36: =Q36*M36 -> 0
A37: =+[23]l7!A37 -> 5 | B37: =+[25]BG!C35 -> 空調鍍鋅鐵皮排風管 500x500mm, δ=0.75mm 含製作及安裝 Ống thoát gió bằng tôn mạ kẽm 500x500mm , δ=0.75mm bao gồm gia công chế tạo và lắp đặt. | L37: =+[25]BG!L35 -> m2 | M37: =+[25]BG!M35 -> 47 | O37: =+N37*M37 -> 0 | R37: =Q37*M37 -> 0
A38: =+[23]l7!A38 -> 6 | B38: =+[25]BG!C36 -> 空調鍍鋅鐵皮排風管2200x350mm EI45, 含製作及安裝 （含越南消防及救護-救難警察局檢定費用） Ống thoát gió bằng tôn mạ kẽm 2200x350mm, EI45, bao gồm gia công chế tạo và lắp đặt. （Bao gồm chi phí kiểm định của cục cảnh sát pccc & CNCH Việt Nam) | L38: =+[25]BG!L36 -> m2 | M38: =+[25]BG!M36 -> 8632.26 | O38: =+N38*M38 -> 0 | R38: =Q38*M38 -> 0
A39: =+[23]l7!A39 -> 7 | B39: =+[25]BG!C37 -> 空調鍍鋅鐵皮排風管2000x350mm EI45, 含製作及安裝 （含越南消防及救護-救難警察局檢定費用） Ống thoát gió bằng tôn mạ kẽm 2000x350mm, EI45, bao gồm gia công chế tạo và lắp đặt. （Bao gồm chi phí kiểm định của cục cảnh sát pccc & CNCH Việt Nam) | L39: =+[25]BG!L37 -> m2 | M39: =+[25]BG!M37 -> 207 | O39: =+N39*M39 -> 0 | R39: =Q39*M39 -> 0
A40: =+[23]l7!A40 -> 8 | B40: =+[25]BG!C38 -> 空調鍍鋅鐵皮排風管1800x350mm EI45, 含製作及安裝 （含越南消防及救護-救難警察局檢定費用） Ống thoát gió bằng tôn mạ kẽm 1800x350mm, EI45, bao gồm gia công chế tạo và lắp đặt. （Bao gồm chi phí kiểm định của cục cảnh sát pccc & CNCH Việt Nam) | L40: =+[25]BG!L38 -> m2 | M40: =+[25]BG!M38 -> 209 | O40: =+N40*M40 -> 0 | R40: =Q40*M40 -> 0
A41: =+[23]l7!A41 -> 9 | B41: =+[25]BG!C39 -> 空調鍍鋅鐵皮排風管1500x350mm EI45, 含製作及安裝 （含越南消防及救護-救難警察局檢定費用） Ống thoát gió bằng tôn mạ kẽm 1500x350mm, EI45, bao gồm gia công chế tạo và lắp đặt. （Bao gồm chi phí kiểm định của cục cảnh sát pccc & CNCH Việt Nam) | L41: =+[25]BG!L39 -> m2 | M41: =+[25]BG!M39 -> 3042 | O41: =+N41*M41 -> 0 | R41: =Q41*M41 -> 0
A42: =+[23]l7!A42 -> 10 | B42: =+[25]BG!C40 -> 空調鍍鋅鐵皮排風管1200x300mm EI45, 含製作及安裝 （含越南消防及救護-救難警察局檢定費用） Ống thoát gió bằng tôn mạ kẽm 1200x300mm, EI45, bao gồm gia công chế tạo và lắp đặt. （Bao gồm chi phí kiểm định của cục cảnh sát pccc & CNCH Việt Nam) | L42: =+[25]BG!L40 -> m2 | M42: =+[25]BG!M40 -> 347 | O42: =+N42*M42 -> 0 | R42: =Q42*M42 -> 0
A43: =+[23]l7!A43 -> 11 | B43: =+[25]BG!C41 -> 空調鍍鋅鐵皮排風管700x300mm EI45, 含製作及安裝 （含越南消防及救護-救難警察局檢定費用） Ống thoát gió bằng tôn mạ kẽm 700x300mm, EI45, bao gồm gia công chế tạo và lắp đặt. （Bao gồm chi phí kiểm định của cục cảnh sát pccc & CNCH Việt Nam) | L43: =+[25]BG!L41 -> m2 | M43: =+[25]BG!M41 -> 759 | O43: =+N43*M43 -> 0 | R43: =Q43*M43 -> 0
... A46: =+[23]l7!A46 -> 14 | B46: =+[25]BG!C44 -> 大小頭、彎頭、三通等連接配件，含安裝Phụ kiện kết nối côn, cút, tê…. bao gồm lắp đặt | L46: =+[25]BG!L44 -> Khoản 式 | M46: =+[25]BG!M44 -> 1 | O46: =+N46*M46 -> 0 | R46: =Q46*M46 -> 0
A47: =+[23]l7!A47 -> 15 | B47: =+[25]BG!C45 -> MFD單葉閥2000x350 ，on/off DC 24v電動機, EI45 Van MFD 1 lá 2000x350, động cơ điện on/off DC 24v, EI45 | C47: SWIND-1.03- MFD-EI90 | D47: SWIND | E47: 2000 | F47: 350 | I47: 2 | J47: 200 | K47: 1.15 | L47: =+[25]BG!L45 -> Cái 個 | M47: =+[25]BG!M45 -> 18 | N47: 9062058.1 | O47: =+N47*M47 -> 1.6311705e+08 | P47: - Van ngăn cháy động cơ - Tiêu chuẩn EI 90 - 2 đầu bích TDC - Gắn kèm động cơ ON-OFF 5Nm, Hãng KLB - Sản xuất theo BCTN số 4651/VLXD-TBMT | Q47: 7780000 | R47: =Q47*M47 -> 140040000
A48: =+[23]l7!A48 -> 16 | B48: =+[25]BG!C46 -> MFD單葉閥1500x350 ，on/off DC 24v電動機, EI45 Van MFD 1 lá 1500x350, động cơ điện on/off DC 24v, EI45 | C48: SWIND-1.03- MFD-EI90 | D48: SWIND | E48: 1500 | F48: 350 | J48: 200 | K48: 1.15 | L48: =+[25]BG!L46 -> Cái 個 | M48: =+[25]BG!M46 -> 20 | N48: 5558304.3 | O48: =+N48*M48 -> 1.1116609e+08 | P48: - Van ngăn cháy động cơ - Tiêu chuẩn EI 90 - 2 đầu bích TDC - Gắn kèm động cơ ON-OFF 5Nm, Hãng KLB - Sản xuất theo BCTN số 4651/VLXD-TBMT | Q48: 7270000 | R48: =Q48*M48 -> 145400000
A49: =+[23]l7!A49 -> 17 | B49: =+[25]BG!C47 -> MFD單葉閥1500x300 ，on/off DC 24v電動機, EI45 Van MFD 1 lá 1500x300, động cơ điện on/off DC 24v, EI45 | C49: SWIND-1.03- MFD-EI90 | D49: SWIND | E49: 1500 | F49: 300 | J49: 200 | K49: 1.15 | L49: =+[25]BG!L47 -> Cái 個 | M49: =+[25]BG!M47 -> 24 | N49: 5347878.2 | O49: =+N49*M49 -> 1.2834908e+08 | P49: - Van ngăn cháy động cơ - Tiêu chuẩn EI 90 - 2 đầu bích TDC - Gắn kèm động cơ ON-OFF 5Nm, Hãng KLB - Sản xuất theo BCTN số 4651/VLXD-TBMT | Q49: 7160000 | R49: =Q49*M49 -> 171840000
A50: =+[23]l7!A50 -> 18 | B50: =+[25]BG!C48 -> MFD單葉閥1050x1200 ，on/off DC 24v電動機, EI45 Van MFD 1 lá 1050x1200, động cơ điện on/off DC 24v, EI45 | C50: SWIND-1.03- MFD-EI90 | D50: SWIND | E50: 1050 | F50: 1200 | I50: 2 | J50: 200 | K50: 1.15 | L50: =+[25]BG!L48 -> Cái 個 | M50: =+[25]BG!M48 -> 36 | N50: 10949386 | O50: =+N50*M50 -> 3.9417789e+08 | P50: - Van ngăn cháy động cơ - Tiêu chuẩn EI 90 - 2 đầu bích TDC - Gắn kèm động cơ ON-OFF 5Nm, Hãng KLB - Sản xuất theo BCTN số 4651/VLXD-TBMT | Q50: 8260000 | R50: =Q50*M50 -> 297360000
A51: =+[23]l7!A51 -> 19 | B51: =+[25]BG!C49 -> MFD單葉閥1200x300 ，on/off DC 24v電動機, EI45 Van MFD 1 lá 1200x300, động cơ điện on/off DC 24v, EI45 | C51: SWIND-1.03- MFD-EI90 | D51: SWIND | E51: 1200 | F51: 300 | J51: 200 | K51: 1.15 | L51: =+[25]BG!L49 -> Cái 個 | M51: =+[25]BG!M49 -> 12 | N51: 4760039.8 | O51: =+N51*M51 -> 57120477 | P51: - Van ngăn cháy động cơ - Tiêu chuẩn EI 90 - 2 đầu bích TDC - Gắn kèm động cơ ON-OFF 5Nm, Hãng KLB - Sản xuất theo BCTN số 4651/VLXD-TBMT | Q51: 4120000 | R51: =Q51*M51 -> 49440000
A52: =+[23]l7!A52 -> 20 | B52: =+[25]BG!C50 -> MD單葉閥4700x1500 ，on/off DC 24v電動機 Van MD 1 lá 4700x1500, động cơ điện on/off DC 24v | C52: MD | D52: SWIND | E52: 4700 | F52: 1500 | J52: 200 | K52: 1.15 | L52: =+[25]BG!L50 -> Cái 個 | M52: =+[25]BG!M50 -> 2 | N52: 12463500 | O52: =+N52*M52 -> 24927000 | P52: Van MD chia 8 modul, 8 động cơ KLB/VIWECO 24V -10N | Q52: 12339000 | R52: =Q52*M52 -> 24678000
A53: =+[23]l7!A53 -> 21 | B53: =+[25]BG!C51 -> MD單葉閥4500x1000 ，on/off DC 24v電動機 Van MD 1 lá 4500x1000, động cơ điện on/off DC 24v | C53: MD | D53: SWIND | E53: 4500 | F53: 1000 | J53: 200 | K53: 1.15 | L53: =+[25]BG!L51 -> Cái 個 | M53: =+[25]BG!M51 -> 26 | N53: 7523250 | O53: =+N53*M53 -> 195604500 | P53: Van MD chia 4 modul, 4 động cơ KLB/VIWECO 24V -10N | Q53: 10260000 | R53: =Q53*M53 -> 266760000
A54: =+[23]l7!A54 -> 22 | B54: =+[25]BG!C52 -> MD單葉閥4500x800 ，on/off DC 24v電動機 Van MD 1 lá 4500x800, động cơ điện on/off DC 24v | C54: MD | D54: SWIND | E54: 4500 | F54: 800 | J54: 200 | K54: 1.15 | L54: =+[25]BG!L52 -> Cái 個 | M54: =+[25]BG!M52 -> 16 | N54: 7168875 | O54: =+N54*M54 -> 114702000 | P54: Van MD chia 4 modul, 4 động cơ KLB/VIWECO 24V -10N | Q54: 9546000 | R54: =Q54*M54 -> 152736000
A55: =+[23]l7!A55 -> 23 | B55: =+[25]BG!C53 -> MD單葉閥3500x1600 ，on/off DC 24v電動機 Van MD 1 lá 3500x1600, động cơ điện on/off DC 24v | C55: MD | D55: SWIND | E55: 3500 | F55: 1600 | J55: 200 | K55: 1.15 | L55: =+[25]BG!L53 -> Cái 個 | M55: =+[25]BG!M53 -> 2 | N55: 8081062.5 | O55: =+N55*M55 -> 16162125 | P55: Van MD chia 4 modul, 4 động cơ KLB/VIWECO 24V -10N | Q55: 9662000 | R55: =Q55*M55 -> 19324000
A56: =+[23]l7!A56 -> 24 | B56: =+[25]BG!C54 -> MD單葉閥3000x1500 ，on/off DC 24v電動機 Van MD 1 lá 3000x1500, động cơ điện on/off DC 24v | C56: MD | D56: SWIND | E56: 3000 | F56: 1500 | J56: 200 | K56: 1.15 | L56: =+[25]BG!L54 -> Cái 個 | M56: =+[25]BG!M54 -> 12 | N56: 7372312.5 | O56: =+N56*M56 -> 88467750 | P56: Van MD chia 4 modul, 4 động cơ KLB/VIWECO 24V -10N | Q56: 8640000 | R56: =Q56*M56 -> 103680000
A57: =+[23]l7!A57 -> 25 | B57: =+[25]BG!C55 -> MD單葉閥2500x1500 ，on/off DC 24v電動機 Van MD 1 lá 2500x1500, động cơ điện on/off DC 24v | C57: MD | D57: SWIND | E57: 2500 | F57: 1500 | J57: 200 | K57: 1.15 | L57: =+[25]BG!L55 -> Cái 個 | M57: =+[25]BG!M55 -> 2 | N57: 6863062.5 | O57: =+N57*M57 -> 13726125 | P57: Van MD chia 4 modul, 4 động cơ KLB/VIWECO 24V -10N | Q57: 6705000 | R57: =Q57*M57 -> 13410000
A58: =+[23]l7!A58 -> 26 | B58: =+[25]BG!C56 -> MD單葉閥2300x1500 ，on/off DC 24v電動機 Van MD 1 lá 2300x1500, động cơ điện on/off DC 24v | C58: MD | D58: SWIND | E58: 2300 | F58: 1500 | J58: 200 | K58: 1.15 | L58: =+[25]BG!L56 -> Cái 個 | M58: =+[25]BG!M56 -> 2 | N58: 6659625 | O58: =+N58*M58 -> 13319250 | P58: Van MD chia 4 modul, 4 động cơ KLB/VIWECO 24V -10N | Q58: 6411000 | R58: =Q58*M58 -> 12822000
A59: =+[23]l7!A59 -> 27 | B59: =+[25]BG!C57 -> MD單葉閥2000x2000 ，on/off DC 24v電動機 Van MD 1 lá 2000x2000, động cơ điện on/off DC 24v | C59: MD | D59: SWIND | E59: 2000 | F59: 2000 | J59: 200 | K59: 1.15 | L59: =+[25]BG!L57 -> Cái 個 | M59: =+[25]BG!M57 -> 9 | N59: 6985125 | O59: =+N59*M59 -> 62866125 | P59: Van MD chia 4 modul, 4 động cơ KLB/VIWECO 24V -10N | Q59: 6880000 | R59: =Q59*M59 -> 61920000
B60: =+[25]BG!C58 -> MD單葉閥2000x1500 ，on/off DC 24v電動機 Van MD 1 lá 2000x1500, động cơ điện on/off DC 24v | C60: MD | D60: SWIND | E60: 2000 | F60: 1500 | J60: 200 | K60: 1.15 | L60: =+[25]BG!L58 -> Cái 個 | M60: =+[25]BG!M58 -> 4 | N60: 6353812.5 | O60: =+N60*M60 -> 25415250 | P60: Van MD chia 4 modul, 4 động cơ KLB/VIWECO 24V -10N | Q60: 5970000 | R60: =Q60*M60 -> 23880000
A61: =+[23]l7!A61 -> 1 | B61: =+[25]BG!C59 -> MD單葉閥1500x1500 ，on/off DC 24v電動機 Van MD 1 lá 1500x1500, động cơ điện on/off DC 24v | C61: MD | D61: SWIND | E61: 1500 | F61: 1500 | J61: 200 | K61: 1.15 | L61: =+[25]BG!L59 -> Cái 個 | M61: =+[25]BG!M59 -> 33 | N61: 5844562.5 | O61: =+N61*M61 -> 1.9287056e+08 | P61: Van MD chia 4 modul, 4 động cơ KLB/VIWECO 24V -10N | Q61: 4035000 | R61: =Q61*M61 -> 133155000
A62: =+[23]l7!A62 -> 2 | B62: =+[25]BG!C60 -> MD單葉閥1300x700 ，on/off DC 24v電動機 Van MD 1 lá 1300x700, động cơ điện on/off DC 24v | C62: MD | D62: SWIND | E62: 1300 | F62: 700 | J62: 200 | K62: 1.15 | L62: =+[25]BG!L60 -> Cái 個 | M62: =+[25]BG!M60 -> 8 | N62: 2383500 | O62: =+N62*M62 -> 19068000 | P62: Van MD, động cơ KLB/VIWECO 24v-10N | Q62: 2677000 | R62: =Q62*M62 -> 21416000
A63: =+[23]l7!A63 -> 3 | B63: =+[25]BG!C61 -> MD單葉閥1000x1000 ，on/off DC 24v電動機 Van MD 1 lá 1000x1000, động cơ điện on/off DC 24v | C63: MD | D63: SWIND | E63: 1000 | F63: 1000 | J63: 200 | K63: 1.15 | L63: =+[25]BG!L61 -> Cái 個 | M63: =+[25]BG!M61 -> 12 | N63: 2287687.5 | O63: =+N63*M63 -> 27452250 | P63: Van MD, động cơ KLB/VIWECO 24v-10N | Q63: 2740000 | R63: =Q63*M63 -> 32880000
A64: =+[23]l7!A64 -> 4 | B64: =+[25]BG!C62 -> MD單葉閥1000x700 ，on/off DC 24v電動機 Van MD 1 lá 1000x700, động cơ điện on/off DC 24v | C64: MD | D64: SWIND | E64: 1000 | F64: 700 | J64: 200 | K64: 1.15 | L64: =+[25]BG!L62 -> Cái 個 | M64: =+[25]BG!M62 -> 16 | N64: 2054062.5 | O64: =+N64*M64 -> 32865000 | P64: Van MD, động cơ KLB/VIWECO 24v-10N | Q64: 2404000 | R64: =Q64*M64 -> 38464000
A65: =+[23]l7!A65 -> 5 | B65: =+[25]BG!C63 -> 1800×1500止回阀安装 Van 1 chiều 1800x1500 | C65: NRD | D65: SWIND | E65: 1800 | F65: 1500 | J65: 200 | K65: 1.15 | L65: =+[25]BG!L63 -> Cái 個 | M65: =+[25]BG!M63 -> 9 | N65: 2523750 | O65: =+N65*M65 -> 22713750 | Q65: 3276000 | R65: =Q65*M65 -> 29484000
A66: =+[23]l7!A66 -> 6 | B66: =+[25]BG!C64 -> 1200×1000止回阀安装 Van 1 chiều 1200x1000 | C66: NRD | D66: SWIND | E66: 1200 | F66: 1000 | J66: 200 | K66: 1.15 | L66: =+[25]BG!L64 -> Cái 個 | M66: =+[25]BG!M64 -> 7 | N66: 1526250 | O66: =+N66*M66 -> 10683750 | Q66: 1764000 | R66: =Q66*M66 -> 12348000
A67: =+[23]l7!A67 -> 7 | B67: =+[25]BG!C65 -> 500×500配重式泄压阀安装 Van xả áp kiểu đối trọng KT:500x500 | C67: PRD | D67: SWIND | E67: 500 | F67: 500 | J67: 200 | K67: 1.15 | L67: =+[25]BG!L65 -> Cái 個 | M67: =+[25]BG!M65 -> 59 | N67: 755000 | O67: =+N67*M67 -> 44545000 | Q67: 455000 | R67: =Q67*M67 -> 26845000
A68: =+[23]l7!A68 -> 8 | B68: =+[25]BG!C66 -> L50x50x5mm吊架，含製造與施工（含一道底漆，及兩道乳白色面漆） Giá treo L50x50x5mm bao gồm chế tạo và thi công ( gồm sơn 1 lớp sơn lót và 2 lớp sơn phủ màu sữa) | L68: =+[25]BG!L66 -> 套 Bộ | M68: =+[25]BG!M66 -> 2097 | O68: =+N68*M68 -> 0 | R68: =Q68*M68 -> 0
A69: =+[23]l7!A69 -> 9 | B69: =+[25]BG!C67 -> Khớp nối mềm kèm bích đầu quạt Bao gồm nhân công phụ kiện lắp đặt 軟接頭含抽煙機頭法蘭。含配件及安裝 | L69: =+[25]BG!L67 -> 個 Cái | M69: =+[25]BG!M67 -> 31 | O69: =+N69*M69 -> 0 | R69: =Q69*M69 -> 0
B70: =+[25]BG!C68 -> Cửa gió louver thải khói + lưới chắn côn trùng 1800x1500 louver風門排煙+擋昆蟲網1800x1500 | C70: WL+LCCT | D70: SWIND | E70: 1800 | F70: 1500 | J70: 200 | K70: 1.15 | L70: =+[25]BG!L68 -> 個 Cái | M70: =+[25]BG!M68 -> 9 | N70: 3285414 | O70: =+N70*M70 -> 29568726 | P70: Louver nan Z cố định + LCCT | Q70: 3400000 | R70: =Q70*M70 -> 30600000
B71: =+[25]BG!C69 -> Cửa gió louver thải khói + lưới chắn côn trùng 1200x1000 louver風門排煙+擋昆蟲網1200x1000 | C71: WL+LCCT | D71: SWIND | E71: 1200 | F71: 1000 | J71: 200 | K71: 1.15 | L71: =+[25]BG!L69 -> 個 Cái | M71: =+[25]BG!M69 -> 7 | N71: 1500741 | O71: =+N71*M71 -> 10505187 | P71: Louver nan Z cố định + LCCT | Q71: 1540000 | R71: =Q71*M71 -> 10780000
B72: =+[25]BG!C70 -> Côn thu đầu quạt 1050x1200/DQ-L800. Bao gồm nhân công lắp đặt, phụ kiện bích nối, zoăng làm kín, kẹp C, bulong+ốc+long đen 1050x1200/DQ-L800抽煙機頭變徑。含安裝及鏈接法蘭、墊圈、C夾、螺栓螺絲等 | L72: =+[25]BG!L70 -> 個 Cái | M72: =+[25]BG!M70 -> 9 | R72: =Q72*M72 -> 0
B73: =+[25]BG!C71 -> Côn thu đầu quạt 550x1200/DQ-L800. Bao gồm nhân công lắp đặt, phụ kiện bích nối, zoăng làm kín, kẹp C, bulong+ốc+long đen 550x1200/DQ-L800抽煙機頭變徑。含安裝及鏈接法蘭、墊圈、C夾、螺栓螺絲等 | L73: =+[25]BG!L71 -> 個 Cái | M73: =+[25]BG!M71 -> 7 | R73: =Q73*M73 -> 0
B74: =+[25]BG!C72 -> Côn thu đầu quạt 2000x500/DQ-L800. Bao gồm nhân công lắp đặt, phụ kiện bích nối, zoăng làm kín, kẹp C, bulong+ốc+long đen 2000x500/DQ-L800抽煙機頭變徑。含安裝及鏈接法蘭、墊圈、C夾、螺栓螺絲等 | L74: =+[25]BG!L72 -> 個 Cái | M74: =+[25]BG!M72 -> 5 | R74: =Q74*M74 -> 0
B75: =+[25]BG!C73 -> Côn thu đầu quạt 800x500/DQ-L800. Bao gồm nhân công lắp đặt, phụ kiện bích nối, zoăng làm kín, kẹp C, bulong+ốc+long đen 800x500/DQ-L800抽煙機頭變徑。含安裝及鏈接法蘭、墊圈、C夾、螺栓螺絲等 | L75: =+[25]BG!L73 -> 個 Cái | M75: =+[25]BG!M73 -> 6 | R75: =Q75*M75 -> 0
B76: =+[25]BG!C74 -> Côn thu đầu quạt 1200x500/DQ-L800. Bao gồm nhân công lắp đặt, phụ kiện bích nối, zoăng làm kín, kẹp C, bulong+ốc+long đen 1200x500/DQ-L800抽煙機頭變徑。含安裝及鏈接法蘭、墊圈、C夾、螺栓螺絲等 | L76: =+[25]BG!L74 -> 個 Cái | M76: =+[25]BG!M74 -> 4 | R76: =Q76*M76 -> 0
B77: =+[25]BG!C75 -> D820排风帽（带防虫网）制作与安装. Chụp thải gió kèm lưới chắn côn trùng D820 | L77: =+[25]BG!L75 -> 個 Cái | M77: =+[25]BG!M75 -> 31 | R77: =Q77*M77 -> 0
B78: =+[25]BG!C76 -> Cút 90 độ 1800x1500R1000. Bao gồm nhân công lắp đặt, phụ kiện bích nối, zoăng làm kín, kẹp C, bulong+ốc+long đen 1800x1500R1000 90度彎頭含安裝及鏈接法蘭、墊圈、C夾、螺栓螺絲等 | L78: =+[25]BG!L76 -> 個 Cái | M78: =+[25]BG!M76 -> 9 | R78: =Q78*M78 -> 0
B79: =+[25]BG!C77 -> Cút 90 độ 1200x1000R1000. Bao gồm nhân công lắp đặt, phụ kiện bích nối, zoăng làm kín, kẹp C, bulong+ốc+long đen 1200x1000R1000 90度彎頭含安裝及鏈接法蘭、墊圈、C夾、螺栓螺絲等 | L79: =+[25]BG!L77 -> 個 Cái | M79: =+[25]BG!M77 -> 7 | R79: =Q79*M79 -> 0
B80: =+[25]BG!C78 -> 45°弯头（1500×1000，TDC法兰）+ 304不锈钢防虫网（4–6mm），板厚0.95mm. Cút 45 độ KT: 1500x1000 - TDC+Lưới chắn côn trùng inox 304 (mắt lưới 4-6mm), chiều dày tôn 0,95mm | L80: =+[25]BG!L78 -> 個 Cái | M80: =+[25]BG!M78 -> 15 | R80: =Q80*M80 -> 0
B81: =+[25]BG!C79 -> Nút ấn khởi động hút khói bằng tay (testing). Bao gồm nhân công lắp đặt, phụ kiện liên kết 手動抽煙啟動按鈕。含安裝及與監控模塊鏈接配件 | L81: =+[25]BG!L79 -> 個 Cái | M81: =+[25]BG!M79 -> 31 | R81: =Q81*M81 -> 0
B82: Chi phí vận chuyển | L82: Lô | M82: 1 | P82: Chưa bao gồm, dự kiến 3% | R82: =Q82*M82 -> 0
B83: Chi phí kiểm định | L83: Lô | M83: 1 | P83: đã bao gồm | R83: =Q83*M83 -> 0
A86: Total/ Tổng Trước thuế | O86: =SUM(O15:O85) -> 2.4069867e+09 | R86: =SUM(R15:R85) -> 2478842000
A87: VAT 8% | O87: =O86*0.08 -> 1.9255894e+08
A88: Total Amount (including VAT 8%)/ Tổng sau thuế | O88: =SUM(O86:O87) -> 2.5995457e+09
B90: - Ghi chú : | N90: XÁC NHẬN ĐẶT HÀNG
B91: * Thời hạn báo giá: Báo giá có giá trị trong vòng 07 ngày kể từ ngày báo.
B92: * Thời gian giao hàng: theo thực tế từng đơn hàng
B93: - Van gió & Phụ kiện : Tôn Hoa Sen Z08/Z18
B94: - Cửa gió và Phụ kiện : Nhôm A6063 T5 - Sơn Tĩnh điện mầu trắng .
B95: ĐIỀU KHOẢN THANH TOÁN VÀ GIAO HÀNG
B96: * Điều kiện thanh toán: Tạm ứng 30%, Thanh toán bằng bảo lãnh thanh toán thời hạn 35 ngày
B97: Xin vui lòng liên hệ với chúng tôi nếu quý khách có cần thêm các yêu cầu nào khác.
B98: Đơn vị thụ hưởng :
B99: Công ty Cổ phần tập đoàn quốc tế Sland
B100: Trụ sở: Thôn 1B, xã Nam Phù, TP Hà Nội
B101: - Số tài khoản : 1359 666 888
B102: - Mở tại : Ngân hàng TMCP Á Châu ( ACB ) chi nhánh Hà Nội
