Workbook
Name \a: #N/A
Name \N: #REF!
Name \s: #N/A
Name \Z: #REF!
Name _: #REF!
Name _??: NA()
Name _??_1: NA()
Name _??_1_1: NA()
Name _??_1_2: NA()
Name _??_1_3: NA()
Name _??_1_4: NA()
Name _??_1_5: NA()
Name _??_6: NA()
Name _??_7: NA()
Name _??_9: NA()
Name _?1: NA()
Name _?1_1: NA()
Name _?1_1_1: NA()
Name _?1_1_2: NA()
Name _?1_1_3: NA()
Name _?1_1_4: NA()
Name _?1_1_5: NA()
Name _?1_6: NA()
Name _?1_7: NA()
Name _?1_9: NA()
Name _?271: NA()
Name _?271_1: NA()
Name _?271_1_1: NA()
Name _?271_1_2: NA()
Name _?271_1_3: NA()
Name _?271_1_4: NA()
Name _?271_1_5: NA()
Name _?271_6: NA()
Name _?271_7: NA()
Name _?271_9: NA()
Name ____DIV3: #REF!
Name ____DIV4: #REF!
Name ___DIV10: #REF!
Name ___DIV15: #REF!
Name ___DIV3: #REF!
Name ___DIV4: #REF!
Name ___DIV5: #REF!
Name ___DIV7: #REF!
Name ___DIV8: #REF!
Name ___DIV9: #REF!
Name ___TB1: #REF!
Name __10: #REF!
Name __12: #REF!
Name __14: #REF!
Name __16: #REF!
Name __18: #REF!
Name __20: #REF!
Name __22: #REF!
Name __24: #REF!
Name __26: #REF!
Name __28: #REF!
Name __30: #REF!
Name __32: #REF!
Name __34: #REF!
Name __36: #REF!

Sheet BG Đơn Cánh ĐC FSLF 24V
C2: CÔNG TY CỔ PHẦN TẬP ĐOÀN QUỐC TẾ SLAND
C3: VPGD: SỐ 49, Ngõ 1295 Giải Phóng, Phường Hoàng Mai, TP Hà Nội
C4: Nhà máy: Thôn Nhân Hiền - xã Thường Tín - TP Hà Nội
C5: Hotline: 082 5577 999
A6: BẢNG BÁO GIÁ (PHƯƠNG ÁN 1: VAN MFD ĐƠN CÁNH - ĐỘNG CƠ BELIMO FSLF24V)
A7: Khách hàng : | M7: Số hiệu
A8: Địa chỉ : | M8: PT Kinh doanh
A9: Người nhận : | M9: Điện thoại
A10: Email: | C10: Số điện thoại : | M10: Dự án
A11: STT | B11: Danh mục sản phẩm | C11: Model | D11: Thương hiệu | E11: Kích thước (mm) | I11: Modul | J11: L | K11: Độ dày (mm) | L11: Unit Đơn vị | M11: Q'ty Số lượng | N11: Đơn Giá (VNĐ) | O11: Total price Thành tiền | P11: Remarks Ghi chú
E12: A1 | F12: A2 | G12: B1 | H12: B2
E13: Face size | G13: Neck size
B14: HỆ THỐNG HÚT KHÓI HẦM XE, HÚT KHÓI SỰ CỐ
A15: 1 | B15: Canvas loại chống cháy cho quạt TAHK | C15: CANVAS | D15: SWIND | E15: Ø | F15: 1000 | J15: 200 | L15: cái | M15: 15 | N15: =ROUND('00_TONG_HOP_BAO_GIA'!Q2, 0) | O15: =N15*M15 | P15: Khớp nối mềm vải bạt chống cháy
A16: 2 | B16: Canvas loại chống cháy cho quạt TAHK | C16: CANVAS | D16: SWIND | E16: Ø | F16: 900 | J16: 200 | L16: cái | M16: 40 | N16: =ROUND('00_TONG_HOP_BAO_GIA'!Q3, 0) | O16: =N16*M16 | P16: Khớp nối mềm vải bạt chống cháy
A17: 3 | B17: Canvas loại chống cháy cho quạt TAHK | C17: CANVAS | D17: SWIND | E17: Ø | F17: 800 | J17: 200 | L17: cái | M17: 40 | N17: =ROUND('00_TONG_HOP_BAO_GIA'!Q4, 0) | O17: =N17*M17 | P17: Khớp nối mềm vải bạt chống cháy
A18: 4 | B18: Canvas loại chống cháy cho quạt TAHK | C18: CANVAS | D18: SWIND | E18: Ø | F18: 710 | J18: 200 | L18: cái | M18: 16 | N18: =ROUND('00_TONG_HOP_BAO_GIA'!Q5, 0) | O18: =N18*M18 | P18: Khớp nối mềm vải bạt chống cháy
A19: 5 | B19: Canvas loại chống cháy cho quạt TAHK | C19: CANVAS | D19: SWIND | E19: Ø | F19: 560 | J19: 200 | L19: cái | M19: 16 | N19: =ROUND('00_TONG_HOP_BAO_GIA'!Q6, 0) | O19: =N19*M19 | P19: Khớp nối mềm vải bạt chống cháy
A20: 6 | B20: Canvas loại thường cho quạt thông gió | C20: CANVAS | D20: SWIND | E20: Ø | F20: 1000 | J20: 200 | L20: cái | M20: 32 | N20: =ROUND('00_TONG_HOP_BAO_GIA'!Q7, 0) | O20: =N20*M20 | P20: Khớp nối mềm vải bạt chống cháy
A21: 7 | B21: Canvas loại thường cho quạt thông gió | C21: CANVAS | D21: SWIND | E21: Ø | F21: 560 | J21: 200 | L21: cái | M21: 24 | N21: =ROUND('00_TONG_HOP_BAO_GIA'!Q8, 0) | O21: =N21*M21 | P21: Khớp nối mềm vải bạt chống cháy
A22: 8 | B22: Van 1 chiều NRD 1250x1250 (EI60) | C22: NRD | D22: SWIND | E22: 1250 | F22: 1250 | G22: 625 | H22: 1250 | I22: 2 | J22: 200 | K22: 1.15 | L22: Cái | M22: 6 | N22: =ROUND('00_TONG_HOP_BAO_GIA'!Q9, 0) | O22: =N22*M22 | P22: Van 1 chiều bọc tấm cách nhiệt dày 10mm KHS
A23: 9 | B23: Van 1 chiều NRD 1700x600 (EI60) | C23: NRD | D23: SWIND | E23: 1700 | F23: 600 | G23: 850 | H23: 600 | I23: 2 | J23: 200 | K23: 0.95 | L23: Cái | M23: 2 | N23: =ROUND('00_TONG_HOP_BAO_GIA'!Q10, 0) | O23: =N23*M23 | P23: Van 1 chiều bọc tấm cách nhiệt dày 10mm KHS
A24: 10 | B24: Van 1 chiều NRD 1200x350 (EI60) | C24: NRD | D24: SWIND | E24: 1200 | F24: 350 | G24: 600 | H24: 350 | I24: 2 | J24: 200 | K24: 0.75 | L24: Cái | M24: 1 | N24: =ROUND('00_TONG_HOP_BAO_GIA'!Q11, 0) | O24: =N24*M24 | P24: Van 1 chiều bọc tấm cách nhiệt dày 10mm KHS
A25: 11 | B25: Van ngăn cháy MFD 1250x1250 (EI60) | C25: SWIND-1.02-MFD-EI90 | D25: SWIND | E25: 1250 | F25: 1250 | G25: 1250 | H25: 625 | I25: 2 | J25: 200 | K25: 1.15 | L25: Cái | M25: 6 | N25: =ROUND(('00_TONG_HOP_BAO_GIA'!Q12-7400000)*0.450035+7400000, 0) | O25: =N25*M25 | P25: - Van chống cháy động cơ - Tiêu chuẩn EI 90 - 2 đầu bích TDC - Gắn kèm động cơ ON-OFF 3.5Nm, 24V (Type: đóng mở nhanh) BELIMO - Model: FSLF24V US - Sản xuất theo BCTN số 4752/VLXD-TBMT - Chia 2 modul khi sản xuất
A26: 12 | B26: Van ngăn cháy MFD 1700x600 (EI60) | C26: SWIND-1.02-MFD-EI90 | D26: SWIND | E26: 1700 | F26: 600 | G26: 850 | H26: 600 | I26: 2 | J26: 200 | K26: 1.15 | L26: Cái | M26: 2 | N26: =ROUND(('00_TONG_HOP_BAO_GIA'!Q13-7400000)*0.564159+7400000, 0) | O26: =N26*M26 | P26: - Van chống cháy động cơ - Tiêu chuẩn EI 90 - 2 đầu bích TDC - Gắn kèm động cơ ON-OFF 3.5Nm, 24V (Type: đóng mở nhanh) BELIMO - Model: FSLF24V US - Sản xuất theo BCTN số 4752/VLXD-TBMT - Chia 2 modul khi sản xuất
A27: 13 | B27: Van ngăn cháy MFD 1200x350 (EI60) | C27: SWIND-1.02-MFD-EI90 | D27: SWIND | E27: 1200 | F27: 350 | J27: 200 | K27: 1.15 | L27: Cái | M27: 1 | N27: =ROUND(('00_TONG_HOP_BAO_GIA'!Q14-3700000)*0.721030+3700000, 0) | O27: =N27*M27 | P27: - Van chống cháy động cơ - Tiêu chuẩn EI 90 - 2 đầu bích TDC - Gắn kèm động cơ ON-OFF 3.5Nm, 24V (Type: đóng mở nhanh) BELIMO - Model: FSLF24V US - Sản xuất theo BCTN số 4752/VLXD-TBMT
A28: 14 | B28: Van ngăn cháy MFD 950x400 (EI30) | C28: SWIND-1.02-MFD-EI90 | D28: SWIND | E28: 950 | F28: 400 | J28: 200 | K28: 1.15 | L28: Cái | M28: 3 | N28: =ROUND(('00_TONG_HOP_BAO_GIA'!Q15-3700000)*0.718482+3700000, 0) | O28: =N28*M28 | P28: - Van chống cháy động cơ - Tiêu chuẩn EI 90 - 2 đầu bích TDC - Gắn kèm động cơ ON-OFF 3.5Nm, 24V (Type: đóng mở nhanh) BELIMO - Model: FSLF24V US - Sản xuất theo BCTN số 4752/VLXD-TBMT
A29: 15 | B29: Van ngăn cháy MFD 950x500 (EI30) | C29: SWIND-1.02-MFD-EI90 | D29: SWIND | E29: 950 | F29: 500 | J29: 200 | K29: 1.15 | L29: Cái | M29: 6 | N29: =ROUND(('00_TONG_HOP_BAO_GIA'!Q16-3700000)*0.571537+3700000, 0) | O29: =N29*M29 | P29: - Van chống cháy động cơ - Tiêu chuẩn EI 90 - 2 đầu bích TDC - Gắn kèm động cơ ON-OFF 3.5Nm, 24V (Type: đóng mở nhanh) BELIMO - Model: FSLF24V US - Sản xuất theo BCTN số 4752/VLXD-TBMT
A30: 16 | B30: Van ngăn cháy MFD 950x200 (EI30) | C30: SWIND-1.02-MFD-EI90 | D30: SWIND | E30: 950 | F30: 200 | J30: 200 | K30: 1.15 | L30: Cái | M30: 9 | N30: =ROUND(('00_TONG_HOP_BAO_GIA'!Q17-3700000)*1.000000+3700000, 0) | O30: =N30*M30 | P30: - Van chống cháy động cơ - Tiêu chuẩn EI 90 - 2 đầu bích TDC - Gắn kèm động cơ ON-OFF 3.5Nm, 24V (Type: đóng mở nhanh) BELIMO - Model: FSLF24V US - Sản xuất theo BCTN số 4752/VLXD-TBMT
A31: 17 | B31: Van ngăn cháy MFD 950x300 (EI30) | C31: SWIND-1.02-MFD-EI90 | D31: SWIND | E31: 950 | F31: 300 | J31: 200 | K31: 1.15 | L31: Cái | M31: 12 | N31: =ROUND(('00_TONG_HOP_BAO_GIA'!Q18-3700000)*0.734150+3700000, 0) | O31: =N31*M31 | P31: - Van chống cháy động cơ - Tiêu chuẩn EI 90 - 2 đầu bích TDC - Gắn kèm động cơ ON-OFF 3.5Nm, 24V (Type: đóng mở nhanh) BELIMO - Model: FSLF24V US - Sản xuất theo BCTN số 4752/VLXD-TBMT
A32: 18 | B32: Van chỉnh lưu lượng VCD 2000x500 (EI60) | C32: VCD | D32: SWIND | E32: 2000 | F32: 500 | G32: 1000 | H32: 500 | I32: 2 | J32: 200 | K32: 1.15 | L32: Cái | M32: 1 | N32: =ROUND('00_TONG_HOP_BAO_GIA'!Q19, 0) | O32: =N32*M32 | P32: Van tay gạt bọc tấm cách nhiệt KHS 10mm
A33: 19 | B33: Van chỉnh lưu lượng VCD 1300x400 (EI60) | C33: VCD | D33: SWIND | E33: 1300 | F33: 400 | G33: 650 | H33: 400 | I33: 2 | J33: 200 | K33: 0.75 | L33: Cái | M33: 2 | N33: =ROUND('00_TONG_HOP_BAO_GIA'!Q20, 0) | O33: =N33*M33 | P33: Van tay gạt bọc tấm cách nhiệt KHS 10mm
A34: 20 | B34: Van chỉnh lưu lượng VCD 1600x400 (EI60) | C34: VCD | D34: SWIND | E34: 1600 | F34: 400 | G34: 800 | H34: 400 | I34: 2 | J34: 200 | K34: 0.95 | L34: Cái | M34: 1 | N34: =ROUND('00_TONG_HOP_BAO_GIA'!Q21, 0) | O34: =N34*M34 | P34: Van tay gạt bọc tấm cách nhiệt KHS 10mm
A35: 21 | B35: Van chỉnh lưu lượng VCD 1600x450 (EI60) | C35: VCD | D35: SWIND | E35: 1600 | F35: 450 | G35: 800 | H35: 450 | I35: 2 | J35: 200 | K35: 0.95 | L35: Cái | M35: 1 | N35: =ROUND('00_TONG_HOP_BAO_GIA'!Q22, 0) | O35: =N35*M35 | P35: Van tay gạt bọc tấm cách nhiệt KHS 10mm
A36: 22 | B36: Van chỉnh lưu lượng VCD 900x350 (EI60) | C36: VCD | D36: SWIND | E36: 900 | F36: 350 | J36: 200 | K36: 0.95 | L36: Cái | M36: 5 | N36: =ROUND('00_TONG_HOP_BAO_GIA'!Q23, 0) | O36: =N36*M36 | P36: Van tay gạt bọc tấm cách nhiệt KHS 10mm
A37: 23 | B37: Van chỉnh lưu lượng VCD 600x300 (EI60) | C37: VCD | D37: SWIND | E37: 600 | F37: 300 | J37: 200 | K37: 0.75 | L37: Cái | M37: 1 | N37: =ROUND('00_TONG_HOP_BAO_GIA'!Q24, 0) | O37: =N37*M37 | P37: Van tay gạt bọc tấm cách nhiệt KHS 10mm
A38: 24 | B38: Miệng gió hút khói EAG 600x300+OBD | C38: ECG+O | D38: SWIND | E38: 600 | F38: 300 | G38: 550 | H38: 250 | L38: Cái | M38: 112 | N38: =ROUND('00_TONG_HOP_BAO_GIA'!Q25, 0) | O38: =N38*M38 | P38: Cửa nan sọt trứng kèm van OBD
A39: 25 | B39: Miệng gió hút khói SEG 1200x600+OBD | C39: SDG+O | D39: SWIND | E39: 1200 | F39: 600 | G39: 1150 | H39: 550 | L39: Cái | M39: 2 | N39: =ROUND('00_TONG_HOP_BAO_GIA'!Q26, 0) | O39: =N39*M39 | P39: Cửa nan bầu dục 1 lớp kèm van OBD
A40: 26 | B40: Miệng gió hút khói SEAG 1000x600+OBD | C40: SDG+O | D40: SWIND | E40: 1000 | F40: 600 | G40: 950 | H40: 550 | L40: Cái | M40: 52 | N40: =ROUND('00_TONG_HOP_BAO_GIA'!Q27, 0) | O40: =N40*M40 | P40: Cửa nan bầu dục 1 lớp kèm van OBD
A41: 27 | B41: Louver EAL 7500x500+IS | C41: WL+N | D41: SWIND | E41: 7500 | F41: 500 | G41: 7450 | H41: 450 | L41: Cái | M41: 1 | N41: =ROUND('00_TONG_HOP_BAO_GIA'!Q28, 0) | O41: =N41*M41 | P41: Louver nan Z + LCCT
A42: 28 | B42: Louver EAL 4500x500+IS | C42: WL+N | D42: SWIND | E42: 4500 | F42: 500 | G42: 4450 | H42: 450 | L42: Cái | M42: 4 | N42: =ROUND('00_TONG_HOP_BAO_GIA'!Q29, 0) | O42: =N42*M42 | P42: Louver nan Z + LCCT
A43: 29 | B43: Louver EAL 4000x500+IS | C43: WL+N | D43: SWIND | E43: 4000 | F43: 500 | G43: 3950 | H43: 450 | L43: Cái | M43: 4 | N43: =ROUND('00_TONG_HOP_BAO_GIA'!Q30, 0) | O43: =N43*M43 | P43: Louver nan Z + LCCT
A44: 30 | B44: Louver EAL 3000x500+IS | C44: WL+N | D44: SWIND | E44: 3000 | F44: 500 | G44: 2950 | H44: 450 | L44: Cái | M44: 1 | N44: =ROUND('00_TONG_HOP_BAO_GIA'!Q31, 0) | O44: =N44*M44 | P44: Louver nan Z + LCCT
A45: 31 | B45: Louver EAL 2750x750+IS | C45: WL+N | D45: SWIND | E45: 2750 | F45: 750 | G45: 2700 | H45: 700 | L45: Cái | M45: 2 | N45: =ROUND('00_TONG_HOP_BAO_GIA'!Q32, 0) | O45: =N45*M45 | P45: Louver nan Z + LCCT
A46: 32 | B46: Box miệng gió 600x300 | C46: BOX | D46: SWIND / Phương Nam | E46: 600 | F46: 300 | J46: 200 | K46: 0.75 | L46: Cái | M46: 112 | N46: =ROUND('00_TONG_HOP_BAO_GIA'!Q33, 0) | O46: =N46*M46 | P46: Box miệng gió tôn mạ kẽm Phương Nam
A47: 33 | B47: Box miệng gió 1200x600 | C47: BOX | D47: SWIND / Phương Nam | E47: 1200 | F47: 600 | J47: 200 | K47: 0.75 | L47: Cái | M47: 2 | N47: =ROUND('00_TONG_HOP_BAO_GIA'!Q34, 0) | O47: =N47*M47 | P47: Box miệng gió tôn mạ kẽm Phương Nam
A48: 34 | B48: Box miệng gió 10006300 | C48: BOX | D48: SWIND / Phương Nam | E48: 1000 | F48: 300 | J48: 200 | K48: 0.75 | L48: Cái | M48: 52 | N48: =ROUND('00_TONG_HOP_BAO_GIA'!Q35, 0) | O48: =N48*M48 | P48: Box miệng gió tôn mạ kẽm Phương Nam
A49: 35 | B49: Vật tư phụ, phụ kiện | L49: Lô | M49: 1 | N49: =ROUND('00_TONG_HOP_BAO_GIA'!Q36, 0) | O49: =N49*M49 | P49: Hạng mục phụ trợ / Nhà thầu tự thực hiện
B50: Ống thông gió và phụ kiện, box miệng gió
A51: 36 | B51: Tole 0.75mm phủ lớp mạ kẽm Z180 | C51: DUCT-TDF | D51: SWIND / Phương Nam | K51: 0.75 | L51: m2 | M51: 2633.4 | N51: =ROUND('00_TONG_HOP_BAO_GIA'!Q37, 0) | O51: =N51*M51 | P51: Ống gió tôn mạ kẽm Phương Nam dày 0.75mm
A52: 37 | B52: Tole 0.95mm phủ lớp mạ kẽm Z180 | C52: DUCT-TDF | D52: SWIND / Phương Nam | K52: 0.95 | L52: m2 | M52: 1291.1 | N52: =ROUND('00_TONG_HOP_BAO_GIA'!Q38, 0) | O52: =N52*M52 | P52: Ống gió tôn mạ kẽm Phương Nam dày 0.95mm
A53: 38 | B53: Tole 1.15mm phủ lớp mạ kẽm Z180 | C53: DUCT-TDF | D53: SWIND / Phương Nam | K53: 1.15 | L53: m2 | M53: 3070.55 | N53: =ROUND('00_TONG_HOP_BAO_GIA'!Q39, 0) | O53: =N53*M53 | P53: Ống gió tôn mạ kẽm Phương Nam dày 1.15mm
A54: 39 | B54: Tole ZAM 1.15mm | C54: DUCT-TDF | D54: SWIND / Phương Nam | K54: 1.15 | L54: m2 | M54: 138 | N54: =ROUND('00_TONG_HOP_BAO_GIA'!Q40, 0) | O54: =N54*M54 | P54: Ống gió tôn mạ kẽm Phương Nam dày 1.15mm
A55: 40 | B55: Lưới bảo vệ | D55: SWIND | L55: cái | M55: 3 | N55: =ROUND('00_TONG_HOP_BAO_GIA'!Q41, 0) | O55: =N55*M55 | P55: Hạng mục phụ trợ / Nhà thầu tự thực hiện
A56: 41 | B56: Lớp chống cháy EI30 | C56: DIỆN TÍCH TÍNH THEO KÍCH THƯỚC HÌNH HỌC (HOÀN THIỆN) | D56: SWIND | L56: m2 | M56: 3621.25 | N56: =ROUND('00_TONG_HOP_BAO_GIA'!Q42, 0) | O56: =N56*M56 | P56: Bọc chống cháy ống gió chuẩn EI
A57: 42 | B57: Lớp chống cháy EI60 | C57: DIỆN TÍCH TÍNH THEO KÍCH THƯỚC HÌNH HỌC (HOÀN THIỆN) | D57: SWIND | L57: m2 | M57: 2821 | N57: =ROUND('00_TONG_HOP_BAO_GIA'!Q43, 0) | O57: =N57*M57 | P57: Bọc chống cháy ống gió chuẩn EI
A58: 43 | B58: Vật tư phụ, phụ kiện | L58: Lô | M58: 1 | N58: =ROUND('00_TONG_HOP_BAO_GIA'!Q44, 0) | O58: =N58*M58 | P58: Hạng mục phụ trợ / Nhà thầu tự thực hiện
B59: HỆ THỐNG TẠO ÁP
A60: 44 | B60: Van 1 chiều NRD 300x200 (EI60) | C60: NRD | D60: SWIND | E60: 300 | F60: 200 | J60: 200 | K60: 0.75 | L60: Cái | M60: 1 | N60: =ROUND('00_TONG_HOP_BAO_GIA'!Q45, 0) | O60: =N60*M60 | P60: Van 1 chiều bọc tấm cách nhiệt dày 10mm KHS
A61: 45 | B61: Van 1 chiều NRD 700x500 (EI60) | C61: NRD | D61: SWIND | E61: 700 | F61: 500 | J61: 200 | K61: 0.95 | L61: Cái | M61: 2 | N61: =ROUND('00_TONG_HOP_BAO_GIA'!Q46, 0) | O61: =N61*M61 | P61: Van 1 chiều bọc tấm cách nhiệt dày 10mm KHS
A62: 46 | B62: Van 1 chiều NRD 700x800 (EI60) | C62: NRD | D62: SWIND | E62: 700 | F62: 800 | J62: 200 | K62: 0.95 | L62: Cái | M62: 2 | N62: =ROUND('00_TONG_HOP_BAO_GIA'!Q47, 0) | O62: =N62*M62 | P62: Van 1 chiều bọc tấm cách nhiệt dày 10mm KHS
A63: 47 | B63: Van 1 chiều NRD 250X200(EI60) | C63: NRD | D63: SWIND | E63: 250 | F63: 200 | J63: 200 | K63: 0.75 | L63: Cái | M63: 1 | N63: =ROUND('00_TONG_HOP_BAO_GIA'!Q48, 0) | O63: =N63*M63 | P63: Van 1 chiều bọc tấm cách nhiệt dày 10mm KHS
A64: 48 | B64: Van 1 chiều NRD 900x400 (EI60) | C64: NRD | D64: SWIND | E64: 900 | F64: 400 | J64: 200 | K64: 0.95 | L64: Cái | M64: 2 | N64: =ROUND('00_TONG_HOP_BAO_GIA'!Q49, 0) | O64: =N64*M64 | P64: Van 1 chiều bọc tấm cách nhiệt dày 10mm KHS
A65: 49 | B65: Van 1 chiều NRD 300x300 (EI60) | C65: NRD | D65: SWIND | E65: 300 | F65: 300 | J65: 200 | K65: 0.75 | L65: Cái | M65: 1 | N65: =ROUND('00_TONG_HOP_BAO_GIA'!Q50, 0) | O65: =N65*M65 | P65: Van 1 chiều bọc tấm cách nhiệt dày 10mm KHS
A66: 50 | B66: Van 1 chiều NRD 350x250 (EI60) | C66: NRD | D66: SWIND | E66: 350 | F66: 250 | J66: 200 | K66: 0.75 | L66: Cái | M66: 1 | N66: =ROUND('00_TONG_HOP_BAO_GIA'!Q51, 0) | O66: =N66*M66 | P66: Van 1 chiều bọc tấm cách nhiệt dày 10mm KHS
A67: 51 | B67: Van 1 chiều NRD 350x150 (EI60) | C67: NRD | D67: SWIND | E67: 350 | F67: 150 | J67: 200 | K67: 0.75 | L67: Cái | M67: 1 | N67: =ROUND('00_TONG_HOP_BAO_GIA'!Q52, 0) | O67: =N67*M67 | P67: Van 1 chiều bọc tấm cách nhiệt dày 10mm KHS
A68: 52 | B68: Van ngăn cháy MFD 350x200 (EI60) | C68: SWIND-1.02-MFD-EI90 | D68: SWIND | E68: 350 | F68: 200 | J68: 200 | K68: 1.15 | L68: Cái | M68: 1 | N68: =ROUND(('00_TONG_HOP_BAO_GIA'!Q53-3700000)*0.772679+3700000, 0) | O68: =N68*M68 | P68: - Van chống cháy động cơ - Tiêu chuẩn EI 90 - 2 đầu bích TDC - Gắn kèm động cơ ON-OFF 3.5Nm, 24V (Type: đóng mở nhanh) BELIMO - Model: FSLF24V US - Sản xuất theo BCTN số 4752/VLXD-TBMT
A69: 53 | B69: Van ngăn cháy MFD 700x500 (EI60) | C69: SWIND-1.02-MFD-EI90 | D69: SWIND | E69: 700 | F69: 500 | J69: 200 | K69: 1.15 | L69: Cái | M69: 2 | N69: =ROUND(('00_TONG_HOP_BAO_GIA'!Q54-3700000)*0.586441+3700000, 0) | O69: =N69*M69 | P69: - Van chống cháy động cơ - Tiêu chuẩn EI 90 - 2 đầu bích TDC - Gắn kèm động cơ ON-OFF 3.5Nm, 24V (Type: đóng mở nhanh) BELIMO - Model: FSLF24V US - Sản xuất theo BCTN số 4752/VLXD-TBMT
A70: 54 | B70: Van ngăn cháy MFD 700x800 (EI60) | C70: SWIND-1.02-MFD-EI90 | D70: SWIND | E70: 700 | F70: 800 | J70: 200 | K70: 1.15 | L70: Cái | M70: 2 | N70: =ROUND(('00_TONG_HOP_BAO_GIA'!Q55-3700000)*0.556873+3700000, 0) | O70: =N70*M70 | P70: - Van chống cháy động cơ - Tiêu chuẩn EI 90 - 2 đầu bích TDC - Gắn kèm động cơ ON-OFF 3.5Nm, 24V (Type: đóng mở nhanh) BELIMO - Model: FSLF24V US - Sản xuất theo BCTN số 4752/VLXD-TBMT
A71: 55 | B71: Van ngăn cháy MFD 1200x600 (EI60) | C71: SWIND-1.02-MFD-EI90 | D71: SWIND | E71: 1200 | F71: 600 | J71: 200 | K71: 1.15 | L71: Cái | M71: 2 | N71: =ROUND(('00_TONG_HOP_BAO_GIA'!Q56-3700000)*0.549333+3700000, 0) | O71: =N71*M71 | P71: - Van chống cháy động cơ - Tiêu chuẩn EI 90 - 2 đầu bích TDC - Gắn kèm động cơ ON-OFF 3.5Nm, 24V (Type: đóng mở nhanh) BELIMO - Model: FSLF24V US - Sản xuất theo BCTN số 4752/VLXD-TBMT
A72: 56 | B72: Van ngăn cháy MFD 250X200 (EI60) | C72: SWIND-1.02-MFD-EI90 | D72: SWIND | E72: 250 | F72: 200 | J72: 200 | K72: 1.15 | L72: Cái | M72: 2 | N72: =ROUND(('00_TONG_HOP_BAO_GIA'!Q57-3700000)*0.778095+3700000, 0) | O72: =N72*M72 | P72: - Van chống cháy động cơ - Tiêu chuẩn EI 90 - 2 đầu bích TDC - Gắn kèm động cơ ON-OFF 3.5Nm, 24V (Type: đóng mở nhanh) BELIMO - Model: FSLF24V US - Sản xuất theo BCTN số 4752/VLXD-TBMT
A73: 57 | B73: Van ngăn cháy MFD 900x400 (EI60) | C73: SWIND-1.02-MFD-EI90 | D73: SWIND | E73: 900 | F73: 400 | J73: 200 | K73: 1.15 | L73: Cái | M73: 5 | N73: =ROUND(('00_TONG_HOP_BAO_GIA'!Q58-3700000)*0.719706+3700000, 0) | O73: =N73*M73 | P73: - Van chống cháy động cơ - Tiêu chuẩn EI 90 - 2 đầu bích TDC - Gắn kèm động cơ ON-OFF 3.5Nm, 24V (Type: đóng mở nhanh) BELIMO - Model: FSLF24V US - Sản xuất theo BCTN số 4752/VLXD-TBMT
A74: 58 | B74: Van ngăn cháy MFD 900x400 (EI120) | C74: SWIND-1.02-MFD-EI90 | D74: SWIND | E74: 900 | F74: 400 | J74: 200 | K74: 1.15 | L74: Cái | M74: 5 | N74: =ROUND(('00_TONG_HOP_BAO_GIA'!Q59-3700000)*0.719706+3700000, 0) | O74: =N74*M74 | P74: - Van chống cháy động cơ - Tiêu chuẩn EI 90 - 2 đầu bích TDC - Gắn kèm động cơ ON-OFF 3.5Nm, 24V (Type: đóng mở nhanh) BELIMO - Model: FSLF24V US - Sản xuất theo BCTN số 4752/VLXD-TBMT
A75: 59 | B75: Van ngăn cháy MFD 300x300 (EI60) | C75: SWIND-1.02-MFD-EI90 | D75: SWIND | E75: 300 | F75: 300 | J75: 200 | K75: 1.15 | L75: Cái | M75: 6 | N75: =ROUND(('00_TONG_HOP_BAO_GIA'!Q60-3700000)*0.760721+3700000, 0) | O75: =N75*M75 | P75: - Van chống cháy động cơ - Tiêu chuẩn EI 90 - 2 đầu bích TDC - Gắn kèm động cơ ON-OFF 3.5Nm, 24V (Type: đóng mở nhanh) BELIMO - Model: FSLF24V US - Sản xuất theo BCTN số 4752/VLXD-TBMT
A76: 60 | B76: Van ngăn cháy MFD 250x200 (EI60) | C76: SWIND-1.02-MFD-EI90 | D76: SWIND | E76: 250 | F76: 200 | J76: 200 | K76: 1.15 | L76: Cái | M76: 1 | N76: =ROUND(('00_TONG_HOP_BAO_GIA'!Q61-3700000)*0.778095+3700000, 0) | O76: =N76*M76 | P76: - Van chống cháy động cơ - Tiêu chuẩn EI 90 - 2 đầu bích TDC - Gắn kèm động cơ ON-OFF 3.5Nm, 24V (Type: đóng mở nhanh) BELIMO - Model: FSLF24V US - Sản xuất theo BCTN số 4752/VLXD-TBMT
A77: 61 | B77: Van ngăn cháy MFD 350x200 (EI60) | C77: SWIND-1.02-MFD-EI90 | D77: SWIND | E77: 350 | F77: 200 | J77: 200 | K77: 1.15 | L77: Cái | M77: 1 | N77: =ROUND(('00_TONG_HOP_BAO_GIA'!Q62-3700000)*0.772679+3700000, 0) | O77: =N77*M77 | P77: - Van chống cháy động cơ - Tiêu chuẩn EI 90 - 2 đầu bích TDC - Gắn kèm động cơ ON-OFF 3.5Nm, 24V (Type: đóng mở nhanh) BELIMO - Model: FSLF24V US - Sản xuất theo BCTN số 4752/VLXD-TBMT
A78: 62 | B78: Van ngăn cháy MFD 350x150 (EI60) | C78: SWIND-1.02-MFD-EI90 | D78: SWIND | E78: 350 | F78: 150 | J78: 200 | K78: 1.15 | L78: Cái | M78: 3 | N78: =ROUND(('00_TONG_HOP_BAO_GIA'!Q63-3700000)*0.783278+3700000, 0) | O78: =N78*M78 | P78: - Van chống cháy động cơ - Tiêu chuẩn EI 90 - 2 đầu bích TDC - Gắn kèm động cơ ON-OFF 3.5Nm, 24V (Type: đóng mở nhanh) BELIMO - Model: FSLF24V US - Sản xuất theo BCTN số 4752/VLXD-TBMT
A79: 63 | B79: Van ngăn cháy MFD 1000x300 (EI60) | C79: SWIND-1.02-MFD-EI90 | D79: SWIND | E79: 1000 | F79: 300 | J79: 200 | K79: 1.15 | L79: Cái | M79: 2 | N79: =ROUND(('00_TONG_HOP_BAO_GIA'!Q64-3700000)*0.733184+3700000, 0) | O79: =N79*M79 | P79: - Van chống cháy động cơ - Tiêu chuẩn EI 90 - 2 đầu bích TDC - Gắn kèm động cơ ON-OFF 3.5Nm, 24V (Type: đóng mở nhanh) BELIMO - Model: FSLF24V US - Sản xuất theo BCTN số 4752/VLXD-TBMT
A80: 64 | B80: Van ngăn cháy MFD 850x300 (EI60) | C80: SWIND-1.02-MFD-EI90 | D80: SWIND | E80: 850 | F80: 300 | J80: 200 | K80: 1.15 | L80: Cái | M80: 2 | N80: =ROUND(('00_TONG_HOP_BAO_GIA'!Q65-3700000)*0.736328+3700000, 0) | O80: =N80*M80 | P80: - Van chống cháy động cơ - Tiêu chuẩn EI 90 - 2 đầu bích TDC - Gắn kèm động cơ ON-OFF 3.5Nm, 24V (Type: đóng mở nhanh) BELIMO - Model: FSLF24V US - Sản xuất theo BCTN số 4752/VLXD-TBMT
A81: 65 | B81: Van ngăn cháy MFD 800x350 (EI60) | C81: SWIND-1.02-MFD-EI90 | D81: SWIND | E81: 800 | F81: 350 | J81: 200 | K81: 1.15 | L81: Cái | M81: 3 | N81: =ROUND(('00_TONG_HOP_BAO_GIA'!Q66-3700000)*0.729370+3700000, 0) | O81: =N81*M81 | P81: - Van chống cháy động cơ - Tiêu chuẩn EI 90 - 2 đầu bích TDC - Gắn kèm động cơ ON-OFF 3.5Nm, 24V (Type: đóng mở nhanh) BELIMO - Model: FSLF24V US - Sản xuất theo BCTN số 4752/VLXD-TBMT
A82: 66 | B82: Van ngăn cháy MFD 2000x650 (EI120) | C82: SWIND-1.02-MFD-EI90 | D82: SWIND | E82: 2000 | F82: 650 | G82: 1000 | H82: 650 | I82: 2 | J82: 200 | K82: 1.15 | L82: Cái | M82: 1 | N82: =ROUND(('00_TONG_HOP_BAO_GIA'!Q67-7400000)*0.551636+7400000, 0) | O82: =N82*M82 | P82: - Van chống cháy động cơ - Tiêu chuẩn EI 90 - 2 đầu bích TDC - Gắn kèm động cơ ON-OFF 3.5Nm, 24V (Type: đóng mở nhanh) BELIMO - Model: FSLF24V US - Sản xuất theo BCTN số 4752/VLXD-TBMT - Chia 2 modul khi sản xuất
A83: 67 | B83: Van ngăn cháy MFD 1000x350 (EI120) | C83: SWIND-1.02-MFD-EI90 | D83: SWIND | E83: 1000 | F83: 350 | J83: 200 | K83: 1.15 | L83: Cái | M83: 2 | N83: =ROUND(('00_TONG_HOP_BAO_GIA'!Q68-3700000)*0.724564+3700000, 0) | O83: =N83*M83 | P83: - Van chống cháy động cơ - Tiêu chuẩn EI 90 - 2 đầu bích TDC - Gắn kèm động cơ ON-OFF 3.5Nm, 24V (Type: đóng mở nhanh) BELIMO - Model: FSLF24V US - Sản xuất theo BCTN số 4752/VLXD-TBMT
A84: 68 | B84: Van ngăn cháy MFD 1200x350 (EI120) | C84: SWIND-1.02-MFD-EI90 | D84: SWIND | E84: 1200 | F84: 350 | J84: 200 | K84: 1.15 | L84: Cái | M84: 2 | N84: =ROUND(('00_TONG_HOP_BAO_GIA'!Q69-3700000)*0.721030+3700000, 0) | O84: =N84*M84 | P84: - Van chống cháy động cơ - Tiêu chuẩn EI 90 - 2 đầu bích TDC - Gắn kèm động cơ ON-OFF 3.5Nm, 24V (Type: đóng mở nhanh) BELIMO - Model: FSLF24V US - Sản xuất theo BCTN số 4752/VLXD-TBMT
A85: 69 | B85: Van ngăn cháy MFD 1100x350 (EI120) | C85: SWIND-1.02-MFD-EI90 | D85: SWIND | E85: 1100 | F85: 350 | J85: 200 | K85: 1.15 | L85: Cái | M85: 1 | N85: =ROUND(('00_TONG_HOP_BAO_GIA'!Q70-3700000)*0.722672+3700000, 0) | O85: =N85*M85 | P85: - Van chống cháy động cơ - Tiêu chuẩn EI 90 - 2 đầu bích TDC - Gắn kèm động cơ ON-OFF 3.5Nm, 24V (Type: đóng mở nhanh) BELIMO - Model: FSLF24V US - Sản xuất theo BCTN số 4752/VLXD-TBMT
A86: 70 | B86: Van ngăn cháy MFD 1200x300 (EI60) | C86: SWIND-1.02-MFD-EI90 | D86: SWIND | E86: 1200 | F86: 300 | J86: 200 | K86: 1.15 | L86: Cái | M86: 9 | N86: =ROUND(('00_TONG_HOP_BAO_GIA'!Q71-3700000)*0.729952+3700000, 0) | O86: =N86*M86 | P86: - Van chống cháy động cơ - Tiêu chuẩn EI 90 - 2 đầu bích TDC - Gắn kèm động cơ ON-OFF 3.5Nm, 24V (Type: đóng mở nhanh) BELIMO - Model: FSLF24V US - Sản xuất theo BCTN số 4752/VLXD-TBMT
A87: 71 | B87: Van ngăn cháy MFD 1200x300 (EI120) | C87: SWIND-1.02-MFD-EI90 | D87: SWIND | E87: 1200 | F87: 300 | J87: 200 | K87: 1.15 | L87: Cái | M87: 1 | N87: =ROUND(('00_TONG_HOP_BAO_GIA'!Q72-3700000)*0.729952+3700000, 0) | O87: =N87*M87 | P87: - Van chống cháy động cơ - Tiêu chuẩn EI 90 - 2 đầu bích TDC - Gắn kèm động cơ ON-OFF 3.5Nm, 24V (Type: đóng mở nhanh) BELIMO - Model: FSLF24V US - Sản xuất theo BCTN số 4752/VLXD-TBMT
A88: 72 | B88: Van ngăn cháy MFD 900x350 (EI120) | C88: SWIND-1.02-MFD-EI90 | D88: SWIND | E88: 900 | F88: 350 | J88: 200 | K88: 1.15 | L88: Cái | M88: 13 | N88: =ROUND(('00_TONG_HOP_BAO_GIA'!Q73-3700000)*0.726768+3700000, 0) | O88: =N88*M88 | P88: - Van chống cháy động cơ - Tiêu chuẩn EI 90 - 2 đầu bích TDC - Gắn kèm động cơ ON-OFF 3.5Nm, 24V (Type: đóng mở nhanh) BELIMO - Model: FSLF24V US - Sản xuất theo BCTN số 4752/VLXD-TBMT
A89: 73 | B89: Van ngăn cháy MFD 1150x350 (EI120) | C89: SWIND-1.02-MFD-EI90 | D89: SWIND | E89: 1150 | F89: 350 | J89: 200 | K89: 1.15 | L89: Cái | M89: 12 | N89: =ROUND(('00_TONG_HOP_BAO_GIA'!Q74-3700000)*0.721823+3700000, 0) | O89: =N89*M89 | P89: - Van chống cháy động cơ - Tiêu chuẩn EI 90 - 2 đầu bích TDC - Gắn kèm động cơ ON-OFF 3.5Nm, 24V (Type: đóng mở nhanh) BELIMO - Model: FSLF24V US - Sản xuất theo BCTN số 4752/VLXD-TBMT
A90: 74 | B90: Van ngăn cháy MFD 1200x450 (EI120) | C90: SWIND-1.02-MFD-EI90 | D90: SWIND | E90: 1200 | F90: 450 | J90: 200 | K90: 1.15 | L90: Cái | M90: 1 | N90: =ROUND(('00_TONG_HOP_BAO_GIA'!Q75-3700000)*0.707286+3700000, 0) | O90: =N90*M90 | P90: - Van chống cháy động cơ - Tiêu chuẩn EI 90 - 2 đầu bích TDC - Gắn kèm động cơ ON-OFF 3.5Nm, 24V (Type: đóng mở nhanh) BELIMO - Model: FSLF24V US - Sản xuất theo BCTN số 4752/VLXD-TBMT
A91: 75 | B91: Van ngăn cháy MFD 350x600 (EI120) | C91: SWIND-1.02-MFD-EI90 | D91: SWIND | E91: 350 | F91: 600 | J91: 200 | K91: 1.15 | L91: Cái | M91: 10 | N91: =ROUND(('00_TONG_HOP_BAO_GIA'!Q76-3700000)*0.618120+3700000, 0) | O91: =N91*M91 | P91: - Van chống cháy động cơ - Tiêu chuẩn EI 90 - 2 đầu bích TDC - Gắn kèm động cơ ON-OFF 3.5Nm, 24V (Type: đóng mở nhanh) BELIMO - Model: FSLF24V US - Sản xuất theo BCTN số 4752/VLXD-TBMT
A92: 76 | B92: Van ngăn cháy MFD 1100x350 (EI120) | C92: SWIND-1.02-MFD-EI90 | D92: SWIND | E92: 1100 | F92: 350 | J92: 200 | K92: 1.15 | L92: Cái | M92: 6 | N92: =ROUND(('00_TONG_HOP_BAO_GIA'!Q77-3700000)*0.722672+3700000, 0) | O92: =N92*M92 | P92: - Van chống cháy động cơ - Tiêu chuẩn EI 90 - 2 đầu bích TDC - Gắn kèm động cơ ON-OFF 3.5Nm, 24V (Type: đóng mở nhanh) BELIMO - Model: FSLF24V US - Sản xuất theo BCTN số 4752/VLXD-TBMT
A93: 77 | B93: Van ngăn cháy MFD 1000x350 (EI120) | C93: SWIND-1.02-MFD-EI90 | D93: SWIND | E93: 1000 | F93: 350 | J93: 200 | K93: 1.15 | L93: Cái | M93: 6 | N93: =ROUND(('00_TONG_HOP_BAO_GIA'!Q78-3700000)*0.724564+3700000, 0) | O93: =N93*M93 | P93: - Van chống cháy động cơ - Tiêu chuẩn EI 90 - 2 đầu bích TDC - Gắn kèm động cơ ON-OFF 3.5Nm, 24V (Type: đóng mở nhanh) BELIMO - Model: FSLF24V US - Sản xuất theo BCTN số 4752/VLXD-TBMT
A94: 78 | B94: Van ngăn cháy MFD 800x300 (EI120) | C94: SWIND-1.02-MFD-EI90 | D94: SWIND | E94: 800 | F94: 300 | J94: 200 | K94: 1.15 | L94: Cái | M94: 8 | N94: =ROUND(('00_TONG_HOP_BAO_GIA'!Q79-3700000)*0.737562+3700000, 0) | O94: =N94*M94 | P94: - Van chống cháy động cơ - Tiêu chuẩn EI 90 - 2 đầu bích TDC - Gắn kèm động cơ ON-OFF 3.5Nm, 24V (Type: đóng mở nhanh) BELIMO - Model: FSLF24V US - Sản xuất theo BCTN số 4752/VLXD-TBMT
A95: 79 | B95: Van ngăn cháy MFD 650x400 | C95: SWIND-1.02-MFD-EI90 | D95: SWIND | E95: 650 | F95: 400 | J95: 200 | K95: 1.15 | L95: Cái | M95: 6 | N95: =ROUND(('00_TONG_HOP_BAO_GIA'!Q80-3700000)*0.727762+3700000, 0) | O95: =N95*M95 | P95: - Van chống cháy động cơ - Tiêu chuẩn EI 90 - 2 đầu bích TDC - Gắn kèm động cơ ON-OFF 3.5Nm, 24V (Type: đóng mở nhanh) BELIMO - Model: FSLF24V US - Sản xuất theo BCTN số 4752/VLXD-TBMT
A96: 80 | B96: Van xả áp | C96: VCD | D96: SWIND | J96: 200 | K96: 0.75 | L96: Cái | M96: 6 | N96: =ROUND('00_TONG_HOP_BAO_GIA'!Q81, 0) | O96: =N96*M96 | P96: Van điều chỉnh lưu lượng tay gạt tôn mạ kẽm
A97: 81 | B97: Van chỉnh lưu lượng VCD250x200 (EI60) | C97: VCD | D97: SWIND | E97: 250 | F97: 200 | J97: 200 | K97: 0.75 | L97: Cái | M97: 1 | N97: =ROUND('00_TONG_HOP_BAO_GIA'!Q82, 0) | O97: =N97*M97 | P97: Van tay gạt bọc tấm cách nhiệt KHS 10mm
A98: 82 | B98: Miệng gió tạo áp PAG 900x400+OBD | C98: SDG+O | D98: SWIND | E98: 900 | F98: 400 | G98: 850 | H98: 350 | L98: Cái | M98: 2 | N98: =ROUND('00_TONG_HOP_BAO_GIA'!Q83, 0) | O98: =N98*M98 | P98: Cửa nan bầu dục 1 lớp kèm van OBD
A99: 83 | B99: Miệng gió tạo áp PAG 300x300+OBD | C99: SDG+O | D99: SWIND | E99: 300 | F99: 300 | G99: 250 | H99: 250 | L99: Cái | M99: 1 | N99: =ROUND('00_TONG_HOP_BAO_GIA'!Q84, 0) | O99: =N99*M99 | P99: Cửa nan bầu dục 1 lớp kèm van OBD
A100: 84 | B100: Miệng gió tạo áp PAG 1200x600+OBD | C100: SDG+O | D100: SWIND | E100: 1200 | F100: 600 | G100: 1150 | H100: 550 | L100: Cái | M100: 2 | N100: =ROUND('00_TONG_HOP_BAO_GIA'!Q85, 0) | O100: =N100*M100 | P100: Cửa nan bầu dục 1 lớp kèm van OBD
A101: 85 | B101: Miệng gió tạo áp PAG 1400x800+OBD | C101: SDG+O | D101: SWIND | E101: 1400 | F101: 800 | G101: 1350 | H101: 750 | L101: Cái | M101: 10 | N101: =ROUND('00_TONG_HOP_BAO_GIA'!Q86, 0) | O101: =N101*M101 | P101: Cửa nan bầu dục 1 lớp kèm van OBD
...

Sheet BG Đa Cánh BFN 24
C2: CÔNG TY CỔ PHẦN TẬP ĐOÀN QUỐC TẾ SLAND
C3: VPGD: SỐ 49, Ngõ 1295 Giải Phóng, Phường Hoàng Mai, TP Hà Nội
C4: Nhà máy: Thôn Nhân Hiền - xã Thường Tín - TP Hà Nội
C5: Hotline: 082 5577 999
A6: BẢNG BÁO GIÁ (PHƯƠNG ÁN 2: VAN MFD ĐA CÁNH - ĐỘNG CƠ BELIMO BFN24)
A7: Khách hàng : | M7: Số hiệu
A8: Địa chỉ : | M8: PT Kinh doanh
A9: Người nhận : | M9: Điện thoại
A10: Email: | C10: Số điện thoại : | M10: Dự án
A11: STT | B11: Danh mục sản phẩm | C11: Model | D11: Thương hiệu | E11: Kích thước (mm) | I11: Modul | J11: L | K11: Độ dày (mm) | L11: Unit Đơn vị | M11: Q'ty Số lượng | N11: Đơn Giá (VNĐ) | O11: Total price Thành tiền | P11: Remarks Ghi chú
E12: A1 | F12: A2 | G12: B1 | H12: B2
E13: Face size | G13: Neck size
B14: HỆ THỐNG HÚT KHÓI HẦM XE, HÚT KHÓI SỰ CỐ
A15: 1 | B15: Canvas loại chống cháy cho quạt TAHK | C15: CANVAS | D15: SWIND | E15: Ø | F15: 1000 | J15: 200 | L15: cái | M15: 15 | N15: =ROUND('00_TONG_HOP_BAO_GIA'!Q2, 0) | O15: =N15*M15 | P15: Khớp nối mềm vải bạt chống cháy
A16: 2 | B16: Canvas loại chống cháy cho quạt TAHK | C16: CANVAS | D16: SWIND | E16: Ø | F16: 900 | J16: 200 | L16: cái | M16: 40 | N16: =ROUND('00_TONG_HOP_BAO_GIA'!Q3, 0) | O16: =N16*M16 | P16: Khớp nối mềm vải bạt chống cháy
A17: 3 | B17: Canvas loại chống cháy cho quạt TAHK | C17: CANVAS | D17: SWIND | E17: Ø | F17: 800 | J17: 200 | L17: cái | M17: 40 | N17: =ROUND('00_TONG_HOP_BAO_GIA'!Q4, 0) | O17: =N17*M17 | P17: Khớp nối mềm vải bạt chống cháy
A18: 4 | B18: Canvas loại chống cháy cho quạt TAHK | C18: CANVAS | D18: SWIND | E18: Ø | F18: 710 | J18: 200 | L18: cái | M18: 16 | N18: =ROUND('00_TONG_HOP_BAO_GIA'!Q5, 0) | O18: =N18*M18 | P18: Khớp nối mềm vải bạt chống cháy
A19: 5 | B19: Canvas loại chống cháy cho quạt TAHK | C19: CANVAS | D19: SWIND | E19: Ø | F19: 560 | J19: 200 | L19: cái | M19: 16 | N19: =ROUND('00_TONG_HOP_BAO_GIA'!Q6, 0) | O19: =N19*M19 | P19: Khớp nối mềm vải bạt chống cháy
A20: 6 | B20: Canvas loại thường cho quạt thông gió | C20: CANVAS | D20: SWIND | E20: Ø | F20: 1000 | J20: 200 | L20: cái | M20: 32 | N20: =ROUND('00_TONG_HOP_BAO_GIA'!Q7, 0) | O20: =N20*M20 | P20: Khớp nối mềm vải bạt chống cháy
A21: 7 | B21: Canvas loại thường cho quạt thông gió | C21: CANVAS | D21: SWIND | E21: Ø | F21: 560 | J21: 200 | L21: cái | M21: 24 | N21: =ROUND('00_TONG_HOP_BAO_GIA'!Q8, 0) | O21: =N21*M21 | P21: Khớp nối mềm vải bạt chống cháy
A22: 8 | B22: Van 1 chiều NRD 1250x1250 (EI60) | C22: NRD | D22: SWIND | E22: 1250 | F22: 1250 | G22: 625 | H22: 1250 | I22: 2 | J22: 200 | K22: 1.15 | L22: Cái | M22: 6 | N22: =ROUND('00_TONG_HOP_BAO_GIA'!Q9, 0) | O22: =N22*M22 | P22: Van 1 chiều bọc tấm cách nhiệt dày 10mm KHS
A23: 9 | B23: Van 1 chiều NRD 1700x600 (EI60) | C23: NRD | D23: SWIND | E23: 1700 | F23: 600 | G23: 850 | H23: 600 | I23: 2 | J23: 200 | K23: 0.95 | L23: Cái | M23: 2 | N23: =ROUND('00_TONG_HOP_BAO_GIA'!Q10, 0) | O23: =N23*M23 | P23: Van 1 chiều bọc tấm cách nhiệt dày 10mm KHS
A24: 10 | B24: Van 1 chiều NRD 1200x350 (EI60) | C24: NRD | D24: SWIND | E24: 1200 | F24: 350 | G24: 600 | H24: 350 | I24: 2 | J24: 200 | K24: 0.75 | L24: Cái | M24: 1 | N24: =ROUND('00_TONG_HOP_BAO_GIA'!Q11, 0) | O24: =N24*M24 | P24: Van 1 chiều bọc tấm cách nhiệt dày 10mm KHS
A25: 11 | B25: Van ngăn cháy MFD 1250x1250 (EI60) | C25: SWIND-1.05- MFD-EI120 | D25: SWIND | E25: 1250 | F25: 1250 | G25: 1250 | H25: 625 | I25: 2 | J25: 200 | K25: 1.15 | L25: Cái | M25: 6 | N25: =ROUND('00_TONG_HOP_BAO_GIA'!Q12, 0) | O25: =N25*M25 | P25: - Van động cơ SWIND-MFD - Tiêu chuẩn EI 120 - 2 đầu bích TDC - Gắn kèm động cơ ON-OFF 9Nm, 24V BELIMO - Model: BFN 24 - Sản xuất theo BCTN số 2390/VLXD-TBMT - Van chia đa cánh - Chia 2 modul khi sản xuất
A26: 12 | B26: Van ngăn cháy MFD 1700x600 (EI60) | C26: SWIND-1.05- MFD-EI120 | D26: SWIND | E26: 1700 | F26: 600 | G26: 850 | H26: 600 | I26: 2 | J26: 200 | K26: 1.15 | L26: Cái | M26: 2 | N26: =ROUND('00_TONG_HOP_BAO_GIA'!Q13, 0) | O26: =N26*M26 | P26: - Van động cơ SWIND-MFD - Tiêu chuẩn EI 120 - 2 đầu bích TDC - Gắn kèm động cơ ON-OFF 9Nm, 24V BELIMO - Model: BFN 24 - Sản xuất theo BCTN số 2390/VLXD-TBMT - Van chia đa cánh - Chia 2 modul khi sản xuất
A27: 13 | B27: Van ngăn cháy MFD 1200x350 (EI60) | C27: SWIND-1.05- MFD-EI120 | D27: SWIND | E27: 1200 | F27: 350 | J27: 200 | K27: 1.15 | L27: Cái | M27: 1 | N27: =ROUND('00_TONG_HOP_BAO_GIA'!Q14, 0) | O27: =N27*M27 | P27: - Van động cơ SWIND-MFD - Tiêu chuẩn EI 120 - 2 đầu bích TDC - Gắn kèm động cơ ON-OFF 9Nm, 24V BELIMO - Model: BFN 24 - Sản xuất theo BCTN số 2390/VLXD-TBMT - Van chia đa cánh
A28: 14 | B28: Van ngăn cháy MFD 950x400 (EI30) | C28: SWIND-1.05- MFD-EI120 | D28: SWIND | E28: 950 | F28: 400 | J28: 200 | K28: 1.15 | L28: Cái | M28: 3 | N28: =ROUND('00_TONG_HOP_BAO_GIA'!Q15, 0) | O28: =N28*M28 | P28: - Van động cơ SWIND-MFD - Tiêu chuẩn EI 120 - 2 đầu bích TDC - Gắn kèm động cơ ON-OFF 9Nm, 24V BELIMO - Model: BFN 24 - Sản xuất theo BCTN số 2390/VLXD-TBMT - Van chia đa cánh
A29: 15 | B29: Van ngăn cháy MFD 950x500 (EI30) | C29: SWIND-1.05- MFD-EI120 | D29: SWIND | E29: 950 | F29: 500 | J29: 200 | K29: 1.15 | L29: Cái | M29: 6 | N29: =ROUND('00_TONG_HOP_BAO_GIA'!Q16, 0) | O29: =N29*M29 | P29: - Van động cơ SWIND-MFD - Tiêu chuẩn EI 120 - 2 đầu bích TDC - Gắn kèm động cơ ON-OFF 9Nm, 24V BELIMO - Model: BFN 24 - Sản xuất theo BCTN số 2390/VLXD-TBMT - Van chia đa cánh
A30: 16 | B30: Van ngăn cháy MFD 950x200 (EI30) | C30: SWIND-1.05- MFD-EI120 | D30: SWIND | E30: 950 | F30: 200 | J30: 200 | K30: 1.15 | L30: Cái | M30: 9 | N30: =ROUND('00_TONG_HOP_BAO_GIA'!Q17, 0) | O30: =N30*M30 | P30: - Van động cơ SWIND-MFD - Tiêu chuẩn EI 120 - 2 đầu bích TDC - Gắn kèm động cơ ON-OFF 9Nm, 24V BELIMO - Model: BFN 24 - Sản xuất theo BCTN số 2390/VLXD-TBMT - Van 1 cánh
A31: 17 | B31: Van ngăn cháy MFD 950x300 (EI30) | C31: SWIND-1.05- MFD-EI120 | D31: SWIND | E31: 950 | F31: 300 | J31: 200 | K31: 1.15 | L31: Cái | M31: 12 | N31: =ROUND('00_TONG_HOP_BAO_GIA'!Q18, 0) | O31: =N31*M31 | P31: - Van động cơ SWIND-MFD - Tiêu chuẩn EI 120 - 2 đầu bích TDC - Gắn kèm động cơ ON-OFF 9Nm, 24V BELIMO - Model: BFN 24 - Sản xuất theo BCTN số 2390/VLXD-TBMT - Van chia đa cánh
A32: 18 | B32: Van chỉnh lưu lượng VCD 2000x500 (EI60) | C32: VCD | D32: SWIND | E32: 2000 | F32: 500 | G32: 1000 | H32: 500 | I32: 2 | J32: 200 | K32: 1.15 | L32: Cái | M32: 1 | N32: =ROUND('00_TONG_HOP_BAO_GIA'!Q19, 0) | O32: =N32*M32 | P32: Van tay gạt bọc tấm cách nhiệt KHS 10mm
A33: 19 | B33: Van chỉnh lưu lượng VCD 1300x400 (EI60) | C33: VCD | D33: SWIND | E33: 1300 | F33: 400 | G33: 650 | H33: 400 | I33: 2 | J33: 200 | K33: 0.75 | L33: Cái | M33: 2 | N33: =ROUND('00_TONG_HOP_BAO_GIA'!Q20, 0) | O33: =N33*M33 | P33: Van tay gạt bọc tấm cách nhiệt KHS 10mm
A34: 20 | B34: Van chỉnh lưu lượng VCD 1600x400 (EI60) | C34: VCD | D34: SWIND | E34: 1600 | F34: 400 | G34: 800 | H34: 400 | I34: 2 | J34: 200 | K34: 0.95 | L34: Cái | M34: 1 | N34: =ROUND('00_TONG_HOP_BAO_GIA'!Q21, 0) | O34: =N34*M34 | P34: Van tay gạt bọc tấm cách nhiệt KHS 10mm
A35: 21 | B35: Van chỉnh lưu lượng VCD 1600x450 (EI60) | C35: VCD | D35: SWIND | E35: 1600 | F35: 450 | G35: 800 | H35: 450 | I35: 2 | J35: 200 | K35: 0.95 | L35: Cái | M35: 1 | N35: =ROUND('00_TONG_HOP_BAO_GIA'!Q22, 0) | O35: =N35*M35 | P35: Van tay gạt bọc tấm cách nhiệt KHS 10mm
A36: 22 | B36: Van chỉnh lưu lượng VCD 900x350 (EI60) | C36: VCD | D36: SWIND | E36: 900 | F36: 350 | J36: 200 | K36: 0.95 | L36: Cái | M36: 5 | N36: =ROUND('00_TONG_HOP_BAO_GIA'!Q23, 0) | O36: =N36*M36 | P36: Van tay gạt bọc tấm cách nhiệt KHS 10mm
A37: 23 | B37: Van chỉnh lưu lượng VCD 600x300 (EI60) | C37: VCD | D37: SWIND | E37: 600 | F37: 300 | J37: 200 | K37: 0.75 | L37: Cái | M37: 1 | N37: =ROUND('00_TONG_HOP_BAO_GIA'!Q24, 0) | O37: =N37*M37 | P37: Van tay gạt bọc tấm cách nhiệt KHS 10mm
A38: 24 | B38: Miệng gió hút khói EAG 600x300+OBD | C38: ECG+O | D38: SWIND | E38: 600 | F38: 300 | G38: 550 | H38: 250 | L38: Cái | M38: 112 | N38: =ROUND('00_TONG_HOP_BAO_GIA'!Q25, 0) | O38: =N38*M38 | P38: Cửa nan sọt trứng kèm van OBD
A39: 25 | B39: Miệng gió hút khói SEG 1200x600+OBD | C39: SDG+O | D39: SWIND | E39: 1200 | F39: 600 | G39: 1150 | H39: 550 | L39: Cái | M39: 2 | N39: =ROUND('00_TONG_HOP_BAO_GIA'!Q26, 0) | O39: =N39*M39 | P39: Cửa nan bầu dục 1 lớp kèm van OBD
A40: 26 | B40: Miệng gió hút khói SEAG 1000x600+OBD | C40: SDG+O | D40: SWIND | E40: 1000 | F40: 600 | G40: 950 | H40: 550 | L40: Cái | M40: 52 | N40: =ROUND('00_TONG_HOP_BAO_GIA'!Q27, 0) | O40: =N40*M40 | P40: Cửa nan bầu dục 1 lớp kèm van OBD
A41: 27 | B41: Louver EAL 7500x500+IS | C41: WL+N | D41: SWIND | E41: 7500 | F41: 500 | G41: 7450 | H41: 450 | L41: Cái | M41: 1 | N41: =ROUND('00_TONG_HOP_BAO_GIA'!Q28, 0) | O41: =N41*M41 | P41: Louver nan Z + LCCT
A42: 28 | B42: Louver EAL 4500x500+IS | C42: WL+N | D42: SWIND | E42: 4500 | F42: 500 | G42: 4450 | H42: 450 | L42: Cái | M42: 4 | N42: =ROUND('00_TONG_HOP_BAO_GIA'!Q29, 0) | O42: =N42*M42 | P42: Louver nan Z + LCCT
A43: 29 | B43: Louver EAL 4000x500+IS | C43: WL+N | D43: SWIND | E43: 4000 | F43: 500 | G43: 3950 | H43: 450 | L43: Cái | M43: 4 | N43: =ROUND('00_TONG_HOP_BAO_GIA'!Q30, 0) | O43: =N43*M43 | P43: Louver nan Z + LCCT
A44: 30 | B44: Louver EAL 3000x500+IS | C44: WL+N | D44: SWIND | E44: 3000 | F44: 500 | G44: 2950 | H44: 450 | L44: Cái | M44: 1 | N44: =ROUND('00_TONG_HOP_BAO_GIA'!Q31, 0) | O44: =N44*M44 | P44: Louver nan Z + LCCT
A45: 31 | B45: Louver EAL 2750x750+IS | C45: WL+N | D45: SWIND | E45: 2750 | F45: 750 | G45: 2700 | H45: 700 | L45: Cái | M45: 2 | N45: =ROUND('00_TONG_HOP_BAO_GIA'!Q32, 0) | O45: =N45*M45 | P45: Louver nan Z + LCCT
A46: 32 | B46: Box miệng gió 600x300 | C46: BOX | D46: SWIND / Phương Nam | E46: 600 | F46: 300 | J46: 200 | K46: 0.75 | L46: Cái | M46: 112 | N46: =ROUND('00_TONG_HOP_BAO_GIA'!Q33, 0) | O46: =N46*M46 | P46: Box miệng gió tôn mạ kẽm Phương Nam
A47: 33 | B47: Box miệng gió 1200x600 | C47: BOX | D47: SWIND / Phương Nam | E47: 1200 | F47: 600 | J47: 200 | K47: 0.75 | L47: Cái | M47: 2 | N47: =ROUND('00_TONG_HOP_BAO_GIA'!Q34, 0) | O47: =N47*M47 | P47: Box miệng gió tôn mạ kẽm Phương Nam
A48: 34 | B48: Box miệng gió 10006300 | C48: BOX | D48: SWIND / Phương Nam | E48: 1000 | F48: 300 | J48: 200 | K48: 0.75 | L48: Cái | M48: 52 | N48: =ROUND('00_TONG_HOP_BAO_GIA'!Q35, 0) | O48: =N48*M48 | P48: Box miệng gió tôn mạ kẽm Phương Nam
A49: 35 | B49: Vật tư phụ, phụ kiện | L49: Lô | M49: 1 | N49: =ROUND('00_TONG_HOP_BAO_GIA'!Q36, 0) | O49: =N49*M49 | P49: Hạng mục phụ trợ / Nhà thầu tự thực hiện
B50: Ống thông gió và phụ kiện, box miệng gió
A51: 36 | B51: Tole 0.75mm phủ lớp mạ kẽm Z180 | C51: DUCT-TDF | D51: SWIND / Phương Nam | K51: 0.75 | L51: m2 | M51: 2633.4 | N51: =ROUND('00_TONG_HOP_BAO_GIA'!Q37, 0) | O51: =N51*M51 | P51: Ống gió tôn mạ kẽm Phương Nam dày 0.75mm
A52: 37 | B52: Tole 0.95mm phủ lớp mạ kẽm Z180 | C52: DUCT-TDF | D52: SWIND / Phương Nam | K52: 0.95 | L52: m2 | M52: 1291.1 | N52: =ROUND('00_TONG_HOP_BAO_GIA'!Q38, 0) | O52: =N52*M52 | P52: Ống gió tôn mạ kẽm Phương Nam dày 0.95mm
A53: 38 | B53: Tole 1.15mm phủ lớp mạ kẽm Z180 | C53: DUCT-TDF | D53: SWIND / Phương Nam | K53: 1.15 | L53: m2 | M53: 3070.55 | N53: =ROUND('00_TONG_HOP_BAO_GIA'!Q39, 0) | O53: =N53*M53 | P53: Ống gió tôn mạ kẽm Phương Nam dày 1.15mm
A54: 39 | B54: Tole ZAM 1.15mm | C54: DUCT-TDF | D54: SWIND / Phương Nam | K54: 1.15 | L54: m2 | M54: 138 | N54: =ROUND('00_TONG_HOP_BAO_GIA'!Q40, 0) | O54: =N54*M54 | P54: Ống gió tôn mạ kẽm Phương Nam dày 1.15mm
A55: 40 | B55: Lưới bảo vệ | D55: SWIND | L55: cái | M55: 3 | N55: =ROUND('00_TONG_HOP_BAO_GIA'!Q41, 0) | O55: =N55*M55 | P55: Hạng mục phụ trợ / Nhà thầu tự thực hiện
A56: 41 | B56: Lớp chống cháy EI30 | C56: DIỆN TÍCH TÍNH THEO KÍCH THƯỚC HÌNH HỌC (HOÀN THIỆN) | D56: SWIND | L56: m2 | M56: 3621.25 | N56: =ROUND('00_TONG_HOP_BAO_GIA'!Q42, 0) | O56: =N56*M56 | P56: Bọc chống cháy ống gió chuẩn EI
A57: 42 | B57: Lớp chống cháy EI60 | C57: DIỆN TÍCH TÍNH THEO KÍCH THƯỚC HÌNH HỌC (HOÀN THIỆN) | D57: SWIND | L57: m2 | M57: 2821 | N57: =ROUND('00_TONG_HOP_BAO_GIA'!Q43, 0) | O57: =N57*M57 | P57: Bọc chống cháy ống gió chuẩn EI
A58: 43 | B58: Vật tư phụ, phụ kiện | L58: Lô | M58: 1 | N58: =ROUND('00_TONG_HOP_BAO_GIA'!Q44, 0) | O58: =N58*M58 | P58: Hạng mục phụ trợ / Nhà thầu tự thực hiện
B59: HỆ THỐNG TẠO ÁP
A60: 44 | B60: Van 1 chiều NRD 300x200 (EI60) | C60: NRD | D60: SWIND | E60: 300 | F60: 200 | J60: 200 | K60: 0.75 | L60: Cái | M60: 1 | N60: =ROUND('00_TONG_HOP_BAO_GIA'!Q45, 0) | O60: =N60*M60 | P60: Van 1 chiều bọc tấm cách nhiệt dày 10mm KHS
A61: 45 | B61: Van 1 chiều NRD 700x500 (EI60) | C61: NRD | D61: SWIND | E61: 700 | F61: 500 | J61: 200 | K61: 0.95 | L61: Cái | M61: 2 | N61: =ROUND('00_TONG_HOP_BAO_GIA'!Q46, 0) | O61: =N61*M61 | P61: Van 1 chiều bọc tấm cách nhiệt dày 10mm KHS
A62: 46 | B62: Van 1 chiều NRD 700x800 (EI60) | C62: NRD | D62: SWIND | E62: 700 | F62: 800 | J62: 200 | K62: 0.95 | L62: Cái | M62: 2 | N62: =ROUND('00_TONG_HOP_BAO_GIA'!Q47, 0) | O62: =N62*M62 | P62: Van 1 chiều bọc tấm cách nhiệt dày 10mm KHS
A63: 47 | B63: Van 1 chiều NRD 250X200(EI60) | C63: NRD | D63: SWIND | E63: 250 | F63: 200 | J63: 200 | K63: 0.75 | L63: Cái | M63: 1 | N63: =ROUND('00_TONG_HOP_BAO_GIA'!Q48, 0) | O63: =N63*M63 | P63: Van 1 chiều bọc tấm cách nhiệt dày 10mm KHS
A64: 48 | B64: Van 1 chiều NRD 900x400 (EI60) | C64: NRD | D64: SWIND | E64: 900 | F64: 400 | J64: 200 | K64: 0.95 | L64: Cái | M64: 2 | N64: =ROUND('00_TONG_HOP_BAO_GIA'!Q49, 0) | O64: =N64*M64 | P64: Van 1 chiều bọc tấm cách nhiệt dày 10mm KHS
A65: 49 | B65: Van 1 chiều NRD 300x300 (EI60) | C65: NRD | D65: SWIND | E65: 300 | F65: 300 | J65: 200 | K65: 0.75 | L65: Cái | M65: 1 | N65: =ROUND('00_TONG_HOP_BAO_GIA'!Q50, 0) | O65: =N65*M65 | P65: Van 1 chiều bọc tấm cách nhiệt dày 10mm KHS
A66: 50 | B66: Van 1 chiều NRD 350x250 (EI60) | C66: NRD | D66: SWIND | E66: 350 | F66: 250 | J66: 200 | K66: 0.75 | L66: Cái | M66: 1 | N66: =ROUND('00_TONG_HOP_BAO_GIA'!Q51, 0) | O66: =N66*M66 | P66: Van 1 chiều bọc tấm cách nhiệt dày 10mm KHS
A67: 51 | B67: Van 1 chiều NRD 350x150 (EI60) | C67: NRD | D67: SWIND | E67: 350 | F67: 150 | J67: 200 | K67: 0.75 | L67: Cái | M67: 1 | N67: =ROUND('00_TONG_HOP_BAO_GIA'!Q52, 0) | O67: =N67*M67 | P67: Van 1 chiều bọc tấm cách nhiệt dày 10mm KHS
A68: 52 | B68: Van ngăn cháy MFD 350x200 (EI60) | C68: SWIND-1.05- MFD-EI120 | D68: SWIND | E68: 350 | F68: 200 | J68: 200 | K68: 1.15 | L68: Cái | M68: 1 | N68: =ROUND('00_TONG_HOP_BAO_GIA'!Q53, 0) | O68: =N68*M68 | P68: - Van động cơ SWIND-MFD - Tiêu chuẩn EI 120 - 2 đầu bích TDC - Gắn kèm động cơ ON-OFF 9Nm, 24V BELIMO - Model: BFN 24 - Sản xuất theo BCTN số 2390/VLXD-TBMT - Van 1 cánh
A69: 53 | B69: Van ngăn cháy MFD 700x500 (EI60) | C69: SWIND-1.05- MFD-EI120 | D69: SWIND | E69: 700 | F69: 500 | J69: 200 | K69: 1.15 | L69: Cái | M69: 2 | N69: =ROUND('00_TONG_HOP_BAO_GIA'!Q54, 0) | O69: =N69*M69 | P69: - Van động cơ SWIND-MFD - Tiêu chuẩn EI 120 - 2 đầu bích TDC - Gắn kèm động cơ ON-OFF 9Nm, 24V BELIMO - Model: BFN 24 - Sản xuất theo BCTN số 2390/VLXD-TBMT - Van chia đa cánh
A70: 54 | B70: Van ngăn cháy MFD 700x800 (EI60) | C70: SWIND-1.05- MFD-EI120 | D70: SWIND | E70: 700 | F70: 800 | J70: 200 | K70: 1.15 | L70: Cái | M70: 2 | N70: =ROUND('00_TONG_HOP_BAO_GIA'!Q55, 0) | O70: =N70*M70 | P70: - Van động cơ SWIND-MFD - Tiêu chuẩn EI 120 - 2 đầu bích TDC - Gắn kèm động cơ ON-OFF 9Nm, 24V BELIMO - Model: BFN 24 - Sản xuất theo BCTN số 2390/VLXD-TBMT - Van chia đa cánh
A71: 55 | B71: Van ngăn cháy MFD 1200x600 (EI60) | C71: SWIND-1.05- MFD-EI120 | D71: SWIND | E71: 1200 | F71: 600 | J71: 200 | K71: 1.15 | L71: Cái | M71: 2 | N71: =ROUND('00_TONG_HOP_BAO_GIA'!Q56, 0) | O71: =N71*M71 | P71: - Van động cơ SWIND-MFD - Tiêu chuẩn EI 120 - 2 đầu bích TDC - Gắn kèm động cơ ON-OFF 9Nm, 24V BELIMO - Model: BFN 24 - Sản xuất theo BCTN số 2390/VLXD-TBMT - Van chia đa cánh
... A81: 65 | B81: Van ngăn cháy MFD 800x350 (EI60) | C81: SWIND-1.05- MFD-EI120 | D81: SWIND | E81: 800 | F81: 350 | J81: 200 | K81: 1.15 | L81: Cái | M81: 3 | N81: =ROUND('00_TONG_HOP_BAO_GIA'!Q66, 0) | O81: =N81*M81 | P81: - Van động cơ SWIND-MFD - Tiêu chuẩn EI 120 - 2 đầu bích TDC - Gắn kèm động cơ ON-OFF 9Nm, 24V BELIMO - Model: BFN 24 - Sản xuất theo BCTN số 2390/VLXD-TBMT - Van chia đa cánh
A82: 66 | B82: Van ngăn cháy MFD 2000x650 (EI120) | C82: SWIND-1.05- MFD-EI120 | D82: SWIND | E82: 2000 | F82: 650 | G82: 1000 | H82: 650 | I82: 2 | J82: 200 | K82: 1.15 | L82: Cái | M82: 1 | N82: =ROUND('00_TONG_HOP_BAO_GIA'!Q67, 0) | O82: =N82*M82 | P82: - Van động cơ SWIND-MFD - Tiêu chuẩn EI 120 - 2 đầu bích TDC - Gắn kèm động cơ ON-OFF 9Nm, 24V BELIMO - Model: BFN 24 - Sản xuất theo BCTN số 2390/VLXD-TBMT - Van chia đa cánh - Chia 2 modul khi sản xuất
A83: 67 | B83: Van ngăn cháy MFD 1000x350 (EI120) | C83: SWIND-1.05- MFD-EI120 | D83: SWIND | E83: 1000 | F83: 350 | J83: 200 | K83: 1.15 | L83: Cái | M83: 2 | N83: =ROUND('00_TONG_HOP_BAO_GIA'!Q68, 0) | O83: =N83*M83 | P83: - Van động cơ SWIND-MFD - Tiêu chuẩn EI 120 - 2 đầu bích TDC - Gắn kèm động cơ ON-OFF 9Nm, 24V BELIMO - Model: BFN 24 - Sản xuất theo BCTN số 2390/VLXD-TBMT - Van chia đa cánh
A84: 68 | B84: Van ngăn cháy MFD 1200x350 (EI120) | C84: SWIND-1.05- MFD-EI120 | D84: SWIND | E84: 1200 | F84: 350 | J84: 200 | K84: 1.15 | L84: Cái | M84: 2 | N84: =ROUND('00_TONG_HOP_BAO_GIA'!Q69, 0) | O84: =N84*M84 | P84: - Van động cơ SWIND-MFD - Tiêu chuẩn EI 120 - 2 đầu bích TDC - Gắn kèm động cơ ON-OFF 9Nm, 24V BELIMO - Model: BFN 24 - Sản xuất theo BCTN số 2390/VLXD-TBMT - Van chia đa cánh
A85: 69 | B85: Van ngăn cháy MFD 1100x350 (EI120) | C85: SWIND-1.05- MFD-EI120 | D85: SWIND | E85: 1100 | F85: 350 | J85: 200 | K85: 1.15 | L85: Cái | M85: 1 | N85: =ROUND('00_TONG_HOP_BAO_GIA'!Q70, 0) | O85: =N85*M85 | P85: - Van động cơ SWIND-MFD - Tiêu chuẩn EI 120 - 2 đầu bích TDC - Gắn kèm động cơ ON-OFF 9Nm, 24V BELIMO - Model: BFN 24 - Sản xuất theo BCTN số 2390/VLXD-TBMT - Van chia đa cánh
A86: 70 | B86: Van ngăn cháy MFD 1200x300 (EI60) | C86: SWIND-1.05- MFD-EI120 | D86: SWIND | E86: 1200 | F86: 300 | J86: 200 | K86: 1.15 | L86: Cái | M86: 9 | N86: =ROUND('00_TONG_HOP_BAO_GIA'!Q71, 0) | O86: =N86*M86 | P86: - Van động cơ SWIND-MFD - Tiêu chuẩn EI 120 - 2 đầu bích TDC - Gắn kèm động cơ ON-OFF 9Nm, 24V BELIMO - Model: BFN 24 - Sản xuất theo BCTN số 2390/VLXD-TBMT - Van chia đa cánh
A87: 71 | B87: Van ngăn cháy MFD 1200x300 (EI120) | C87: SWIND-1.05- MFD-EI120 | D87: SWIND | E87: 1200 | F87: 300 | J87: 200 | K87: 1.15 | L87: Cái | M87: 1 | N87: =ROUND('00_TONG_HOP_BAO_GIA'!Q72, 0) | O87: =N87*M87 | P87: - Van động cơ SWIND-MFD - Tiêu chuẩn EI 120 - 2 đầu bích TDC - Gắn kèm động cơ ON-OFF 9Nm, 24V BELIMO - Model: BFN 24 - Sản xuất theo BCTN số 2390/VLXD-TBMT - Van chia đa cánh
A88: 72 | B88: Van ngăn cháy MFD 900x350 (EI120) | C88: SWIND-1.05- MFD-EI120 | D88: SWIND | E88: 900 | F88: 350 | J88: 200 | K88: 1.15 | L88: Cái | M88: 13 | N88: =ROUND('00_TONG_HOP_BAO_GIA'!Q73, 0) | O88: =N88*M88 | P88: - Van động cơ SWIND-MFD - Tiêu chuẩn EI 120 - 2 đầu bích TDC - Gắn kèm động cơ ON-OFF 9Nm, 24V BELIMO - Model: BFN 24 - Sản xuất theo BCTN số 2390/VLXD-TBMT - Van chia đa cánh
A89: 73 | B89: Van ngăn cháy MFD 1150x350 (EI120) | C89: SWIND-1.05- MFD-EI120 | D89: SWIND | E89: 1150 | F89: 350 | J89: 200 | K89: 1.15 | L89: Cái | M89: 12 | N89: =ROUND('00_TONG_HOP_BAO_GIA'!Q74, 0) | O89: =N89*M89 | P89: - Van động cơ SWIND-MFD - Tiêu chuẩn EI 120 - 2 đầu bích TDC - Gắn kèm động cơ ON-OFF 9Nm, 24V BELIMO - Model: BFN 24 - Sản xuất theo BCTN số 2390/VLXD-TBMT - Van chia đa cánh
A90: 74 | B90: Van ngăn cháy MFD 1200x450 (EI120) | C90: SWIND-1.05- MFD-EI120 | D90: SWIND | E90: 1200 | F90: 450 | J90: 200 | K90: 1.15 | L90: Cái | M90: 1 | N90: =ROUND('00_TONG_HOP_BAO_GIA'!Q75, 0) | O90: =N90*M90 | P90: - Van động cơ SWIND-MFD - Tiêu chuẩn EI 120 - 2 đầu bích TDC - Gắn kèm động cơ ON-OFF 9Nm, 24V BELIMO - Model: BFN 24 - Sản xuất theo BCTN số 2390/VLXD-TBMT - Van chia đa cánh
A91: 75 | B91: Van ngăn cháy MFD 350x600 (EI120) | C91: SWIND-1.05- MFD-EI120 | D91: SWIND | E91: 350 | F91: 600 | J91: 200 | K91: 1.15 | L91: Cái | M91: 10 | N91: =ROUND('00_TONG_HOP_BAO_GIA'!Q76, 0) | O91: =N91*M91 | P91: - Van động cơ SWIND-MFD - Tiêu chuẩn EI 120 - 2 đầu bích TDC - Gắn kèm động cơ ON-OFF 9Nm, 24V BELIMO - Model: BFN 24 - Sản xuất theo BCTN số 2390/VLXD-TBMT - Van chia đa cánh
A92: 76 | B92: Van ngăn cháy MFD 1100x350 (EI120) | C92: SWIND-1.05- MFD-EI120 | D92: SWIND | E92: 1100 | F92: 350 | J92: 200 | K92: 1.15 | L92: Cái | M92: 6 | N92: =ROUND('00_TONG_HOP_BAO_GIA'!Q77, 0) | O92: =N92*M92 | P92: - Van động cơ SWIND-MFD - Tiêu chuẩn EI 120 - 2 đầu bích TDC - Gắn kèm động cơ ON-OFF 9Nm, 24V BELIMO - Model: BFN 24 - Sản xuất theo BCTN số 2390/VLXD-TBMT - Van chia đa cánh
A93: 77 | B93: Van ngăn cháy MFD 1000x350 (EI120) | C93: SWIND-1.05- MFD-EI120 | D93: SWIND | E93: 1000 | F93: 350 | J93: 200 | K93: 1.15 | L93: Cái | M93: 6 | N93: =ROUND('00_TONG_HOP_BAO_GIA'!Q78, 0) | O93: =N93*M93 | P93: - Van động cơ SWIND-MFD - Tiêu chuẩn EI 120 - 2 đầu bích TDC - Gắn kèm động cơ ON-OFF 9Nm, 24V BELIMO - Model: BFN 24 - Sản xuất theo BCTN số 2390/VLXD-TBMT - Van chia đa cánh
A94: 78 | B94: Van ngăn cháy MFD 800x300 (EI120) | C94: SWIND-1.05- MFD-EI120 | D94: SWIND | E94: 800 | F94: 300 | J94: 200 | K94: 1.15 | L94: Cái | M94: 8 | N94: =ROUND('00_TONG_HOP_BAO_GIA'!Q79, 0) | O94: =N94*M94 | P94: - Van động cơ SWIND-MFD - Tiêu chuẩn EI 120 - 2 đầu bích TDC - Gắn kèm động cơ ON-OFF 9Nm, 24V BELIMO - Model: BFN 24 - Sản xuất theo BCTN số 2390/VLXD-TBMT - Van chia đa cánh
A95: 79 | B95: Van ngăn cháy MFD 650x400 | C95: SWIND-1.05- MFD-EI120 | D95: SWIND | E95: 650 | F95: 400 | J95: 200 | K95: 1.15 | L95: Cái | M95: 6 | N95: =ROUND('00_TONG_HOP_BAO_GIA'!Q80, 0) | O95: =N95*M95 | P95: - Van động cơ SWIND-MFD - Tiêu chuẩn EI 120 - 2 đầu bích TDC - Gắn kèm động cơ ON-OFF 9Nm, 24V BELIMO - Model: BFN 24 - Sản xuất theo BCTN số 2390/VLXD-TBMT - Van chia đa cánh
A96: 80 | B96: Van xả áp | C96: VCD | D96: SWIND | J96: 200 | K96: 0.75 | L96: Cái | M96: 6 | N96: =ROUND('00_TONG_HOP_BAO_GIA'!Q81, 0) | O96: =N96*M96 | P96: Van điều chỉnh lưu lượng tay gạt tôn mạ kẽm
A97: 81 | B97: Van chỉnh lưu lượng VCD250x200 (EI60) | C97: VCD | D97: SWIND | E97: 250 | F97: 200 | J97: 200 | K97: 0.75 | L97: Cái | M97: 1 | N97: =ROUND('00_TONG_HOP_BAO_GIA'!Q82, 0) | O97: =N97*M97 | P97: Van tay gạt bọc tấm cách nhiệt KHS 10mm
A98: 82 | B98: Miệng gió tạo áp PAG 900x400+OBD | C98: SDG+O | D98: SWIND | E98: 900 | F98: 400 | G98: 850 | H98: 350 | L98: Cái | M98: 2 | N98: =ROUND('00_TONG_HOP_BAO_GIA'!Q83, 0) | O98: =N98*M98 | P98: Cửa nan bầu dục 1 lớp kèm van OBD
A99: 83 | B99: Miệng gió tạo áp PAG 300x300+OBD | C99: SDG+O | D99: SWIND | E99: 300 | F99: 300 | G99: 250 | H99: 250 | L99: Cái | M99: 1 | N99: =ROUND('00_TONG_HOP_BAO_GIA'!Q84, 0) | O99: =N99*M99 | P99: Cửa nan bầu dục 1 lớp kèm van OBD
A100: 84 | B100: Miệng gió tạo áp PAG 1200x600+OBD | C100: SDG+O | D100: SWIND | E100: 1200 | F100: 600 | G100: 1150 | H100: 550 | L100: Cái | M100: 2 | N100: =ROUND('00_TONG_HOP_BAO_GIA'!Q85, 0) | O100: =N100*M100 | P100: Cửa nan bầu dục 1 lớp kèm van OBD
A101: 85 | B101: Miệng gió tạo áp PAG 1400x800+OBD | C101: SDG+O | D101: SWIND | E101: 1400 | F101: 800 | G101: 1350 | H101: 750 | L101: Cái | M101: 10 | N101: =ROUND('00_TONG_HOP_BAO_GIA'!Q86, 0) | O101: =N101*M101 | P101: Cửa nan bầu dục 1 lớp kèm van OBD
A102: 86 | B102: Miệng gió tạo áp PAG 1200x600+OBD | C102: SDG+O | D102: SWIND | E102: 1200 | F102: 600 | G102: 1150 | H102: 550 | L102: Cái | M102: 2 | N102: =ROUND('00_TONG_HOP_BAO_GIA'!Q87, 0) | O102: =N102*M102 | P102: Cửa nan bầu dục 1 lớp kèm van OBD
A103: 87 | B103: Miệng gió tạo áp PAG 300x300+OBD | C103: SDG+O | D103: SWIND | E103: 300 | F103: 300 | G103: 250 | H103: 250 | L103: Cái | M103: 8 | N103: =ROUND('00_TONG_HOP_BAO_GIA'!Q88, 0) | O103: =N103*M103 | P103: Cửa nan bầu dục 1 lớp kèm van OBD
A104: 88 | B104: Miệng gió tạo áp PAG 500x200+OBD | C104: SDG+O | D104: SWIND | E104: 500 | F104: 200 | G104: 450 | H104: 150 | L104: Cái | M104: 3 | N104: =ROUND('00_TONG_HOP_BAO_GIA'!Q89, 0) | O104: =N104*M104 | P104: Cửa nan bầu dục 1 lớp kèm van OBD
A105: 89 | B105: Miệng gió tạo áp PAG1400x800+OBD | C105: SDG+O | D105: SWIND | E105: 1400 | F105: 800 | G105: 1350 | H105: 750 | L105: Cái | M105: 49 | N105: =ROUND('00_TONG_HOP_BAO_GIA'!Q90, 0) | O105: =N105*M105 | P105: Cửa nan bầu dục 1 lớp kèm van OBD
A106: 90 | B106: Miệng gió tạo áp PAG 900x350+OBD | C106: SDG+O | D106: SWIND | E106: 900 | F106: 350 | G106: 850 | H106: 300 | L106: Cái | M106: 18 | N106: =ROUND('00_TONG_HOP_BAO_GIA'!Q91, 0) | O106: =N106*M106 | P106: Cửa nan bầu dục 1 lớp kèm van OBD
A107: 91 | B107: Miệng gió tạo áp PAG 350x600+OBD | C107: SDG+O | D107: SWIND | E107: 350 | F107: 600 | G107: 300 | H107: 550 | L107: Cái | M107: 13 | N107: =ROUND('00_TONG_HOP_BAO_GIA'!Q92, 0) | O107: =N107*M107 | P107: Cửa nan bầu dục 1 lớp kèm van OBD
A108: 92 | B108: Miệng gió tạo áp PAG 800x400 OBD | C108: SDG+O | D108: SWIND | E108: 800 | F108: 400 | G108: 750 | H108: 350 | L108: Cái | M108: 7 | N108: =ROUND('00_TONG_HOP_BAO_GIA'!Q93, 0) | O108: =N108*M108 | P108: Cửa nan bầu dục 1 lớp kèm van OBD
A109: 93 | B109: Miệng gió tạo áp PAG 700x400 OBD | C109: SDG+O | D109: SWIND | E109: 700 | F109: 400 | G109: 650 | H109: 350 | L109: Cái | M109: 17 | N109: =ROUND('00_TONG_HOP_BAO_GIA'!Q94, 0) | O109: =N109*M109 | P109: Cửa nan bầu dục 1 lớp kèm van OBD
... A112: 96 | B112: Louver 3500x1000+IS | C112: WL+N | D112: SWIND | E112: 3500 | F112: 1000 | G112: 3450 | H112: 950 | L112: Cái | M112: 1 | N112: =ROUND('00_TONG_HOP_BAO_GIA'!Q97, 0) | O112: =N112*M112 | P112: Louver nan Z + LCCT
...

Sheet 00_BANG_CHAO_GIA
A1: BILL: HỆ THỐNG ĐHKK & THÔNG GIÓ
A3: STT | B3: MÔ TẢ CÔNG TÁC | C3: MÃ HIỆU | D3: NHÃN HIỆU | E3: XUẤT XỨ | F3: LỌC | G3: Đơn vị | H3: Khối lượng | I3: ĐƠN GIÁ | L3: THÀNH TIỀN | O3: GHI CHÚ
I4: VẬT TƯ | J4: NHÂN CÔNG | K4: TỔNG | L4: VẬT TƯ | M4: NHÂN CÔNG | N4: TỔNG
A5: A | B5: HỆ THỐNG THÔNG GIÓ | F5: M
A6: A1 | B6: HỆ THỐNG HÚT KHÓI HẦM XE, HÚT KHÓI SỰ CỐ | F6: M
A7: =SUBTOTAL(3,$G7:G$7) | B7: Quạt hướng trục CEF-B2-Z1-01~02 5290/9430 l/s @ 500/1350 Pa, chống cháy 300°C trong 2h, | C7: CEF | D7: Fantech (ELTA Fans), Systemair, Wolter, Kruger | F7: QUẠT | G7: Cái | H7: 2
A8: =SUBTOTAL(3,$G$7:G8) | B8: Quạt hướng trục CEF-B2-Z2-01~02 5490/8910 l/s @ 600/1350 Pa, chống cháy 300°C trong 2h | C8: CEF | D8: Fantech (ELTA Fans), Systemair, Wolter, Kruger | F8: QUẠT | G8: Cái | H8: 2
A9: =SUBTOTAL(3,$G$7:G9) | B9: Quạt hướng trục CEF-B1-Z1-01~02 5590/8385 l/s @ 600/1350 Pa, chống cháy 300°C trong 2h | C9: CEF | D9: Fantech (ELTA Fans), Systemair, Wolter, Kruger | F9: QUẠT | G9: Cái | H9: 2
A10: =SUBTOTAL(3,$G$7:G10) | B10: Quạt hướng trục CEF-B1-Z2-01~02 5135/7700 l/s @ 600/1350 Pa, chống cháy 300°C trong 2h | C10: CEF | D10: Fantech (ELTA Fans), Systemair, Wolter, Kruger | F10: QUẠT | G10: Cái | H10: 2
A11: =SUBTOTAL(3,$G$7:G11) | B11: Quạt hướng trục SEF-B1-Z2-01 4800 l/s @ 500 Pa, chống cháy 300°C trong 2h | C11: SEF | D11: Fantech (ELTA Fans), Systemair, Wolter, Kruger | F11: QUẠT | G11: Cái | H11: 1
A12: =SUBTOTAL(3,$G$7:G12) | B12: Quạt hướng trục SEF-A1.1-03F-01~02 7400 l/s @ 400 Pa, chống cháy 300°C trong 2h | C12: SEF | D12: Fantech (ELTA Fans), Systemair, Wolter, Kruger | F12: QUẠT | G12: Cái | H12: 2
A13: =SUBTOTAL(3,$G$7:G13) | B13: Quạt hướng trục SEF-A1.2-03F-01~02 6700 l/s @ 500 Pa, chống cháy 300°C trong 2h | C13: SEF | D13: Fantech (ELTA Fans), Systemair, Wolter, Kruger | F13: QUẠT | G13: Cái | H13: 2
A14: =SUBTOTAL(3,$G$7:G14) | B14: Quạt hướng trục SEF-A1.2-03F-03 5100 l/s @ 500 Pa, chống cháy 300°C trong 2h | C14: SEF | D14: Fantech (ELTA Fans), Systemair, Wolter, Kruger | F14: QUẠT | G14: Cái | H14: 1
A15: =SUBTOTAL(3,$G$7:G15) | B15: Quạt hướng trục SEF-A1.3-03F-01~03 4800 l/s @ 500 Pa, chống cháy 300°C trong 2h | C15: SEF | D15: Fantech (ELTA Fans), Systemair, Wolter, Kruger | F15: QUẠT | G15: Cái | H15: 3
A16: =SUBTOTAL(3,$G$7:G16) | B16: Quạt hướng trục SEF-A1.3-03F-04 4800 l/s @ 450 Pa, chống cháy 300°C trong 2h | C16: SEF | D16: Fantech (ELTA Fans), Systemair, Wolter, Kruger | F16: QUẠT | G16: Cái | H16: 1
A17: =SUBTOTAL(3,$G$7:G17) | B17: Quạt hướng trục SEF-A1.3-03F-05~07 4800 l/s @ 500 Pa, chống cháy 300°C trong 2h | C17: SEF | D17: Fantech (ELTA Fans), Systemair, Wolter, Kruger | F17: QUẠT | G17: Cái | H17: 3
A18: =SUBTOTAL(3,$G$7:G18) | B18: Quạt hướng trục SEF-A1.3-10F-01 7100 l/s @ 600 Pa, chống cháy 300°C trong 2h | C18: SEF | D18: Fantech (ELTA Fans), Systemair, Wolter, Kruger | F18: QUẠT | G18: Cái | H18: 1
A19: =SUBTOTAL(3,$G$7:G19) | B19: Quạt hướng trục SEF-A1.2-12F-01 8800 l/s @ 650 Pa, chống cháy 300°C trong 2h | C19: SEF | D19: Fantech (ELTA Fans), Systemair, Wolter, Kruger | F19: QUẠT | G19: Cái | H19: 1
A20: =SUBTOTAL(3,$G$7:G20) | B20: Quạt hướng trục SEF-A1.1-RF-01 8100 l/s @ 650 Pa, chống cháy 300°C trong 2h | C20: SEF | D20: Fantech (ELTA Fans), Systemair, Wolter, Kruger | F20: QUẠT | G20: Cái | H20: 1
B21: Canvas loại chống cháy cho quạt TAHK | C21: D1000, L=200mm | F21: CANVAS | G21: cái | H21: 15 | I21: =IF('00_TONG_HOP_BAO_GIA'!G2>0, ('00_TONG_HOP_BAO_GIA'!K2 + '00_TONG_HOP_BAO_GIA'!M2) * (1 + '00_TONG_HOP_BAO_GIA'!P2) / '00_TONG_HOP_BAO_GIA'!G2, 0) | J21: =IF('00_TONG_HOP_BAO_GIA'!G2>0, '00_TONG_HOP_BAO_GIA'!L2 * (1 + '00_TONG_HOP_BAO_GIA'!P2) / '00_TONG_HOP_BAO_GIA'!G2, 0) | K21: ='00_TONG_HOP_BAO_GIA'!Q2 | L21: =('00_TONG_HOP_BAO_GIA'!K2 + '00_TONG_HOP_BAO_GIA'!M2) * (1 + '00_TONG_HOP_BAO_GIA'!P2) | M21: ='00_TONG_HOP_BAO_GIA'!L2 * (1 + '00_TONG_HOP_BAO_GIA'!P2) | N21: ='00_TONG_HOP_BAO_GIA'!R2 | O21: =IF(K21=0, "CẢNH BÁO: Đơn giá = 0. Tra cứu lại Sheet 06!", '00_TONG_HOP_BAO_GIA'!S2)
B22: Canvas loại chống cháy cho quạt TAHK | C22: D900, L=200mm | F22: CANVAS | G22: cái | H22: 40 | I22: =IF('00_TONG_HOP_BAO_GIA'!G3>0, ('00_TONG_HOP_BAO_GIA'!K3 + '00_TONG_HOP_BAO_GIA'!M3) * (1 + '00_TONG_HOP_BAO_GIA'!P3) / '00_TONG_HOP_BAO_GIA'!G3, 0) | J22: =IF('00_TONG_HOP_BAO_GIA'!G3>0, '00_TONG_HOP_BAO_GIA'!L3 * (1 + '00_TONG_HOP_BAO_GIA'!P3) / '00_TONG_HOP_BAO_GIA'!G3, 0) | K22: ='00_TONG_HOP_BAO_GIA'!Q3 | L22: =('00_TONG_HOP_BAO_GIA'!K3 + '00_TONG_HOP_BAO_GIA'!M3) * (1 + '00_TONG_HOP_BAO_GIA'!P3) | M22: ='00_TONG_HOP_BAO_GIA'!L3 * (1 + '00_TONG_HOP_BAO_GIA'!P3) | N22: ='00_TONG_HOP_BAO_GIA'!R3 | O22: =IF(K22=0, "CẢNH BÁO: Đơn giá = 0. Tra cứu lại Sheet 06!", '00_TONG_HOP_BAO_GIA'!S3)
B23: Canvas loại chống cháy cho quạt TAHK | C23: D800, L=200mm | F23: CANVAS | G23: cái | H23: 40 | I23: =IF('00_TONG_HOP_BAO_GIA'!G4>0, ('00_TONG_HOP_BAO_GIA'!K4 + '00_TONG_HOP_BAO_GIA'!M4) * (1 + '00_TONG_HOP_BAO_GIA'!P4) / '00_TONG_HOP_BAO_GIA'!G4, 0) | J23: =IF('00_TONG_HOP_BAO_GIA'!G4>0, '00_TONG_HOP_BAO_GIA'!L4 * (1 + '00_TONG_HOP_BAO_GIA'!P4) / '00_TONG_HOP_BAO_GIA'!G4, 0) | K23: ='00_TONG_HOP_BAO_GIA'!Q4 | L23: =('00_TONG_HOP_BAO_GIA'!K4 + '00_TONG_HOP_BAO_GIA'!M4) * (1 + '00_TONG_HOP_BAO_GIA'!P4) | M23: ='00_TONG_HOP_BAO_GIA'!L4 * (1 + '00_TONG_HOP_BAO_GIA'!P4) | N23: ='00_TONG_HOP_BAO_GIA'!R4 | O23: =IF(K23=0, "CẢNH BÁO: Đơn giá = 0. Tra cứu lại Sheet 06!", '00_TONG_HOP_BAO_GIA'!S4)
B24: Canvas loại chống cháy cho quạt TAHK | C24: D710, L=200mm | F24: CANVAS | G24: cái | H24: 16 | I24: =IF('00_TONG_HOP_BAO_GIA'!G5>0, ('00_TONG_HOP_BAO_GIA'!K5 + '00_TONG_HOP_BAO_GIA'!M5) * (1 + '00_TONG_HOP_BAO_GIA'!P5) / '00_TONG_HOP_BAO_GIA'!G5, 0) | J24: =IF('00_TONG_HOP_BAO_GIA'!G5>0, '00_TONG_HOP_BAO_GIA'!L5 * (1 + '00_TONG_HOP_BAO_GIA'!P5) / '00_TONG_HOP_BAO_GIA'!G5, 0) | K24: ='00_TONG_HOP_BAO_GIA'!Q5 | L24: =('00_TONG_HOP_BAO_GIA'!K5 + '00_TONG_HOP_BAO_GIA'!M5) * (1 + '00_TONG_HOP_BAO_GIA'!P5) | M24: ='00_TONG_HOP_BAO_GIA'!L5 * (1 + '00_TONG_HOP_BAO_GIA'!P5) | N24: ='00_TONG_HOP_BAO_GIA'!R5 | O24: =IF(K24=0, "CẢNH BÁO: Đơn giá = 0. Tra cứu lại Sheet 06!", '00_TONG_HOP_BAO_GIA'!S5)
B25: Canvas loại chống cháy cho quạt TAHK | C25: D560, L=200mm | F25: CANVAS | G25: cái | H25: 16 | I25: =IF('00_TONG_HOP_BAO_GIA'!G6>0, ('00_TONG_HOP_BAO_GIA'!K6 + '00_TONG_HOP_BAO_GIA'!M6) * (1 + '00_TONG_HOP_BAO_GIA'!P6) / '00_TONG_HOP_BAO_GIA'!G6, 0) | J25: =IF('00_TONG_HOP_BAO_GIA'!G6>0, '00_TONG_HOP_BAO_GIA'!L6 * (1 + '00_TONG_HOP_BAO_GIA'!P6) / '00_TONG_HOP_BAO_GIA'!G6, 0) | K25: ='00_TONG_HOP_BAO_GIA'!Q6 | L25: =('00_TONG_HOP_BAO_GIA'!K6 + '00_TONG_HOP_BAO_GIA'!M6) * (1 + '00_TONG_HOP_BAO_GIA'!P6) | M25: ='00_TONG_HOP_BAO_GIA'!L6 * (1 + '00_TONG_HOP_BAO_GIA'!P6) | N25: ='00_TONG_HOP_BAO_GIA'!R6 | O25: =IF(K25=0, "CẢNH BÁO: Đơn giá = 0. Tra cứu lại Sheet 06!", '00_TONG_HOP_BAO_GIA'!S6)
B26: Canvas loại thường cho quạt thông gió | C26: D1000, L=200mm | F26: CANVAS | G26: cái | H26: 32 | I26: =IF('00_TONG_HOP_BAO_GIA'!G7>0, ('00_TONG_HOP_BAO_GIA'!K7 + '00_TONG_HOP_BAO_GIA'!M7) * (1 + '00_TONG_HOP_BAO_GIA'!P7) / '00_TONG_HOP_BAO_GIA'!G7, 0) | J26: =IF('00_TONG_HOP_BAO_GIA'!G7>0, '00_TONG_HOP_BAO_GIA'!L7 * (1 + '00_TONG_HOP_BAO_GIA'!P7) / '00_TONG_HOP_BAO_GIA'!G7, 0) | K26: ='00_TONG_HOP_BAO_GIA'!Q7 | L26: =('00_TONG_HOP_BAO_GIA'!K7 + '00_TONG_HOP_BAO_GIA'!M7) * (1 + '00_TONG_HOP_BAO_GIA'!P7) | M26: ='00_TONG_HOP_BAO_GIA'!L7 * (1 + '00_TONG_HOP_BAO_GIA'!P7) | N26: ='00_TONG_HOP_BAO_GIA'!R7 | O26: =IF(K26=0, "CẢNH BÁO: Đơn giá = 0. Tra cứu lại Sheet 06!", '00_TONG_HOP_BAO_GIA'!S7)
B27: Canvas loại thường cho quạt thông gió | C27: D560, L=200mm | F27: CANVAS | G27: cái | H27: 24 | I27: =IF('00_TONG_HOP_BAO_GIA'!G8>0, ('00_TONG_HOP_BAO_GIA'!K8 + '00_TONG_HOP_BAO_GIA'!M8) * (1 + '00_TONG_HOP_BAO_GIA'!P8) / '00_TONG_HOP_BAO_GIA'!G8, 0) | J27: =IF('00_TONG_HOP_BAO_GIA'!G8>0, '00_TONG_HOP_BAO_GIA'!L8 * (1 + '00_TONG_HOP_BAO_GIA'!P8) / '00_TONG_HOP_BAO_GIA'!G8, 0) | K27: ='00_TONG_HOP_BAO_GIA'!Q8 | L27: =('00_TONG_HOP_BAO_GIA'!K8 + '00_TONG_HOP_BAO_GIA'!M8) * (1 + '00_TONG_HOP_BAO_GIA'!P8) | M27: ='00_TONG_HOP_BAO_GIA'!L8 * (1 + '00_TONG_HOP_BAO_GIA'!P8) | N27: ='00_TONG_HOP_BAO_GIA'!R8 | O27: =IF(K27=0, "CẢNH BÁO: Đơn giá = 0. Tra cứu lại Sheet 06!", '00_TONG_HOP_BAO_GIA'!S8)
A28: =SUBTOTAL(3,$G$7:G28) | B28: Tiêu âm quạt | D28: SX tại Việt Nam theo bản vẽ thiết kế | E28: Việt Nam (SX theo bản vẽ thiết kế) | F28: QUẠT | G28: Bộ | H28: 16
A29: =SUBTOTAL(3,$G$7:G29) | B29: Van 1 chiều NRD 1250x1250 (EI60) | C29: NRD | D29: NSCA, Evegreen, Swind | E29: Việt Nam / Singapore | G29: Cái | H29: 6 | I29: =IF('00_TONG_HOP_BAO_GIA'!G9>0, ('00_TONG_HOP_BAO_GIA'!K9 + '00_TONG_HOP_BAO_GIA'!M9) * (1 + '00_TONG_HOP_BAO_GIA'!P9) / '00_TONG_HOP_BAO_GIA'!G9, 0) | J29: =IF('00_TONG_HOP_BAO_GIA'!G9>0, '00_TONG_HOP_BAO_GIA'!L9 * (1 + '00_TONG_HOP_BAO_GIA'!P9) / '00_TONG_HOP_BAO_GIA'!G9, 0) | K29: ='00_TONG_HOP_BAO_GIA'!Q9 | L29: =('00_TONG_HOP_BAO_GIA'!K9 + '00_TONG_HOP_BAO_GIA'!M9) * (1 + '00_TONG_HOP_BAO_GIA'!P9) | M29: ='00_TONG_HOP_BAO_GIA'!L9 * (1 + '00_TONG_HOP_BAO_GIA'!P9) | N29: ='00_TONG_HOP_BAO_GIA'!R9 | O29: =IF(K29=0, "CẢNH BÁO: Đơn giá = 0. Tra cứu lại Sheet 06!", '00_TONG_HOP_BAO_GIA'!S9)
A30: =SUBTOTAL(3,$G$7:G30) | B30: Van 1 chiều NRD 1700x600 (EI60) | C30: NRD | D30: NSCA, Evegreen, Swind | E30: Việt Nam / Singapore | G30: Cái | H30: 2 | I30: =IF('00_TONG_HOP_BAO_GIA'!G10>0, ('00_TONG_HOP_BAO_GIA'!K10 + '00_TONG_HOP_BAO_GIA'!M10) * (1 + '00_TONG_HOP_BAO_GIA'!P10) / '00_TONG_HOP_BAO_GIA'!G10, 0) | J30: =IF('00_TONG_HOP_BAO_GIA'!G10>0, '00_TONG_HOP_BAO_GIA'!L10 * (1 + '00_TONG_HOP_BAO_GIA'!P10) / '00_TONG_HOP_BAO_GIA'!G10, 0) | K30: ='00_TONG_HOP_BAO_GIA'!Q10 | L30: =('00_TONG_HOP_BAO_GIA'!K10 + '00_TONG_HOP_BAO_GIA'!M10) * (1 + '00_TONG_HOP_BAO_GIA'!P10) | M30: ='00_TONG_HOP_BAO_GIA'!L10 * (1 + '00_TONG_HOP_BAO_GIA'!P10) | N30: ='00_TONG_HOP_BAO_GIA'!R10 | O30: =IF(K30=0, "CẢNH BÁO: Đơn giá = 0. Tra cứu lại Sheet 06!", '00_TONG_HOP_BAO_GIA'!S10)
A31: =SUBTOTAL(3,$G$7:G31) | B31: Van 1 chiều NRD 1200x350 (EI60) | C31: NRD | D31: NSCA, Evegreen, Swind | E31: Việt Nam / Singapore | G31: Cái | H31: 1 | I31: =IF('00_TONG_HOP_BAO_GIA'!G11>0, ('00_TONG_HOP_BAO_GIA'!K11 + '00_TONG_HOP_BAO_GIA'!M11) * (1 + '00_TONG_HOP_BAO_GIA'!P11) / '00_TONG_HOP_BAO_GIA'!G11, 0) | J31: =IF('00_TONG_HOP_BAO_GIA'!G11>0, '00_TONG_HOP_BAO_GIA'!L11 * (1 + '00_TONG_HOP_BAO_GIA'!P11) / '00_TONG_HOP_BAO_GIA'!G11, 0) | K31: ='00_TONG_HOP_BAO_GIA'!Q11 | L31: =('00_TONG_HOP_BAO_GIA'!K11 + '00_TONG_HOP_BAO_GIA'!M11) * (1 + '00_TONG_HOP_BAO_GIA'!P11) | M31: ='00_TONG_HOP_BAO_GIA'!L11 * (1 + '00_TONG_HOP_BAO_GIA'!P11) | N31: ='00_TONG_HOP_BAO_GIA'!R11 | O31: =IF(K31=0, "CẢNH BÁO: Đơn giá = 0. Tra cứu lại Sheet 06!", '00_TONG_HOP_BAO_GIA'!S11)
A32: =SUBTOTAL(3,$G$7:G32) | B32: Van ngăn cháy MFD 1250x1250 (EI60) | C32: MFD | D32: Van: NSCA, Evegreen, Swind, tđ ĐC: Belimo, Johnson Controls, tđ | E32: Việt Nam / Singapore | G32: Cái | H32: 6 | I32: =IF('00_TONG_HOP_BAO_GIA'!G12>0, ('00_TONG_HOP_BAO_GIA'!K12 + '00_TONG_HOP_BAO_GIA'!M12) * (1 + '00_TONG_HOP_BAO_GIA'!P12) / '00_TONG_HOP_BAO_GIA'!G12, 0) | J32: =IF('00_TONG_HOP_BAO_GIA'!G12>0, '00_TONG_HOP_BAO_GIA'!L12 * (1 + '00_TONG_HOP_BAO_GIA'!P12) / '00_TONG_HOP_BAO_GIA'!G12, 0) | K32: ='00_TONG_HOP_BAO_GIA'!Q12 | L32: =('00_TONG_HOP_BAO_GIA'!K12 + '00_TONG_HOP_BAO_GIA'!M12) * (1 + '00_TONG_HOP_BAO_GIA'!P12) | M32: ='00_TONG_HOP_BAO_GIA'!L12 * (1 + '00_TONG_HOP_BAO_GIA'!P12) | N32: ='00_TONG_HOP_BAO_GIA'!R12 | O32: =IF(K32=0, "CẢNH BÁO: Đơn giá = 0. Tra cứu lại Sheet 06!", '00_TONG_HOP_BAO_GIA'!S12)
A33: =SUBTOTAL(3,$G$7:G33) | B33: Van ngăn cháy MFD 1700x600 (EI60) | C33: MFD | D33: Van: NSCA, Evegreen, Swind, tđ ĐC: Belimo, Johnson Controls, tđ | E33: Việt Nam / Singapore | G33: Cái | H33: 2 | I33: =IF('00_TONG_HOP_BAO_GIA'!G13>0, ('00_TONG_HOP_BAO_GIA'!K13 + '00_TONG_HOP_BAO_GIA'!M13) * (1 + '00_TONG_HOP_BAO_GIA'!P13) / '00_TONG_HOP_BAO_GIA'!G13, 0) | J33: =IF('00_TONG_HOP_BAO_GIA'!G13>0, '00_TONG_HOP_BAO_GIA'!L13 * (1 + '00_TONG_HOP_BAO_GIA'!P13) / '00_TONG_HOP_BAO_GIA'!G13, 0) | K33: ='00_TONG_HOP_BAO_GIA'!Q13 | L33: =('00_TONG_HOP_BAO_GIA'!K13 + '00_TONG_HOP_BAO_GIA'!M13) * (1 + '00_TONG_HOP_BAO_GIA'!P13) | M33: ='00_TONG_HOP_BAO_GIA'!L13 * (1 + '00_TONG_HOP_BAO_GIA'!P13) | N33: ='00_TONG_HOP_BAO_GIA'!R13 | O33: =IF(K33=0, "CẢNH BÁO: Đơn giá = 0. Tra cứu lại Sheet 06!", '00_TONG_HOP_BAO_GIA'!S13)
A34: =SUBTOTAL(3,$G$7:G34) | B34: Van ngăn cháy MFD 1200x350 (EI60) | C34: MFD | D34: Van: NSCA, Evegreen, Swind, tđ ĐC: Belimo, Johnson Controls, tđ | E34: Việt Nam / Singapore | G34: Cái | H34: 1 | I34: =IF('00_TONG_HOP_BAO_GIA'!G14>0, ('00_TONG_HOP_BAO_GIA'!K14 + '00_TONG_HOP_BAO_GIA'!M14) * (1 + '00_TONG_HOP_BAO_GIA'!P14) / '00_TONG_HOP_BAO_GIA'!G14, 0) | J34: =IF('00_TONG_HOP_BAO_GIA'!G14>0, '00_TONG_HOP_BAO_GIA'!L14 * (1 + '00_TONG_HOP_BAO_GIA'!P14) / '00_TONG_HOP_BAO_GIA'!G14, 0) | K34: ='00_TONG_HOP_BAO_GIA'!Q14 | L34: =('00_TONG_HOP_BAO_GIA'!K14 + '00_TONG_HOP_BAO_GIA'!M14) * (1 + '00_TONG_HOP_BAO_GIA'!P14) | M34: ='00_TONG_HOP_BAO_GIA'!L14 * (1 + '00_TONG_HOP_BAO_GIA'!P14) | N34: ='00_TONG_HOP_BAO_GIA'!R14 | O34: =IF(K34=0, "CẢNH BÁO: Đơn giá = 0. Tra cứu lại Sheet 06!", '00_TONG_HOP_BAO_GIA'!S14)
A35: =SUBTOTAL(3,$G$7:G35) | B35: Van ngăn cháy MFD 950x400 (EI30) | C35: MFD | D35: Van: NSCA, Evegreen, Swind, tđ ĐC: Belimo, Johnson Controls, tđ | E35: Việt Nam / Singapore | G35: Cái | H35: 3 | I35: =IF('00_TONG_HOP_BAO_GIA'!G15>0, ('00_TONG_HOP_BAO_GIA'!K15 + '00_TONG_HOP_BAO_GIA'!M15) * (1 + '00_TONG_HOP_BAO_GIA'!P15) / '00_TONG_HOP_BAO_GIA'!G15, 0) | J35: =IF('00_TONG_HOP_BAO_GIA'!G15>0, '00_TONG_HOP_BAO_GIA'!L15 * (1 + '00_TONG_HOP_BAO_GIA'!P15) / '00_TONG_HOP_BAO_GIA'!G15, 0) | K35: ='00_TONG_HOP_BAO_GIA'!Q15 | L35: =('00_TONG_HOP_BAO_GIA'!K15 + '00_TONG_HOP_BAO_GIA'!M15) * (1 + '00_TONG_HOP_BAO_GIA'!P15) | M35: ='00_TONG_HOP_BAO_GIA'!L15 * (1 + '00_TONG_HOP_BAO_GIA'!P15) | N35: ='00_TONG_HOP_BAO_GIA'!R15 | O35: =IF(K35=0, "CẢNH BÁO: Đơn giá = 0. Tra cứu lại Sheet 06!", '00_TONG_HOP_BAO_GIA'!S15)
A36: =SUBTOTAL(3,$G$7:G36) | B36: Van ngăn cháy MFD 950x500 (EI30) | C36: MFD | D36: Van: NSCA, Evegreen, Swind, tđ ĐC: Belimo, Johnson Controls, tđ | E36: Việt Nam / Singapore | G36: Cái | H36: 6 | I36: =IF('00_TONG_HOP_BAO_GIA'!G16>0, ('00_TONG_HOP_BAO_GIA'!K16 + '00_TONG_HOP_BAO_GIA'!M16) * (1 + '00_TONG_HOP_BAO_GIA'!P16) / '00_TONG_HOP_BAO_GIA'!G16, 0) | J36: =IF('00_TONG_HOP_BAO_GIA'!G16>0, '00_TONG_HOP_BAO_GIA'!L16 * (1 + '00_TONG_HOP_BAO_GIA'!P16) / '00_TONG_HOP_BAO_GIA'!G16, 0) | K36: ='00_TONG_HOP_BAO_GIA'!Q16 | L36: =('00_TONG_HOP_BAO_GIA'!K16 + '00_TONG_HOP_BAO_GIA'!M16) * (1 + '00_TONG_HOP_BAO_GIA'!P16) | M36: ='00_TONG_HOP_BAO_GIA'!L16 * (1 + '00_TONG_HOP_BAO_GIA'!P16) | N36: ='00_TONG_HOP_BAO_GIA'!R16 | O36: =IF(K36=0, "CẢNH BÁO: Đơn giá = 0. Tra cứu lại Sheet 06!", '00_TONG_HOP_BAO_GIA'!S16)
A37: =SUBTOTAL(3,$G$7:G37) | B37: Van ngăn cháy MFD 950x200 (EI30) | C37: MFD | D37: Van: NSCA, Evegreen, Swind, tđ ĐC: Belimo, Johnson Controls, tđ | E37: Việt Nam / Singapore | G37: Cái | H37: 9 | I37: =IF('00_TONG_HOP_BAO_GIA'!G17>0, ('00_TONG_HOP_BAO_GIA'!K17 + '00_TONG_HOP_BAO_GIA'!M17) * (1 + '00_TONG_HOP_BAO_GIA'!P17) / '00_TONG_HOP_BAO_GIA'!G17, 0) | J37: =IF('00_TONG_HOP_BAO_GIA'!G17>0, '00_TONG_HOP_BAO_GIA'!L17 * (1 + '00_TONG_HOP_BAO_GIA'!P17) / '00_TONG_HOP_BAO_GIA'!G17, 0) | K37: ='00_TONG_HOP_BAO_GIA'!Q17 | L37: =('00_TONG_HOP_BAO_GIA'!K17 + '00_TONG_HOP_BAO_GIA'!M17) * (1 + '00_TONG_HOP_BAO_GIA'!P17) | M37: ='00_TONG_HOP_BAO_GIA'!L17 * (1 + '00_TONG_HOP_BAO_GIA'!P17) | N37: ='00_TONG_HOP_BAO_GIA'!R17 | O37: =IF(K37=0, "CẢNH BÁO: Đơn giá = 0. Tra cứu lại Sheet 06!", '00_TONG_HOP_BAO_GIA'!S17)
A38: =SUBTOTAL(3,$G$7:G38) | B38: Van ngăn cháy MFD 950x300 (EI30) | C38: MFD | D38: Van: NSCA, Evegreen, Swind, tđ ĐC: Belimo, Johnson Controls, tđ | E38: Việt Nam / Singapore | G38: Cái | H38: 12 | I38: =IF('00_TONG_HOP_BAO_GIA'!G18>0, ('00_TONG_HOP_BAO_GIA'!K18 + '00_TONG_HOP_BAO_GIA'!M18) * (1 + '00_TONG_HOP_BAO_GIA'!P18) / '00_TONG_HOP_BAO_GIA'!G18, 0) | J38: =IF('00_TONG_HOP_BAO_GIA'!G18>0, '00_TONG_HOP_BAO_GIA'!L18 * (1 + '00_TONG_HOP_BAO_GIA'!P18) / '00_TONG_HOP_BAO_GIA'!G18, 0) | K38: ='00_TONG_HOP_BAO_GIA'!Q18 | L38: =('00_TONG_HOP_BAO_GIA'!K18 + '00_TONG_HOP_BAO_GIA'!M18) * (1 + '00_TONG_HOP_BAO_GIA'!P18) | M38: ='00_TONG_HOP_BAO_GIA'!L18 * (1 + '00_TONG_HOP_BAO_GIA'!P18) | N38: ='00_TONG_HOP_BAO_GIA'!R18 | O38: =IF(K38=0, "CẢNH BÁO: Đơn giá = 0. Tra cứu lại Sheet 06!", '00_TONG_HOP_BAO_GIA'!S18)
A39: =SUBTOTAL(3,$G$7:G39) | B39: Van chỉnh lưu lượng VCD 2000x500 (EI60) | C39: VCD | D39: NSCA, Evegreen, Swind | E39: Việt Nam / Singapore | G39: Cái | H39: 1 | I39: =IF('00_TONG_HOP_BAO_GIA'!G19>0, ('00_TONG_HOP_BAO_GIA'!K19 + '00_TONG_HOP_BAO_GIA'!M19) * (1 + '00_TONG_HOP_BAO_GIA'!P19) / '00_TONG_HOP_BAO_GIA'!G19, 0) | J39: =IF('00_TONG_HOP_BAO_GIA'!G19>0, '00_TONG_HOP_BAO_GIA'!L19 * (1 + '00_TONG_HOP_BAO_GIA'!P19) / '00_TONG_HOP_BAO_GIA'!G19, 0) | K39: ='00_TONG_HOP_BAO_GIA'!Q19 | L39: =('00_TONG_HOP_BAO_GIA'!K19 + '00_TONG_HOP_BAO_GIA'!M19) * (1 + '00_TONG_HOP_BAO_GIA'!P19) | M39: ='00_TONG_HOP_BAO_GIA'!L19 * (1 + '00_TONG_HOP_BAO_GIA'!P19) | N39: ='00_TONG_HOP_BAO_GIA'!R19 | O39: =IF(K39=0, "CẢNH BÁO: Đơn giá = 0. Tra cứu lại Sheet 06!", '00_TONG_HOP_BAO_GIA'!S19)
A40: =SUBTOTAL(3,$G$7:G40) | B40: Van chỉnh lưu lượng VCD 1300x400 (EI60) | C40: VCD | D40: NSCA, Evegreen, Swind | E40: Việt Nam / Singapore | G40: Cái | H40: 2 | I40: =IF('00_TONG_HOP_BAO_GIA'!G20>0, ('00_TONG_HOP_BAO_GIA'!K20 + '00_TONG_HOP_BAO_GIA'!M20) * (1 + '00_TONG_HOP_BAO_GIA'!P20) / '00_TONG_HOP_BAO_GIA'!G20, 0) | J40: =IF('00_TONG_HOP_BAO_GIA'!G20>0, '00_TONG_HOP_BAO_GIA'!L20 * (1 + '00_TONG_HOP_BAO_GIA'!P20) / '00_TONG_HOP_BAO_GIA'!G20, 0) | K40: ='00_TONG_HOP_BAO_GIA'!Q20 | L40: =('00_TONG_HOP_BAO_GIA'!K20 + '00_TONG_HOP_BAO_GIA'!M20) * (1 + '00_TONG_HOP_BAO_GIA'!P20) | M40: ='00_TONG_HOP_BAO_GIA'!L20 * (1 + '00_TONG_HOP_BAO_GIA'!P20) | N40: ='00_TONG_HOP_BAO_GIA'!R20 | O40: =IF(K40=0, "CẢNH BÁO: Đơn giá = 0. Tra cứu lại Sheet 06!", '00_TONG_HOP_BAO_GIA'!S20)
... A52: =SUBTOTAL(3,$G$7:G52) | B52: Louver EAL 2750x750+IS | C52: EAL | D52: NSCA, Evegreen, Swind | E52: Việt Nam (SX theo bản vẽ thiết kế) | G52: Cái | H52: 2 | I52: =IF('00_TONG_HOP_BAO_GIA'!G32>0, ('00_TONG_HOP_BAO_GIA'!K32 + '00_TONG_HOP_BAO_GIA'!M32) * (1 + '00_TONG_HOP_BAO_GIA'!P32) / '00_TONG_HOP_BAO_GIA'!G32, 0) | J52: =IF('00_TONG_HOP_BAO_GIA'!G32>0, '00_TONG_HOP_BAO_GIA'!L32 * (1 + '00_TONG_HOP_BAO_GIA'!P32) / '00_TONG_HOP_BAO_GIA'!G32, 0) | K52: ='00_TONG_HOP_BAO_GIA'!Q32 | L52: =('00_TONG_HOP_BAO_GIA'!K32 + '00_TONG_HOP_BAO_GIA'!M32) * (1 + '00_TONG_HOP_BAO_GIA'!P32) | M52: ='00_TONG_HOP_BAO_GIA'!L32 * (1 + '00_TONG_HOP_BAO_GIA'!P32) | N52: ='00_TONG_HOP_BAO_GIA'!R32 | O52: =IF(K52=0, "CẢNH BÁO: Đơn giá = 0. Tra cứu lại Sheet 06!", '00_TONG_HOP_BAO_GIA'!S32)
B53: Box miệng gió 600x300 | D53: NSCA, Evegreen, Swind | E53: Việt Nam (SX theo bản vẽ thiết kế) | G53: Cái | H53: 112 | I53: =IF('00_TONG_HOP_BAO_GIA'!G33>0, ('00_TONG_HOP_BAO_GIA'!K33 + '00_TONG_HOP_BAO_GIA'!M33) * (1 + '00_TONG_HOP_BAO_GIA'!P33) / '00_TONG_HOP_BAO_GIA'!G33, 0) | J53: =IF('00_TONG_HOP_BAO_GIA'!G33>0, '00_TONG_HOP_BAO_GIA'!L33 * (1 + '00_TONG_HOP_BAO_GIA'!P33) / '00_TONG_HOP_BAO_GIA'!G33, 0) | K53: ='00_TONG_HOP_BAO_GIA'!Q33 | L53: =('00_TONG_HOP_BAO_GIA'!K33 + '00_TONG_HOP_BAO_GIA'!M33) * (1 + '00_TONG_HOP_BAO_GIA'!P33) | M53: ='00_TONG_HOP_BAO_GIA'!L33 * (1 + '00_TONG_HOP_BAO_GIA'!P33) | N53: ='00_TONG_HOP_BAO_GIA'!R33 | O53: =IF(K53=0, "CẢNH BÁO: Đơn giá = 0. Tra cứu lại Sheet 06!", '00_TONG_HOP_BAO_GIA'!S33)
B54: Box miệng gió 1200x600 | D54: NSCA, Evegreen, Swind | E54: Việt Nam (SX theo bản vẽ thiết kế) | G54: Cái | H54: 2 | I54: =IF('00_TONG_HOP_BAO_GIA'!G34>0, ('00_TONG_HOP_BAO_GIA'!K34 + '00_TONG_HOP_BAO_GIA'!M34) * (1 + '00_TONG_HOP_BAO_GIA'!P34) / '00_TONG_HOP_BAO_GIA'!G34, 0) | J54: =IF('00_TONG_HOP_BAO_GIA'!G34>0, '00_TONG_HOP_BAO_GIA'!L34 * (1 + '00_TONG_HOP_BAO_GIA'!P34) / '00_TONG_HOP_BAO_GIA'!G34, 0) | K54: ='00_TONG_HOP_BAO_GIA'!Q34 | L54: =('00_TONG_HOP_BAO_GIA'!K34 + '00_TONG_HOP_BAO_GIA'!M34) * (1 + '00_TONG_HOP_BAO_GIA'!P34) | M54: ='00_TONG_HOP_BAO_GIA'!L34 * (1 + '00_TONG_HOP_BAO_GIA'!P34) | N54: ='00_TONG_HOP_BAO_GIA'!R34 | O54: =IF(K54=0, "CẢNH BÁO: Đơn giá = 0. Tra cứu lại Sheet 06!", '00_TONG_HOP_BAO_GIA'!S34)
B55: Box miệng gió 10006300 | D55: NSCA, Evegreen, Swind | E55: Việt Nam (SX theo bản vẽ thiết kế) | G55: Cái | H55: 52 | I55: =IF('00_TONG_HOP_BAO_GIA'!G35>0, ('00_TONG_HOP_BAO_GIA'!K35 + '00_TONG_HOP_BAO_GIA'!M35) * (1 + '00_TONG_HOP_BAO_GIA'!P35) / '00_TONG_HOP_BAO_GIA'!G35, 0) | J55: =IF('00_TONG_HOP_BAO_GIA'!G35>0, '00_TONG_HOP_BAO_GIA'!L35 * (1 + '00_TONG_HOP_BAO_GIA'!P35) / '00_TONG_HOP_BAO_GIA'!G35, 0) | K55: ='00_TONG_HOP_BAO_GIA'!Q35 | L55: =('00_TONG_HOP_BAO_GIA'!K35 + '00_TONG_HOP_BAO_GIA'!M35) * (1 + '00_TONG_HOP_BAO_GIA'!P35) | M55: ='00_TONG_HOP_BAO_GIA'!L35 * (1 + '00_TONG_HOP_BAO_GIA'!P35) | N55: ='00_TONG_HOP_BAO_GIA'!R35 | O55: =IF(K55=0, "CẢNH BÁO: Đơn giá = 0. Tra cứu lại Sheet 06!", '00_TONG_HOP_BAO_GIA'!S35)
A56: =SUBTOTAL(3,$G$7:G56) | B56: Vật tư phụ, phụ kiện | F56: VTP | G56: Lô | H56: 1 | I56: =IF('00_TONG_HOP_BAO_GIA'!G36>0, ('00_TONG_HOP_BAO_GIA'!K36 + '00_TONG_HOP_BAO_GIA'!M36) * (1 + '00_TONG_HOP_BAO_GIA'!P36) / '00_TONG_HOP_BAO_GIA'!G36, 0) | J56: =IF('00_TONG_HOP_BAO_GIA'!G36>0, '00_TONG_HOP_BAO_GIA'!L36 * (1 + '00_TONG_HOP_BAO_GIA'!P36) / '00_TONG_HOP_BAO_GIA'!G36, 0) | K56: ='00_TONG_HOP_BAO_GIA'!Q36 | L56: =('00_TONG_HOP_BAO_GIA'!K36 + '00_TONG_HOP_BAO_GIA'!M36) * (1 + '00_TONG_HOP_BAO_GIA'!P36) | M56: ='00_TONG_HOP_BAO_GIA'!L36 * (1 + '00_TONG_HOP_BAO_GIA'!P36) | N56: ='00_TONG_HOP_BAO_GIA'!R36 | O56: =IF(K56=0, "CẢNH BÁO: Đơn giá = 0. Tra cứu lại Sheet 06!", '00_TONG_HOP_BAO_GIA'!S36)
B57: Ống thông gió và phụ kiện, box miệng gió | F57: M
A58: =SUBTOTAL(3,$G$7:G58) | B58: Tole 0.75mm phủ lớp mạ kẽm Z180 | C58: Diện tích tính theo kích thước hình học (Hoàn thiện) | D58: Hoa Sen, Phương Nam | E58: Hoa Sen / Phương Nam / Nam Kim / tđ | G58: m2 | H58: 2633.4 | I58: =IF('00_TONG_HOP_BAO_GIA'!G37>0, ('00_TONG_HOP_BAO_GIA'!K37 + '00_TONG_HOP_BAO_GIA'!M37) * (1 + '00_TONG_HOP_BAO_GIA'!P37) / '00_TONG_HOP_BAO_GIA'!G37, 0) | J58: =IF('00_TONG_HOP_BAO_GIA'!G37>0, '00_TONG_HOP_BAO_GIA'!L37 * (1 + '00_TONG_HOP_BAO_GIA'!P37) / '00_TONG_HOP_BAO_GIA'!G37, 0) | K58: ='00_TONG_HOP_BAO_GIA'!Q37 | L58: =('00_TONG_HOP_BAO_GIA'!K37 + '00_TONG_HOP_BAO_GIA'!M37) * (1 + '00_TONG_HOP_BAO_GIA'!P37) | M58: ='00_TONG_HOP_BAO_GIA'!L37 * (1 + '00_TONG_HOP_BAO_GIA'!P37) | N58: ='00_TONG_HOP_BAO_GIA'!R37 | O58: =IF(K58=0, "CẢNH BÁO: Đơn giá = 0. Tra cứu lại Sheet 06!", '00_TONG_HOP_BAO_GIA'!S37)
A59: =SUBTOTAL(3,$G$7:G59) | B59: Tole 0.95mm phủ lớp mạ kẽm Z180 | C59: Diện tích tính theo kích thước hình học (Hoàn thiện) | D59: Hoa Sen, Phương Nam | E59: Hoa Sen / Phương Nam / Nam Kim / tđ | G59: m2 | H59: 1291.1 | I59: =IF('00_TONG_HOP_BAO_GIA'!G38>0, ('00_TONG_HOP_BAO_GIA'!K38 + '00_TONG_HOP_BAO_GIA'!M38) * (1 + '00_TONG_HOP_BAO_GIA'!P38) / '00_TONG_HOP_BAO_GIA'!G38, 0) | J59: =IF('00_TONG_HOP_BAO_GIA'!G38>0, '00_TONG_HOP_BAO_GIA'!L38 * (1 + '00_TONG_HOP_BAO_GIA'!P38) / '00_TONG_HOP_BAO_GIA'!G38, 0) | K59: ='00_TONG_HOP_BAO_GIA'!Q38 | L59: =('00_TONG_HOP_BAO_GIA'!K38 + '00_TONG_HOP_BAO_GIA'!M38) * (1 + '00_TONG_HOP_BAO_GIA'!P38) | M59: ='00_TONG_HOP_BAO_GIA'!L38 * (1 + '00_TONG_HOP_BAO_GIA'!P38) | N59: ='00_TONG_HOP_BAO_GIA'!R38 | O59: =IF(K59=0, "CẢNH BÁO: Đơn giá = 0. Tra cứu lại Sheet 06!", '00_TONG_HOP_BAO_GIA'!S38)
A60: =SUBTOTAL(3,$G$7:G60) | B60: Tole 1.15mm phủ lớp mạ kẽm Z180 | C60: Diện tích tính theo kích thước hình học (Hoàn thiện) | D60: Hoa Sen, Phương Nam | E60: Hoa Sen / Phương Nam / Nam Kim / tđ | G60: m2 | H60: 3070.55 | I60: =IF('00_TONG_HOP_BAO_GIA'!G39>0, ('00_TONG_HOP_BAO_GIA'!K39 + '00_TONG_HOP_BAO_GIA'!M39) * (1 + '00_TONG_HOP_BAO_GIA'!P39) / '00_TONG_HOP_BAO_GIA'!G39, 0) | J60: =IF('00_TONG_HOP_BAO_GIA'!G39>0, '00_TONG_HOP_BAO_GIA'!L39 * (1 + '00_TONG_HOP_BAO_GIA'!P39) / '00_TONG_HOP_BAO_GIA'!G39, 0) | K60: ='00_TONG_HOP_BAO_GIA'!Q39 | L60: =('00_TONG_HOP_BAO_GIA'!K39 + '00_TONG_HOP_BAO_GIA'!M39) * (1 + '00_TONG_HOP_BAO_GIA'!P39) | M60: ='00_TONG_HOP_BAO_GIA'!L39 * (1 + '00_TONG_HOP_BAO_GIA'!P39) | N60: ='00_TONG_HOP_BAO_GIA'!R39 | O60: =IF(K60=0, "CẢNH BÁO: Đơn giá = 0. Tra cứu lại Sheet 06!", '00_TONG_HOP_BAO_GIA'!S39)
A61: =SUBTOTAL(3,$G$7:G61) | B61: Tole ZAM 1.15mm | C61: Diện tích tính theo kích thước hình học (Hoàn thiện) | D61: Hoa Sen, Phương Nam | E61: Hoa Sen / Phương Nam / Nam Kim / tđ | G61: m2 | H61: 138 | I61: =IF('00_TONG_HOP_BAO_GIA'!G40>0, ('00_TONG_HOP_BAO_GIA'!K40 + '00_TONG_HOP_BAO_GIA'!M40) * (1 + '00_TONG_HOP_BAO_GIA'!P40) / '00_TONG_HOP_BAO_GIA'!G40, 0) | J61: =IF('00_TONG_HOP_BAO_GIA'!G40>0, '00_TONG_HOP_BAO_GIA'!L40 * (1 + '00_TONG_HOP_BAO_GIA'!P40) / '00_TONG_HOP_BAO_GIA'!G40, 0) | K61: ='00_TONG_HOP_BAO_GIA'!Q40 | L61: =('00_TONG_HOP_BAO_GIA'!K40 + '00_TONG_HOP_BAO_GIA'!M40) * (1 + '00_TONG_HOP_BAO_GIA'!P40) | M61: ='00_TONG_HOP_BAO_GIA'!L40 * (1 + '00_TONG_HOP_BAO_GIA'!P40) | N61: ='00_TONG_HOP_BAO_GIA'!R40 | O61: =IF(K61=0, "CẢNH BÁO: Đơn giá = 0. Tra cứu lại Sheet 06!", '00_TONG_HOP_BAO_GIA'!S40)
A62: =SUBTOTAL(3,$G$7:G62) | B62: Lưới bảo vệ | G62: cái | H62: 3 | I62: =IF('00_TONG_HOP_BAO_GIA'!G41>0, ('00_TONG_HOP_BAO_GIA'!K41 + '00_TONG_HOP_BAO_GIA'!M41) * (1 + '00_TONG_HOP_BAO_GIA'!P41) / '00_TONG_HOP_BAO_GIA'!G41, 0) | J62: =IF('00_TONG_HOP_BAO_GIA'!G41>0, '00_TONG_HOP_BAO_GIA'!L41 * (1 + '00_TONG_HOP_BAO_GIA'!P41) / '00_TONG_HOP_BAO_GIA'!G41, 0) | K62: ='00_TONG_HOP_BAO_GIA'!Q41 | L62: =('00_TONG_HOP_BAO_GIA'!K41 + '00_TONG_HOP_BAO_GIA'!M41) * (1 + '00_TONG_HOP_BAO_GIA'!P41) | M62: ='00_TONG_HOP_BAO_GIA'!L41 * (1 + '00_TONG_HOP_BAO_GIA'!P41) | N62: ='00_TONG_HOP_BAO_GIA'!R41 | O62: =IF(K62=0, "CẢNH BÁO: Đơn giá = 0. Tra cứu lại Sheet 06!", '00_TONG_HOP_BAO_GIA'!S41)
A63: =SUBTOTAL(3,$G$7:G63) | B63: Lớp chống cháy EI30 | C63: Diện tích tính theo kích thước hình học (Hoàn thiện) | D63: 3M, Flamebar, Kova | E63: 3M / Flamebar / Hilti / tđ | G63: m2 | H63: 3621.25 | I63: =IF('00_TONG_HOP_BAO_GIA'!G42>0, ('00_TONG_HOP_BAO_GIA'!K42 + '00_TONG_HOP_BAO_GIA'!M42) * (1 + '00_TONG_HOP_BAO_GIA'!P42) / '00_TONG_HOP_BAO_GIA'!G42, 0) | J63: =IF('00_TONG_HOP_BAO_GIA'!G42>0, '00_TONG_HOP_BAO_GIA'!L42 * (1 + '00_TONG_HOP_BAO_GIA'!P42) / '00_TONG_HOP_BAO_GIA'!G42, 0) | K63: ='00_TONG_HOP_BAO_GIA'!Q42 | L63: =('00_TONG_HOP_BAO_GIA'!K42 + '00_TONG_HOP_BAO_GIA'!M42) * (1 + '00_TONG_HOP_BAO_GIA'!P42) | M63: ='00_TONG_HOP_BAO_GIA'!L42 * (1 + '00_TONG_HOP_BAO_GIA'!P42) | N63: ='00_TONG_HOP_BAO_GIA'!R42 | O63: =IF(K63=0, "CẢNH BÁO: Đơn giá = 0. Tra cứu lại Sheet 06!", '00_TONG_HOP_BAO_GIA'!S42)
A64: =SUBTOTAL(3,$G$7:G64) | B64: Lớp chống cháy EI60 | C64: Diện tích tính theo kích thước hình học (Hoàn thiện) | D64: 3M, Flamebar, Kova | E64: 3M / Flamebar / Hilti / tđ | G64: m2 | H64: 2821 | I64: =IF('00_TONG_HOP_BAO_GIA'!G43>0, ('00_TONG_HOP_BAO_GIA'!K43 + '00_TONG_HOP_BAO_GIA'!M43) * (1 + '00_TONG_HOP_BAO_GIA'!P43) / '00_TONG_HOP_BAO_GIA'!G43, 0) | J64: =IF('00_TONG_HOP_BAO_GIA'!G43>0, '00_TONG_HOP_BAO_GIA'!L43 * (1 + '00_TONG_HOP_BAO_GIA'!P43) / '00_TONG_HOP_BAO_GIA'!G43, 0) | K64: ='00_TONG_HOP_BAO_GIA'!Q43 | L64: =('00_TONG_HOP_BAO_GIA'!K43 + '00_TONG_HOP_BAO_GIA'!M43) * (1 + '00_TONG_HOP_BAO_GIA'!P43) | M64: ='00_TONG_HOP_BAO_GIA'!L43 * (1 + '00_TONG_HOP_BAO_GIA'!P43) | N64: ='00_TONG_HOP_BAO_GIA'!R43 | O64: =IF(K64=0, "CẢNH BÁO: Đơn giá = 0. Tra cứu lại Sheet 06!", '00_TONG_HOP_BAO_GIA'!S43)
A65: =SUBTOTAL(3,$G$7:G65) | B65: Vật tư phụ, phụ kiện | G65: Lô | H65: 1 | I65: =IF('00_TONG_HOP_BAO_GIA'!G44>0, ('00_TONG_HOP_BAO_GIA'!K44 + '00_TONG_HOP_BAO_GIA'!M44) * (1 + '00_TONG_HOP_BAO_GIA'!P44) / '00_TONG_HOP_BAO_GIA'!G44, 0) | J65: =IF('00_TONG_HOP_BAO_GIA'!G44>0, '00_TONG_HOP_BAO_GIA'!L44 * (1 + '00_TONG_HOP_BAO_GIA'!P44) / '00_TONG_HOP_BAO_GIA'!G44, 0) | K65: ='00_TONG_HOP_BAO_GIA'!Q44 | L65: =('00_TONG_HOP_BAO_GIA'!K44 + '00_TONG_HOP_BAO_GIA'!M44) * (1 + '00_TONG_HOP_BAO_GIA'!P44) | M65: ='00_TONG_HOP_BAO_GIA'!L44 * (1 + '00_TONG_HOP_BAO_GIA'!P44) | N65: ='00_TONG_HOP_BAO_GIA'!R44 | O65: =IF(K65=0, "CẢNH BÁO: Đơn giá = 0. Tra cứu lại Sheet 06!", '00_TONG_HOP_BAO_GIA'!S44)
A66: A2 | B66: HỆ THỐNG TẠO ÁP | F66: M
A67: =SUBTOTAL(3,$G$7:G67) | B67: Quạt hướng trục BPF-B2-Z2-01 400 l/s @ 650 Pa, chống cháy 300°C trong 2h | C67: BPF | D67: Fantech (ELTA Fans), Systemair, Wolter, Kruger | F67: QUẠT | G67: Cái | H67: 1
A68: =SUBTOTAL(3,$G$7:G68) | B68: Quạt hướng trục BPF-B2-Z2-02 1200 l/s @ 550 Pa, chống cháy 300°C trong 2h | C68: BPF | D68: Fantech (ELTA Fans), Systemair, Wolter, Kruger | F68: QUẠT | G68: Cái | H68: 1
A69: =SUBTOTAL(3,$G$7:G69) | B69: Quạt hướng trục BPF-B2-Z2-03 4200 l/s @ 400 Pa, chống cháy 300°C trong 2h | C69: BPF | D69: Fantech (ELTA Fans), Systemair, Wolter, Kruger | F69: QUẠT | G69: Cái | H69: 1
A70: =SUBTOTAL(3,$G$7:G70) | B70: Quạt hướng trục BPF-B2-Z2-04 4200 l/s @ 400 Pa, chống cháy 300°C trong 2h | C70: BPF | D70: Fantech (ELTA Fans), Systemair, Wolter, Kruger | F70: QUẠT | G70: Cái | H70: 1
A71: =SUBTOTAL(3,$G$7:G71) | B71: Quạt hướng trục BPF-B1-Z1-01 5400 l/s @ 700 Pa, chống cháy 300°C trong 2h | C71: BPF | D71: Fantech (ELTA Fans), Systemair, Wolter, Kruger | F71: QUẠT | G71: Cái | H71: 1
A72: =SUBTOTAL(3,$G$7:G72) | B72: Quạt hướng trục BPF-B1-Z1-02 5800 l/s @ 700 Pa, chống cháy 300°C trong 2h | C72: BPF | D72: Fantech (ELTA Fans), Systemair, Wolter, Kruger | F72: QUẠT | G72: Cái | H72: 1
A73: =SUBTOTAL(3,$G$7:G73) | B73: Quạt hướng trục BPF-B1-Z1-03 400 l/s @ 550 Pa, chống cháy 300°C trong 2h | C73: BPF | D73: Fantech (ELTA Fans), Systemair, Wolter, Kruger | F73: QUẠT | G73: Cái | H73: 1
A74: =SUBTOTAL(3,$G$7:G74) | B74: Quạt hướng trục BPF-B1-Z1-04 5400 l/s @ 450 Pa, chống cháy 300°C trong 2h | C74: BPF | D74: Fantech (ELTA Fans), Systemair, Wolter, Kruger | F74: QUẠT | G74: Cái | H74: 1
A75: =SUBTOTAL(3,$G$7:G75) | B75: Quạt hướng trục BPF-B1-Z1-05 1100 l/s @ 500 Pa, chống cháy 300°C trong 2h | C75: BPF | D75: Fantech (ELTA Fans), Systemair, Wolter, Kruger | F75: QUẠT | G75: Cái | H75: 1
A76: =SUBTOTAL(3,$G$7:G76) | B76: Quạt hướng trục BPF-B1-Z1-06 400 l/s @ 650 Pa, chống cháy 300°C trong 2h | C76: BPF | D76: Fantech (ELTA Fans), Systemair, Wolter, Kruger | F76: QUẠT | G76: Cái | H76: 1
A77: =SUBTOTAL(3,$G$7:G77) | B77: Quạt hướng trục BPF-B1-Z2-01 400 l/s @ 400 Pa, chống cháy 300°C trong 2h | C77: BPF | D77: Fantech (ELTA Fans), Systemair, Wolter, Kruger | F77: QUẠT | G77: Cái | H77: 1
A78: =SUBTOTAL(3,$G$7:G78) | B78: Quạt hướng trục BPF-B1-Z2-02 5400 l/s @ 700 Pa, chống cháy 300°C trong 2h | C78: BPF | D78: Fantech (ELTA Fans), Systemair, Wolter, Kruger | F78: QUẠT | G78: Cái | H78: 1
... A94: =SUBTOTAL(3,$G$7:G94) | B94: Quạt hướng trục BPF-A1.1-RF-01 6100 l/s @ 600 Pa, chống cháy 300°C trong 2h | C94: BPF | D94: Fantech (ELTA Fans), Systemair, Wolter, Kruger | F94: QUẠT | G94: Cái | H94: 1
A95: =SUBTOTAL(3,$G$7:G95) | B95: Van 1 chiều NRD 300x200 (EI60) | C95: NRD | D95: NSCA, Evegreen, Swind, tđ | E95: Việt Nam / Singapore | G95: Cái | H95: 1 | I95: =IF('00_TONG_HOP_BAO_GIA'!G45>0, ('00_TONG_HOP_BAO_GIA'!K45 + '00_TONG_HOP_BAO_GIA'!M45) * (1 + '00_TONG_HOP_BAO_GIA'!P45) / '00_TONG_HOP_BAO_GIA'!G45, 0) | J95: =IF('00_TONG_HOP_BAO_GIA'!G45>0, '00_TONG_HOP_BAO_GIA'!L45 * (1 + '00_TONG_HOP_BAO_GIA'!P45) / '00_TONG_HOP_BAO_GIA'!G45, 0) | K95: ='00_TONG_HOP_BAO_GIA'!Q45 | L95: =('00_TONG_HOP_BAO_GIA'!K45 + '00_TONG_HOP_BAO_GIA'!M45) * (1 + '00_TONG_HOP_BAO_GIA'!P45) | M95: ='00_TONG_HOP_BAO_GIA'!L45 * (1 + '00_TONG_HOP_BAO_GIA'!P45) | N95: ='00_TONG_HOP_BAO_GIA'!R45 | O95: =IF(K95=0, "CẢNH BÁO: Đơn giá = 0. Tra cứu lại Sheet 06!", '00_TONG_HOP_BAO_GIA'!S45)
A96: =SUBTOTAL(3,$G$7:G96) | B96: Van 1 chiều NRD 700x500 (EI60) | C96: NRD | D96: NSCA, Evegreen, Swind, tđ | E96: Việt Nam / Singapore | G96: Cái | H96: 2 | I96: =IF('00_TONG_HOP_BAO_GIA'!G46>0, ('00_TONG_HOP_BAO_GIA'!K46 + '00_TONG_HOP_BAO_GIA'!M46) * (1 + '00_TONG_HOP_BAO_GIA'!P46) / '00_TONG_HOP_BAO_GIA'!G46, 0) | J96: =IF('00_TONG_HOP_BAO_GIA'!G46>0, '00_TONG_HOP_BAO_GIA'!L46 * (1 + '00_TONG_HOP_BAO_GIA'!P46) / '00_TONG_HOP_BAO_GIA'!G46, 0) | K96: ='00_TONG_HOP_BAO_GIA'!Q46 | L96: =('00_TONG_HOP_BAO_GIA'!K46 + '00_TONG_HOP_BAO_GIA'!M46) * (1 + '00_TONG_HOP_BAO_GIA'!P46) | M96: ='00_TONG_HOP_BAO_GIA'!L46 * (1 + '00_TONG_HOP_BAO_GIA'!P46) | N96: ='00_TONG_HOP_BAO_GIA'!R46 | O96: =IF(K96=0, "CẢNH BÁO: Đơn giá = 0. Tra cứu lại Sheet 06!", '00_TONG_HOP_BAO_GIA'!S46)
A97: =SUBTOTAL(3,$G$7:G97) | B97: Van 1 chiều NRD 700x800 (EI60) | C97: NRD | D97: NSCA, Evegreen, Swind, tđ | E97: Việt Nam / Singapore | G97: Cái | H97: 2 | I97: =IF('00_TONG_HOP_BAO_GIA'!G47>0, ('00_TONG_HOP_BAO_GIA'!K47 + '00_TONG_HOP_BAO_GIA'!M47) * (1 + '00_TONG_HOP_BAO_GIA'!P47) / '00_TONG_HOP_BAO_GIA'!G47, 0) | J97: =IF('00_TONG_HOP_BAO_GIA'!G47>0, '00_TONG_HOP_BAO_GIA'!L47 * (1 + '00_TONG_HOP_BAO_GIA'!P47) / '00_TONG_HOP_BAO_GIA'!G47, 0) | K97: ='00_TONG_HOP_BAO_GIA'!Q47 | L97: =('00_TONG_HOP_BAO_GIA'!K47 + '00_TONG_HOP_BAO_GIA'!M47) * (1 + '00_TONG_HOP_BAO_GIA'!P47) | M97: ='00_TONG_HOP_BAO_GIA'!L47 * (1 + '00_TONG_HOP_BAO_GIA'!P47) | N97: ='00_TONG_HOP_BAO_GIA'!R47 | O97: =IF(K97=0, "CẢNH BÁO: Đơn giá = 0. Tra cứu lại Sheet 06!", '00_TONG_HOP_BAO_GIA'!S47)
A98: =SUBTOTAL(3,$G$7:G98) | B98: Van 1 chiều NRD 250X200(EI60) | C98: NRD | D98: NSCA, Evegreen, Swind, tđ | E98: Việt Nam / Singapore | G98: Cái | H98: 1 | I98: =IF('00_TONG_HOP_BAO_GIA'!G48>0, ('00_TONG_HOP_BAO_GIA'!K48 + '00_TONG_HOP_BAO_GIA'!M48) * (1 + '00_TONG_HOP_BAO_GIA'!P48) / '00_TONG_HOP_BAO_GIA'!G48, 0) | J98: =IF('00_TONG_HOP_BAO_GIA'!G48>0, '00_TONG_HOP_BAO_GIA'!L48 * (1 + '00_TONG_HOP_BAO_GIA'!P48) / '00_TONG_HOP_BAO_GIA'!G48, 0) | K98: ='00_TONG_HOP_BAO_GIA'!Q48 | L98: =('00_TONG_HOP_BAO_GIA'!K48 + '00_TONG_HOP_BAO_GIA'!M48) * (1 + '00_TONG_HOP_BAO_GIA'!P48) | M98: ='00_TONG_HOP_BAO_GIA'!L48 * (1 + '00_TONG_HOP_BAO_GIA'!P48) | N98: ='00_TONG_HOP_BAO_GIA'!R48 | O98: =IF(K98=0, "CẢNH BÁO: Đơn giá = 0. Tra cứu lại Sheet 06!", '00_TONG_HOP_BAO_GIA'!S48)
A99: =SUBTOTAL(3,$G$7:G99) | B99: Van 1 chiều NRD 900x400 (EI60) | C99: NRD | D99: NSCA, Evegreen, Swind, tđ | E99: Việt Nam / Singapore | G99: Cái | H99: 2 | I99: =IF('00_TONG_HOP_BAO_GIA'!G49>0, ('00_TONG_HOP_BAO_GIA'!K49 + '00_TONG_HOP_BAO_GIA'!M49) * (1 + '00_TONG_HOP_BAO_GIA'!P49) / '00_TONG_HOP_BAO_GIA'!G49, 0) | J99: =IF('00_TONG_HOP_BAO_GIA'!G49>0, '00_TONG_HOP_BAO_GIA'!L49 * (1 + '00_TONG_HOP_BAO_GIA'!P49) / '00_TONG_HOP_BAO_GIA'!G49, 0) | K99: ='00_TONG_HOP_BAO_GIA'!Q49 | L99: =('00_TONG_HOP_BAO_GIA'!K49 + '00_TONG_HOP_BAO_GIA'!M49) * (1 + '00_TONG_HOP_BAO_GIA'!P49) | M99: ='00_TONG_HOP_BAO_GIA'!L49 * (1 + '00_TONG_HOP_BAO_GIA'!P49) | N99: ='00_TONG_HOP_BAO_GIA'!R49 | O99: =IF(K99=0, "CẢNH BÁO: Đơn giá = 0. Tra cứu lại Sheet 06!", '00_TONG_HOP_BAO_GIA'!S49)
A100: =SUBTOTAL(3,$G$7:G100) | B100: Van 1 chiều NRD 300x300 (EI60) | C100: NRD | D100: NSCA, Evegreen, Swind, tđ | E100: Việt Nam / Singapore | G100: Cái | H100: 1 | I100: =IF('00_TONG_HOP_BAO_GIA'!G50>0, ('00_TONG_HOP_BAO_GIA'!K50 + '00_TONG_HOP_BAO_GIA'!M50) * (1 + '00_TONG_HOP_BAO_GIA'!P50) / '00_TONG_HOP_BAO_GIA'!G50, 0) | J100: =IF('00_TONG_HOP_BAO_GIA'!G50>0, '00_TONG_HOP_BAO_GIA'!L50 * (1 + '00_TONG_HOP_BAO_GIA'!P50) / '00_TONG_HOP_BAO_GIA'!G50, 0) | K100: ='00_TONG_HOP_BAO_GIA'!Q50 | L100: =('00_TONG_HOP_BAO_GIA'!K50 + '00_TONG_HOP_BAO_GIA'!M50) * (1 + '00_TONG_HOP_BAO_GIA'!P50) | M100: ='00_TONG_HOP_BAO_GIA'!L50 * (1 + '00_TONG_HOP_BAO_GIA'!P50) | N100: ='00_TONG_HOP_BAO_GIA'!R50 | O100: =IF(K100=0, "CẢNH BÁO: Đơn giá = 0. Tra cứu lại Sheet 06!", '00_TONG_HOP_BAO_GIA'!S50)
A101: =SUBTOTAL(3,$G$7:G101) | B101: Van 1 chiều NRD 350x250 (EI60) | C101: NRD | D101: NSCA, Evegreen, Swind, tđ | E101: Việt Nam / Singapore | G101: Cái | H101: 1 | I101: =IF('00_TONG_HOP_BAO_GIA'!G51>0, ('00_TONG_HOP_BAO_GIA'!K51 + '00_TONG_HOP_BAO_GIA'!M51) * (1 + '00_TONG_HOP_BAO_GIA'!P51) / '00_TONG_HOP_BAO_GIA'!G51, 0) | J101: =IF('00_TONG_HOP_BAO_GIA'!G51>0, '00_TONG_HOP_BAO_GIA'!L51 * (1 + '00_TONG_HOP_BAO_GIA'!P51) / '00_TONG_HOP_BAO_GIA'!G51, 0) | K101: ='00_TONG_HOP_BAO_GIA'!Q51 | L101: =('00_TONG_HOP_BAO_GIA'!K51 + '00_TONG_HOP_BAO_GIA'!M51) * (1 + '00_TONG_HOP_BAO_GIA'!P51) | M101: ='00_TONG_HOP_BAO_GIA'!L51 * (1 + '00_TONG_HOP_BAO_GIA'!P51) | N101: ='00_TONG_HOP_BAO_GIA'!R51 | O101: =IF(K101=0, "CẢNH BÁO: Đơn giá = 0. Tra cứu lại Sheet 06!", '00_TONG_HOP_BAO_GIA'!S51)
A102: =SUBTOTAL(3,$G$7:G102) | B102: Van 1 chiều NRD 350x150 (EI60) | C102: NRD | D102: NSCA, Evegreen, Swind, tđ | E102: Việt Nam / Singapore | G102: Cái | H102: 1 | I102: =IF('00_TONG_HOP_BAO_GIA'!G52>0, ('00_TONG_HOP_BAO_GIA'!K52 + '00_TONG_HOP_BAO_GIA'!M52) * (1 + '00_TONG_HOP_BAO_GIA'!P52) / '00_TONG_HOP_BAO_GIA'!G52, 0) | J102: =IF('00_TONG_HOP_BAO_GIA'!G52>0, '00_TONG_HOP_BAO_GIA'!L52 * (1 + '00_TONG_HOP_BAO_GIA'!P52) / '00_TONG_HOP_BAO_GIA'!G52, 0) | K102: ='00_TONG_HOP_BAO_GIA'!Q52 | L102: =('00_TONG_HOP_BAO_GIA'!K52 + '00_TONG_HOP_BAO_GIA'!M52) * (1 + '00_TONG_HOP_BAO_GIA'!P52) | M102: ='00_TONG_HOP_BAO_GIA'!L52 * (1 + '00_TONG_HOP_BAO_GIA'!P52) | N102: ='00_TONG_HOP_BAO_GIA'!R52 | O102: =IF(K102=0, "CẢNH BÁO: Đơn giá = 0. Tra cứu lại Sheet 06!", '00_TONG_HOP_BAO_GIA'!S52)
A103: =SUBTOTAL(3,$G$7:G103) | B103: Van ngăn cháy MFD 350x200 (EI60) | C103: MFD | D103: Van: NSCA, Evegreen, Swind, tđ ĐC: Belimo, Johnson Controls, tđ | E103: Việt Nam / Singapore | G103: Cái | H103: 1 | I103: =IF('00_TONG_HOP_BAO_GIA'!G53>0, ('00_TONG_HOP_BAO_GIA'!K53 + '00_TONG_HOP_BAO_GIA'!M53) * (1 + '00_TONG_HOP_BAO_GIA'!P53) / '00_TONG_HOP_BAO_GIA'!G53, 0) | J103: =IF('00_TONG_HOP_BAO_GIA'!G53>0, '00_TONG_HOP_BAO_GIA'!L53 * (1 + '00_TONG_HOP_BAO_GIA'!P53) / '00_TONG_HOP_BAO_GIA'!G53, 0) | K103: ='00_TONG_HOP_BAO_GIA'!Q53 | L103: =('00_TONG_HOP_BAO_GIA'!K53 + '00_TONG_HOP_BAO_GIA'!M53) * (1 + '00_TONG_HOP_BAO_GIA'!P53) | M103: ='00_TONG_HOP_BAO_GIA'!L53 * (1 + '00_TONG_HOP_BAO_GIA'!P53) | N103: ='00_TONG_HOP_BAO_GIA'!R53 | O103: =IF(K103=0, "CẢNH BÁO: Đơn giá = 0. Tra cứu lại Sheet 06!", '00_TONG_HOP_BAO_GIA'!S53)
A104: =SUBTOTAL(3,$G$7:G104) | B104: Van ngăn cháy MFD 700x500 (EI60) | C104: MFD | D104: Van: NSCA, Evegreen, Swind, tđ ĐC: Belimo, Johnson Controls, tđ | E104: Việt Nam / Singapore | G104: Cái | H104: 2 | I104: =IF('00_TONG_HOP_BAO_GIA'!G54>0, ('00_TONG_HOP_BAO_GIA'!K54 + '00_TONG_HOP_BAO_GIA'!M54) * (1 + '00_TONG_HOP_BAO_GIA'!P54) / '00_TONG_HOP_BAO_GIA'!G54, 0) | J104: =IF('00_TONG_HOP_BAO_GIA'!G54>0, '00_TONG_HOP_BAO_GIA'!L54 * (1 + '00_TONG_HOP_BAO_GIA'!P54) / '00_TONG_HOP_BAO_GIA'!G54, 0) | K104: ='00_TONG_HOP_BAO_GIA'!Q54 | L104: =('00_TONG_HOP_BAO_GIA'!K54 + '00_TONG_HOP_BAO_GIA'!M54) * (1 + '00_TONG_HOP_BAO_GIA'!P54) | M104: ='00_TONG_HOP_BAO_GIA'!L54 * (1 + '00_TONG_HOP_BAO_GIA'!P54) | N104: ='00_TONG_HOP_BAO_GIA'!R54 | O104: =IF(K104=0, "CẢNH BÁO: Đơn giá = 0. Tra cứu lại Sheet 06!", '00_TONG_HOP_BAO_GIA'!S54)
A105: =SUBTOTAL(3,$G$7:G105) | B105: Van ngăn cháy MFD 700x800 (EI60) | C105: MFD | D105: Van: NSCA, Evegreen, Swind, tđ ĐC: Belimo, Johnson Controls, tđ | E105: Việt Nam / Singapore | G105: Cái | H105: 2 | I105: =IF('00_TONG_HOP_BAO_GIA'!G55>0, ('00_TONG_HOP_BAO_GIA'!K55 + '00_TONG_HOP_BAO_GIA'!M55) * (1 + '00_TONG_HOP_BAO_GIA'!P55) / '00_TONG_HOP_BAO_GIA'!G55, 0) | J105: =IF('00_TONG_HOP_BAO_GIA'!G55>0, '00_TONG_HOP_BAO_GIA'!L55 * (1 + '00_TONG_HOP_BAO_GIA'!P55) / '00_TONG_HOP_BAO_GIA'!G55, 0) | K105: ='00_TONG_HOP_BAO_GIA'!Q55 | L105: =('00_TONG_HOP_BAO_GIA'!K55 + '00_TONG_HOP_BAO_GIA'!M55) * (1 + '00_TONG_HOP_BAO_GIA'!P55) | M105: ='00_TONG_HOP_BAO_GIA'!L55 * (1 + '00_TONG_HOP_BAO_GIA'!P55) | N105: ='00_TONG_HOP_BAO_GIA'!R55 | O105: =IF(K105=0, "CẢNH BÁO: Đơn giá = 0. Tra cứu lại Sheet 06!", '00_TONG_HOP_BAO_GIA'!S55)
A106: =SUBTOTAL(3,$G$7:G106) | B106: Van ngăn cháy MFD 1200x600 (EI60) | C106: MFD | D106: Van: NSCA, Evegreen, Swind, tđ ĐC: Belimo, Johnson Controls, tđ | E106: Việt Nam / Singapore | G106: Cái | H106: 2 | I106: =IF('00_TONG_HOP_BAO_GIA'!G56>0, ('00_TONG_HOP_BAO_GIA'!K56 + '00_TONG_HOP_BAO_GIA'!M56) * (1 + '00_TONG_HOP_BAO_GIA'!P56) / '00_TONG_HOP_BAO_GIA'!G56, 0) | J106: =IF('00_TONG_HOP_BAO_GIA'!G56>0, '00_TONG_HOP_BAO_GIA'!L56 * (1 + '00_TONG_HOP_BAO_GIA'!P56) / '00_TONG_HOP_BAO_GIA'!G56, 0) | K106: ='00_TONG_HOP_BAO_GIA'!Q56 | L106: =('00_TONG_HOP_BAO_GIA'!K56 + '00_TONG_HOP_BAO_GIA'!M56) * (1 + '00_TONG_HOP_BAO_GIA'!P56) | M106: ='00_TONG_HOP_BAO_GIA'!L56 * (1 + '00_TONG_HOP_BAO_GIA'!P56) | N106: ='00_TONG_HOP_BAO_GIA'!R56 | O106: =IF(K106=0, "CẢNH BÁO: Đơn giá = 0. Tra cứu lại Sheet 06!", '00_TONG_HOP_BAO_GIA'!S56)
... A130: =SUBTOTAL(3,$G$7:G130) | B130: Van ngăn cháy MFD 650x400 | C130: MFD | D130: Van: NSCA, Evegreen, Swind, tđ ĐC: Belimo, Johnson Controls, tđ | E130: Việt Nam / Singapore | G130: Cái | H130: 6 | I130: =IF('00_TONG_HOP_BAO_GIA'!G80>0, ('00_TONG_HOP_BAO_GIA'!K80 + '00_TONG_HOP_BAO_GIA'!M80) * (1 + '00_TONG_HOP_BAO_GIA'!P80) / '00_TONG_HOP_BAO_GIA'!G80, 0) | J130: =IF('00_TONG_HOP_BAO_GIA'!G80>0, '00_TONG_HOP_BAO_GIA'!L80 * (1 + '00_TONG_HOP_BAO_GIA'!P80) / '00_TONG_HOP_BAO_GIA'!G80, 0) | K130: ='00_TONG_HOP_BAO_GIA'!Q80 | L130: =('00_TONG_HOP_BAO_GIA'!K80 + '00_TONG_HOP_BAO_GIA'!M80) * (1 + '00_TONG_HOP_BAO_GIA'!P80) | M130: ='00_TONG_HOP_BAO_GIA'!L80 * (1 + '00_TONG_HOP_BAO_GIA'!P80) | N130: ='00_TONG_HOP_BAO_GIA'!R80 | O130: =IF(K130=0, "CẢNH BÁO: Đơn giá = 0. Tra cứu lại Sheet 06!", '00_TONG_HOP_BAO_GIA'!S80)
A131: =SUBTOTAL(3,$G$7:G131) | B131: Van xả áp | D131: NSCA, Evegreen, Swind, tđ | G131: Cái | H131: 6 | I131: =IF('00_TONG_HOP_BAO_GIA'!G81>0, ('00_TONG_HOP_BAO_GIA'!K81 + '00_TONG_HOP_BAO_GIA'!M81) * (1 + '00_TONG_HOP_BAO_GIA'!P81) / '00_TONG_HOP_BAO_GIA'!G81, 0) | J131: =IF('00_TONG_HOP_BAO_GIA'!G81>0, '00_TONG_HOP_BAO_GIA'!L81 * (1 + '00_TONG_HOP_BAO_GIA'!P81) / '00_TONG_HOP_BAO_GIA'!G81, 0) | K131: ='00_TONG_HOP_BAO_GIA'!Q81 | L131: =('00_TONG_HOP_BAO_GIA'!K81 + '00_TONG_HOP_BAO_GIA'!M81) * (1 + '00_TONG_HOP_BAO_GIA'!P81) | M131: ='00_TONG_HOP_BAO_GIA'!L81 * (1 + '00_TONG_HOP_BAO_GIA'!P81) | N131: ='00_TONG_HOP_BAO_GIA'!R81 | O131: =IF(K131=0, "CẢNH BÁO: Đơn giá = 0. Tra cứu lại Sheet 06!", '00_TONG_HOP_BAO_GIA'!S81)
A132: =SUBTOTAL(3,$G$7:G132) | B132: Van chỉnh lưu lượng VCD250x200 (EI60) | C132: VCD | D132: NSCA, Evegreen, Swind, tđ | E132: Việt Nam / Singapore | G132: Cái | H132: 1 | I132: =IF('00_TONG_HOP_BAO_GIA'!G82>0, ('00_TONG_HOP_BAO_GIA'!K82 + '00_TONG_HOP_BAO_GIA'!M82) * (1 + '00_TONG_HOP_BAO_GIA'!P82) / '00_TONG_HOP_BAO_GIA'!G82, 0) | J132: =IF('00_TONG_HOP_BAO_GIA'!G82>0, '00_TONG_HOP_BAO_GIA'!L82 * (1 + '00_TONG_HOP_BAO_GIA'!P82) / '00_TONG_HOP_BAO_GIA'!G82, 0) | K132: ='00_TONG_HOP_BAO_GIA'!Q82 | L132: =('00_TONG_HOP_BAO_GIA'!K82 + '00_TONG_HOP_BAO_GIA'!M82) * (1 + '00_TONG_HOP_BAO_GIA'!P82) | M132: ='00_TONG_HOP_BAO_GIA'!L82 * (1 + '00_TONG_HOP_BAO_GIA'!P82) | N132: ='00_TONG_HOP_BAO_GIA'!R82 | O132: =IF(K132=0, "CẢNH BÁO: Đơn giá = 0. Tra cứu lại Sheet 06!", '00_TONG_HOP_BAO_GIA'!S82)
A133: =SUBTOTAL(3,$G$7:G133) | B133: Miệng gió tạo áp PAG 900x400+OBD | D133: NSCA, Evegreen, Swind, tđ | G133: Cái | H133: 2 | I133: =IF('00_TONG_HOP_BAO_GIA'!G83>0, ('00_TONG_HOP_BAO_GIA'!K83 + '00_TONG_HOP_BAO_GIA'!M83) * (1 + '00_TONG_HOP_BAO_GIA'!P83) / '00_TONG_HOP_BAO_GIA'!G83, 0) | J133: =IF('00_TONG_HOP_BAO_GIA'!G83>0, '00_TONG_HOP_BAO_GIA'!L83 * (1 + '00_TONG_HOP_BAO_GIA'!P83) / '00_TONG_HOP_BAO_GIA'!G83, 0) | K133: ='00_TONG_HOP_BAO_GIA'!Q83 | L133: =('00_TONG_HOP_BAO_GIA'!K83 + '00_TONG_HOP_BAO_GIA'!M83) * (1 + '00_TONG_HOP_BAO_GIA'!P83) | M133: ='00_TONG_HOP_BAO_GIA'!L83 * (1 + '00_TONG_HOP_BAO_GIA'!P83) | N133: ='00_TONG_HOP_BAO_GIA'!R83 | O133: =IF(K133=0, "CẢNH BÁO: Đơn giá = 0. Tra cứu lại Sheet 06!", '00_TONG_HOP_BAO_GIA'!S83)
A134: =SUBTOTAL(3,$G$7:G134) | B134: Miệng gió tạo áp PAG 300x300+OBD | D134: NSCA, Evegreen, Swind, tđ | G134: Cái | H134: 1 | I134: =IF('00_TONG_HOP_BAO_GIA'!G84>0, ('00_TONG_HOP_BAO_GIA'!K84 + '00_TONG_HOP_BAO_GIA'!M84) * (1 + '00_TONG_HOP_BAO_GIA'!P84) / '00_TONG_HOP_BAO_GIA'!G84, 0) | J134: =IF('00_TONG_HOP_BAO_GIA'!G84>0, '00_TONG_HOP_BAO_GIA'!L84 * (1 + '00_TONG_HOP_BAO_GIA'!P84) / '00_TONG_HOP_BAO_GIA'!G84, 0) | K134: ='00_TONG_HOP_BAO_GIA'!Q84 | L134: =('00_TONG_HOP_BAO_GIA'!K84 + '00_TONG_HOP_BAO_GIA'!M84) * (1 + '00_TONG_HOP_BAO_GIA'!P84) | M134: ='00_TONG_HOP_BAO_GIA'!L84 * (1 + '00_TONG_HOP_BAO_GIA'!P84) | N134: ='00_TONG_HOP_BAO_GIA'!R84 | O134: =IF(K134=0, "CẢNH BÁO: Đơn giá = 0. Tra cứu lại Sheet 06!", '00_TONG_HOP_BAO_GIA'!S84)
A135: =SUBTOTAL(3,$G$7:G135) | B135: Miệng gió tạo áp PAG 1200x600+OBD | D135: NSCA, Evegreen, Swind, tđ | G135: Cái | H135: 2 | I135: =IF('00_TONG_HOP_BAO_GIA'!G85>0, ('00_TONG_HOP_BAO_GIA'!K85 + '00_TONG_HOP_BAO_GIA'!M85) * (1 + '00_TONG_HOP_BAO_GIA'!P85) / '00_TONG_HOP_BAO_GIA'!G85, 0) | J135: =IF('00_TONG_HOP_BAO_GIA'!G85>0, '00_TONG_HOP_BAO_GIA'!L85 * (1 + '00_TONG_HOP_BAO_GIA'!P85) / '00_TONG_HOP_BAO_GIA'!G85, 0) | K135: ='00_TONG_HOP_BAO_GIA'!Q85 | L135: =('00_TONG_HOP_BAO_GIA'!K85 + '00_TONG_HOP_BAO_GIA'!M85) * (1 + '00_TONG_HOP_BAO_GIA'!P85) | M135: ='00_TONG_HOP_BAO_GIA'!L85 * (1 + '00_TONG_HOP_BAO_GIA'!P85) | N135: ='00_TONG_HOP_BAO_GIA'!R85 | O135: =IF(K135=0, "CẢNH BÁO: Đơn giá = 0. Tra cứu lại Sheet 06!", '00_TONG_HOP_BAO_GIA'!S85)
A136: =SUBTOTAL(3,$G$7:G136) | B136: Miệng gió tạo áp PAG 1400x800+OBD | D136: NSCA, Evegreen, Swind, tđ | G136: Cái | H136: 10 | I136: =IF('00_TONG_HOP_BAO_GIA'!G86>0, ('00_TONG_HOP_BAO_GIA'!K86 + '00_TONG_HOP_BAO_GIA'!M86) * (1 + '00_TONG_HOP_BAO_GIA'!P86) / '00_TONG_HOP_BAO_GIA'!G86, 0) | J136: =IF('00_TONG_HOP_BAO_GIA'!G86>0, '00_TONG_HOP_BAO_GIA'!L86 * (1 + '00_TONG_HOP_BAO_GIA'!P86) / '00_TONG_HOP_BAO_GIA'!G86, 0) | K136: ='00_TONG_HOP_BAO_GIA'!Q86 | L136: =('00_TONG_HOP_BAO_GIA'!K86 + '00_TONG_HOP_BAO_GIA'!M86) * (1 + '00_TONG_HOP_BAO_GIA'!P86) | M136: ='00_TONG_HOP_BAO_GIA'!L86 * (1 + '00_TONG_HOP_BAO_GIA'!P86) | N136: ='00_TONG_HOP_BAO_GIA'!R86 | O136: =IF(K136=0, "CẢNH BÁO: Đơn giá = 0. Tra cứu lại Sheet 06!", '00_TONG_HOP_BAO_GIA'!S86)
A137: =SUBTOTAL(3,$G$7:G137) | B137: Miệng gió tạo áp PAG 1200x600+OBD | D137: NSCA, Evegreen, Swind, tđ | G137: Cái | H137: 2 | I137: =IF('00_TONG_HOP_BAO_GIA'!G87>0, ('00_TONG_HOP_BAO_GIA'!K87 + '00_TONG_HOP_BAO_GIA'!M87) * (1 + '00_TONG_HOP_BAO_GIA'!P87) / '00_TONG_HOP_BAO_GIA'!G87, 0) | J137: =IF('00_TONG_HOP_BAO_GIA'!G87>0, '00_TONG_HOP_BAO_GIA'!L87 * (1 + '00_TONG_HOP_BAO_GIA'!P87) / '00_TONG_HOP_BAO_GIA'!G87, 0) | K137: ='00_TONG_HOP_BAO_GIA'!Q87 | L137: =('00_TONG_HOP_BAO_GIA'!K87 + '00_TONG_HOP_BAO_GIA'!M87) * (1 + '00_TONG_HOP_BAO_GIA'!P87) | M137: ='00_TONG_HOP_BAO_GIA'!L87 * (1 + '00_TONG_HOP_BAO_GIA'!P87) | N137: ='00_TONG_HOP_BAO_GIA'!R87 | O137: =IF(K137=0, "CẢNH BÁO: Đơn giá = 0. Tra cứu lại Sheet 06!", '00_TONG_HOP_BAO_GIA'!S87)
A138: =SUBTOTAL(3,$G$7:G138) | B138: Miệng gió tạo áp PAG 300x300+OBD | D138: NSCA, Evegreen, Swind, tđ | G138: Cái | H138: 8 | I138: =IF('00_TONG_HOP_BAO_GIA'!G88>0, ('00_TONG_HOP_BAO_GIA'!K88 + '00_TONG_HOP_BAO_GIA'!M88) * (1 + '00_TONG_HOP_BAO_GIA'!P88) / '00_TONG_HOP_BAO_GIA'!G88, 0) | J138: =IF('00_TONG_HOP_BAO_GIA'!G88>0, '00_TONG_HOP_BAO_GIA'!L88 * (1 + '00_TONG_HOP_BAO_GIA'!P88) / '00_TONG_HOP_BAO_GIA'!G88, 0) | K138: ='00_TONG_HOP_BAO_GIA'!Q88 | L138: =('00_TONG_HOP_BAO_GIA'!K88 + '00_TONG_HOP_BAO_GIA'!M88) * (1 + '00_TONG_HOP_BAO_GIA'!P88) | M138: ='00_TONG_HOP_BAO_GIA'!L88 * (1 + '00_TONG_HOP_BAO_GIA'!P88) | N138: ='00_TONG_HOP_BAO_GIA'!R88 | O138: =IF(K138=0, "CẢNH BÁO: Đơn giá = 0. Tra cứu lại Sheet 06!", '00_TONG_HOP_BAO_GIA'!S88)
A139: =SUBTOTAL(3,$G$7:G139) | B139: Miệng gió tạo áp PAG 500x200+OBD | D139: NSCA, Evegreen, Swind, tđ | G139: Cái | H139: 3 | I139: =IF('00_TONG_HOP_BAO_GIA'!G89>0, ('00_TONG_HOP_BAO_GIA'!K89 + '00_TONG_HOP_BAO_GIA'!M89) * (1 + '00_TONG_HOP_BAO_GIA'!P89) / '00_TONG_HOP_BAO_GIA'!G89, 0) | J139: =IF('00_TONG_HOP_BAO_GIA'!G89>0, '00_TONG_HOP_BAO_GIA'!L89 * (1 + '00_TONG_HOP_BAO_GIA'!P89) / '00_TONG_HOP_BAO_GIA'!G89, 0) | K139: ='00_TONG_HOP_BAO_GIA'!Q89 | L139: =('00_TONG_HOP_BAO_GIA'!K89 + '00_TONG_HOP_BAO_GIA'!M89) * (1 + '00_TONG_HOP_BAO_GIA'!P89) | M139: ='00_TONG_HOP_BAO_GIA'!L89 * (1 + '00_TONG_HOP_BAO_GIA'!P89) | N139: ='00_TONG_HOP_BAO_GIA'!R89 | O139: =IF(K139=0, "CẢNH BÁO: Đơn giá = 0. Tra cứu lại Sheet 06!", '00_TONG_HOP_BAO_GIA'!S89)
A140: =SUBTOTAL(3,$G$7:G140) | B140: Miệng gió tạo áp PAG1400x800+OBD | D140: NSCA, Evegreen, Swind, tđ | G140: Cái | H140: 49 | I140: =IF('00_TONG_HOP_BAO_GIA'!G90>0, ('00_TONG_HOP_BAO_GIA'!K90 + '00_TONG_HOP_BAO_GIA'!M90) * (1 + '00_TONG_HOP_BAO_GIA'!P90) / '00_TONG_HOP_BAO_GIA'!G90, 0) | J140: =IF('00_TONG_HOP_BAO_GIA'!G90>0, '00_TONG_HOP_BAO_GIA'!L90 * (1 + '00_TONG_HOP_BAO_GIA'!P90) / '00_TONG_HOP_BAO_GIA'!G90, 0) | K140: ='00_TONG_HOP_BAO_GIA'!Q90 | L140: =('00_TONG_HOP_BAO_GIA'!K90 + '00_TONG_HOP_BAO_GIA'!M90) * (1 + '00_TONG_HOP_BAO_GIA'!P90) | M140: ='00_TONG_HOP_BAO_GIA'!L90 * (1 + '00_TONG_HOP_BAO_GIA'!P90) | N140: ='00_TONG_HOP_BAO_GIA'!R90 | O140: =IF(K140=0, "CẢNH BÁO: Đơn giá = 0. Tra cứu lại Sheet 06!", '00_TONG_HOP_BAO_GIA'!S90)
A141: =SUBTOTAL(3,$G$7:G141) | B141: Miệng gió tạo áp PAG 900x350+OBD | D141: NSCA, Evegreen, Swind, tđ | G141: Cái | H141: 18 | I141: =IF('00_TONG_HOP_BAO_GIA'!G91>0, ('00_TONG_HOP_BAO_GIA'!K91 + '00_TONG_HOP_BAO_GIA'!M91) * (1 + '00_TONG_HOP_BAO_GIA'!P91) / '00_TONG_HOP_BAO_GIA'!G91, 0) | J141: =IF('00_TONG_HOP_BAO_GIA'!G91>0, '00_TONG_HOP_BAO_GIA'!L91 * (1 + '00_TONG_HOP_BAO_GIA'!P91) / '00_TONG_HOP_BAO_GIA'!G91, 0) | K141: ='00_TONG_HOP_BAO_GIA'!Q91 | L141: =('00_TONG_HOP_BAO_GIA'!K91 + '00_TONG_HOP_BAO_GIA'!M91) * (1 + '00_TONG_HOP_BAO_GIA'!P91) | M141: ='00_TONG_HOP_BAO_GIA'!L91 * (1 + '00_TONG_HOP_BAO_GIA'!P91) | N141: ='00_TONG_HOP_BAO_GIA'!R91 | O141: =IF(K141=0, "CẢNH BÁO: Đơn giá = 0. Tra cứu lại Sheet 06!", '00_TONG_HOP_BAO_GIA'!S91)
A142: =SUBTOTAL(3,$G$7:G142) | B142: Miệng gió tạo áp PAG 350x600+OBD | D142: NSCA, Evegreen, Swind, tđ | G142: Cái | H142: 13 | I142: =IF('00_TONG_HOP_BAO_GIA'!G92>0, ('00_TONG_HOP_BAO_GIA'!K92 + '00_TONG_HOP_BAO_GIA'!M92) * (1 + '00_TONG_HOP_BAO_GIA'!P92) / '00_TONG_HOP_BAO_GIA'!G92, 0) | J142: =IF('00_TONG_HOP_BAO_GIA'!G92>0, '00_TONG_HOP_BAO_GIA'!L92 * (1 + '00_TONG_HOP_BAO_GIA'!P92) / '00_TONG_HOP_BAO_GIA'!G92, 0) | K142: ='00_TONG_HOP_BAO_GIA'!Q92 | L142: =('00_TONG_HOP_BAO_GIA'!K92 + '00_TONG_HOP_BAO_GIA'!M92) * (1 + '00_TONG_HOP_BAO_GIA'!P92) | M142: ='00_TONG_HOP_BAO_GIA'!L92 * (1 + '00_TONG_HOP_BAO_GIA'!P92) | N142: ='00_TONG_HOP_BAO_GIA'!R92 | O142: =IF(K142=0, "CẢNH BÁO: Đơn giá = 0. Tra cứu lại Sheet 06!", '00_TONG_HOP_BAO_GIA'!S92)
A143: =SUBTOTAL(3,$G$7:G143) | B143: Miệng gió tạo áp PAG 800x400 OBD | D143: NSCA, Evegreen, Swind, tđ | G143: Cái | H143: 7 | I143: =IF('00_TONG_HOP_BAO_GIA'!G93>0, ('00_TONG_HOP_BAO_GIA'!K93 + '00_TONG_HOP_BAO_GIA'!M93) * (1 + '00_TONG_HOP_BAO_GIA'!P93) / '00_TONG_HOP_BAO_GIA'!G93, 0) | J143: =IF('00_TONG_HOP_BAO_GIA'!G93>0, '00_TONG_HOP_BAO_GIA'!L93 * (1 + '00_TONG_HOP_BAO_GIA'!P93) / '00_TONG_HOP_BAO_GIA'!G93, 0) | K143: ='00_TONG_HOP_BAO_GIA'!Q93 | L143: =('00_TONG_HOP_BAO_GIA'!K93 + '00_TONG_HOP_BAO_GIA'!M93) * (1 + '00_TONG_HOP_BAO_GIA'!P93) | M143: ='00_TONG_HOP_BAO_GIA'!L93 * (1 + '00_TONG_HOP_BAO_GIA'!P93) | N143: ='00_TONG_HOP_BAO_GIA'!R93 | O143: =IF(K143=0, "CẢNH BÁO: Đơn giá = 0. Tra cứu lại Sheet 06!", '00_TONG_HOP_BAO_GIA'!S93)
A144: =SUBTOTAL(3,$G$7:G144) | B144: Miệng gió tạo áp PAG 700x400 OBD | D144: NSCA, Evegreen, Swind, tđ | G144: Cái | H144: 17 | I144: =IF('00_TONG_HOP_BAO_GIA'!G94>0, ('00_TONG_HOP_BAO_GIA'!K94 + '00_TONG_HOP_BAO_GIA'!M94) * (1 + '00_TONG_HOP_BAO_GIA'!P94) / '00_TONG_HOP_BAO_GIA'!G94, 0) | J144: =IF('00_TONG_HOP_BAO_GIA'!G94>0, '00_TONG_HOP_BAO_GIA'!L94 * (1 + '00_TONG_HOP_BAO_GIA'!P94) / '00_TONG_HOP_BAO_GIA'!G94, 0) | K144: ='00_TONG_HOP_BAO_GIA'!Q94 | L144: =('00_TONG_HOP_BAO_GIA'!K94 + '00_TONG_HOP_BAO_GIA'!M94) * (1 + '00_TONG_HOP_BAO_GIA'!P94) | M144: ='00_TONG_HOP_BAO_GIA'!L94 * (1 + '00_TONG_HOP_BAO_GIA'!P94) | N144: ='00_TONG_HOP_BAO_GIA'!R94 | O144: =IF(K144=0, "CẢNH BÁO: Đơn giá = 0. Tra cứu lại Sheet 06!", '00_TONG_HOP_BAO_GIA'!S94)
... A147: =SUBTOTAL(3,$G$7:G147) | B147: Louver 3500x1000+IS | D147: NSCA, Evegreen, Swind, tđ | G147: Cái | H147: 1 | I147: =IF('00_TONG_HOP_BAO_GIA'!G97>0, ('00_TONG_HOP_BAO_GIA'!K97 + '00_TONG_HOP_BAO_GIA'!M97) * (1 + '00_TONG_HOP_BAO_GIA'!P97) / '00_TONG_HOP_BAO_GIA'!G97, 0) | J147: =IF('00_TONG_HOP_BAO_GIA'!G97>0, '00_TONG_HOP_BAO_GIA'!L97 * (1 + '00_TONG_HOP_BAO_GIA'!P97) / '00_TONG_HOP_BAO_GIA'!G97, 0) | K147: ='00_TONG_HOP_BAO_GIA'!Q97 | L147: =('00_TONG_HOP_BAO_GIA'!K97 + '00_TONG_HOP_BAO_GIA'!M97) * (1 + '00_TONG_HOP_BAO_GIA'!P97) | M147: ='00_TONG_HOP_BAO_GIA'!L97 * (1 + '00_TONG_HOP_BAO_GIA'!P97) | N147: ='00_TONG_HOP_BAO_GIA'!R97 | O147: =IF(K147=0, "CẢNH BÁO: Đơn giá = 0. Tra cứu lại Sheet 06!", '00_TONG_HOP_BAO_GIA'!S97)
A148: =SUBTOTAL(3,$G$7:G148) | B148: Vật tư phụ, phụ kiện | G148: Lô | H148: 1 | I148: =IF('00_TONG_HOP_BAO_GIA'!G98>0, ('00_TONG_HOP_BAO_GIA'!K98 + '00_TONG_HOP_BAO_GIA'!M98) * (1 + '00_TONG_HOP_BAO_GIA'!P98) / '00_TONG_HOP_BAO_GIA'!G98, 0) | J148: =IF('00_TONG_HOP_BAO_GIA'!G98>0, '00_TONG_HOP_BAO_GIA'!L98 * (1 + '00_TONG_HOP_BAO_GIA'!P98) / '00_TONG_HOP_BAO_GIA'!G98, 0) | K148: ='00_TONG_HOP_BAO_GIA'!Q98 | L148: =('00_TONG_HOP_BAO_GIA'!K98 + '00_TONG_HOP_BAO_GIA'!M98) * (1 + '00_TONG_HOP_BAO_GIA'!P98) | M148: ='00_TONG_HOP_BAO_GIA'!L98 * (1 + '00_TONG_HOP_BAO_GIA'!P98) | N148: ='00_TONG_HOP_BAO_GIA'!R98 | O148: =IF(K148=0, "CẢNH BÁO: Đơn giá = 0. Tra cứu lại Sheet 06!", '00_TONG_HOP_BAO_GIA'!S98)
B149: Hệ thống ống thông gió tạo áp, box miệng gió… | F149: M
A150: =SUBTOTAL(3,$G$7:G150) | B150: Tole 0.75mm phủ lớp mạ kẽm Z180 | C150: Diện tích tính theo kích thước hình học (Hoàn thiện) | D150: Hoa Sen, Phương Nam | E150: Hoa Sen / Phương Nam / Nam Kim / tđ | G150: m2 | H150: 1936.7013 | I150: =IF('00_TONG_HOP_BAO_GIA'!G99>0, ('00_TONG_HOP_BAO_GIA'!K99 + '00_TONG_HOP_BAO_GIA'!M99) * (1 + '00_TONG_HOP_BAO_GIA'!P99) / '00_TONG_HOP_BAO_GIA'!G99, 0) | J150: =IF('00_TONG_HOP_BAO_GIA'!G99>0, '00_TONG_HOP_BAO_GIA'!L99 * (1 + '00_TONG_HOP_BAO_GIA'!P99) / '00_TONG_HOP_BAO_GIA'!G99, 0) | K150: ='00_TONG_HOP_BAO_GIA'!Q99 | L150: =('00_TONG_HOP_BAO_GIA'!K99 + '00_TONG_HOP_BAO_GIA'!M99) * (1 + '00_TONG_HOP_BAO_GIA'!P99) | M150: ='00_TONG_HOP_BAO_GIA'!L99 * (1 + '00_TONG_HOP_BAO_GIA'!P99) | N150: ='00_TONG_HOP_BAO_GIA'!R99 | O150: =IF(K150=0, "CẢNH BÁO: Đơn giá = 0. Tra cứu lại Sheet 06!", '00_TONG_HOP_BAO_GIA'!S99)
A151: =SUBTOTAL(3,$G$7:G151) | B151: Tole 0.95mm phủ lớp mạ kẽm Z180 | C151: Diện tích tính theo kích thước hình học (Hoàn thiện) | D151: Hoa Sen, Phương Nam | E151: Hoa Sen / Phương Nam / Nam Kim / tđ | G151: m2 | H151: 1588.05 | I151: =IF('00_TONG_HOP_BAO_GIA'!G100>0, ('00_TONG_HOP_BAO_GIA'!K100 + '00_TONG_HOP_BAO_GIA'!M100) * (1 + '00_TONG_HOP_BAO_GIA'!P100) / '00_TONG_HOP_BAO_GIA'!G100, 0) | J151: =IF('00_TONG_HOP_BAO_GIA'!G100>0, '00_TONG_HOP_BAO_GIA'!L100 * (1 + '00_TONG_HOP_BAO_GIA'!P100) / '00_TONG_HOP_BAO_GIA'!G100, 0) | K151: ='00_TONG_HOP_BAO_GIA'!Q100 | L151: =('00_TONG_HOP_BAO_GIA'!K100 + '00_TONG_HOP_BAO_GIA'!M100) * (1 + '00_TONG_HOP_BAO_GIA'!P100) | M151: ='00_TONG_HOP_BAO_GIA'!L100 * (1 + '00_TONG_HOP_BAO_GIA'!P100) | N151: ='00_TONG_HOP_BAO_GIA'!R100 | O151: =IF(K151=0, "CẢNH BÁO: Đơn giá = 0. Tra cứu lại Sheet 06!", '00_TONG_HOP_BAO_GIA'!S100)
A152: =SUBTOTAL(3,$G$7:G152) | B152: Tole 1.15mm phủ lớp mạ kẽm Z180 | C152: Diện tích tính theo kích thước hình học (Hoàn thiện) | D152: Hoa Sen, Phương Nam | E152: Hoa Sen / Phương Nam / Nam Kim / tđ | G152: m2 | H152: 1681 | I152: =IF('00_TONG_HOP_BAO_GIA'!G101>0, ('00_TONG_HOP_BAO_GIA'!K101 + '00_TONG_HOP_BAO_GIA'!M101) * (1 + '00_TONG_HOP_BAO_GIA'!P101) / '00_TONG_HOP_BAO_GIA'!G101, 0) | J152: =IF('00_TONG_HOP_BAO_GIA'!G101>0, '00_TONG_HOP_BAO_GIA'!L101 * (1 + '00_TONG_HOP_BAO_GIA'!P101) / '00_TONG_HOP_BAO_GIA'!G101, 0) | K152: ='00_TONG_HOP_BAO_GIA'!Q101 | L152: =('00_TONG_HOP_BAO_GIA'!K101 + '00_TONG_HOP_BAO_GIA'!M101) * (1 + '00_TONG_HOP_BAO_GIA'!P101) | M152: ='00_TONG_HOP_BAO_GIA'!L101 * (1 + '00_TONG_HOP_BAO_GIA'!P101) | N152: ='00_TONG_HOP_BAO_GIA'!R101 | O152: =IF(K152=0, "CẢNH BÁO: Đơn giá = 0. Tra cứu lại Sheet 06!", '00_TONG_HOP_BAO_GIA'!S101)
...

Sheet 00_TONG_HOP_BAO_GIA
A1: STT | B1: ITEM_ID | C1: PHÂN NHÓM | D1: TÊN SẢN PHẨM | E1: QUY CÁCH (WxH) | F1: ĐVT | G1: SỐ LƯỢNG | H1: CP VẬT TƯ ỐNG | I1: CP VẬT TƯ CỬA | J1: CP VẬT TƯ VAN | K1: TỔNG CP VẬT TƯ | L1: NHÂN CÔNG (25%) | M1: CP XƯỞNG (10%) | N1: TỔNG GIÁ VỐN | O1: GIÁ VỐN / ĐVT | P1: MARGIN (%) | Q1: ĐƠN GIÁ BÁN | R1: THÀNH TIỀN (VNĐ) | S1: GHI CHÚ
A2: 1 | B2: SW-CV-001 | C2: KHỚP NỐI MỀM | D2: HỆ THỐNG HÚT KHÓI HẦM XE, HÚT KHÓI SỰ CỐ Canvas loại chống cháy cho quạt TAHK | E2: D1000 | F2: cái | G2: 15 | H2: =SUMIF('01_BOC_TACH_ONG'!B:B, B2, '01_BOC_TACH_ONG'!K:K) | I2: =SUMIF('02_BOC_TACH_CUA'!B:B, B2, '02_BOC_TACH_CUA'!K:K) | J2: =SUMIF('03_BOC_TACH_VAN'!B:B, B2, '03_BOC_TACH_VAN'!K:K) | K2: =SUM(H2:J2) | L2: =(K2-SUMIFS('03_BOC_TACH_VAN'!K:K, '03_BOC_TACH_VAN'!B:B, B2, '03_BOC_TACH_VAN'!D:D, "ĐỘNG_CƠ_VÀ_CẢM_BIẾN"))*0.25 | M2: =(K2-SUMIFS('03_BOC_TACH_VAN'!K:K, '03_BOC_TACH_VAN'!B:B, B2, '03_BOC_TACH_VAN'!D:D, "ĐỘNG_CƠ_VÀ_CẢM_BIẾN"))*0.10 | N2: =K2+L2+M2 | O2: =IF(G2>0, N2/G2, 0) | P2: 0.18 | Q2: =IF(G2>0, ((N2-SUMIFS('03_BOC_TACH_VAN'!K:K, '03_BOC_TACH_VAN'!B:B, B2, '03_BOC_TACH_VAN'!D:D, "ĐỘNG_CƠ_VÀ_CẢM_BIẾN"))*(1+P2)+SUMIFS('03_BOC_TACH_VAN'!K:K, '03_BOC_TACH_VAN'!B:B, B2, '03_BOC_TACH_VAN'!D:D, "ĐỘNG_CƠ_VÀ_CẢM_BIẾN"))/G2, 0) | R2: =G2*Q2
A3: 2 | B3: SW-CV-002 | C3: KHỚP NỐI MỀM | D3: HỆ THỐNG HÚT KHÓI HẦM XE, HÚT KHÓI SỰ CỐ Canvas loại chống cháy cho quạt TAHK | E3: D900 | F3: cái | G3: 40 | H3: =SUMIF('01_BOC_TACH_ONG'!B:B, B3, '01_BOC_TACH_ONG'!K:K) | I3: =SUMIF('02_BOC_TACH_CUA'!B:B, B3, '02_BOC_TACH_CUA'!K:K) | J3: =SUMIF('03_BOC_TACH_VAN'!B:B, B3, '03_BOC_TACH_VAN'!K:K) | K3: =SUM(H3:J3) | L3: =(K3-SUMIFS('03_BOC_TACH_VAN'!K:K, '03_BOC_TACH_VAN'!B:B, B3, '03_BOC_TACH_VAN'!D:D, "ĐỘNG_CƠ_VÀ_CẢM_BIẾN"))*0.25 | M3: =(K3-SUMIFS('03_BOC_TACH_VAN'!K:K, '03_BOC_TACH_VAN'!B:B, B3, '03_BOC_TACH_VAN'!D:D, "ĐỘNG_CƠ_VÀ_CẢM_BIẾN"))*0.10 | N3: =K3+L3+M3 | O3: =IF(G3>0, N3/G3, 0) | P3: 0.18 | Q3: =IF(G3>0, ((N3-SUMIFS('03_BOC_TACH_VAN'!K:K, '03_BOC_TACH_VAN'!B:B, B3, '03_BOC_TACH_VAN'!D:D, "ĐỘNG_CƠ_VÀ_CẢM_BIẾN"))*(1+P3)+SUMIFS('03_BOC_TACH_VAN'!K:K, '03_BOC_TACH_VAN'!B:B, B3, '03_BOC_TACH_VAN'!D:D, "ĐỘNG_CƠ_VÀ_CẢM_BIẾN"))/G3, 0) | R3: =G3*Q3
A4: 3 | B4: SW-CV-003 | C4: KHỚP NỐI MỀM | D4: HỆ THỐNG HÚT KHÓI HẦM XE, HÚT KHÓI SỰ CỐ Canvas loại chống cháy cho quạt TAHK | E4: D800 | F4: cái | G4: 40 | H4: =SUMIF('01_BOC_TACH_ONG'!B:B, B4, '01_BOC_TACH_ONG'!K:K) | I4: =SUMIF('02_BOC_TACH_CUA'!B:B, B4, '02_BOC_TACH_CUA'!K:K) | J4: =SUMIF('03_BOC_TACH_VAN'!B:B, B4, '03_BOC_TACH_VAN'!K:K) | K4: =SUM(H4:J4) | L4: =(K4-SUMIFS('03_BOC_TACH_VAN'!K:K, '03_BOC_TACH_VAN'!B:B, B4, '03_BOC_TACH_VAN'!D:D, "ĐỘNG_CƠ_VÀ_CẢM_BIẾN"))*0.25 | M4: =(K4-SUMIFS('03_BOC_TACH_VAN'!K:K, '03_BOC_TACH_VAN'!B:B, B4, '03_BOC_TACH_VAN'!D:D, "ĐỘNG_CƠ_VÀ_CẢM_BIẾN"))*0.10 | N4: =K4+L4+M4 | O4: =IF(G4>0, N4/G4, 0) | P4: 0.18 | Q4: =IF(G4>0, ((N4-SUMIFS('03_BOC_TACH_VAN'!K:K, '03_BOC_TACH_VAN'!B:B, B4, '03_BOC_TACH_VAN'!D:D, "ĐỘNG_CƠ_VÀ_CẢM_BIẾN"))*(1+P4)+SUMIFS('03_BOC_TACH_VAN'!K:K, '03_BOC_TACH_VAN'!B:B, B4, '03_BOC_TACH_VAN'!D:D, "ĐỘNG_CƠ_VÀ_CẢM_BIẾN"))/G4, 0) | R4: =G4*Q4
A5: 4 | B5: SW-CV-004 | C5: KHỚP NỐI MỀM | D5: HỆ THỐNG HÚT KHÓI HẦM XE, HÚT KHÓI SỰ CỐ Canvas loại chống cháy cho quạt TAHK | E5: D710 | F5: cái | G5: 16 | H5: =SUMIF('01_BOC_TACH_ONG'!B:B, B5, '01_BOC_TACH_ONG'!K:K) | I5: =SUMIF('02_BOC_TACH_CUA'!B:B, B5, '02_BOC_TACH_CUA'!K:K) | J5: =SUMIF('03_BOC_TACH_VAN'!B:B, B5, '03_BOC_TACH_VAN'!K:K) | K5: =SUM(H5:J5) | L5: =(K5-SUMIFS('03_BOC_TACH_VAN'!K:K, '03_BOC_TACH_VAN'!B:B, B5, '03_BOC_TACH_VAN'!D:D, "ĐỘNG_CƠ_VÀ_CẢM_BIẾN"))*0.25 | M5: =(K5-SUMIFS('03_BOC_TACH_VAN'!K:K, '03_BOC_TACH_VAN'!B:B, B5, '03_BOC_TACH_VAN'!D:D, "ĐỘNG_CƠ_VÀ_CẢM_BIẾN"))*0.10 | N5: =K5+L5+M5 | O5: =IF(G5>0, N5/G5, 0) | P5: 0.18 | Q5: =IF(G5>0, ((N5-SUMIFS('03_BOC_TACH_VAN'!K:K, '03_BOC_TACH_VAN'!B:B, B5, '03_BOC_TACH_VAN'!D:D, "ĐỘNG_CƠ_VÀ_CẢM_BIẾN"))*(1+P5)+SUMIFS('03_BOC_TACH_VAN'!K:K, '03_BOC_TACH_VAN'!B:B, B5, '03_BOC_TACH_VAN'!D:D, "ĐỘNG_CƠ_VÀ_CẢM_BIẾN"))/G5, 0) | R5: =G5*Q5
A6: 5 | B6: SW-CV-005 | C6: KHỚP NỐI MỀM | D6: HỆ THỐNG HÚT KHÓI HẦM XE, HÚT KHÓI SỰ CỐ Canvas loại chống cháy cho quạt TAHK | E6: D560 | F6: cái | G6: 16 | H6: =SUMIF('01_BOC_TACH_ONG'!B:B, B6, '01_BOC_TACH_ONG'!K:K) | I6: =SUMIF('02_BOC_TACH_CUA'!B:B, B6, '02_BOC_TACH_CUA'!K:K) | J6: =SUMIF('03_BOC_TACH_VAN'!B:B, B6, '03_BOC_TACH_VAN'!K:K) | K6: =SUM(H6:J6) | L6: =(K6-SUMIFS('03_BOC_TACH_VAN'!K:K, '03_BOC_TACH_VAN'!B:B, B6, '03_BOC_TACH_VAN'!D:D, "ĐỘNG_CƠ_VÀ_CẢM_BIẾN"))*0.25 | M6: =(K6-SUMIFS('03_BOC_TACH_VAN'!K:K, '03_BOC_TACH_VAN'!B:B, B6, '03_BOC_TACH_VAN'!D:D, "ĐỘNG_CƠ_VÀ_CẢM_BIẾN"))*0.10 | N6: =K6+L6+M6 | O6: =IF(G6>0, N6/G6, 0) | P6: 0.18 | Q6: =IF(G6>0, ((N6-SUMIFS('03_BOC_TACH_VAN'!K:K, '03_BOC_TACH_VAN'!B:B, B6, '03_BOC_TACH_VAN'!D:D, "ĐỘNG_CƠ_VÀ_CẢM_BIẾN"))*(1+P6)+SUMIFS('03_BOC_TACH_VAN'!K:K, '03_BOC_TACH_VAN'!B:B, B6, '03_BOC_TACH_VAN'!D:D, "ĐỘNG_CƠ_VÀ_CẢM_BIẾN"))/G6, 0) | R6: =G6*Q6
A7: 6 | B7: SW-CV-006 | C7: KHỚP NỐI MỀM | D7: HỆ THỐNG HÚT KHÓI HẦM XE, HÚT KHÓI SỰ CỐ Canvas loại thường cho quạt thông gió | E7: D1000 | F7: cái | G7: 32 | H7: =SUMIF('01_BOC_TACH_ONG'!B:B, B7, '01_BOC_TACH_ONG'!K:K) | I7: =SUMIF('02_BOC_TACH_CUA'!B:B, B7, '02_BOC_TACH_CUA'!K:K) | J7: =SUMIF('03_BOC_TACH_VAN'!B:B, B7, '03_BOC_TACH_VAN'!K:K) | K7: =SUM(H7:J7) | L7: =(K7-SUMIFS('03_BOC_TACH_VAN'!K:K, '03_BOC_TACH_VAN'!B:B, B7, '03_BOC_TACH_VAN'!D:D, "ĐỘNG_CƠ_VÀ_CẢM_BIẾN"))*0.25 | M7: =(K7-SUMIFS('03_BOC_TACH_VAN'!K:K, '03_BOC_TACH_VAN'!B:B, B7, '03_BOC_TACH_VAN'!D:D, "ĐỘNG_CƠ_VÀ_CẢM_BIẾN"))*0.10 | N7: =K7+L7+M7 | O7: =IF(G7>0, N7/G7, 0) | P7: 0.18 | Q7: =IF(G7>0, ((N7-SUMIFS('03_BOC_TACH_VAN'!K:K, '03_BOC_TACH_VAN'!B:B, B7, '03_BOC_TACH_VAN'!D:D, "ĐỘNG_CƠ_VÀ_CẢM_BIẾN"))*(1+P7)+SUMIFS('03_BOC_TACH_VAN'!K:K, '03_BOC_TACH_VAN'!B:B, B7, '03_BOC_TACH_VAN'!D:D, "ĐỘNG_CƠ_VÀ_CẢM_BIẾN"))/G7, 0) | R7: =G7*Q7
A8: 7 | B8: SW-CV-007 | C8: KHỚP NỐI MỀM | D8: HỆ THỐNG HÚT KHÓI HẦM XE, HÚT KHÓI SỰ CỐ Canvas loại thường cho quạt thông gió | E8: D560 | F8: cái | G8: 24 | H8: =SUMIF('01_BOC_TACH_ONG'!B:B, B8, '01_BOC_TACH_ONG'!K:K) | I8: =SUMIF('02_BOC_TACH_CUA'!B:B, B8, '02_BOC_TACH_CUA'!K:K) | J8: =SUMIF('03_BOC_TACH_VAN'!B:B, B8, '03_BOC_TACH_VAN'!K:K) | K8: =SUM(H8:J8) | L8: =(K8-SUMIFS('03_BOC_TACH_VAN'!K:K, '03_BOC_TACH_VAN'!B:B, B8, '03_BOC_TACH_VAN'!D:D, "ĐỘNG_CƠ_VÀ_CẢM_BIẾN"))*0.25 | M8: =(K8-SUMIFS('03_BOC_TACH_VAN'!K:K, '03_BOC_TACH_VAN'!B:B, B8, '03_BOC_TACH_VAN'!D:D, "ĐỘNG_CƠ_VÀ_CẢM_BIẾN"))*0.10 | N8: =K8+L8+M8 | O8: =IF(G8>0, N8/G8, 0) | P8: 0.18 | Q8: =IF(G8>0, ((N8-SUMIFS('03_BOC_TACH_VAN'!K:K, '03_BOC_TACH_VAN'!B:B, B8, '03_BOC_TACH_VAN'!D:D, "ĐỘNG_CƠ_VÀ_CẢM_BIẾN"))*(1+P8)+SUMIFS('03_BOC_TACH_VAN'!K:K, '03_BOC_TACH_VAN'!B:B, B8, '03_BOC_TACH_VAN'!D:D, "ĐỘNG_CƠ_VÀ_CẢM_BIẾN"))/G8, 0) | R8: =G8*Q8
A9: 8 | B9: SW-DAMPER-008 | C9: VAN GIÓ | D9: HỆ THỐNG HÚT KHÓI HẦM XE, HÚT KHÓI SỰ CỐ Van 1 chiều NRD 1250x1250 (EI60) | E9: 1250x1250 | F9: Cái | G9: 6 | H9: =SUMIF('01_BOC_TACH_ONG'!B:B, B9, '01_BOC_TACH_ONG'!K:K) | I9: =SUMIF('02_BOC_TACH_CUA'!B:B, B9, '02_BOC_TACH_CUA'!K:K) | J9: =SUMIF('03_BOC_TACH_VAN'!B:B, B9, '03_BOC_TACH_VAN'!K:K) | K9: =SUM(H9:J9) | L9: =(K9-SUMIFS('03_BOC_TACH_VAN'!K:K, '03_BOC_TACH_VAN'!B:B, B9, '03_BOC_TACH_VAN'!D:D, "ĐỘNG_CƠ_VÀ_CẢM_BIẾN"))*0.25 | M9: =(K9-SUMIFS('03_BOC_TACH_VAN'!K:K, '03_BOC_TACH_VAN'!B:B, B9, '03_BOC_TACH_VAN'!D:D, "ĐỘNG_CƠ_VÀ_CẢM_BIẾN"))*0.10 | N9: =K9+L9+M9 | O9: =IF(G9>0, N9/G9, 0) | P9: 0.18 | Q9: =IF(G9>0, ((N9-SUMIFS('03_BOC_TACH_VAN'!K:K, '03_BOC_TACH_VAN'!B:B, B9, '03_BOC_TACH_VAN'!D:D, "ĐỘNG_CƠ_VÀ_CẢM_BIẾN"))*(1+P9)+SUMIFS('03_BOC_TACH_VAN'!K:K, '03_BOC_TACH_VAN'!B:B, B9, '03_BOC_TACH_VAN'!D:D, "ĐỘNG_CƠ_VÀ_CẢM_BIẾN"))/G9, 0) | R9: =G9*Q9
A10: 9 | B10: SW-DAMPER-009 | C10: VAN GIÓ | D10: HỆ THỐNG HÚT KHÓI HẦM XE, HÚT KHÓI SỰ CỐ Van 1 chiều NRD 1700x600 (EI60) | E10: 1700x600 | F10: Cái | G10: 2 | H10: =SUMIF('01_BOC_TACH_ONG'!B:B, B10, '01_BOC_TACH_ONG'!K:K) | I10: =SUMIF('02_BOC_TACH_CUA'!B:B, B10, '02_BOC_TACH_CUA'!K:K) | J10: =SUMIF('03_BOC_TACH_VAN'!B:B, B10, '03_BOC_TACH_VAN'!K:K) | K10: =SUM(H10:J10) | L10: =(K10-SUMIFS('03_BOC_TACH_VAN'!K:K, '03_BOC_TACH_VAN'!B:B, B10, '03_BOC_TACH_VAN'!D:D, "ĐỘNG_CƠ_VÀ_CẢM_BIẾN"))*0.25 | M10: =(K10-SUMIFS('03_BOC_TACH_VAN'!K:K, '03_BOC_TACH_VAN'!B:B, B10, '03_BOC_TACH_VAN'!D:D, "ĐỘNG_CƠ_VÀ_CẢM_BIẾN"))*0.10 | N10: =K10+L10+M10 | O10: =IF(G10>0, N10/G10, 0) | P10: 0.18 | Q10: =IF(G10>0, ((N10-SUMIFS('03_BOC_TACH_VAN'!K:K, '03_BOC_TACH_VAN'!B:B, B10, '03_BOC_TACH_VAN'!D:D, "ĐỘNG_CƠ_VÀ_CẢM_BIẾN"))*(1+P10)+SUMIFS('03_BOC_TACH_VAN'!K:K, '03_BOC_TACH_VAN'!B:B, B10, '03_BOC_TACH_VAN'!D:D, "ĐỘNG_CƠ_VÀ_CẢM_BIẾN"))/G10, 0) | R10: =G10*Q10
A11: 10 | B11: SW-DAMPER-010 | C11: VAN GIÓ | D11: HỆ THỐNG HÚT KHÓI HẦM XE, HÚT KHÓI SỰ CỐ Van 1 chiều NRD 1200x350 (EI60) | E11: 1200x350 | F11: Cái | G11: 1 | H11: =SUMIF('01_BOC_TACH_ONG'!B:B, B11, '01_BOC_TACH_ONG'!K:K) | I11: =SUMIF('02_BOC_TACH_CUA'!B:B, B11, '02_BOC_TACH_CUA'!K:K) | J11: =SUMIF('03_BOC_TACH_VAN'!B:B, B11, '03_BOC_TACH_VAN'!K:K) | K11: =SUM(H11:J11) | L11: =(K11-SUMIFS('03_BOC_TACH_VAN'!K:K, '03_BOC_TACH_VAN'!B:B, B11, '03_BOC_TACH_VAN'!D:D, "ĐỘNG_CƠ_VÀ_CẢM_BIẾN"))*0.25 | M11: =(K11-SUMIFS('03_BOC_TACH_VAN'!K:K, '03_BOC_TACH_VAN'!B:B, B11, '03_BOC_TACH_VAN'!D:D, "ĐỘNG_CƠ_VÀ_CẢM_BIẾN"))*0.10 | N11: =K11+L11+M11 | O11: =IF(G11>0, N11/G11, 0) | P11: 0.18 | Q11: =IF(G11>0, ((N11-SUMIFS('03_BOC_TACH_VAN'!K:K, '03_BOC_TACH_VAN'!B:B, B11, '03_BOC_TACH_VAN'!D:D, "ĐỘNG_CƠ_VÀ_CẢM_BIẾN"))*(1+P11)+SUMIFS('03_BOC_TACH_VAN'!K:K, '03_BOC_TACH_VAN'!B:B, B11, '03_BOC_TACH_VAN'!D:D, "ĐỘNG_CƠ_VÀ_CẢM_BIẾN"))/G11, 0) | R11: =G11*Q11
A12: 11 | B12: SW-DAMPER-011 | C12: VAN GIÓ | D12: HỆ THỐNG HÚT KHÓI HẦM XE, HÚT KHÓI SỰ CỐ Van ngăn cháy MFD 1250x1250 (EI60) | E12: 1250x1250 | F12: Cái | G12: 6 | H12: =SUMIF('01_BOC_TACH_ONG'!B:B, B12, '01_BOC_TACH_ONG'!K:K) | I12: =SUMIF('02_BOC_TACH_CUA'!B:B, B12, '02_BOC_TACH_CUA'!K:K) | J12: =SUMIF('03_BOC_TACH_VAN'!B:B, B12, '03_BOC_TACH_VAN'!K:K) | K12: =SUM(H12:J12) | L12: =(K12-SUMIFS('03_BOC_TACH_VAN'!K:K, '03_BOC_TACH_VAN'!B:B, B12, '03_BOC_TACH_VAN'!D:D, "ĐỘNG_CƠ_VÀ_CẢM_BIẾN"))*0.25 | M12: =(K12-SUMIFS('03_BOC_TACH_VAN'!K:K, '03_BOC_TACH_VAN'!B:B, B12, '03_BOC_TACH_VAN'!D:D, "ĐỘNG_CƠ_VÀ_CẢM_BIẾN"))*0.10 | N12: =K12+L12+M12 | O12: =IF(G12>0, N12/G12, 0) | P12: 0.18 | Q12: =IF(G12>0, ((N12-SUMIFS('03_BOC_TACH_VAN'!K:K, '03_BOC_TACH_VAN'!B:B, B12, '03_BOC_TACH_VAN'!D:D, "ĐỘNG_CƠ_VÀ_CẢM_BIẾN"))*(1+P12)+SUMIFS('03_BOC_TACH_VAN'!K:K, '03_BOC_TACH_VAN'!B:B, B12, '03_BOC_TACH_VAN'!D:D, "ĐỘNG_CƠ_VÀ_CẢM_BIẾN"))/G12, 0) | R12: =G12*Q12
A13: 12 | B13: SW-DAMPER-012 | C13: VAN GIÓ | D13: HỆ THỐNG HÚT KHÓI HẦM XE, HÚT KHÓI SỰ CỐ Van ngăn cháy MFD 1700x600 (EI60) | E13: 1700x600 | F13: Cái | G13: 2 | H13: =SUMIF('01_BOC_TACH_ONG'!B:B, B13, '01_BOC_TACH_ONG'!K:K) | I13: =SUMIF('02_BOC_TACH_CUA'!B:B, B13, '02_BOC_TACH_CUA'!K:K) | J13: =SUMIF('03_BOC_TACH_VAN'!B:B, B13, '03_BOC_TACH_VAN'!K:K) | K13: =SUM(H13:J13) | L13: =(K13-SUMIFS('03_BOC_TACH_VAN'!K:K, '03_BOC_TACH_VAN'!B:B, B13, '03_BOC_TACH_VAN'!D:D, "ĐỘNG_CƠ_VÀ_CẢM_BIẾN"))*0.25 | M13: =(K13-SUMIFS('03_BOC_TACH_VAN'!K:K, '03_BOC_TACH_VAN'!B:B, B13, '03_BOC_TACH_VAN'!D:D, "ĐỘNG_CƠ_VÀ_CẢM_BIẾN"))*0.10 | N13: =K13+L13+M13 | O13: =IF(G13>0, N13/G13, 0) | P13: 0.18 | Q13: =IF(G13>0, ((N13-SUMIFS('03_BOC_TACH_VAN'!K:K, '03_BOC_TACH_VAN'!B:B, B13, '03_BOC_TACH_VAN'!D:D, "ĐỘNG_CƠ_VÀ_CẢM_BIẾN"))*(1+P13)+SUMIFS('03_BOC_TACH_VAN'!K:K, '03_BOC_TACH_VAN'!B:B, B13, '03_BOC_TACH_VAN'!D:D, "ĐỘNG_CƠ_VÀ_CẢM_BIẾN"))/G13, 0) | R13: =G13*Q13
... A35: 34 | B35: SW-DUCT-034 | C35: ỐNG GIÓ | D35: HỆ THỐNG HÚT KHÓI HẦM XE, HÚT KHÓI SỰ CỐ Box miệng gió 10006300 | E35: 1000x300 | F35: Cái | G35: 52 | H35: =SUMIF('01_BOC_TACH_ONG'!B:B, B35, '01_BOC_TACH_ONG'!K:K) | I35: =SUMIF('02_BOC_TACH_CUA'!B:B, B35, '02_BOC_TACH_CUA'!K:K) | J35: =SUMIF('03_BOC_TACH_VAN'!B:B, B35, '03_BOC_TACH_VAN'!K:K) | K35: =SUM(H35:J35) | L35: =(K35-SUMIFS('03_BOC_TACH_VAN'!K:K, '03_BOC_TACH_VAN'!B:B, B35, '03_BOC_TACH_VAN'!D:D, "ĐỘNG_CƠ_VÀ_CẢM_BIẾN"))*0.25 | M35: =(K35-SUMIFS('03_BOC_TACH_VAN'!K:K, '03_BOC_TACH_VAN'!B:B, B35, '03_BOC_TACH_VAN'!D:D, "ĐỘNG_CƠ_VÀ_CẢM_BIẾN"))*0.10 | N35: =K35+L35+M35 | O35: =IF(G35>0, N35/G35, 0) | P35: 0.18 | Q35: =IF(G35>0, ((N35-SUMIFS('03_BOC_TACH_VAN'!K:K, '03_BOC_TACH_VAN'!B:B, B35, '03_BOC_TACH_VAN'!D:D, "ĐỘNG_CƠ_VÀ_CẢM_BIẾN"))*(1+P35)+SUMIFS('03_BOC_TACH_VAN'!K:K, '03_BOC_TACH_VAN'!B:B, B35, '03_BOC_TACH_VAN'!D:D, "ĐỘNG_CƠ_VÀ_CẢM_BIẾN"))/G35, 0) | R35: =G35*Q35
A36: 35 | B36: SW-TRD-035 | C36: THƯƠNG MẠI | D36: HỆ THỐNG HÚT KHÓI HẦM XE, HÚT KHÓI SỰ CỐ Vật tư phụ, phụ kiện | E36: - | F36: Lô | G36: 1 | H36: =SUMIF('01_BOC_TACH_ONG'!B:B, B36, '01_BOC_TACH_ONG'!K:K) | I36: =SUMIF('02_BOC_TACH_CUA'!B:B, B36, '02_BOC_TACH_CUA'!K:K) | J36: =SUMIF('03_BOC_TACH_VAN'!B:B, B36, '03_BOC_TACH_VAN'!K:K) | K36: =SUM(H36:J36) | L36: =(K36-SUMIFS('03_BOC_TACH_VAN'!K:K, '03_BOC_TACH_VAN'!B:B, B36, '03_BOC_TACH_VAN'!D:D, "ĐỘNG_CƠ_VÀ_CẢM_BIẾN"))*0.00 | M36: =(K36-SUMIFS('03_BOC_TACH_VAN'!K:K, '03_BOC_TACH_VAN'!B:B, B36, '03_BOC_TACH_VAN'!D:D, "ĐỘNG_CƠ_VÀ_CẢM_BIẾN"))*0.02 | N36: =K36+L36+M36 | O36: =IF(G36>0, N36/G36, 0) | P36: 0.1 | Q36: =IF(G36>0, ((N36-SUMIFS('03_BOC_TACH_VAN'!K:K, '03_BOC_TACH_VAN'!B:B, B36, '03_BOC_TACH_VAN'!D:D, "ĐỘNG_CƠ_VÀ_CẢM_BIẾN"))*(1+P36)+SUMIFS('03_BOC_TACH_VAN'!K:K, '03_BOC_TACH_VAN'!B:B, B36, '03_BOC_TACH_VAN'!D:D, "ĐỘNG_CƠ_VÀ_CẢM_BIẾN"))/G36, 0) | R36: =G36*Q36 | S36: Hàng thương mại
A37: 36 | B37: SW-DUCT-036 | C37: ỐNG GIÓ | D37: Ống thông gió và phụ kiện, box miệng gió Tole 0.75mm phủ lớp mạ kẽm Z180 | E37: 0.75mm | F37: m2 | G37: 2633.4 | H37: =SUMIF('01_BOC_TACH_ONG'!B:B, B37, '01_BOC_TACH_ONG'!K:K) | I37: =SUMIF('02_BOC_TACH_CUA'!B:B, B37, '02_BOC_TACH_CUA'!K:K) | J37: =SUMIF('03_BOC_TACH_VAN'!B:B, B37, '03_BOC_TACH_VAN'!K:K) | K37: =SUM(H37:J37) | L37: =(K37-SUMIFS('03_BOC_TACH_VAN'!K:K, '03_BOC_TACH_VAN'!B:B, B37, '03_BOC_TACH_VAN'!D:D, "ĐỘNG_CƠ_VÀ_CẢM_BIẾN"))*0.25 | M37: =(K37-SUMIFS('03_BOC_TACH_VAN'!K:K, '03_BOC_TACH_VAN'!B:B, B37, '03_BOC_TACH_VAN'!D:D, "ĐỘNG_CƠ_VÀ_CẢM_BIẾN"))*0.10 | N37: =K37+L37+M37 | O37: =IF(G37>0, N37/G37, 0) | P37: 0.18 | Q37: =IF(G37>0, ((N37-SUMIFS('03_BOC_TACH_VAN'!K:K, '03_BOC_TACH_VAN'!B:B, B37, '03_BOC_TACH_VAN'!D:D, "ĐỘNG_CƠ_VÀ_CẢM_BIẾN"))*(1+P37)+SUMIFS('03_BOC_TACH_VAN'!K:K, '03_BOC_TACH_VAN'!B:B, B37, '03_BOC_TACH_VAN'!D:D, "ĐỘNG_CƠ_VÀ_CẢM_BIẾN"))/G37, 0) | R37: =G37*Q37
A38: 37 | B38: SW-DUCT-037 | C38: ỐNG GIÓ | D38: Ống thông gió và phụ kiện, box miệng gió Tole 0.95mm phủ lớp mạ kẽm Z180 | E38: 0.95mm | F38: m2 | G38: 1291.1 | H38: =SUMIF('01_BOC_TACH_ONG'!B:B, B38, '01_BOC_TACH_ONG'!K:K) | I38: =SUMIF('02_BOC_TACH_CUA'!B:B, B38, '02_BOC_TACH_CUA'!K:K) | J38: =SUMIF('03_BOC_TACH_VAN'!B:B, B38, '03_BOC_TACH_VAN'!K:K) | K38: =SUM(H38:J38) | L38: =(K38-SUMIFS('03_BOC_TACH_VAN'!K:K, '03_BOC_TACH_VAN'!B:B, B38, '03_BOC_TACH_VAN'!D:D, "ĐỘNG_CƠ_VÀ_CẢM_BIẾN"))*0.25 | M38: =(K38-SUMIFS('03_BOC_TACH_VAN'!K:K, '03_BOC_TACH_VAN'!B:B, B38, '03_BOC_TACH_VAN'!D:D, "ĐỘNG_CƠ_VÀ_CẢM_BIẾN"))*0.10 | N38: =K38+L38+M38 | O38: =IF(G38>0, N38/G38, 0) | P38: 0.18 | Q38: =IF(G38>0, ((N38-SUMIFS('03_BOC_TACH_VAN'!K:K, '03_BOC_TACH_VAN'!B:B, B38, '03_BOC_TACH_VAN'!D:D, "ĐỘNG_CƠ_VÀ_CẢM_BIẾN"))*(1+P38)+SUMIFS('03_BOC_TACH_VAN'!K:K, '03_BOC_TACH_VAN'!B:B, B38, '03_BOC_TACH_VAN'!D:D, "ĐỘNG_CƠ_VÀ_CẢM_BIẾN"))/G38, 0) | R38: =G38*Q38
A39: 38 | B39: SW-DUCT-038 | C39: ỐNG GIÓ | D39: Ống thông gió và phụ kiện, box miệng gió Tole 1.15mm phủ lớp mạ kẽm Z180 | E39: 1.15mm | F39: m2 | G39: 3070.55 | H39: =SUMIF('01_BOC_TACH_ONG'!B:B, B39, '01_BOC_TACH_ONG'!K:K) | I39: =SUMIF('02_BOC_TACH_CUA'!B:B, B39, '02_BOC_TACH_CUA'!K:K) | J39: =SUMIF('03_BOC_TACH_VAN'!B:B, B39, '03_BOC_TACH_VAN'!K:K) | K39: =SUM(H39:J39) | L39: =(K39-SUMIFS('03_BOC_TACH_VAN'!K:K, '03_BOC_TACH_VAN'!B:B, B39, '03_BOC_TACH_VAN'!D:D, "ĐỘNG_CƠ_VÀ_CẢM_BIẾN"))*0.25 | M39: =(K39-SUMIFS('03_BOC_TACH_VAN'!K:K, '03_BOC_TACH_VAN'!B:B, B39, '03_BOC_TACH_VAN'!D:D, "ĐỘNG_CƠ_VÀ_CẢM_BIẾN"))*0.10 | N39: =K39+L39+M39 | O39: =IF(G39>0, N39/G39, 0) | P39: 0.18 | Q39: =IF(G39>0, ((N39-SUMIFS('03_BOC_TACH_VAN'!K:K, '03_BOC_TACH_VAN'!B:B, B39, '03_BOC_TACH_VAN'!D:D, "ĐỘNG_CƠ_VÀ_CẢM_BIẾN"))*(1+P39)+SUMIFS('03_BOC_TACH_VAN'!K:K, '03_BOC_TACH_VAN'!B:B, B39, '03_BOC_TACH_VAN'!D:D, "ĐỘNG_CƠ_VÀ_CẢM_BIẾN"))/G39, 0) | R39: =G39*Q39
A40: 39 | B40: SW-DUCT-039 | C40: ỐNG GIÓ | D40: Ống thông gió và phụ kiện, box miệng gió Tole ZAM 1.15mm | E40: 1.15mm | F40: m2 | G40: 138 | H40: =SUMIF('01_BOC_TACH_ONG'!B:B, B40, '01_BOC_TACH_ONG'!K:K) | I40: =SUMIF('02_BOC_TACH_CUA'!B:B, B40, '02_BOC_TACH_CUA'!K:K) | J40: =SUMIF('03_BOC_TACH_VAN'!B:B, B40, '03_BOC_TACH_VAN'!K:K) | K40: =SUM(H40:J40) | L40: =(K40-SUMIFS('03_BOC_TACH_VAN'!K:K, '03_BOC_TACH_VAN'!B:B, B40, '03_BOC_TACH_VAN'!D:D, "ĐỘNG_CƠ_VÀ_CẢM_BIẾN"))*0.25 | M40: =(K40-SUMIFS('03_BOC_TACH_VAN'!K:K, '03_BOC_TACH_VAN'!B:B, B40, '03_BOC_TACH_VAN'!D:D, "ĐỘNG_CƠ_VÀ_CẢM_BIẾN"))*0.10 | N40: =K40+L40+M40 | O40: =IF(G40>0, N40/G40, 0) | P40: 0.18 | Q40: =IF(G40>0, ((N40-SUMIFS('03_BOC_TACH_VAN'!K:K, '03_BOC_TACH_VAN'!B:B, B40, '03_BOC_TACH_VAN'!D:D, "ĐỘNG_CƠ_VÀ_CẢM_BIẾN"))*(1+P40)+SUMIFS('03_BOC_TACH_VAN'!K:K, '03_BOC_TACH_VAN'!B:B, B40, '03_BOC_TACH_VAN'!D:D, "ĐỘNG_CƠ_VÀ_CẢM_BIẾN"))/G40, 0) | R40: =G40*Q40
A41: 40 | B41: SW-TRD-040 | C41: THƯƠNG MẠI | D41: Ống thông gió và phụ kiện, box miệng gió Lưới bảo vệ | E41: - | F41: cái | G41: 3 | H41: =SUMIF('01_BOC_TACH_ONG'!B:B, B41, '01_BOC_TACH_ONG'!K:K) | I41: =SUMIF('02_BOC_TACH_CUA'!B:B, B41, '02_BOC_TACH_CUA'!K:K) | J41: =SUMIF('03_BOC_TACH_VAN'!B:B, B41, '03_BOC_TACH_VAN'!K:K) | K41: =SUM(H41:J41) | L41: =(K41-SUMIFS('03_BOC_TACH_VAN'!K:K, '03_BOC_TACH_VAN'!B:B, B41, '03_BOC_TACH_VAN'!D:D, "ĐỘNG_CƠ_VÀ_CẢM_BIẾN"))*0.00 | M41: =(K41-SUMIFS('03_BOC_TACH_VAN'!K:K, '03_BOC_TACH_VAN'!B:B, B41, '03_BOC_TACH_VAN'!D:D, "ĐỘNG_CƠ_VÀ_CẢM_BIẾN"))*0.02 | N41: =K41+L41+M41 | O41: =IF(G41>0, N41/G41, 0) | P41: 0.1 | Q41: =IF(G41>0, ((N41-SUMIFS('03_BOC_TACH_VAN'!K:K, '03_BOC_TACH_VAN'!B:B, B41, '03_BOC_TACH_VAN'!D:D, "ĐỘNG_CƠ_VÀ_CẢM_BIẾN"))*(1+P41)+SUMIFS('03_BOC_TACH_VAN'!K:K, '03_BOC_TACH_VAN'!B:B, B41, '03_BOC_TACH_VAN'!D:D, "ĐỘNG_CƠ_VÀ_CẢM_BIẾN"))/G41, 0) | R41: =G41*Q41 | S41: Hàng thương mại
A42: 41 | B42: SW-TRD-041 | C42: THƯƠNG MẠI | D42: Ống thông gió và phụ kiện, box miệng gió Lớp chống cháy EI30 | E42: - | F42: m2 | G42: 3621.25 | H42: =SUMIF('01_BOC_TACH_ONG'!B:B, B42, '01_BOC_TACH_ONG'!K:K) | I42: =SUMIF('02_BOC_TACH_CUA'!B:B, B42, '02_BOC_TACH_CUA'!K:K) | J42: =SUMIF('03_BOC_TACH_VAN'!B:B, B42, '03_BOC_TACH_VAN'!K:K) | K42: =SUM(H42:J42) | L42: =(K42-SUMIFS('03_BOC_TACH_VAN'!K:K, '03_BOC_TACH_VAN'!B:B, B42, '03_BOC_TACH_VAN'!D:D, "ĐỘNG_CƠ_VÀ_CẢM_BIẾN"))*0.00 | M42: =(K42-SUMIFS('03_BOC_TACH_VAN'!K:K, '03_BOC_TACH_VAN'!B:B, B42, '03_BOC_TACH_VAN'!D:D, "ĐỘNG_CƠ_VÀ_CẢM_BIẾN"))*0.02 | N42: =K42+L42+M42 | O42: =IF(G42>0, N42/G42, 0) | P42: 0.1 | Q42: =IF(G42>0, ((N42-SUMIFS('03_BOC_TACH_VAN'!K:K, '03_BOC_TACH_VAN'!B:B, B42, '03_BOC_TACH_VAN'!D:D, "ĐỘNG_CƠ_VÀ_CẢM_BIẾN"))*(1+P42)+SUMIFS('03_BOC_TACH_VAN'!K:K, '03_BOC_TACH_VAN'!B:B, B42, '03_BOC_TACH_VAN'!D:D, "ĐỘNG_CƠ_VÀ_CẢM_BIẾN"))/G42, 0) | R42: =G42*Q42 | S42: Hàng thương mại
A43: 42 | B43: SW-TRD-042 | C43: THƯƠNG MẠI | D43: Ống thông gió và phụ kiện, box miệng gió Lớp chống cháy EI60 | E43: - | F43: m2 | G43: 2821 | H43: =SUMIF('01_BOC_TACH_ONG'!B:B, B43, '01_BOC_TACH_ONG'!K:K) | I43: =SUMIF('02_BOC_TACH_CUA'!B:B, B43, '02_BOC_TACH_CUA'!K:K) | J43: =SUMIF('03_BOC_TACH_VAN'!B:B, B43, '03_BOC_TACH_VAN'!K:K) | K43: =SUM(H43:J43) | L43: =(K43-SUMIFS('03_BOC_TACH_VAN'!K:K, '03_BOC_TACH_VAN'!B:B, B43, '03_BOC_TACH_VAN'!D:D, "ĐỘNG_CƠ_VÀ_CẢM_BIẾN"))*0.00 | M43: =(K43-SUMIFS('03_BOC_TACH_VAN'!K:K, '03_BOC_TACH_VAN'!B:B, B43, '03_BOC_TACH_VAN'!D:D, "ĐỘNG_CƠ_VÀ_CẢM_BIẾN"))*0.02 | N43: =K43+L43+M43 | O43: =IF(G43>0, N43/G43, 0) | P43: 0.1 | Q43: =IF(G43>0, ((N43-SUMIFS('03_BOC_TACH_VAN'!K:K, '03_BOC_TACH_VAN'!B:B, B43, '03_BOC_TACH_VAN'!D:D, "ĐỘNG_CƠ_VÀ_CẢM_BIẾN"))*(1+P43)+SUMIFS('03_BOC_TACH_VAN'!K:K, '03_BOC_TACH_VAN'!B:B, B43, '03_BOC_TACH_VAN'!D:D, "ĐỘNG_CƠ_VÀ_CẢM_BIẾN"))/G43, 0) | R43: =G43*Q43 | S43: Hàng thương mại
A44: 43 | B44: SW-TRD-043 | C44: THƯƠNG MẠI | D44: Ống thông gió và phụ kiện, box miệng gió Vật tư phụ, phụ kiện | E44: - | F44: Lô | G44: 1 | H44: =SUMIF('01_BOC_TACH_ONG'!B:B, B44, '01_BOC_TACH_ONG'!K:K) | I44: =SUMIF('02_BOC_TACH_CUA'!B:B, B44, '02_BOC_TACH_CUA'!K:K) | J44: =SUMIF('03_BOC_TACH_VAN'!B:B, B44, '03_BOC_TACH_VAN'!K:K) | K44: =SUM(H44:J44) | L44: =(K44-SUMIFS('03_BOC_TACH_VAN'!K:K, '03_BOC_TACH_VAN'!B:B, B44, '03_BOC_TACH_VAN'!D:D, "ĐỘNG_CƠ_VÀ_CẢM_BIẾN"))*0.00 | M44: =(K44-SUMIFS('03_BOC_TACH_VAN'!K:K, '03_BOC_TACH_VAN'!B:B, B44, '03_BOC_TACH_VAN'!D:D, "ĐỘNG_CƠ_VÀ_CẢM_BIẾN"))*0.02 | N44: =K44+L44+M44 | O44: =IF(G44>0, N44/G44, 0) | P44: 0.1 | Q44: =IF(G44>0, ((N44-SUMIFS('03_BOC_TACH_VAN'!K:K, '03_BOC_TACH_VAN'!B:B, B44, '03_BOC_TACH_VAN'!D:D, "ĐỘNG_CƠ_VÀ_CẢM_BIẾN"))*(1+P44)+SUMIFS('03_BOC_TACH_VAN'!K:K, '03_BOC_TACH_VAN'!B:B, B44, '03_BOC_TACH_VAN'!D:D, "ĐỘNG_CƠ_VÀ_CẢM_BIẾN"))/G44, 0) | R44: =G44*Q44 | S44: Hàng thương mại
A45: 44 | B45: SW-DAMPER-044 | C45: VAN GIÓ | D45: HỆ THỐNG TẠO ÁP Van 1 chiều NRD 300x200 (EI60) | E45: 300x200 | F45: Cái | G45: 1 | H45: =SUMIF('01_BOC_TACH_ONG'!B:B, B45, '01_BOC_TACH_ONG'!K:K) | I45: =SUMIF('02_BOC_TACH_CUA'!B:B, B45, '02_BOC_TACH_CUA'!K:K) | J45: =SUMIF('03_BOC_TACH_VAN'!B:B, B45, '03_BOC_TACH_VAN'!K:K) | K45: =SUM(H45:J45) | L45: =(K45-SUMIFS('03_BOC_TACH_VAN'!K:K, '03_BOC_TACH_VAN'!B:B, B45, '03_BOC_TACH_VAN'!D:D, "ĐỘNG_CƠ_VÀ_CẢM_BIẾN"))*0.25 | M45: =(K45-SUMIFS('03_BOC_TACH_VAN'!K:K, '03_BOC_TACH_VAN'!B:B, B45, '03_BOC_TACH_VAN'!D:D, "ĐỘNG_CƠ_VÀ_CẢM_BIẾN"))*0.10 | N45: =K45+L45+M45 | O45: =IF(G45>0, N45/G45, 0) | P45: 0.18 | Q45: =IF(G45>0, ((N45-SUMIFS('03_BOC_TACH_VAN'!K:K, '03_BOC_TACH_VAN'!B:B, B45, '03_BOC_TACH_VAN'!D:D, "ĐỘNG_CƠ_VÀ_CẢM_BIẾN"))*(1+P45)+SUMIFS('03_BOC_TACH_VAN'!K:K, '03_BOC_TACH_VAN'!B:B, B45, '03_BOC_TACH_VAN'!D:D, "ĐỘNG_CƠ_VÀ_CẢM_BIẾN"))/G45, 0) | R45: =G45*Q45
A46: 45 | B46: SW-DAMPER-045 | C46: VAN GIÓ | D46: HỆ THỐNG TẠO ÁP Van 1 chiều NRD 700x500 (EI60) | E46: 700x500 | F46: Cái | G46: 2 | H46: =SUMIF('01_BOC_TACH_ONG'!B:B, B46, '01_BOC_TACH_ONG'!K:K) | I46: =SUMIF('02_BOC_TACH_CUA'!B:B, B46, '02_BOC_TACH_CUA'!K:K) | J46: =SUMIF('03_BOC_TACH_VAN'!B:B, B46, '03_BOC_TACH_VAN'!K:K) | K46: =SUM(H46:J46) | L46: =(K46-SUMIFS('03_BOC_TACH_VAN'!K:K, '03_BOC_TACH_VAN'!B:B, B46, '03_BOC_TACH_VAN'!D:D, "ĐỘNG_CƠ_VÀ_CẢM_BIẾN"))*0.25 | M46: =(K46-SUMIFS('03_BOC_TACH_VAN'!K:K, '03_BOC_TACH_VAN'!B:B, B46, '03_BOC_TACH_VAN'!D:D, "ĐỘNG_CƠ_VÀ_CẢM_BIẾN"))*0.10 | N46: =K46+L46+M46 | O46: =IF(G46>0, N46/G46, 0) | P46: 0.18 | Q46: =IF(G46>0, ((N46-SUMIFS('03_BOC_TACH_VAN'!K:K, '03_BOC_TACH_VAN'!B:B, B46, '03_BOC_TACH_VAN'!D:D, "ĐỘNG_CƠ_VÀ_CẢM_BIẾN"))*(1+P46)+SUMIFS('03_BOC_TACH_VAN'!K:K, '03_BOC_TACH_VAN'!B:B, B46, '03_BOC_TACH_VAN'!D:D, "ĐỘNG_CƠ_VÀ_CẢM_BIẾN"))/G46, 0) | R46: =G46*Q46
A47: 46 | B47: SW-DAMPER-046 | C47: VAN GIÓ | D47: HỆ THỐNG TẠO ÁP Van 1 chiều NRD 700x800 (EI60) | E47: 700x800 | F47: Cái | G47: 2 | H47: =SUMIF('01_BOC_TACH_ONG'!B:B, B47, '01_BOC_TACH_ONG'!K:K) | I47: =SUMIF('02_BOC_TACH_CUA'!B:B, B47, '02_BOC_TACH_CUA'!K:K) | J47: =SUMIF('03_BOC_TACH_VAN'!B:B, B47, '03_BOC_TACH_VAN'!K:K) | K47: =SUM(H47:J47) | L47: =(K47-SUMIFS('03_BOC_TACH_VAN'!K:K, '03_BOC_TACH_VAN'!B:B, B47, '03_BOC_TACH_VAN'!D:D, "ĐỘNG_CƠ_VÀ_CẢM_BIẾN"))*0.25 | M47: =(K47-SUMIFS('03_BOC_TACH_VAN'!K:K, '03_BOC_TACH_VAN'!B:B, B47, '03_BOC_TACH_VAN'!D:D, "ĐỘNG_CƠ_VÀ_CẢM_BIẾN"))*0.10 | N47: =K47+L47+M47 | O47: =IF(G47>0, N47/G47, 0) | P47: 0.18 | Q47: =IF(G47>0, ((N47-SUMIFS('03_BOC_TACH_VAN'!K:K, '03_BOC_TACH_VAN'!B:B, B47, '03_BOC_TACH_VAN'!D:D, "ĐỘNG_CƠ_VÀ_CẢM_BIẾN"))*(1+P47)+SUMIFS('03_BOC_TACH_VAN'!K:K, '03_BOC_TACH_VAN'!B:B, B47, '03_BOC_TACH_VAN'!D:D, "ĐỘNG_CƠ_VÀ_CẢM_BIẾN"))/G47, 0) | R47: =G47*Q47
A48: 47 | B48: SW-DAMPER-047 | C48: VAN GIÓ | D48: HỆ THỐNG TẠO ÁP Van 1 chiều NRD 250X200(EI60) | E48: 250x200 | F48: Cái | G48: 1 | H48: =SUMIF('01_BOC_TACH_ONG'!B:B, B48, '01_BOC_TACH_ONG'!K:K) | I48: =SUMIF('02_BOC_TACH_CUA'!B:B, B48, '02_BOC_TACH_CUA'!K:K) | J48: =SUMIF('03_BOC_TACH_VAN'!B:B, B48, '03_BOC_TACH_VAN'!K:K) | K48: =SUM(H48:J48) | L48: =(K48-SUMIFS('03_BOC_TACH_VAN'!K:K, '03_BOC_TACH_VAN'!B:B, B48, '03_BOC_TACH_VAN'!D:D, "ĐỘNG_CƠ_VÀ_CẢM_BIẾN"))*0.25 | M48: =(K48-SUMIFS('03_BOC_TACH_VAN'!K:K, '03_BOC_TACH_VAN'!B:B, B48, '03_BOC_TACH_VAN'!D:D, "ĐỘNG_CƠ_VÀ_CẢM_BIẾN"))*0.10 | N48: =K48+L48+M48 | O48: =IF(G48>0, N48/G48, 0) | P48: 0.18 | Q48: =IF(G48>0, ((N48-SUMIFS('03_BOC_TACH_VAN'!K:K, '03_BOC_TACH_VAN'!B:B, B48, '03_BOC_TACH_VAN'!D:D, "ĐỘNG_CƠ_VÀ_CẢM_BIẾN"))*(1+P48)+SUMIFS('03_BOC_TACH_VAN'!K:K, '03_BOC_TACH_VAN'!B:B, B48, '03_BOC_TACH_VAN'!D:D, "ĐỘNG_CƠ_VÀ_CẢM_BIẾN"))/G48, 0) | R48: =G48*Q48
A49: 48 | B49: SW-DAMPER-048 | C49: VAN GIÓ | D49: HỆ THỐNG TẠO ÁP Van 1 chiều NRD 900x400 (EI60) | E49: 900x400 | F49: Cái | G49: 2 | H49: =SUMIF('01_BOC_TACH_ONG'!B:B, B49, '01_BOC_TACH_ONG'!K:K) | I49: =SUMIF('02_BOC_TACH_CUA'!B:B, B49, '02_BOC_TACH_CUA'!K:K) | J49: =SUMIF('03_BOC_TACH_VAN'!B:B, B49, '03_BOC_TACH_VAN'!K:K) | K49: =SUM(H49:J49) | L49: =(K49-SUMIFS('03_BOC_TACH_VAN'!K:K, '03_BOC_TACH_VAN'!B:B, B49, '03_BOC_TACH_VAN'!D:D, "ĐỘNG_CƠ_VÀ_CẢM_BIẾN"))*0.25 | M49: =(K49-SUMIFS('03_BOC_TACH_VAN'!K:K, '03_BOC_TACH_VAN'!B:B, B49, '03_BOC_TACH_VAN'!D:D, "ĐỘNG_CƠ_VÀ_CẢM_BIẾN"))*0.10 | N49: =K49+L49+M49 | O49: =IF(G49>0, N49/G49, 0) | P49: 0.18 | Q49: =IF(G49>0, ((N49-SUMIFS('03_BOC_TACH_VAN'!K:K, '03_BOC_TACH_VAN'!B:B, B49, '03_BOC_TACH_VAN'!D:D, "ĐỘNG_CƠ_VÀ_CẢM_BIẾN"))*(1+P49)+SUMIFS('03_BOC_TACH_VAN'!K:K, '03_BOC_TACH_VAN'!B:B, B49, '03_BOC_TACH_VAN'!D:D, "ĐỘNG_CƠ_VÀ_CẢM_BIẾN"))/G49, 0) | R49: =G49*Q49
A50: 49 | B50: SW-DAMPER-049 | C50: VAN GIÓ | D50: HỆ THỐNG TẠO ÁP Van 1 chiều NRD 300x300 (EI60) | E50: 300x300 | F50: Cái | G50: 1 | H50: =SUMIF('01_BOC_TACH_ONG'!B:B, B50, '01_BOC_TACH_ONG'!K:K) | I50: =SUMIF('02_BOC_TACH_CUA'!B:B, B50, '02_BOC_TACH_CUA'!K:K) | J50: =SUMIF('03_BOC_TACH_VAN'!B:B, B50, '03_BOC_TACH_VAN'!K:K) | K50: =SUM(H50:J50) | L50: =(K50-SUMIFS('03_BOC_TACH_VAN'!K:K, '03_BOC_TACH_VAN'!B:B, B50, '03_BOC_TACH_VAN'!D:D, "ĐỘNG_CƠ_VÀ_CẢM_BIẾN"))*0.25 | M50: =(K50-SUMIFS('03_BOC_TACH_VAN'!K:K, '03_BOC_TACH_VAN'!B:B, B50, '03_BOC_TACH_VAN'!D:D, "ĐỘNG_CƠ_VÀ_CẢM_BIẾN"))*0.10 | N50: =K50+L50+M50 | O50: =IF(G50>0, N50/G50, 0) | P50: 0.18 | Q50: =IF(G50>0, ((N50-SUMIFS('03_BOC_TACH_VAN'!K:K, '03_BOC_TACH_VAN'!B:B, B50, '03_BOC_TACH_VAN'!D:D, "ĐỘNG_CƠ_VÀ_CẢM_BIẾN"))*(1+P50)+SUMIFS('03_BOC_TACH_VAN'!K:K, '03_BOC_TACH_VAN'!B:B, B50, '03_BOC_TACH_VAN'!D:D, "ĐỘNG_CƠ_VÀ_CẢM_BIẾN"))/G50, 0) | R50: =G50*Q50
A51: 50 | B51: SW-DAMPER-050 | C51: VAN GIÓ | D51: HỆ THỐNG TẠO ÁP Van 1 chiều NRD 350x250 (EI60) | E51: 350x250 | F51: Cái | G51: 1 | H51: =SUMIF('01_BOC_TACH_ONG'!B:B, B51, '01_BOC_TACH_ONG'!K:K) | I51: =SUMIF('02_BOC_TACH_CUA'!B:B, B51, '02_BOC_TACH_CUA'!K:K) | J51: =SUMIF('03_BOC_TACH_VAN'!B:B, B51, '03_BOC_TACH_VAN'!K:K) | K51: =SUM(H51:J51) | L51: =(K51-SUMIFS('03_BOC_TACH_VAN'!K:K, '03_BOC_TACH_VAN'!B:B, B51, '03_BOC_TACH_VAN'!D:D, "ĐỘNG_CƠ_VÀ_CẢM_BIẾN"))*0.25 | M51: =(K51-SUMIFS('03_BOC_TACH_VAN'!K:K, '03_BOC_TACH_VAN'!B:B, B51, '03_BOC_TACH_VAN'!D:D, "ĐỘNG_CƠ_VÀ_CẢM_BIẾN"))*0.10 | N51: =K51+L51+M51 | O51: =IF(G51>0, N51/G51, 0) | P51: 0.18 | Q51: =IF(G51>0, ((N51-SUMIFS('03_BOC_TACH_VAN'!K:K, '03_BOC_TACH_VAN'!B:B, B51, '03_BOC_TACH_VAN'!D:D, "ĐỘNG_CƠ_VÀ_CẢM_BIẾN"))*(1+P51)+SUMIFS('03_BOC_TACH_VAN'!K:K, '03_BOC_TACH_VAN'!B:B, B51, '03_BOC_TACH_VAN'!D:D, "ĐỘNG_CƠ_VÀ_CẢM_BIẾN"))/G51, 0) | R51: =G51*Q51
A52: 51 | B52: SW-DAMPER-051 | C52: VAN GIÓ | D52: HỆ THỐNG TẠO ÁP Van 1 chiều NRD 350x150 (EI60) | E52: 350x150 | F52: Cái | G52: 1 | H52: =SUMIF('01_BOC_TACH_ONG'!B:B, B52, '01_BOC_TACH_ONG'!K:K) | I52: =SUMIF('02_BOC_TACH_CUA'!B:B, B52, '02_BOC_TACH_CUA'!K:K) | J52: =SUMIF('03_BOC_TACH_VAN'!B:B, B52, '03_BOC_TACH_VAN'!K:K) | K52: =SUM(H52:J52) | L52: =(K52-SUMIFS('03_BOC_TACH_VAN'!K:K, '03_BOC_TACH_VAN'!B:B, B52, '03_BOC_TACH_VAN'!D:D, "ĐỘNG_CƠ_VÀ_CẢM_BIẾN"))*0.25 | M52: =(K52-SUMIFS('03_BOC_TACH_VAN'!K:K, '03_BOC_TACH_VAN'!B:B, B52, '03_BOC_TACH_VAN'!D:D, "ĐỘNG_CƠ_VÀ_CẢM_BIẾN"))*0.10 | N52: =K52+L52+M52 | O52: =IF(G52>0, N52/G52, 0) | P52: 0.18 | Q52: =IF(G52>0, ((N52-SUMIFS('03_BOC_TACH_VAN'!K:K, '03_BOC_TACH_VAN'!B:B, B52, '03_BOC_TACH_VAN'!D:D, "ĐỘNG_CƠ_VÀ_CẢM_BIẾN"))*(1+P52)+SUMIFS('03_BOC_TACH_VAN'!K:K, '03_BOC_TACH_VAN'!B:B, B52, '03_BOC_TACH_VAN'!D:D, "ĐỘNG_CƠ_VÀ_CẢM_BIẾN"))/G52, 0) | R52: =G52*Q52
A53: 52 | B53: SW-DAMPER-052 | C53: VAN GIÓ | D53: HỆ THỐNG TẠO ÁP Van ngăn cháy MFD 350x200 (EI60) | E53: 350x200 | F53: Cái | G53: 1 | H53: =SUMIF('01_BOC_TACH_ONG'!B:B, B53, '01_BOC_TACH_ONG'!K:K) | I53: =SUMIF('02_BOC_TACH_CUA'!B:B, B53, '02_BOC_TACH_CUA'!K:K) | J53: =SUMIF('03_BOC_TACH_VAN'!B:B, B53, '03_BOC_TACH_VAN'!K:K) | K53: =SUM(H53:J53) | L53: =(K53-SUMIFS('03_BOC_TACH_VAN'!K:K, '03_BOC_TACH_VAN'!B:B, B53, '03_BOC_TACH_VAN'!D:D, "ĐỘNG_CƠ_VÀ_CẢM_BIẾN"))*0.25 | M53: =(K53-SUMIFS('03_BOC_TACH_VAN'!K:K, '03_BOC_TACH_VAN'!B:B, B53, '03_BOC_TACH_VAN'!D:D, "ĐỘNG_CƠ_VÀ_CẢM_BIẾN"))*0.10 | N53: =K53+L53+M53 | O53: =IF(G53>0, N53/G53, 0) | P53: 0.18 | Q53: =IF(G53>0, ((N53-SUMIFS('03_BOC_TACH_VAN'!K:K, '03_BOC_TACH_VAN'!B:B, B53, '03_BOC_TACH_VAN'!D:D, "ĐỘNG_CƠ_VÀ_CẢM_BIẾN"))*(1+P53)+SUMIFS('03_BOC_TACH_VAN'!K:K, '03_BOC_TACH_VAN'!B:B, B53, '03_BOC_TACH_VAN'!D:D, "ĐỘNG_CƠ_VÀ_CẢM_BIẾN"))/G53, 0) | R53: =G53*Q53
A54: 53 | B54: SW-DAMPER-053 | C54: VAN GIÓ | D54: HỆ THỐNG TẠO ÁP Van ngăn cháy MFD 700x500 (EI60) | E54: 700x500 | F54: Cái | G54: 2 | H54: =SUMIF('01_BOC_TACH_ONG'!B:B, B54, '01_BOC_TACH_ONG'!K:K) | I54: =SUMIF('02_BOC_TACH_CUA'!B:B, B54, '02_BOC_TACH_CUA'!K:K) | J54: =SUMIF('03_BOC_TACH_VAN'!B:B, B54, '03_BOC_TACH_VAN'!K:K) | K54: =SUM(H54:J54) | L54: =(K54-SUMIFS('03_BOC_TACH_VAN'!K:K, '03_BOC_TACH_VAN'!B:B, B54, '03_BOC_TACH_VAN'!D:D, "ĐỘNG_CƠ_VÀ_CẢM_BIẾN"))*0.25 | M54: =(K54-SUMIFS('03_BOC_TACH_VAN'!K:K, '03_BOC_TACH_VAN'!B:B, B54, '03_BOC_TACH_VAN'!D:D, "ĐỘNG_CƠ_VÀ_CẢM_BIẾN"))*0.10 | N54: =K54+L54+M54 | O54: =IF(G54>0, N54/G54, 0) | P54: 0.18 | Q54: =IF(G54>0, ((N54-SUMIFS('03_BOC_TACH_VAN'!K:K, '03_BOC_TACH_VAN'!B:B, B54, '03_BOC_TACH_VAN'!D:D, "ĐỘNG_CƠ_VÀ_CẢM_BIẾN"))*(1+P54)+SUMIFS('03_BOC_TACH_VAN'!K:K, '03_BOC_TACH_VAN'!B:B, B54, '03_BOC_TACH_VAN'!D:D, "ĐỘNG_CƠ_VÀ_CẢM_BIẾN"))/G54, 0) | R54: =G54*Q54
A55: 54 | B55: SW-DAMPER-054 | C55: VAN GIÓ | D55: HỆ THỐNG TẠO ÁP Van ngăn cháy MFD 700x800 (EI60) | E55: 700x800 | F55: Cái | G55: 2 | H55: =SUMIF('01_BOC_TACH_ONG'!B:B, B55, '01_BOC_TACH_ONG'!K:K) | I55: =SUMIF('02_BOC_TACH_CUA'!B:B, B55, '02_BOC_TACH_CUA'!K:K) | J55: =SUMIF('03_BOC_TACH_VAN'!B:B, B55, '03_BOC_TACH_VAN'!K:K) | K55: =SUM(H55:J55) | L55: =(K55-SUMIFS('03_BOC_TACH_VAN'!K:K, '03_BOC_TACH_VAN'!B:B, B55, '03_BOC_TACH_VAN'!D:D, "ĐỘNG_CƠ_VÀ_CẢM_BIẾN"))*0.25 | M55: =(K55-SUMIFS('03_BOC_TACH_VAN'!K:K, '03_BOC_TACH_VAN'!B:B, B55, '03_BOC_TACH_VAN'!D:D, "ĐỘNG_CƠ_VÀ_CẢM_BIẾN"))*0.10 | N55: =K55+L55+M55 | O55: =IF(G55>0, N55/G55, 0) | P55: 0.18 | Q55: =IF(G55>0, ((N55-SUMIFS('03_BOC_TACH_VAN'!K:K, '03_BOC_TACH_VAN'!B:B, B55, '03_BOC_TACH_VAN'!D:D, "ĐỘNG_CƠ_VÀ_CẢM_BIẾN"))*(1+P55)+SUMIFS('03_BOC_TACH_VAN'!K:K, '03_BOC_TACH_VAN'!B:B, B55, '03_BOC_TACH_VAN'!D:D, "ĐỘNG_CƠ_VÀ_CẢM_BIẾN"))/G55, 0) | R55: =G55*Q55
A56: 55 | B56: SW-DAMPER-055 | C56: VAN GIÓ | D56: HỆ THỐNG TẠO ÁP Van ngăn cháy MFD 1200x600 (EI60) | E56: 1200x600 | F56: Cái | G56: 2 | H56: =SUMIF('01_BOC_TACH_ONG'!B:B, B56, '01_BOC_TACH_ONG'!K:K) | I56: =SUMIF('02_BOC_TACH_CUA'!B:B, B56, '02_BOC_TACH_CUA'!K:K) | J56: =SUMIF('03_BOC_TACH_VAN'!B:B, B56, '03_BOC_TACH_VAN'!K:K) | K56: =SUM(H56:J56) | L56: =(K56-SUMIFS('03_BOC_TACH_VAN'!K:K, '03_BOC_TACH_VAN'!B:B, B56, '03_BOC_TACH_VAN'!D:D, "ĐỘNG_CƠ_VÀ_CẢM_BIẾN"))*0.25 | M56: =(K56-SUMIFS('03_BOC_TACH_VAN'!K:K, '03_BOC_TACH_VAN'!B:B, B56, '03_BOC_TACH_VAN'!D:D, "ĐỘNG_CƠ_VÀ_CẢM_BIẾN"))*0.10 | N56: =K56+L56+M56 | O56: =IF(G56>0, N56/G56, 0) | P56: 0.18 | Q56: =IF(G56>0, ((N56-SUMIFS('03_BOC_TACH_VAN'!K:K, '03_BOC_TACH_VAN'!B:B, B56, '03_BOC_TACH_VAN'!D:D, "ĐỘNG_CƠ_VÀ_CẢM_BIẾN"))*(1+P56)+SUMIFS('03_BOC_TACH_VAN'!K:K, '03_BOC_TACH_VAN'!B:B, B56, '03_BOC_TACH_VAN'!D:D, "ĐỘNG_CƠ_VÀ_CẢM_BIẾN"))/G56, 0) | R56: =G56*Q56
... A97: 96 | B97: SW-DIFF-096 | C97: CỬA GIÓ | D97: HỆ THỐNG TẠO ÁP Louver 3500x1000+IS | E97: 3500x1000 | F97: Cái | G97: 1 | H97: =SUMIF('01_BOC_TACH_ONG'!B:B, B97, '01_BOC_TACH_ONG'!K:K) | I97: =SUMIF('02_BOC_TACH_CUA'!B:B, B97, '02_BOC_TACH_CUA'!K:K) | J97: =SUMIF('03_BOC_TACH_VAN'!B:B, B97, '03_BOC_TACH_VAN'!K:K) | K97: =SUM(H97:J97) | L97: =(K97-SUMIFS('03_BOC_TACH_VAN'!K:K, '03_BOC_TACH_VAN'!B:B, B97, '03_BOC_TACH_VAN'!D:D, "ĐỘNG_CƠ_VÀ_CẢM_BIẾN"))*0.25 | M97: =(K97-SUMIFS('03_BOC_TACH_VAN'!K:K, '03_BOC_TACH_VAN'!B:B, B97, '03_BOC_TACH_VAN'!D:D, "ĐỘNG_CƠ_VÀ_CẢM_BIẾN"))*0.10 | N97: =K97+L97+M97 | O97: =IF(G97>0, N97/G97, 0) | P97: 0.18 | Q97: =IF(G97>0, ((N97-SUMIFS('03_BOC_TACH_VAN'!K:K, '03_BOC_TACH_VAN'!B:B, B97, '03_BOC_TACH_VAN'!D:D, "ĐỘNG_CƠ_VÀ_CẢM_BIẾN"))*(1+P97)+SUMIFS('03_BOC_TACH_VAN'!K:K, '03_BOC_TACH_VAN'!B:B, B97, '03_BOC_TACH_VAN'!D:D, "ĐỘNG_CƠ_VÀ_CẢM_BIẾN"))/G97, 0) | R97: =G97*Q97
A98: 97 | B98: SW-TRD-097 | C98: THƯƠNG MẠI | D98: HỆ THỐNG TẠO ÁP Vật tư phụ, phụ kiện | E98: - | F98: Lô | G98: 1 | H98: =SUMIF('01_BOC_TACH_ONG'!B:B, B98, '01_BOC_TACH_ONG'!K:K) | I98: =SUMIF('02_BOC_TACH_CUA'!B:B, B98, '02_BOC_TACH_CUA'!K:K) | J98: =SUMIF('03_BOC_TACH_VAN'!B:B, B98, '03_BOC_TACH_VAN'!K:K) | K98: =SUM(H98:J98) | L98: =(K98-SUMIFS('03_BOC_TACH_VAN'!K:K, '03_BOC_TACH_VAN'!B:B, B98, '03_BOC_TACH_VAN'!D:D, "ĐỘNG_CƠ_VÀ_CẢM_BIẾN"))*0.00 | M98: =(K98-SUMIFS('03_BOC_TACH_VAN'!K:K, '03_BOC_TACH_VAN'!B:B, B98, '03_BOC_TACH_VAN'!D:D, "ĐỘNG_CƠ_VÀ_CẢM_BIẾN"))*0.02 | N98: =K98+L98+M98 | O98: =IF(G98>0, N98/G98, 0) | P98: 0.1 | Q98: =IF(G98>0, ((N98-SUMIFS('03_BOC_TACH_VAN'!K:K, '03_BOC_TACH_VAN'!B:B, B98, '03_BOC_TACH_VAN'!D:D, "ĐỘNG_CƠ_VÀ_CẢM_BIẾN"))*(1+P98)+SUMIFS('03_BOC_TACH_VAN'!K:K, '03_BOC_TACH_VAN'!B:B, B98, '03_BOC_TACH_VAN'!D:D, "ĐỘNG_CƠ_VÀ_CẢM_BIẾN"))/G98, 0) | R98: =G98*Q98 | S98: Hàng thương mại
A99: 98 | B99: SW-DUCT-098 | C99: ỐNG GIÓ | D99: Hệ thống ống thông gió tạo áp, box miệng gió… Tole 0.75mm phủ lớp mạ kẽm Z180 | E99: 0.75mm | F99: m2 | G99: 1936.7013 | H99: =SUMIF('01_BOC_TACH_ONG'!B:B, B99, '01_BOC_TACH_ONG'!K:K) | I99: =SUMIF('02_BOC_TACH_CUA'!B:B, B99, '02_BOC_TACH_CUA'!K:K) | J99: =SUMIF('03_BOC_TACH_VAN'!B:B, B99, '03_BOC_TACH_VAN'!K:K) | K99: =SUM(H99:J99) | L99: =(K99-SUMIFS('03_BOC_TACH_VAN'!K:K, '03_BOC_TACH_VAN'!B:B, B99, '03_BOC_TACH_VAN'!D:D, "ĐỘNG_CƠ_VÀ_CẢM_BIẾN"))*0.25 | M99: =(K99-SUMIFS('03_BOC_TACH_VAN'!K:K, '03_BOC_TACH_VAN'!B:B, B99, '03_BOC_TACH_VAN'!D:D, "ĐỘNG_CƠ_VÀ_CẢM_BIẾN"))*0.10 | N99: =K99+L99+M99 | O99: =IF(G99>0, N99/G99, 0) | P99: 0.18 | Q99: =IF(G99>0, ((N99-SUMIFS('03_BOC_TACH_VAN'!K:K, '03_BOC_TACH_VAN'!B:B, B99, '03_BOC_TACH_VAN'!D:D, "ĐỘNG_CƠ_VÀ_CẢM_BIẾN"))*(1+P99)+SUMIFS('03_BOC_TACH_VAN'!K:K, '03_BOC_TACH_VAN'!B:B, B99, '03_BOC_TACH_VAN'!D:D, "ĐỘNG_CƠ_VÀ_CẢM_BIẾN"))/G99, 0) | R99: =G99*Q99
A100: 99 | B100: SW-DUCT-099 | C100: ỐNG GIÓ | D100: Hệ thống ống thông gió tạo áp, box miệng gió… Tole 0.95mm phủ lớp mạ kẽm Z180 | E100: 0.95mm | F100: m2 | G100: 1588.05 | H100: =SUMIF('01_BOC_TACH_ONG'!B:B, B100, '01_BOC_TACH_ONG'!K:K) | I100: =SUMIF('02_BOC_TACH_CUA'!B:B, B100, '02_BOC_TACH_CUA'!K:K) | J100: =SUMIF('03_BOC_TACH_VAN'!B:B, B100, '03_BOC_TACH_VAN'!K:K) | K100: =SUM(H100:J100) | L100: =(K100-SUMIFS('03_BOC_TACH_VAN'!K:K, '03_BOC_TACH_VAN'!B:B, B100, '03_BOC_TACH_VAN'!D:D, "ĐỘNG_CƠ_VÀ_CẢM_BIẾN"))*0.25 | M100: =(K100-SUMIFS('03_BOC_TACH_VAN'!K:K, '03_BOC_TACH_VAN'!B:B, B100, '03_BOC_TACH_VAN'!D:D, "ĐỘNG_CƠ_VÀ_CẢM_BIẾN"))*0.10 | N100: =K100+L100+M100 | O100: =IF(G100>0, N100/G100, 0) | P100: 0.18 | Q100: =IF(G100>0, ((N100-SUMIFS('03_BOC_TACH_VAN'!K:K, '03_BOC_TACH_VAN'!B:B, B100, '03_BOC_TACH_VAN'!D:D, "ĐỘNG_CƠ_VÀ_CẢM_BIẾN"))*(1+P100)+SUMIFS('03_BOC_TACH_VAN'!K:K, '03_BOC_TACH_VAN'!B:B, B100, '03_BOC_TACH_VAN'!D:D, "ĐỘNG_CƠ_VÀ_CẢM_BIẾN"))/G100, 0) | R100: =G100*Q100
A101: 100 | B101: SW-DUCT-100 | C101: ỐNG GIÓ | D101: Hệ thống ống thông gió tạo áp, box miệng gió… Tole 1.15mm phủ lớp mạ kẽm Z180 | E101: 1.15mm | F101: m2 | G101: 1681 | H101: =SUMIF('01_BOC_TACH_ONG'!B:B, B101, '01_BOC_TACH_ONG'!K:K) | I101: =SUMIF('02_BOC_TACH_CUA'!B:B, B101, '02_BOC_TACH_CUA'!K:K) | J101: =SUMIF('03_BOC_TACH_VAN'!B:B, B101, '03_BOC_TACH_VAN'!K:K) | K101: =SUM(H101:J101) | L101: =(K101-SUMIFS('03_BOC_TACH_VAN'!K:K, '03_BOC_TACH_VAN'!B:B, B101, '03_BOC_TACH_VAN'!D:D, "ĐỘNG_CƠ_VÀ_CẢM_BIẾN"))*0.25 | M101: =(K101-SUMIFS('03_BOC_TACH_VAN'!K:K, '03_BOC_TACH_VAN'!B:B, B101, '03_BOC_TACH_VAN'!D:D, "ĐỘNG_CƠ_VÀ_CẢM_BIẾN"))*0.10 | N101: =K101+L101+M101 | O101: =IF(G101>0, N101/G101, 0) | P101: 0.18 | Q101: =IF(G101>0, ((N101-SUMIFS('03_BOC_TACH_VAN'!K:K, '03_BOC_TACH_VAN'!B:B, B101, '03_BOC_TACH_VAN'!D:D, "ĐỘNG_CƠ_VÀ_CẢM_BIẾN"))*(1+P101)+SUMIFS('03_BOC_TACH_VAN'!K:K, '03_BOC_TACH_VAN'!B:B, B101, '03_BOC_TACH_VAN'!D:D, "ĐỘNG_CƠ_VÀ_CẢM_BIẾN"))/G101, 0) | R101: =G101*Q101
A102: 101 | B102: SW-DUCT-101 | C102: ỐNG GIÓ | D102: Hệ thống ống thông gió tạo áp, box miệng gió… Tole ZAM 1.15mm | E102: 1.15mm | F102: m2 | G102: 380 | H102: =SUMIF('01_BOC_TACH_ONG'!B:B, B102, '01_BOC_TACH_ONG'!K:K) | I102: =SUMIF('02_BOC_TACH_CUA'!B:B, B102, '02_BOC_TACH_CUA'!K:K) | J102: =SUMIF('03_BOC_TACH_VAN'!B:B, B102, '03_BOC_TACH_VAN'!K:K) | K102: =SUM(H102:J102) | L102: =(K102-SUMIFS('03_BOC_TACH_VAN'!K:K, '03_BOC_TACH_VAN'!B:B, B102, '03_BOC_TACH_VAN'!D:D, "ĐỘNG_CƠ_VÀ_CẢM_BIẾN"))*0.25 | M102: =(K102-SUMIFS('03_BOC_TACH_VAN'!K:K, '03_BOC_TACH_VAN'!B:B, B102, '03_BOC_TACH_VAN'!D:D, "ĐỘNG_CƠ_VÀ_CẢM_BIẾN"))*0.10 | N102: =K102+L102+M102 | O102: =IF(G102>0, N102/G102, 0) | P102: 0.18 | Q102: =IF(G102>0, ((N102-SUMIFS('03_BOC_TACH_VAN'!K:K, '03_BOC_TACH_VAN'!B:B, B102, '03_BOC_TACH_VAN'!D:D, "ĐỘNG_CƠ_VÀ_CẢM_BIẾN"))*(1+P102)+SUMIFS('03_BOC_TACH_VAN'!K:K, '03_BOC_TACH_VAN'!B:B, B102, '03_BOC_TACH_VAN'!D:D, "ĐỘNG_CƠ_VÀ_CẢM_BIẾN"))/G102, 0) | R102: =G102*Q102
A103: 102 | B103: SW-TRD-102 | C103: THƯƠNG MẠI | D103: Hệ thống ống thông gió tạo áp, box miệng gió… Lưới bảo vệ | E103: - | F103: cái | G103: 10 | H103: =SUMIF('01_BOC_TACH_ONG'!B:B, B103, '01_BOC_TACH_ONG'!K:K) | I103: =SUMIF('02_BOC_TACH_CUA'!B:B, B103, '02_BOC_TACH_CUA'!K:K) | J103: =SUMIF('03_BOC_TACH_VAN'!B:B, B103, '03_BOC_TACH_VAN'!K:K) | K103: =SUM(H103:J103) | L103: =(K103-SUMIFS('03_BOC_TACH_VAN'!K:K, '03_BOC_TACH_VAN'!B:B, B103, '03_BOC_TACH_VAN'!D:D, "ĐỘNG_CƠ_VÀ_CẢM_BIẾN"))*0.00 | M103: =(K103-SUMIFS('03_BOC_TACH_VAN'!K:K, '03_BOC_TACH_VAN'!B:B, B103, '03_BOC_TACH_VAN'!D:D, "ĐỘNG_CƠ_VÀ_CẢM_BIẾN"))*0.02 | N103: =K103+L103+M103 | O103: =IF(G103>0, N103/G103, 0) | P103: 0.1 | Q103: =IF(G103>0, ((N103-SUMIFS('03_BOC_TACH_VAN'!K:K, '03_BOC_TACH_VAN'!B:B, B103, '03_BOC_TACH_VAN'!D:D, "ĐỘNG_CƠ_VÀ_CẢM_BIẾN"))*(1+P103)+SUMIFS('03_BOC_TACH_VAN'!K:K, '03_BOC_TACH_VAN'!B:B, B103, '03_BOC_TACH_VAN'!D:D, "ĐỘNG_CƠ_VÀ_CẢM_BIẾN"))/G103, 0) | R103: =G103*Q103 | S103: Hàng thương mại
A104: 103 | B104: SW-TRD-103 | C104: THƯƠNG MẠI | D104: Hệ thống ống thông gió tạo áp, box miệng gió… Lớp chống cháy EI60 | E104: - | F104: m2 | G104: 1805.9 | H104: =SUMIF('01_BOC_TACH_ONG'!B:B, B104, '01_BOC_TACH_ONG'!K:K) | I104: =SUMIF('02_BOC_TACH_CUA'!B:B, B104, '02_BOC_TACH_CUA'!K:K) | J104: =SUMIF('03_BOC_TACH_VAN'!B:B, B104, '03_BOC_TACH_VAN'!K:K) | K104: =SUM(H104:J104) | L104: =(K104-SUMIFS('03_BOC_TACH_VAN'!K:K, '03_BOC_TACH_VAN'!B:B, B104, '03_BOC_TACH_VAN'!D:D, "ĐỘNG_CƠ_VÀ_CẢM_BIẾN"))*0.00 | M104: =(K104-SUMIFS('03_BOC_TACH_VAN'!K:K, '03_BOC_TACH_VAN'!B:B, B104, '03_BOC_TACH_VAN'!D:D, "ĐỘNG_CƠ_VÀ_CẢM_BIẾN"))*0.02 | N104: =K104+L104+M104 | O104: =IF(G104>0, N104/G104, 0) | P104: 0.1 | Q104: =IF(G104>0, ((N104-SUMIFS('03_BOC_TACH_VAN'!K:K, '03_BOC_TACH_VAN'!B:B, B104, '03_BOC_TACH_VAN'!D:D, "ĐỘNG_CƠ_VÀ_CẢM_BIẾN"))*(1+P104)+SUMIFS('03_BOC_TACH_VAN'!K:K, '03_BOC_TACH_VAN'!B:B, B104, '03_BOC_TACH_VAN'!D:D, "ĐỘNG_CƠ_VÀ_CẢM_BIẾN"))/G104, 0) | R104: =G104*Q104 | S104: Hàng thương mại
A105: 104 | B105: SW-TRD-104 | C105: THƯƠNG MẠI | D105: Hệ thống ống thông gió tạo áp, box miệng gió… Lớp chống cháy EI120 | E105: - | F105: m2 | G105: 1347.3 | H105: =SUMIF('01_BOC_TACH_ONG'!B:B, B105, '01_BOC_TACH_ONG'!K:K) | I105: =SUMIF('02_BOC_TACH_CUA'!B:B, B105, '02_BOC_TACH_CUA'!K:K) | J105: =SUMIF('03_BOC_TACH_VAN'!B:B, B105, '03_BOC_TACH_VAN'!K:K) | K105: =SUM(H105:J105) | L105: =(K105-SUMIFS('03_BOC_TACH_VAN'!K:K, '03_BOC_TACH_VAN'!B:B, B105, '03_BOC_TACH_VAN'!D:D, "ĐỘNG_CƠ_VÀ_CẢM_BIẾN"))*0.00 | M105: =(K105-SUMIFS('03_BOC_TACH_VAN'!K:K, '03_BOC_TACH_VAN'!B:B, B105, '03_BOC_TACH_VAN'!D:D, "ĐỘNG_CƠ_VÀ_CẢM_BIẾN"))*0.02 | N105: =K105+L105+M105 | O105: =IF(G105>0, N105/G105, 0) | P105: 0.1 | Q105: =IF(G105>0, ((N105-SUMIFS('03_BOC_TACH_VAN'!K:K, '03_BOC_TACH_VAN'!B:B, B105, '03_BOC_TACH_VAN'!D:D, "ĐỘNG_CƠ_VÀ_CẢM_BIẾN"))*(1+P105)+SUMIFS('03_BOC_TACH_VAN'!K:K, '03_BOC_TACH_VAN'!B:B, B105, '03_BOC_TACH_VAN'!D:D, "ĐỘNG_CƠ_VÀ_CẢM_BIẾN"))/G105, 0) | R105: =G105*Q105 | S105: Hàng thương mại
A106: 105 | B106: SW-TRD-105 | C106: THƯƠNG MẠI | D106: Hệ thống ống thông gió tạo áp, box miệng gió… Vật tư phụ, phụ kiện | E106: - | F106: Lô | G106: 1 | H106: =SUMIF('01_BOC_TACH_ONG'!B:B, B106, '01_BOC_TACH_ONG'!K:K) | I106: =SUMIF('02_BOC_TACH_CUA'!B:B, B106, '02_BOC_TACH_CUA'!K:K) | J106: =SUMIF('03_BOC_TACH_VAN'!B:B, B106, '03_BOC_TACH_VAN'!K:K) | K106: =SUM(H106:J106) | L106: =(K106-SUMIFS('03_BOC_TACH_VAN'!K:K, '03_BOC_TACH_VAN'!B:B, B106, '03_BOC_TACH_VAN'!D:D, "ĐỘNG_CƠ_VÀ_CẢM_BIẾN"))*0.00 | M106: =(K106-SUMIFS('03_BOC_TACH_VAN'!K:K, '03_BOC_TACH_VAN'!B:B, B106, '03_BOC_TACH_VAN'!D:D, "ĐỘNG_CƠ_VÀ_CẢM_BIẾN"))*0.02 | N106: =K106+L106+M106 | O106: =IF(G106>0, N106/G106, 0) | P106: 0.1 | Q106: =IF(G106>0, ((N106-SUMIFS('03_BOC_TACH_VAN'!K:K, '03_BOC_TACH_VAN'!B:B, B106, '03_BOC_TACH_VAN'!D:D, "ĐỘNG_CƠ_VÀ_CẢM_BIẾN"))*(1+P106)+SUMIFS('03_BOC_TACH_VAN'!K:K, '03_BOC_TACH_VAN'!B:B, B106, '03_BOC_TACH_VAN'!D:D, "ĐỘNG_CƠ_VÀ_CẢM_BIẾN"))/G106, 0) | R106: =G106*Q106 | S106: Hàng thương mại
A107: 106 | B107: SW-ACST-106 | C107: VÁCH NGĂN / HỘP TIÊU ÂM | D107: HỆ THỐNG CẤP GIÓ TƯƠI, GIÓ BÙ Tiêu âm quạt | E107: - | F107: Bộ | G107: 8 | H107: =SUMIF('01_BOC_TACH_ONG'!B:B, B107, '01_BOC_TACH_ONG'!K:K) | I107: =SUMIF('02_BOC_TACH_CUA'!B:B, B107, '02_BOC_TACH_CUA'!K:K) | J107: =SUMIF('03_BOC_TACH_VAN'!B:B, B107, '03_BOC_TACH_VAN'!K:K) | K107: =SUM(H107:J107) | L107: =(K107-SUMIFS('03_BOC_TACH_VAN'!K:K, '03_BOC_TACH_VAN'!B:B, B107, '03_BOC_TACH_VAN'!D:D, "ĐỘNG_CƠ_VÀ_CẢM_BIẾN"))*0.25 | M107: =(K107-SUMIFS('03_BOC_TACH_VAN'!K:K, '03_BOC_TACH_VAN'!B:B, B107, '03_BOC_TACH_VAN'!D:D, "ĐỘNG_CƠ_VÀ_CẢM_BIẾN"))*0.10 | N107: =K107+L107+M107 | O107: =IF(G107>0, N107/G107, 0) | P107: 0.18 | Q107: =IF(G107>0, ((N107-SUMIFS('03_BOC_TACH_VAN'!K:K, '03_BOC_TACH_VAN'!B:B, B107, '03_BOC_TACH_VAN'!D:D, "ĐỘNG_CƠ_VÀ_CẢM_BIẾN"))*(1+P107)+SUMIFS('03_BOC_TACH_VAN'!K:K, '03_BOC_TACH_VAN'!B:B, B107, '03_BOC_TACH_VAN'!D:D, "ĐỘNG_CƠ_VÀ_CẢM_BIẾN"))/G107, 0) | R107: =G107*Q107
A108: 107 | B108: SW-DAMPER-107 | C108: VAN GIÓ | D108: HỆ THỐNG CẤP GIÓ TƯƠI, GIÓ BÙ Van 1 chiều NRD 1350x1250 (EI60) | E108: 1350x1250 | F108: Cái | G108: 4 | H108: =SUMIF('01_BOC_TACH_ONG'!B:B, B108, '01_BOC_TACH_ONG'!K:K) | I108: =SUMIF('02_BOC_TACH_CUA'!B:B, B108, '02_BOC_TACH_CUA'!K:K) | J108: =SUMIF('03_BOC_TACH_VAN'!B:B, B108, '03_BOC_TACH_VAN'!K:K) | K108: =SUM(H108:J108) | L108: =(K108-SUMIFS('03_BOC_TACH_VAN'!K:K, '03_BOC_TACH_VAN'!B:B, B108, '03_BOC_TACH_VAN'!D:D, "ĐỘNG_CƠ_VÀ_CẢM_BIẾN"))*0.25 | M108: =(K108-SUMIFS('03_BOC_TACH_VAN'!K:K, '03_BOC_TACH_VAN'!B:B, B108, '03_BOC_TACH_VAN'!D:D, "ĐỘNG_CƠ_VÀ_CẢM_BIẾN"))*0.10 | N108: =K108+L108+M108 | O108: =IF(G108>0, N108/G108, 0) | P108: 0.18 | Q108: =IF(G108>0, ((N108-SUMIFS('03_BOC_TACH_VAN'!K:K, '03_BOC_TACH_VAN'!B:B, B108, '03_BOC_TACH_VAN'!D:D, "ĐỘNG_CƠ_VÀ_CẢM_BIẾN"))*(1+P108)+SUMIFS('03_BOC_TACH_VAN'!K:K, '03_BOC_TACH_VAN'!B:B, B108, '03_BOC_TACH_VAN'!D:D, "ĐỘNG_CƠ_VÀ_CẢM_BIẾN"))/G108, 0) | R108: =G108*Q108
A109: 108 | B109: SW-DAMPER-108 | C109: VAN GIÓ | D109: HỆ THỐNG CẤP GIÓ TƯƠI, GIÓ BÙ Van 1 chiều NRD1250x600 (EI60) | E109: 1250x600 | F109: Cái | G109: 4 | H109: =SUMIF('01_BOC_TACH_ONG'!B:B, B109, '01_BOC_TACH_ONG'!K:K) | I109: =SUMIF('02_BOC_TACH_CUA'!B:B, B109, '02_BOC_TACH_CUA'!K:K) | J109: =SUMIF('03_BOC_TACH_VAN'!B:B, B109, '03_BOC_TACH_VAN'!K:K) | K109: =SUM(H109:J109) | L109: =(K109-SUMIFS('03_BOC_TACH_VAN'!K:K, '03_BOC_TACH_VAN'!B:B, B109, '03_BOC_TACH_VAN'!D:D, "ĐỘNG_CƠ_VÀ_CẢM_BIẾN"))*0.25 | M109: =(K109-SUMIFS('03_BOC_TACH_VAN'!K:K, '03_BOC_TACH_VAN'!B:B, B109, '03_BOC_TACH_VAN'!D:D, "ĐỘNG_CƠ_VÀ_CẢM_BIẾN"))*0.10 | N109: =K109+L109+M109 | O109: =IF(G109>0, N109/G109, 0) | P109: 0.18 | Q109: =IF(G109>0, ((N109-SUMIFS('03_BOC_TACH_VAN'!K:K, '03_BOC_TACH_VAN'!B:B, B109, '03_BOC_TACH_VAN'!D:D, "ĐỘNG_CƠ_VÀ_CẢM_BIẾN"))*(1+P109)+SUMIFS('03_BOC_TACH_VAN'!K:K, '03_BOC_TACH_VAN'!B:B, B109, '03_BOC_TACH_VAN'!D:D, "ĐỘNG_CƠ_VÀ_CẢM_BIẾN"))/G109, 0) | R109: =G109*Q109
A110: 109 | B110: SW-DAMPER-109 | C110: VAN GIÓ | D110: HỆ THỐNG CẤP GIÓ TƯƠI, GIÓ BÙ Van 1 chiều NRD 800x250 | E110: 800x250 | F110: Cái | G110: 1 | H110: =SUMIF('01_BOC_TACH_ONG'!B:B, B110, '01_BOC_TACH_ONG'!K:K) | I110: =SUMIF('02_BOC_TACH_CUA'!B:B, B110, '02_BOC_TACH_CUA'!K:K) | J110: =SUMIF('03_BOC_TACH_VAN'!B:B, B110, '03_BOC_TACH_VAN'!K:K) | K110: =SUM(H110:J110) | L110: =(K110-SUMIFS('03_BOC_TACH_VAN'!K:K, '03_BOC_TACH_VAN'!B:B, B110, '03_BOC_TACH_VAN'!D:D, "ĐỘNG_CƠ_VÀ_CẢM_BIẾN"))*0.25 | M110: =(K110-SUMIFS('03_BOC_TACH_VAN'!K:K, '03_BOC_TACH_VAN'!B:B, B110, '03_BOC_TACH_VAN'!D:D, "ĐỘNG_CƠ_VÀ_CẢM_BIẾN"))*0.10 | N110: =K110+L110+M110 | O110: =IF(G110>0, N110/G110, 0) | P110: 0.18 | Q110: =IF(G110>0, ((N110-SUMIFS('03_BOC_TACH_VAN'!K:K, '03_BOC_TACH_VAN'!B:B, B110, '03_BOC_TACH_VAN'!D:D, "ĐỘNG_CƠ_VÀ_CẢM_BIẾN"))*(1+P110)+SUMIFS('03_BOC_TACH_VAN'!K:K, '03_BOC_TACH_VAN'!B:B, B110, '03_BOC_TACH_VAN'!D:D, "ĐỘNG_CƠ_VÀ_CẢM_BIẾN"))/G110, 0) | R110: =G110*Q110
A111: 110 | B111: SW-DAMPER-110 | C111: VAN GIÓ | D111: HỆ THỐNG CẤP GIÓ TƯƠI, GIÓ BÙ Van 1 chiều NRD 800x450 | E111: 800x450 | F111: Cái | G111: 6 | H111: =SUMIF('01_BOC_TACH_ONG'!B:B, B111, '01_BOC_TACH_ONG'!K:K) | I111: =SUMIF('02_BOC_TACH_CUA'!B:B, B111, '02_BOC_TACH_CUA'!K:K) | J111: =SUMIF('03_BOC_TACH_VAN'!B:B, B111, '03_BOC_TACH_VAN'!K:K) | K111: =SUM(H111:J111) | L111: =(K111-SUMIFS('03_BOC_TACH_VAN'!K:K, '03_BOC_TACH_VAN'!B:B, B111, '03_BOC_TACH_VAN'!D:D, "ĐỘNG_CƠ_VÀ_CẢM_BIẾN"))*0.25 | M111: =(K111-SUMIFS('03_BOC_TACH_VAN'!K:K, '03_BOC_TACH_VAN'!B:B, B111, '03_BOC_TACH_VAN'!D:D, "ĐỘNG_CƠ_VÀ_CẢM_BIẾN"))*0.10 | N111: =K111+L111+M111 | O111: =IF(G111>0, N111/G111, 0) | P111: 0.18 | Q111: =IF(G111>0, ((N111-SUMIFS('03_BOC_TACH_VAN'!K:K, '03_BOC_TACH_VAN'!B:B, B111, '03_BOC_TACH_VAN'!D:D, "ĐỘNG_CƠ_VÀ_CẢM_BIẾN"))*(1+P111)+SUMIFS('03_BOC_TACH_VAN'!K:K, '03_BOC_TACH_VAN'!B:B, B111, '03_BOC_TACH_VAN'!D:D, "ĐỘNG_CƠ_VÀ_CẢM_BIẾN"))/G111, 0) | R111: =G111*Q111
A112: 111 | B112: SW-DAMPER-111 | C112: VAN GIÓ | D112: HỆ THỐNG CẤP GIÓ TƯƠI, GIÓ BÙ Van ngăn cháy MFD 1350x1250 (EI60) | E112: 1350x1250 | F112: Cái | G112: 4 | H112: =SUMIF('01_BOC_TACH_ONG'!B:B, B112, '01_BOC_TACH_ONG'!K:K) | I112: =SUMIF('02_BOC_TACH_CUA'!B:B, B112, '02_BOC_TACH_CUA'!K:K) | J112: =SUMIF('03_BOC_TACH_VAN'!B:B, B112, '03_BOC_TACH_VAN'!K:K) | K112: =SUM(H112:J112) | L112: =(K112-SUMIFS('03_BOC_TACH_VAN'!K:K, '03_BOC_TACH_VAN'!B:B, B112, '03_BOC_TACH_VAN'!D:D, "ĐỘNG_CƠ_VÀ_CẢM_BIẾN"))*0.25 | M112: =(K112-SUMIFS('03_BOC_TACH_VAN'!K:K, '03_BOC_TACH_VAN'!B:B, B112, '03_BOC_TACH_VAN'!D:D, "ĐỘNG_CƠ_VÀ_CẢM_BIẾN"))*0.10 | N112: =K112+L112+M112 | O112: =IF(G112>0, N112/G112, 0) | P112: 0.18 | Q112: =IF(G112>0, ((N112-SUMIFS('03_BOC_TACH_VAN'!K:K, '03_BOC_TACH_VAN'!B:B, B112, '03_BOC_TACH_VAN'!D:D, "ĐỘNG_CƠ_VÀ_CẢM_BIẾN"))*(1+P112)+SUMIFS('03_BOC_TACH_VAN'!K:K, '03_BOC_TACH_VAN'!B:B, B112, '03_BOC_TACH_VAN'!D:D, "ĐỘNG_CƠ_VÀ_CẢM_BIẾN"))/G112, 0) | R112: =G112*Q112
A113: 112 | B113: SW-DAMPER-112 | C113: VAN GIÓ | D113: HỆ THỐNG CẤP GIÓ TƯƠI, GIÓ BÙ Van ngăn cháy MFD 1250x600 (EI60) | E113: 1250x600 | F113: Cái | G113: 4 | H113: =SUMIF('01_BOC_TACH_ONG'!B:B, B113, '01_BOC_TACH_ONG'!K:K) | I113: =SUMIF('02_BOC_TACH_CUA'!B:B, B113, '02_BOC_TACH_CUA'!K:K) | J113: =SUMIF('03_BOC_TACH_VAN'!B:B, B113, '03_BOC_TACH_VAN'!K:K) | K113: =SUM(H113:J113) | L113: =(K113-SUMIFS('03_BOC_TACH_VAN'!K:K, '03_BOC_TACH_VAN'!B:B, B113, '03_BOC_TACH_VAN'!D:D, "ĐỘNG_CƠ_VÀ_CẢM_BIẾN"))*0.25 | M113: =(K113-SUMIFS('03_BOC_TACH_VAN'!K:K, '03_BOC_TACH_VAN'!B:B, B113, '03_BOC_TACH_VAN'!D:D, "ĐỘNG_CƠ_VÀ_CẢM_BIẾN"))*0.10 | N113: =K113+L113+M113 | O113: =IF(G113>0, N113/G113, 0) | P113: 0.18 | Q113: =IF(G113>0, ((N113-SUMIFS('03_BOC_TACH_VAN'!K:K, '03_BOC_TACH_VAN'!B:B, B113, '03_BOC_TACH_VAN'!D:D, "ĐỘNG_CƠ_VÀ_CẢM_BIẾN"))*(1+P113)+SUMIFS('03_BOC_TACH_VAN'!K:K, '03_BOC_TACH_VAN'!B:B, B113, '03_BOC_TACH_VAN'!D:D, "ĐỘNG_CƠ_VÀ_CẢM_BIẾN"))/G113, 0) | R113: =G113*Q113
A114: 113 | B114: SW-DAMPER-113 | C114: VAN GIÓ | D114: HỆ THỐNG CẤP GIÓ TƯƠI, GIÓ BÙ Van ngăn cháy MFD 1050x350 (EI120) | E114: 1050x350 | F114: Cái | G114: 3 | H114: =SUMIF('01_BOC_TACH_ONG'!B:B, B114, '01_BOC_TACH_ONG'!K:K) | I114: =SUMIF('02_BOC_TACH_CUA'!B:B, B114, '02_BOC_TACH_CUA'!K:K) | J114: =SUMIF('03_BOC_TACH_VAN'!B:B, B114, '03_BOC_TACH_VAN'!K:K) | K114: =SUM(H114:J114) | L114: =(K114-SUMIFS('03_BOC_TACH_VAN'!K:K, '03_BOC_TACH_VAN'!B:B, B114, '03_BOC_TACH_VAN'!D:D, "ĐỘNG_CƠ_VÀ_CẢM_BIẾN"))*0.25 | M114: =(K114-SUMIFS('03_BOC_TACH_VAN'!K:K, '03_BOC_TACH_VAN'!B:B, B114, '03_BOC_TACH_VAN'!D:D, "ĐỘNG_CƠ_VÀ_CẢM_BIẾN"))*0.10 | N114: =K114+L114+M114 | O114: =IF(G114>0, N114/G114, 0) | P114: 0.18 | Q114: =IF(G114>0, ((N114-SUMIFS('03_BOC_TACH_VAN'!K:K, '03_BOC_TACH_VAN'!B:B, B114, '03_BOC_TACH_VAN'!D:D, "ĐỘNG_CƠ_VÀ_CẢM_BIẾN"))*(1+P114)+SUMIFS('03_BOC_TACH_VAN'!K:K, '03_BOC_TACH_VAN'!B:B, B114, '03_BOC_TACH_VAN'!D:D, "ĐỘNG_CƠ_VÀ_CẢM_BIẾN"))/G114, 0) | R114: =G114*Q114
A115: 114 | B115: SW-DAMPER-114 | C115: VAN GIÓ | D115: HỆ THỐNG CẤP GIÓ TƯƠI, GIÓ BÙ Van ngăn cháy MFD 800x350 (EI30) | E115: 800x350 | F115: Cái | G115: 7 | H115: =SUMIF('01_BOC_TACH_ONG'!B:B, B115, '01_BOC_TACH_ONG'!K:K) | I115: =SUMIF('02_BOC_TACH_CUA'!B:B, B115, '02_BOC_TACH_CUA'!K:K) | J115: =SUMIF('03_BOC_TACH_VAN'!B:B, B115, '03_BOC_TACH_VAN'!K:K) | K115: =SUM(H115:J115) | L115: =(K115-SUMIFS('03_BOC_TACH_VAN'!K:K, '03_BOC_TACH_VAN'!B:B, B115, '03_BOC_TACH_VAN'!D:D, "ĐỘNG_CƠ_VÀ_CẢM_BIẾN"))*0.25 | M115: =(K115-SUMIFS('03_BOC_TACH_VAN'!K:K, '03_BOC_TACH_VAN'!B:B, B115, '03_BOC_TACH_VAN'!D:D, "ĐỘNG_CƠ_VÀ_CẢM_BIẾN"))*0.10 | N115: =K115+L115+M115 | O115: =IF(G115>0, N115/G115, 0) | P115: 0.18 | Q115: =IF(G115>0, ((N115-SUMIFS('03_BOC_TACH_VAN'!K:K, '03_BOC_TACH_VAN'!B:B, B115, '03_BOC_TACH_VAN'!D:D, "ĐỘNG_CƠ_VÀ_CẢM_BIẾN"))*(1+P115)+SUMIFS('03_BOC_TACH_VAN'!K:K, '03_BOC_TACH_VAN'!B:B, B115, '03_BOC_TACH_VAN'!D:D, "ĐỘNG_CƠ_VÀ_CẢM_BIẾN"))/G115, 0) | R115: =G115*Q115
A116: 115 | B116: SW-DAMPER-115 | C116: VAN GIÓ | D116: HỆ THỐNG CẤP GIÓ TƯƠI, GIÓ BÙ Van ngăn cháy MFD 900x350 (EI120) | E116: 900x350 | F116: Cái | G116: 2 | H116: =SUMIF('01_BOC_TACH_ONG'!B:B, B116, '01_BOC_TACH_ONG'!K:K) | I116: =SUMIF('02_BOC_TACH_CUA'!B:B, B116, '02_BOC_TACH_CUA'!K:K) | J116: =SUMIF('03_BOC_TACH_VAN'!B:B, B116, '03_BOC_TACH_VAN'!K:K) | K116: =SUM(H116:J116) | L116: =(K116-SUMIFS('03_BOC_TACH_VAN'!K:K, '03_BOC_TACH_VAN'!B:B, B116, '03_BOC_TACH_VAN'!D:D, "ĐỘNG_CƠ_VÀ_CẢM_BIẾN"))*0.25 | M116: =(K116-SUMIFS('03_BOC_TACH_VAN'!K:K, '03_BOC_TACH_VAN'!B:B, B116, '03_BOC_TACH_VAN'!D:D, "ĐỘNG_CƠ_VÀ_CẢM_BIẾN"))*0.10 | N116: =K116+L116+M116 | O116: =IF(G116>0, N116/G116, 0) | P116: 0.18 | Q116: =IF(G116>0, ((N116-SUMIFS('03_BOC_TACH_VAN'!K:K, '03_BOC_TACH_VAN'!B:B, B116, '03_BOC_TACH_VAN'!D:D, "ĐỘNG_CƠ_VÀ_CẢM_BIẾN"))*(1+P116)+SUMIFS('03_BOC_TACH_VAN'!K:K, '03_BOC_TACH_VAN'!B:B, B116, '03_BOC_TACH_VAN'!D:D, "ĐỘNG_CƠ_VÀ_CẢM_BIẾN"))/G116, 0) | R116: =G116*Q116
A117: 116 | B117: SW-DAMPER-116 | C117: VAN GIÓ | D117: HỆ THỐNG CẤP GIÓ TƯƠI, GIÓ BÙ Van ngăn cháy MFD 900x350 (EI30) | E117: 900x350 | F117: Cái | G117: 2 | H117: =SUMIF('01_BOC_TACH_ONG'!B:B, B117, '01_BOC_TACH_ONG'!K:K) | I117: =SUMIF('02_BOC_TACH_CUA'!B:B, B117, '02_BOC_TACH_CUA'!K:K) | J117: =SUMIF('03_BOC_TACH_VAN'!B:B, B117, '03_BOC_TACH_VAN'!K:K) | K117: =SUM(H117:J117) | L117: =(K117-SUMIFS('03_BOC_TACH_VAN'!K:K, '03_BOC_TACH_VAN'!B:B, B117, '03_BOC_TACH_VAN'!D:D, "ĐỘNG_CƠ_VÀ_CẢM_BIẾN"))*0.25 | M117: =(K117-SUMIFS('03_BOC_TACH_VAN'!K:K, '03_BOC_TACH_VAN'!B:B, B117, '03_BOC_TACH_VAN'!D:D, "ĐỘNG_CƠ_VÀ_CẢM_BIẾN"))*0.10 | N117: =K117+L117+M117 | O117: =IF(G117>0, N117/G117, 0) | P117: 0.18 | Q117: =IF(G117>0, ((N117-SUMIFS('03_BOC_TACH_VAN'!K:K, '03_BOC_TACH_VAN'!B:B, B117, '03_BOC_TACH_VAN'!D:D, "ĐỘNG_CƠ_VÀ_CẢM_BIẾN"))*(1+P117)+SUMIFS('03_BOC_TACH_VAN'!K:K, '03_BOC_TACH_VAN'!B:B, B117, '03_BOC_TACH_VAN'!D:D, "ĐỘNG_CƠ_VÀ_CẢM_BIẾN"))/G117, 0) | R117: =G117*Q117
A118: 117 | B118: SW-DAMPER-117 | C118: VAN GIÓ | D118: HỆ THỐNG CẤP GIÓ TƯƠI, GIÓ BÙ Van ngăn cháy MFD 110x350 (EI30) | E118: 110x350 | F118: Cái | G118: 1 | H118: =SUMIF('01_BOC_TACH_ONG'!B:B, B118, '01_BOC_TACH_ONG'!K:K) | I118: =SUMIF('02_BOC_TACH_CUA'!B:B, B118, '02_BOC_TACH_CUA'!K:K) | J118: =SUMIF('03_BOC_TACH_VAN'!B:B, B118, '03_BOC_TACH_VAN'!K:K) | K118: =SUM(H118:J118) | L118: =(K118-SUMIFS('03_BOC_TACH_VAN'!K:K, '03_BOC_TACH_VAN'!B:B, B118, '03_BOC_TACH_VAN'!D:D, "ĐỘNG_CƠ_VÀ_CẢM_BIẾN"))*0.25 | M118: =(K118-SUMIFS('03_BOC_TACH_VAN'!K:K, '03_BOC_TACH_VAN'!B:B, B118, '03_BOC_TACH_VAN'!D:D, "ĐỘNG_CƠ_VÀ_CẢM_BIẾN"))*0.10 | N118: =K118+L118+M118 | O118: =IF(G118>0, N118/G118, 0) | P118: 0.18 | Q118: =IF(G118>0, ((N118-SUMIFS('03_BOC_TACH_VAN'!K:K, '03_BOC_TACH_VAN'!B:B, B118, '03_BOC_TACH_VAN'!D:D, "ĐỘNG_CƠ_VÀ_CẢM_BIẾN"))*(1+P118)+SUMIFS('03_BOC_TACH_VAN'!K:K, '03_BOC_TACH_VAN'!B:B, B118, '03_BOC_TACH_VAN'!D:D, "ĐỘNG_CƠ_VÀ_CẢM_BIẾN"))/G118, 0) | R118: =G118*Q118
... A163: 162 | B163: SW-DUCT-162 | C163: ỐNG GIÓ | D163: Hệ thống ống thông cấp gió tươi, gió bù, box miệng gió Tole ZAM 0.75mm | E163: 0.75mm | F163: m2 | G163: 136 | H163: =SUMIF('01_BOC_TACH_ONG'!B:B, B163, '01_BOC_TACH_ONG'!K:K) | I163: =SUMIF('02_BOC_TACH_CUA'!B:B, B163, '02_BOC_TACH_CUA'!K:K) | J163: =SUMIF('03_BOC_TACH_VAN'!B:B, B163, '03_BOC_TACH_VAN'!K:K) | K163: =SUM(H163:J163) | L163: =(K163-SUMIFS('03_BOC_TACH_VAN'!K:K, '03_BOC_TACH_VAN'!B:B, B163, '03_BOC_TACH_VAN'!D:D, "ĐỘNG_CƠ_VÀ_CẢM_BIẾN"))*0.25 | M163: =(K163-SUMIFS('03_BOC_TACH_VAN'!K:K, '03_BOC_TACH_VAN'!B:B, B163, '03_BOC_TACH_VAN'!D:D, "ĐỘNG_CƠ_VÀ_CẢM_BIẾN"))*0.10 | N163: =K163+L163+M163 | O163: =IF(G163>0, N163/G163, 0) | P163: 0.18 | Q163: =IF(G163>0, ((N163-SUMIFS('03_BOC_TACH_VAN'!K:K, '03_BOC_TACH_VAN'!B:B, B163, '03_BOC_TACH_VAN'!D:D, "ĐỘNG_CƠ_VÀ_CẢM_BIẾN"))*(1+P163)+SUMIFS('03_BOC_TACH_VAN'!K:K, '03_BOC_TACH_VAN'!B:B, B163, '03_BOC_TACH_VAN'!D:D, "ĐỘNG_CƠ_VÀ_CẢM_BIẾN"))/G163, 0) | R163: =G163*Q163
A164: 163 | B164: SW-TRD-163 | C164: THƯƠNG MẠI | D164: Hệ thống ống thông cấp gió tươi, gió bù, box miệng gió Lớp chống cháy EI30 | E164: - | F164: m2 | G164: 364.55 | H164: =SUMIF('01_BOC_TACH_ONG'!B:B, B164, '01_BOC_TACH_ONG'!K:K) | I164: =SUMIF('02_BOC_TACH_CUA'!B:B, B164, '02_BOC_TACH_CUA'!K:K) | J164: =SUMIF('03_BOC_TACH_VAN'!B:B, B164, '03_BOC_TACH_VAN'!K:K) | K164: =SUM(H164:J164) | L164: =(K164-SUMIFS('03_BOC_TACH_VAN'!K:K, '03_BOC_TACH_VAN'!B:B, B164, '03_BOC_TACH_VAN'!D:D, "ĐỘNG_CƠ_VÀ_CẢM_BIẾN"))*0.00 | M164: =(K164-SUMIFS('03_BOC_TACH_VAN'!K:K, '03_BOC_TACH_VAN'!B:B, B164, '03_BOC_TACH_VAN'!D:D, "ĐỘNG_CƠ_VÀ_CẢM_BIẾN"))*0.02 | N164: =K164+L164+M164 | O164: =IF(G164>0, N164/G164, 0) | P164: 0.1 | Q164: =IF(G164>0, ((N164-SUMIFS('03_BOC_TACH_VAN'!K:K, '03_BOC_TACH_VAN'!B:B, B164, '03_BOC_TACH_VAN'!D:D, "ĐỘNG_CƠ_VÀ_CẢM_BIẾN"))*(1+P164)+SUMIFS('03_BOC_TACH_VAN'!K:K, '03_BOC_TACH_VAN'!B:B, B164, '03_BOC_TACH_VAN'!D:D, "ĐỘNG_CƠ_VÀ_CẢM_BIẾN"))/G164, 0) | R164: =G164*Q164 | S164: Hàng thương mại
A165: 164 | B165: SW-TRD-164 | C165: THƯƠNG MẠI | D165: Hệ thống ống thông cấp gió tươi, gió bù, box miệng gió Lớp chống cháy EI60 | E165: - | F165: m2 | G165: 3334 | H165: =SUMIF('01_BOC_TACH_ONG'!B:B, B165, '01_BOC_TACH_ONG'!K:K) | I165: =SUMIF('02_BOC_TACH_CUA'!B:B, B165, '02_BOC_TACH_CUA'!K:K) | J165: =SUMIF('03_BOC_TACH_VAN'!B:B, B165, '03_BOC_TACH_VAN'!K:K) | K165: =SUM(H165:J165) | L165: =(K165-SUMIFS('03_BOC_TACH_VAN'!K:K, '03_BOC_TACH_VAN'!B:B, B165, '03_BOC_TACH_VAN'!D:D, "ĐỘNG_CƠ_VÀ_CẢM_BIẾN"))*0.00 | M165: =(K165-SUMIFS('03_BOC_TACH_VAN'!K:K, '03_BOC_TACH_VAN'!B:B, B165, '03_BOC_TACH_VAN'!D:D, "ĐỘNG_CƠ_VÀ_CẢM_BIẾN"))*0.02 | N165: =K165+L165+M165 | O165: =IF(G165>0, N165/G165, 0) | P165: 0.1 | Q165: =IF(G165>0, ((N165-SUMIFS('03_BOC_TACH_VAN'!K:K, '03_BOC_TACH_VAN'!B:B, B165, '03_BOC_TACH_VAN'!D:D, "ĐỘNG_CƠ_VÀ_CẢM_BIẾN"))*(1+P165)+SUMIFS('03_BOC_TACH_VAN'!K:K, '03_BOC_TACH_VAN'!B:B, B165, '03_BOC_TACH_VAN'!D:D, "ĐỘNG_CƠ_VÀ_CẢM_BIẾN"))/G165, 0) | R165: =G165*Q165 | S165: Hàng thương mại
A166: 165 | B166: SW-TRD-165 | C166: THƯƠNG MẠI | D166: Hệ thống ống thông cấp gió tươi, gió bù, box miệng gió Lớp chống cháy EI120 | E166: - | F166: m2 | G166: 109.365 | H166: =SUMIF('01_BOC_TACH_ONG'!B:B, B166, '01_BOC_TACH_ONG'!K:K) | I166: =SUMIF('02_BOC_TACH_CUA'!B:B, B166, '02_BOC_TACH_CUA'!K:K) | J166: =SUMIF('03_BOC_TACH_VAN'!B:B, B166, '03_BOC_TACH_VAN'!K:K) | K166: =SUM(H166:J166) | L166: =(K166-SUMIFS('03_BOC_TACH_VAN'!K:K, '03_BOC_TACH_VAN'!B:B, B166, '03_BOC_TACH_VAN'!D:D, "ĐỘNG_CƠ_VÀ_CẢM_BIẾN"))*0.00 | M166: =(K166-SUMIFS('03_BOC_TACH_VAN'!K:K, '03_BOC_TACH_VAN'!B:B, B166, '03_BOC_TACH_VAN'!D:D, "ĐỘNG_CƠ_VÀ_CẢM_BIẾN"))*0.02 | N166: =K166+L166+M166 | O166: =IF(G166>0, N166/G166, 0) | P166: 0.1 | Q166: =IF(G166>0, ((N166-SUMIFS('03_BOC_TACH_VAN'!K:K, '03_BOC_TACH_VAN'!B:B, B166, '03_BOC_TACH_VAN'!D:D, "ĐỘNG_CƠ_VÀ_CẢM_BIẾN"))*(1+P166)+SUMIFS('03_BOC_TACH_VAN'!K:K, '03_BOC_TACH_VAN'!B:B, B166, '03_BOC_TACH_VAN'!D:D, "ĐỘNG_CƠ_VÀ_CẢM_BIẾN"))/G166, 0) | R166: =G166*Q166 | S166: Hàng thương mại
A167: 166 | B167: SW-TRD-166 | C167: THƯƠNG MẠI | D167: Hệ thống ống thông cấp gió tươi, gió bù, box miệng gió Vật tư phụ, phụ kiện | E167: - | F167: Lô | G167: 1 | H167: =SUMIF('01_BOC_TACH_ONG'!B:B, B167, '01_BOC_TACH_ONG'!K:K) | I167: =SUMIF('02_BOC_TACH_CUA'!B:B, B167, '02_BOC_TACH_CUA'!K:K) | J167: =SUMIF('03_BOC_TACH_VAN'!B:B, B167, '03_BOC_TACH_VAN'!K:K) | K167: =SUM(H167:J167) | L167: =(K167-SUMIFS('03_BOC_TACH_VAN'!K:K, '03_BOC_TACH_VAN'!B:B, B167, '03_BOC_TACH_VAN'!D:D, "ĐỘNG_CƠ_VÀ_CẢM_BIẾN"))*0.00 | M167: =(K167-SUMIFS('03_BOC_TACH_VAN'!K:K, '03_BOC_TACH_VAN'!B:B, B167, '03_BOC_TACH_VAN'!D:D, "ĐỘNG_CƠ_VÀ_CẢM_BIẾN"))*0.02 | N167: =K167+L167+M167 | O167: =IF(G167>0, N167/G167, 0) | P167: 0.1 | Q167: =IF(G167>0, ((N167-SUMIFS('03_BOC_TACH_VAN'!K:K, '03_BOC_TACH_VAN'!B:B, B167, '03_BOC_TACH_VAN'!D:D, "ĐỘNG_CƠ_VÀ_CẢM_BIẾN"))*(1+P167)+SUMIFS('03_BOC_TACH_VAN'!K:K, '03_BOC_TACH_VAN'!B:B, B167, '03_BOC_TACH_VAN'!D:D, "ĐỘNG_CƠ_VÀ_CẢM_BIẾN"))/G167, 0) | R167: =G167*Q167 | S167: Hàng thương mại
A168: 167 | B168: SW-DAMPER-167 | C168: VAN GIÓ | D168: Hệ thống hút gió thải, hút gió bếp Van FD 150x150 (EI60) | E168: 150x150 | F168: Cái | G168: 62 | H168: =SUMIF('01_BOC_TACH_ONG'!B:B, B168, '01_BOC_TACH_ONG'!K:K) | I168: =SUMIF('02_BOC_TACH_CUA'!B:B, B168, '02_BOC_TACH_CUA'!K:K) | J168: =SUMIF('03_BOC_TACH_VAN'!B:B, B168, '03_BOC_TACH_VAN'!K:K) | K168: =SUM(H168:J168) | L168: =(K168-SUMIFS('03_BOC_TACH_VAN'!K:K, '03_BOC_TACH_VAN'!B:B, B168, '03_BOC_TACH_VAN'!D:D, "ĐỘNG_CƠ_VÀ_CẢM_BIẾN"))*0.25 | M168: =(K168-SUMIFS('03_BOC_TACH_VAN'!K:K, '03_BOC_TACH_VAN'!B:B, B168, '03_BOC_TACH_VAN'!D:D, "ĐỘNG_CƠ_VÀ_CẢM_BIẾN"))*0.10 | N168: =K168+L168+M168 | O168: =IF(G168>0, N168/G168, 0) | P168: 0.18 | Q168: =IF(G168>0, ((N168-SUMIFS('03_BOC_TACH_VAN'!K:K, '03_BOC_TACH_VAN'!B:B, B168, '03_BOC_TACH_VAN'!D:D, "ĐỘNG_CƠ_VÀ_CẢM_BIẾN"))*(1+P168)+SUMIFS('03_BOC_TACH_VAN'!K:K, '03_BOC_TACH_VAN'!B:B, B168, '03_BOC_TACH_VAN'!D:D, "ĐỘNG_CƠ_VÀ_CẢM_BIẾN"))/G168, 0) | R168: =G168*Q168
A169: 168 | B169: SW-DAMPER-168 | C169: VAN GIÓ | D169: Hệ thống hút gió thải, hút gió bếp Van FD 400x150 | E169: 400x150 | F169: Cái | G169: 2 | H169: =SUMIF('01_BOC_TACH_ONG'!B:B, B169, '01_BOC_TACH_ONG'!K:K) | I169: =SUMIF('02_BOC_TACH_CUA'!B:B, B169, '02_BOC_TACH_CUA'!K:K) | J169: =SUMIF('03_BOC_TACH_VAN'!B:B, B169, '03_BOC_TACH_VAN'!K:K) | K169: =SUM(H169:J169) | L169: =(K169-SUMIFS('03_BOC_TACH_VAN'!K:K, '03_BOC_TACH_VAN'!B:B, B169, '03_BOC_TACH_VAN'!D:D, "ĐỘNG_CƠ_VÀ_CẢM_BIẾN"))*0.25 | M169: =(K169-SUMIFS('03_BOC_TACH_VAN'!K:K, '03_BOC_TACH_VAN'!B:B, B169, '03_BOC_TACH_VAN'!D:D, "ĐỘNG_CƠ_VÀ_CẢM_BIẾN"))*0.10 | N169: =K169+L169+M169 | O169: =IF(G169>0, N169/G169, 0) | P169: 0.18 | Q169: =IF(G169>0, ((N169-SUMIFS('03_BOC_TACH_VAN'!K:K, '03_BOC_TACH_VAN'!B:B, B169, '03_BOC_TACH_VAN'!D:D, "ĐỘNG_CƠ_VÀ_CẢM_BIẾN"))*(1+P169)+SUMIFS('03_BOC_TACH_VAN'!K:K, '03_BOC_TACH_VAN'!B:B, B169, '03_BOC_TACH_VAN'!D:D, "ĐỘNG_CƠ_VÀ_CẢM_BIẾN"))/G169, 0) | R169: =G169*Q169
A170: 169 | B170: SW-DAMPER-169 | C170: VAN GIÓ | D170: Hệ thống hút gió thải, hút gió bếp Van FD 400x200 | E170: 400x200 | F170: Cái | G170: 2 | H170: =SUMIF('01_BOC_TACH_ONG'!B:B, B170, '01_BOC_TACH_ONG'!K:K) | I170: =SUMIF('02_BOC_TACH_CUA'!B:B, B170, '02_BOC_TACH_CUA'!K:K) | J170: =SUMIF('03_BOC_TACH_VAN'!B:B, B170, '03_BOC_TACH_VAN'!K:K) | K170: =SUM(H170:J170) | L170: =(K170-SUMIFS('03_BOC_TACH_VAN'!K:K, '03_BOC_TACH_VAN'!B:B, B170, '03_BOC_TACH_VAN'!D:D, "ĐỘNG_CƠ_VÀ_CẢM_BIẾN"))*0.25 | M170: =(K170-SUMIFS('03_BOC_TACH_VAN'!K:K, '03_BOC_TACH_VAN'!B:B, B170, '03_BOC_TACH_VAN'!D:D, "ĐỘNG_CƠ_VÀ_CẢM_BIẾN"))*0.10 | N170: =K170+L170+M170 | O170: =IF(G170>0, N170/G170, 0) | P170: 0.18 | Q170: =IF(G170>0, ((N170-SUMIFS('03_BOC_TACH_VAN'!K:K, '03_BOC_TACH_VAN'!B:B, B170, '03_BOC_TACH_VAN'!D:D, "ĐỘNG_CƠ_VÀ_CẢM_BIẾN"))*(1+P170)+SUMIFS('03_BOC_TACH_VAN'!K:K, '03_BOC_TACH_VAN'!B:B, B170, '03_BOC_TACH_VAN'!D:D, "ĐỘNG_CƠ_VÀ_CẢM_BIẾN"))/G170, 0) | R170: =G170*Q170
A171: 170 | B171: SW-DAMPER-170 | C171: VAN GIÓ | D171: Hệ thống hút gió thải, hút gió bếp Van FD 300x150 | E171: 300x150 | F171: Cái | G171: 4 | H171: =SUMIF('01_BOC_TACH_ONG'!B:B, B171, '01_BOC_TACH_ONG'!K:K) | I171: =SUMIF('02_BOC_TACH_CUA'!B:B, B171, '02_BOC_TACH_CUA'!K:K) | J171: =SUMIF('03_BOC_TACH_VAN'!B:B, B171, '03_BOC_TACH_VAN'!K:K) | K171: =SUM(H171:J171) | L171: =(K171-SUMIFS('03_BOC_TACH_VAN'!K:K, '03_BOC_TACH_VAN'!B:B, B171, '03_BOC_TACH_VAN'!D:D, "ĐỘNG_CƠ_VÀ_CẢM_BIẾN"))*0.25 | M171: =(K171-SUMIFS('03_BOC_TACH_VAN'!K:K, '03_BOC_TACH_VAN'!B:B, B171, '03_BOC_TACH_VAN'!D:D, "ĐỘNG_CƠ_VÀ_CẢM_BIẾN"))*0.10 | N171: =K171+L171+M171 | O171: =IF(G171>0, N171/G171, 0) | P171: 0.18 | Q171: =IF(G171>0, ((N171-SUMIFS('03_BOC_TACH_VAN'!K:K, '03_BOC_TACH_VAN'!B:B, B171, '03_BOC_TACH_VAN'!D:D, "ĐỘNG_CƠ_VÀ_CẢM_BIẾN"))*(1+P171)+SUMIFS('03_BOC_TACH_VAN'!K:K, '03_BOC_TACH_VAN'!B:B, B171, '03_BOC_TACH_VAN'!D:D, "ĐỘNG_CƠ_VÀ_CẢM_BIẾN"))/G171, 0) | R171: =G171*Q171
A172: 171 | B172: SW-DAMPER-171 | C172: VAN GIÓ | D172: Hệ thống hút gió thải, hút gió bếp Van FD 300x200 | E172: 300x200 | F172: Cái | G172: 2 | H172: =SUMIF('01_BOC_TACH_ONG'!B:B, B172, '01_BOC_TACH_ONG'!K:K) | I172: =SUMIF('02_BOC_TACH_CUA'!B:B, B172, '02_BOC_TACH_CUA'!K:K) | J172: =SUMIF('03_BOC_TACH_VAN'!B:B, B172, '03_BOC_TACH_VAN'!K:K) | K172: =SUM(H172:J172) | L172: =(K172-SUMIFS('03_BOC_TACH_VAN'!K:K, '03_BOC_TACH_VAN'!B:B, B172, '03_BOC_TACH_VAN'!D:D, "ĐỘNG_CƠ_VÀ_CẢM_BIẾN"))*0.25 | M172: =(K172-SUMIFS('03_BOC_TACH_VAN'!K:K, '03_BOC_TACH_VAN'!B:B, B172, '03_BOC_TACH_VAN'!D:D, "ĐỘNG_CƠ_VÀ_CẢM_BIẾN"))*0.10 | N172: =K172+L172+M172 | O172: =IF(G172>0, N172/G172, 0) | P172: 0.18 | Q172: =IF(G172>0, ((N172-SUMIFS('03_BOC_TACH_VAN'!K:K, '03_BOC_TACH_VAN'!B:B, B172, '03_BOC_TACH_VAN'!D:D, "ĐỘNG_CƠ_VÀ_CẢM_BIẾN"))*(1+P172)+SUMIFS('03_BOC_TACH_VAN'!K:K, '03_BOC_TACH_VAN'!B:B, B172, '03_BOC_TACH_VAN'!D:D, "ĐỘNG_CƠ_VÀ_CẢM_BIẾN"))/G172, 0) | R172: =G172*Q172
A173: 172 | B173: SW-DAMPER-172 | C173: VAN GIÓ | D173: Hệ thống hút gió thải, hút gió bếp Van FD 400x150 | E173: 400x150 | F173: Cái | G173: 1 | H173: =SUMIF('01_BOC_TACH_ONG'!B:B, B173, '01_BOC_TACH_ONG'!K:K) | I173: =SUMIF('02_BOC_TACH_CUA'!B:B, B173, '02_BOC_TACH_CUA'!K:K) | J173: =SUMIF('03_BOC_TACH_VAN'!B:B, B173, '03_BOC_TACH_VAN'!K:K) | K173: =SUM(H173:J173) | L173: =(K173-SUMIFS('03_BOC_TACH_VAN'!K:K, '03_BOC_TACH_VAN'!B:B, B173, '03_BOC_TACH_VAN'!D:D, "ĐỘNG_CƠ_VÀ_CẢM_BIẾN"))*0.25 | M173: =(K173-SUMIFS('03_BOC_TACH_VAN'!K:K, '03_BOC_TACH_VAN'!B:B, B173, '03_BOC_TACH_VAN'!D:D, "ĐỘNG_CƠ_VÀ_CẢM_BIẾN"))*0.10 | N173: =K173+L173+M173 | O173: =IF(G173>0, N173/G173, 0) | P173: 0.18 | Q173: =IF(G173>0, ((N173-SUMIFS('03_BOC_TACH_VAN'!K:K, '03_BOC_TACH_VAN'!B:B, B173, '03_BOC_TACH_VAN'!D:D, "ĐỘNG_CƠ_VÀ_CẢM_BIẾN"))*(1+P173)+SUMIFS('03_BOC_TACH_VAN'!K:K, '03_BOC_TACH_VAN'!B:B, B173, '03_BOC_TACH_VAN'!D:D, "ĐỘNG_CƠ_VÀ_CẢM_BIẾN"))/G173, 0) | R173: =G173*Q173
A174: 173 | B174: SW-DAMPER-173 | C174: VAN GIÓ | D174: Hệ thống hút gió thải, hút gió bếp Van FD 800x250 | E174: 800x250 | F174: Cái | G174: 1 | H174: =SUMIF('01_BOC_TACH_ONG'!B:B, B174, '01_BOC_TACH_ONG'!K:K) | I174: =SUMIF('02_BOC_TACH_CUA'!B:B, B174, '02_BOC_TACH_CUA'!K:K) | J174: =SUMIF('03_BOC_TACH_VAN'!B:B, B174, '03_BOC_TACH_VAN'!K:K) | K174: =SUM(H174:J174) | L174: =(K174-SUMIFS('03_BOC_TACH_VAN'!K:K, '03_BOC_TACH_VAN'!B:B, B174, '03_BOC_TACH_VAN'!D:D, "ĐỘNG_CƠ_VÀ_CẢM_BIẾN"))*0.25 | M174: =(K174-SUMIFS('03_BOC_TACH_VAN'!K:K, '03_BOC_TACH_VAN'!B:B, B174, '03_BOC_TACH_VAN'!D:D, "ĐỘNG_CƠ_VÀ_CẢM_BIẾN"))*0.10 | N174: =K174+L174+M174 | O174: =IF(G174>0, N174/G174, 0) | P174: 0.18 | Q174: =IF(G174>0, ((N174-SUMIFS('03_BOC_TACH_VAN'!K:K, '03_BOC_TACH_VAN'!B:B, B174, '03_BOC_TACH_VAN'!D:D, "ĐỘNG_CƠ_VÀ_CẢM_BIẾN"))*(1+P174)+SUMIFS('03_BOC_TACH_VAN'!K:K, '03_BOC_TACH_VAN'!B:B, B174, '03_BOC_TACH_VAN'!D:D, "ĐỘNG_CƠ_VÀ_CẢM_BIẾN"))/G174, 0) | R174: =G174*Q174
A175: 174 | B175: SW-DAMPER-174 | C175: VAN GIÓ | D175: Hệ thống hút gió thải, hút gió bếp Van FD 1200x350 | E175: 1200x350 | F175: Cái | G175: 1 | H175: =SUMIF('01_BOC_TACH_ONG'!B:B, B175, '01_BOC_TACH_ONG'!K:K) | I175: =SUMIF('02_BOC_TACH_CUA'!B:B, B175, '02_BOC_TACH_CUA'!K:K) | J175: =SUMIF('03_BOC_TACH_VAN'!B:B, B175, '03_BOC_TACH_VAN'!K:K) | K175: =SUM(H175:J175) | L175: =(K175-SUMIFS('03_BOC_TACH_VAN'!K:K, '03_BOC_TACH_VAN'!B:B, B175, '03_BOC_TACH_VAN'!D:D, "ĐỘNG_CƠ_VÀ_CẢM_BIẾN"))*0.25 | M175: =(K175-SUMIFS('03_BOC_TACH_VAN'!K:K, '03_BOC_TACH_VAN'!B:B, B175, '03_BOC_TACH_VAN'!D:D, "ĐỘNG_CƠ_VÀ_CẢM_BIẾN"))*0.10 | N175: =K175+L175+M175 | O175: =IF(G175>0, N175/G175, 0) | P175: 0.18 | Q175: =IF(G175>0, ((N175-SUMIFS('03_BOC_TACH_VAN'!K:K, '03_BOC_TACH_VAN'!B:B, B175, '03_BOC_TACH_VAN'!D:D, "ĐỘNG_CƠ_VÀ_CẢM_BIẾN"))*(1+P175)+SUMIFS('03_BOC_TACH_VAN'!K:K, '03_BOC_TACH_VAN'!B:B, B175, '03_BOC_TACH_VAN'!D:D, "ĐỘNG_CƠ_VÀ_CẢM_BIẾN"))/G175, 0) | R175: =G175*Q175
A176: 175 | B176: SW-DAMPER-175 | C176: VAN GIÓ | D176: Hệ thống hút gió thải, hút gió bếp Van FD 1000x300 | E176: 1000x300 | F176: Cái | G176: 1 | H176: =SUMIF('01_BOC_TACH_ONG'!B:B, B176, '01_BOC_TACH_ONG'!K:K) | I176: =SUMIF('02_BOC_TACH_CUA'!B:B, B176, '02_BOC_TACH_CUA'!K:K) | J176: =SUMIF('03_BOC_TACH_VAN'!B:B, B176, '03_BOC_TACH_VAN'!K:K) | K176: =SUM(H176:J176) | L176: =(K176-SUMIFS('03_BOC_TACH_VAN'!K:K, '03_BOC_TACH_VAN'!B:B, B176, '03_BOC_TACH_VAN'!D:D, "ĐỘNG_CƠ_VÀ_CẢM_BIẾN"))*0.25 | M176: =(K176-SUMIFS('03_BOC_TACH_VAN'!K:K, '03_BOC_TACH_VAN'!B:B, B176, '03_BOC_TACH_VAN'!D:D, "ĐỘNG_CƠ_VÀ_CẢM_BIẾN"))*0.10 | N176: =K176+L176+M176 | O176: =IF(G176>0, N176/G176, 0) | P176: 0.18 | Q176: =IF(G176>0, ((N176-SUMIFS('03_BOC_TACH_VAN'!K:K, '03_BOC_TACH_VAN'!B:B, B176, '03_BOC_TACH_VAN'!D:D, "ĐỘNG_CƠ_VÀ_CẢM_BIẾN"))*(1+P176)+SUMIFS('03_BOC_TACH_VAN'!K:K, '03_BOC_TACH_VAN'!B:B, B176, '03_BOC_TACH_VAN'!D:D, "ĐỘNG_CƠ_VÀ_CẢM_BIẾN"))/G176, 0) | R176: =G176*Q176
A177: 176 | B177: SW-DAMPER-176 | C177: VAN GIÓ | D177: Hệ thống hút gió thải, hút gió bếp Van FD 600x300 | E177: 600x300 | F177: Cái | G177: 1 | H177: =SUMIF('01_BOC_TACH_ONG'!B:B, B177, '01_BOC_TACH_ONG'!K:K) | I177: =SUMIF('02_BOC_TACH_CUA'!B:B, B177, '02_BOC_TACH_CUA'!K:K) | J177: =SUMIF('03_BOC_TACH_VAN'!B:B, B177, '03_BOC_TACH_VAN'!K:K) | K177: =SUM(H177:J177) | L177: =(K177-SUMIFS('03_BOC_TACH_VAN'!K:K, '03_BOC_TACH_VAN'!B:B, B177, '03_BOC_TACH_VAN'!D:D, "ĐỘNG_CƠ_VÀ_CẢM_BIẾN"))*0.25 | M177: =(K177-SUMIFS('03_BOC_TACH_VAN'!K:K, '03_BOC_TACH_VAN'!B:B, B177, '03_BOC_TACH_VAN'!D:D, "ĐỘNG_CƠ_VÀ_CẢM_BIẾN"))*0.10 | N177: =K177+L177+M177 | O177: =IF(G177>0, N177/G177, 0) | P177: 0.18 | Q177: =IF(G177>0, ((N177-SUMIFS('03_BOC_TACH_VAN'!K:K, '03_BOC_TACH_VAN'!B:B, B177, '03_BOC_TACH_VAN'!D:D, "ĐỘNG_CƠ_VÀ_CẢM_BIẾN"))*(1+P177)+SUMIFS('03_BOC_TACH_VAN'!K:K, '03_BOC_TACH_VAN'!B:B, B177, '03_BOC_TACH_VAN'!D:D, "ĐỘNG_CƠ_VÀ_CẢM_BIẾN"))/G177, 0) | R177: =G177*Q177
A178: 177 | B178: SW-DAMPER-177 | C178: VAN GIÓ | D178: Hệ thống hút gió thải, hút gió bếp Van FD 400x200 | E178: 400x200 | F178: cái | G178: 9 | H178: =SUMIF('01_BOC_TACH_ONG'!B:B, B178, '01_BOC_TACH_ONG'!K:K) | I178: =SUMIF('02_BOC_TACH_CUA'!B:B, B178, '02_BOC_TACH_CUA'!K:K) | J178: =SUMIF('03_BOC_TACH_VAN'!B:B, B178, '03_BOC_TACH_VAN'!K:K) | K178: =SUM(H178:J178) | L178: =(K178-SUMIFS('03_BOC_TACH_VAN'!K:K, '03_BOC_TACH_VAN'!B:B, B178, '03_BOC_TACH_VAN'!D:D, "ĐỘNG_CƠ_VÀ_CẢM_BIẾN"))*0.25 | M178: =(K178-SUMIFS('03_BOC_TACH_VAN'!K:K, '03_BOC_TACH_VAN'!B:B, B178, '03_BOC_TACH_VAN'!D:D, "ĐỘNG_CƠ_VÀ_CẢM_BIẾN"))*0.10 | N178: =K178+L178+M178 | O178: =IF(G178>0, N178/G178, 0) | P178: 0.18 | Q178: =IF(G178>0, ((N178-SUMIFS('03_BOC_TACH_VAN'!K:K, '03_BOC_TACH_VAN'!B:B, B178, '03_BOC_TACH_VAN'!D:D, "ĐỘNG_CƠ_VÀ_CẢM_BIẾN"))*(1+P178)+SUMIFS('03_BOC_TACH_VAN'!K:K, '03_BOC_TACH_VAN'!B:B, B178, '03_BOC_TACH_VAN'!D:D, "ĐỘNG_CƠ_VÀ_CẢM_BIẾN"))/G178, 0) | R178: =G178*Q178
A179: 178 | B179: SW-DAMPER-178 | C179: VAN GIÓ | D179: Hệ thống hút gió thải, hút gió bếp Van FD 300x200 | E179: 300x200 | F179: cái | G179: 7 | H179: =SUMIF('01_BOC_TACH_ONG'!B:B, B179, '01_BOC_TACH_ONG'!K:K) | I179: =SUMIF('02_BOC_TACH_CUA'!B:B, B179, '02_BOC_TACH_CUA'!K:K) | J179: =SUMIF('03_BOC_TACH_VAN'!B:B, B179, '03_BOC_TACH_VAN'!K:K) | K179: =SUM(H179:J179) | L179: =(K179-SUMIFS('03_BOC_TACH_VAN'!K:K, '03_BOC_TACH_VAN'!B:B, B179, '03_BOC_TACH_VAN'!D:D, "ĐỘNG_CƠ_VÀ_CẢM_BIẾN"))*0.25 | M179: =(K179-SUMIFS('03_BOC_TACH_VAN'!K:K, '03_BOC_TACH_VAN'!B:B, B179, '03_BOC_TACH_VAN'!D:D, "ĐỘNG_CƠ_VÀ_CẢM_BIẾN"))*0.10 | N179: =K179+L179+M179 | O179: =IF(G179>0, N179/G179, 0) | P179: 0.18 | Q179: =IF(G179>0, ((N179-SUMIFS('03_BOC_TACH_VAN'!K:K, '03_BOC_TACH_VAN'!B:B, B179, '03_BOC_TACH_VAN'!D:D, "ĐỘNG_CƠ_VÀ_CẢM_BIẾN"))*(1+P179)+SUMIFS('03_BOC_TACH_VAN'!K:K, '03_BOC_TACH_VAN'!B:B, B179, '03_BOC_TACH_VAN'!D:D, "ĐỘNG_CƠ_VÀ_CẢM_BIẾN"))/G179, 0) | R179: =G179*Q179
... A216: 215 | B216: SW-DUCT-215 | C216: ỐNG GIÓ | D216: Hệ thống ống thông gió hút gió thải Tole ZAM 0.58mm | E216: 0.58mm | F216: m2 | G216: 134 | H216: =SUMIF('01_BOC_TACH_ONG'!B:B, B216, '01_BOC_TACH_ONG'!K:K) | I216: =SUMIF('02_BOC_TACH_CUA'!B:B, B216, '02_BOC_TACH_CUA'!K:K) | J216: =SUMIF('03_BOC_TACH_VAN'!B:B, B216, '03_BOC_TACH_VAN'!K:K) | K216: =SUM(H216:J216) | L216: =(K216-SUMIFS('03_BOC_TACH_VAN'!K:K, '03_BOC_TACH_VAN'!B:B, B216, '03_BOC_TACH_VAN'!D:D, "ĐỘNG_CƠ_VÀ_CẢM_BIẾN"))*0.25 | M216: =(K216-SUMIFS('03_BOC_TACH_VAN'!K:K, '03_BOC_TACH_VAN'!B:B, B216, '03_BOC_TACH_VAN'!D:D, "ĐỘNG_CƠ_VÀ_CẢM_BIẾN"))*0.10 | N216: =K216+L216+M216 | O216: =IF(G216>0, N216/G216, 0) | P216: 0.18 | Q216: =IF(G216>0, ((N216-SUMIFS('03_BOC_TACH_VAN'!K:K, '03_BOC_TACH_VAN'!B:B, B216, '03_BOC_TACH_VAN'!D:D, "ĐỘNG_CƠ_VÀ_CẢM_BIẾN"))*(1+P216)+SUMIFS('03_BOC_TACH_VAN'!K:K, '03_BOC_TACH_VAN'!B:B, B216, '03_BOC_TACH_VAN'!D:D, "ĐỘNG_CƠ_VÀ_CẢM_BIẾN"))/G216, 0) | R216: =G216*Q216
A217: 216 | B217: SW-FLEX-216 | C217: ỐNG GIÓ MỀM | D217: Hệ thống ống thông gió hút gió thải Ống gió mềm D100 không cách nhiệt | E217: D100 | F217: m | G217: 42.5 | H217: =SUMIF('01_BOC_TACH_ONG'!B:B, B217, '01_BOC_TACH_ONG'!K:K) | I217: =SUMIF('02_BOC_TACH_CUA'!B:B, B217, '02_BOC_TACH_CUA'!K:K) | J217: =SUMIF('03_BOC_TACH_VAN'!B:B, B217, '03_BOC_TACH_VAN'!K:K) | K217: =SUM(H217:J217) | L217: =(K217-SUMIFS('03_BOC_TACH_VAN'!K:K, '03_BOC_TACH_VAN'!B:B, B217, '03_BOC_TACH_VAN'!D:D, "ĐỘNG_CƠ_VÀ_CẢM_BIẾN"))*0.00 | M217: =(K217-SUMIFS('03_BOC_TACH_VAN'!K:K, '03_BOC_TACH_VAN'!B:B, B217, '03_BOC_TACH_VAN'!D:D, "ĐỘNG_CƠ_VÀ_CẢM_BIẾN"))*0.02 | N217: =K217+L217+M217 | O217: =IF(G217>0, N217/G217, 0) | P217: 0.1 | Q217: =IF(G217>0, ((N217-SUMIFS('03_BOC_TACH_VAN'!K:K, '03_BOC_TACH_VAN'!B:B, B217, '03_BOC_TACH_VAN'!D:D, "ĐỘNG_CƠ_VÀ_CẢM_BIẾN"))*(1+P217)+SUMIFS('03_BOC_TACH_VAN'!K:K, '03_BOC_TACH_VAN'!B:B, B217, '03_BOC_TACH_VAN'!D:D, "ĐỘNG_CƠ_VÀ_CẢM_BIẾN"))/G217, 0) | R217: =G217*Q217 | S217: Ống mềm
A218: 217 | B218: SW-FLEX-217 | C218: ỐNG GIÓ MỀM | D218: Hệ thống ống thông gió hút gió thải Ống gió mềm D150 không cách nhiệt | E218: D150 | F218: m | G218: 150 | H218: =SUMIF('01_BOC_TACH_ONG'!B:B, B218, '01_BOC_TACH_ONG'!K:K) | I218: =SUMIF('02_BOC_TACH_CUA'!B:B, B218, '02_BOC_TACH_CUA'!K:K) | J218: =SUMIF('03_BOC_TACH_VAN'!B:B, B218, '03_BOC_TACH_VAN'!K:K) | K218: =SUM(H218:J218) | L218: =(K218-SUMIFS('03_BOC_TACH_VAN'!K:K, '03_BOC_TACH_VAN'!B:B, B218, '03_BOC_TACH_VAN'!D:D, "ĐỘNG_CƠ_VÀ_CẢM_BIẾN"))*0.00 | M218: =(K218-SUMIFS('03_BOC_TACH_VAN'!K:K, '03_BOC_TACH_VAN'!B:B, B218, '03_BOC_TACH_VAN'!D:D, "ĐỘNG_CƠ_VÀ_CẢM_BIẾN"))*0.02 | N218: =K218+L218+M218 | O218: =IF(G218>0, N218/G218, 0) | P218: 0.1 | Q218: =IF(G218>0, ((N218-SUMIFS('03_BOC_TACH_VAN'!K:K, '03_BOC_TACH_VAN'!B:B, B218, '03_BOC_TACH_VAN'!D:D, "ĐỘNG_CƠ_VÀ_CẢM_BIẾN"))*(1+P218)+SUMIFS('03_BOC_TACH_VAN'!K:K, '03_BOC_TACH_VAN'!B:B, B218, '03_BOC_TACH_VAN'!D:D, "ĐỘNG_CƠ_VÀ_CẢM_BIẾN"))/G218, 0) | R218: =G218*Q218 | S218: Ống mềm
A219: 218 | B219: SW-TRD-218 | C219: THƯƠNG MẠI | D219: Hệ thống ống thông gió hút gió thải Vật tư phụ, phụ kiện | E219: - | F219: Lô | G219: 1 | H219: =SUMIF('01_BOC_TACH_ONG'!B:B, B219, '01_BOC_TACH_ONG'!K:K) | I219: =SUMIF('02_BOC_TACH_CUA'!B:B, B219, '02_BOC_TACH_CUA'!K:K) | J219: =SUMIF('03_BOC_TACH_VAN'!B:B, B219, '03_BOC_TACH_VAN'!K:K) | K219: =SUM(H219:J219) | L219: =(K219-SUMIFS('03_BOC_TACH_VAN'!K:K, '03_BOC_TACH_VAN'!B:B, B219, '03_BOC_TACH_VAN'!D:D, "ĐỘNG_CƠ_VÀ_CẢM_BIẾN"))*0.00 | M219: =(K219-SUMIFS('03_BOC_TACH_VAN'!K:K, '03_BOC_TACH_VAN'!B:B, B219, '03_BOC_TACH_VAN'!D:D, "ĐỘNG_CƠ_VÀ_CẢM_BIẾN"))*0.02 | N219: =K219+L219+M219 | O219: =IF(G219>0, N219/G219, 0) | P219: 0.1 | Q219: =IF(G219>0, ((N219-SUMIFS('03_BOC_TACH_VAN'!K:K, '03_BOC_TACH_VAN'!B:B, B219, '03_BOC_TACH_VAN'!D:D, "ĐỘNG_CƠ_VÀ_CẢM_BIẾN"))*(1+P219)+SUMIFS('03_BOC_TACH_VAN'!K:K, '03_BOC_TACH_VAN'!B:B, B219, '03_BOC_TACH_VAN'!D:D, "ĐỘNG_CƠ_VÀ_CẢM_BIẾN"))/G219, 0) | R219: =G219*Q219 | S219: Hàng thương mại
A220: 219 | B220: SW-DUCT-219 | C220: ỐNG GIÓ | D220: Hệ thống ống thông gió hút bếp Tole 0.58mm phủ lớp mạ kẽm Z180 | E220: 0.58mm | F220: m2 | G220: 1630.01 | H220: =SUMIF('01_BOC_TACH_ONG'!B:B, B220, '01_BOC_TACH_ONG'!K:K) | I220: =SUMIF('02_BOC_TACH_CUA'!B:B, B220, '02_BOC_TACH_CUA'!K:K) | J220: =SUMIF('03_BOC_TACH_VAN'!B:B, B220, '03_BOC_TACH_VAN'!K:K) | K220: =SUM(H220:J220) | L220: =(K220-SUMIFS('03_BOC_TACH_VAN'!K:K, '03_BOC_TACH_VAN'!B:B, B220, '03_BOC_TACH_VAN'!D:D, "ĐỘNG_CƠ_VÀ_CẢM_BIẾN"))*0.25 | M220: =(K220-SUMIFS('03_BOC_TACH_VAN'!K:K, '03_BOC_TACH_VAN'!B:B, B220, '03_BOC_TACH_VAN'!D:D, "ĐỘNG_CƠ_VÀ_CẢM_BIẾN"))*0.10 | N220: =K220+L220+M220 | O220: =IF(G220>0, N220/G220, 0) | P220: 0.18 | Q220: =IF(G220>0, ((N220-SUMIFS('03_BOC_TACH_VAN'!K:K, '03_BOC_TACH_VAN'!B:B, B220, '03_BOC_TACH_VAN'!D:D, "ĐỘNG_CƠ_VÀ_CẢM_BIẾN"))*(1+P220)+SUMIFS('03_BOC_TACH_VAN'!K:K, '03_BOC_TACH_VAN'!B:B, B220, '03_BOC_TACH_VAN'!D:D, "ĐỘNG_CƠ_VÀ_CẢM_BIẾN"))/G220, 0) | R220: =G220*Q220
A221: 220 | B221: SW-DUCT-220 | C221: ỐNG GIÓ | D221: Hệ thống ống thông gió hút bếp Tole 0.75mm phủ lớp mạ kẽm Z180 | E221: 0.75mm | F221: m2 | G221: 153.35 | H221: =SUMIF('01_BOC_TACH_ONG'!B:B, B221, '01_BOC_TACH_ONG'!K:K) | I221: =SUMIF('02_BOC_TACH_CUA'!B:B, B221, '02_BOC_TACH_CUA'!K:K) | J221: =SUMIF('03_BOC_TACH_VAN'!B:B, B221, '03_BOC_TACH_VAN'!K:K) | K221: =SUM(H221:J221) | L221: =(K221-SUMIFS('03_BOC_TACH_VAN'!K:K, '03_BOC_TACH_VAN'!B:B, B221, '03_BOC_TACH_VAN'!D:D, "ĐỘNG_CƠ_VÀ_CẢM_BIẾN"))*0.25 | M221: =(K221-SUMIFS('03_BOC_TACH_VAN'!K:K, '03_BOC_TACH_VAN'!B:B, B221, '03_BOC_TACH_VAN'!D:D, "ĐỘNG_CƠ_VÀ_CẢM_BIẾN"))*0.10 | N221: =K221+L221+M221 | O221: =IF(G221>0, N221/G221, 0) | P221: 0.18 | Q221: =IF(G221>0, ((N221-SUMIFS('03_BOC_TACH_VAN'!K:K, '03_BOC_TACH_VAN'!B:B, B221, '03_BOC_TACH_VAN'!D:D, "ĐỘNG_CƠ_VÀ_CẢM_BIẾN"))*(1+P221)+SUMIFS('03_BOC_TACH_VAN'!K:K, '03_BOC_TACH_VAN'!B:B, B221, '03_BOC_TACH_VAN'!D:D, "ĐỘNG_CƠ_VÀ_CẢM_BIẾN"))/G221, 0) | R221: =G221*Q221
A222: 221 | B222: SW-DUCT-221 | C222: ỐNG GIÓ | D222: Hệ thống ống thông gió hút bếp Tole 0.95mm phủ lớp mạ kẽm Z180 | E222: 0.95mm | F222: m2 | G222: 200 | H222: =SUMIF('01_BOC_TACH_ONG'!B:B, B222, '01_BOC_TACH_ONG'!K:K) | I222: =SUMIF('02_BOC_TACH_CUA'!B:B, B222, '02_BOC_TACH_CUA'!K:K) | J222: =SUMIF('03_BOC_TACH_VAN'!B:B, B222, '03_BOC_TACH_VAN'!K:K) | K222: =SUM(H222:J222) | L222: =(K222-SUMIFS('03_BOC_TACH_VAN'!K:K, '03_BOC_TACH_VAN'!B:B, B222, '03_BOC_TACH_VAN'!D:D, "ĐỘNG_CƠ_VÀ_CẢM_BIẾN"))*0.25 | M222: =(K222-SUMIFS('03_BOC_TACH_VAN'!K:K, '03_BOC_TACH_VAN'!B:B, B222, '03_BOC_TACH_VAN'!D:D, "ĐỘNG_CƠ_VÀ_CẢM_BIẾN"))*0.10 | N222: =K222+L222+M222 | O222: =IF(G222>0, N222/G222, 0) | P222: 0.18 | Q222: =IF(G222>0, ((N222-SUMIFS('03_BOC_TACH_VAN'!K:K, '03_BOC_TACH_VAN'!B:B, B222, '03_BOC_TACH_VAN'!D:D, "ĐỘNG_CƠ_VÀ_CẢM_BIẾN"))*(1+P222)+SUMIFS('03_BOC_TACH_VAN'!K:K, '03_BOC_TACH_VAN'!B:B, B222, '03_BOC_TACH_VAN'!D:D, "ĐỘNG_CƠ_VÀ_CẢM_BIẾN"))/G222, 0) | R222: =G222*Q222
A223: 222 | B223: SW-DUCT-222 | C223: ỐNG GIÓ | D223: Hệ thống ống thông gió hút bếp Tole ZAM 0.75mm | E223: 0.75mm | F223: m2 | G223: 133 | H223: =SUMIF('01_BOC_TACH_ONG'!B:B, B223, '01_BOC_TACH_ONG'!K:K) | I223: =SUMIF('02_BOC_TACH_CUA'!B:B, B223, '02_BOC_TACH_CUA'!K:K) | J223: =SUMIF('03_BOC_TACH_VAN'!B:B, B223, '03_BOC_TACH_VAN'!K:K) | K223: =SUM(H223:J223) | L223: =(K223-SUMIFS('03_BOC_TACH_VAN'!K:K, '03_BOC_TACH_VAN'!B:B, B223, '03_BOC_TACH_VAN'!D:D, "ĐỘNG_CƠ_VÀ_CẢM_BIẾN"))*0.25 | M223: =(K223-SUMIFS('03_BOC_TACH_VAN'!K:K, '03_BOC_TACH_VAN'!B:B, B223, '03_BOC_TACH_VAN'!D:D, "ĐỘNG_CƠ_VÀ_CẢM_BIẾN"))*0.10 | N223: =K223+L223+M223 | O223: =IF(G223>0, N223/G223, 0) | P223: 0.18 | Q223: =IF(G223>0, ((N223-SUMIFS('03_BOC_TACH_VAN'!K:K, '03_BOC_TACH_VAN'!B:B, B223, '03_BOC_TACH_VAN'!D:D, "ĐỘNG_CƠ_VÀ_CẢM_BIẾN"))*(1+P223)+SUMIFS('03_BOC_TACH_VAN'!K:K, '03_BOC_TACH_VAN'!B:B, B223, '03_BOC_TACH_VAN'!D:D, "ĐỘNG_CƠ_VÀ_CẢM_BIẾN"))/G223, 0) | R223: =G223*Q223
A224: 223 | B224: SW-TRD-223 | C224: THƯƠNG MẠI | D224: Hệ thống ống thông gió hút bếp Vật tư phụ, phụ kiện | E224: - | F224: Lô | G224: 1 | H224: =SUMIF('01_BOC_TACH_ONG'!B:B, B224, '01_BOC_TACH_ONG'!K:K) | I224: =SUMIF('02_BOC_TACH_CUA'!B:B, B224, '02_BOC_TACH_CUA'!K:K) | J224: =SUMIF('03_BOC_TACH_VAN'!B:B, B224, '03_BOC_TACH_VAN'!K:K) | K224: =SUM(H224:J224) | L224: =(K224-SUMIFS('03_BOC_TACH_VAN'!K:K, '03_BOC_TACH_VAN'!B:B, B224, '03_BOC_TACH_VAN'!D:D, "ĐỘNG_CƠ_VÀ_CẢM_BIẾN"))*0.00 | M224: =(K224-SUMIFS('03_BOC_TACH_VAN'!K:K, '03_BOC_TACH_VAN'!B:B, B224, '03_BOC_TACH_VAN'!D:D, "ĐỘNG_CƠ_VÀ_CẢM_BIẾN"))*0.02 | N224: =K224+L224+M224 | O224: =IF(G224>0, N224/G224, 0) | P224: 0.1 | Q224: =IF(G224>0, ((N224-SUMIFS('03_BOC_TACH_VAN'!K:K, '03_BOC_TACH_VAN'!B:B, B224, '03_BOC_TACH_VAN'!D:D, "ĐỘNG_CƠ_VÀ_CẢM_BIẾN"))*(1+P224)+SUMIFS('03_BOC_TACH_VAN'!K:K, '03_BOC_TACH_VAN'!B:B, B224, '03_BOC_TACH_VAN'!D:D, "ĐỘNG_CƠ_VÀ_CẢM_BIẾN"))/G224, 0) | R224: =G224*Q224 | S224: Hàng thương mại
A225: 224 | B225: SW-ACST-224 | C225: VÁCH NGĂN / HỘP TIÊU ÂM | D225: MIỆNG GIÓ Box gió cấp và box gió hồi máy lạnh kèm tiêu âm dày 25mm 14kW | E225: - | F225: Bộ | G225: 21 | H225: =SUMIF('01_BOC_TACH_ONG'!B:B, B225, '01_BOC_TACH_ONG'!K:K) | I225: =SUMIF('02_BOC_TACH_CUA'!B:B, B225, '02_BOC_TACH_CUA'!K:K) | J225: =SUMIF('03_BOC_TACH_VAN'!B:B, B225, '03_BOC_TACH_VAN'!K:K) | K225: =SUM(H225:J225) | L225: =(K225-SUMIFS('03_BOC_TACH_VAN'!K:K, '03_BOC_TACH_VAN'!B:B, B225, '03_BOC_TACH_VAN'!D:D, "ĐỘNG_CƠ_VÀ_CẢM_BIẾN"))*0.25 | M225: =(K225-SUMIFS('03_BOC_TACH_VAN'!K:K, '03_BOC_TACH_VAN'!B:B, B225, '03_BOC_TACH_VAN'!D:D, "ĐỘNG_CƠ_VÀ_CẢM_BIẾN"))*0.10 | N225: =K225+L225+M225 | O225: =IF(G225>0, N225/G225, 0) | P225: 0.18 | Q225: =IF(G225>0, ((N225-SUMIFS('03_BOC_TACH_VAN'!K:K, '03_BOC_TACH_VAN'!B:B, B225, '03_BOC_TACH_VAN'!D:D, "ĐỘNG_CƠ_VÀ_CẢM_BIẾN"))*(1+P225)+SUMIFS('03_BOC_TACH_VAN'!K:K, '03_BOC_TACH_VAN'!B:B, B225, '03_BOC_TACH_VAN'!D:D, "ĐỘNG_CƠ_VÀ_CẢM_BIẾN"))/G225, 0) | R225: =G225*Q225
A226: 225 | B226: SW-ACST-225 | C226: VÁCH NGĂN / HỘP TIÊU ÂM | D226: MIỆNG GIÓ Box gió cấp và box gió hồi máy lạnh kèm tiêu âm dày 25mm 11.2kW | E226: - | F226: Bộ | G226: 40 | H226: =SUMIF('01_BOC_TACH_ONG'!B:B, B226, '01_BOC_TACH_ONG'!K:K) | I226: =SUMIF('02_BOC_TACH_CUA'!B:B, B226, '02_BOC_TACH_CUA'!K:K) | J226: =SUMIF('03_BOC_TACH_VAN'!B:B, B226, '03_BOC_TACH_VAN'!K:K) | K226: =SUM(H226:J226) | L226: =(K226-SUMIFS('03_BOC_TACH_VAN'!K:K, '03_BOC_TACH_VAN'!B:B, B226, '03_BOC_TACH_VAN'!D:D, "ĐỘNG_CƠ_VÀ_CẢM_BIẾN"))*0.25 | M226: =(K226-SUMIFS('03_BOC_TACH_VAN'!K:K, '03_BOC_TACH_VAN'!B:B, B226, '03_BOC_TACH_VAN'!D:D, "ĐỘNG_CƠ_VÀ_CẢM_BIẾN"))*0.10 | N226: =K226+L226+M226 | O226: =IF(G226>0, N226/G226, 0) | P226: 0.18 | Q226: =IF(G226>0, ((N226-SUMIFS('03_BOC_TACH_VAN'!K:K, '03_BOC_TACH_VAN'!B:B, B226, '03_BOC_TACH_VAN'!D:D, "ĐỘNG_CƠ_VÀ_CẢM_BIẾN"))*(1+P226)+SUMIFS('03_BOC_TACH_VAN'!K:K, '03_BOC_TACH_VAN'!B:B, B226, '03_BOC_TACH_VAN'!D:D, "ĐỘNG_CƠ_VÀ_CẢM_BIẾN"))/G226, 0) | R226: =G226*Q226
A227: 226 | B227: SW-ACST-226 | C227: VÁCH NGĂN / HỘP TIÊU ÂM | D227: MIỆNG GIÓ Box gió cấp và box gió hồi máy lạnh kèm tiêu âm dày 25mm 9.0kW | E227: - | F227: Bộ | G227: 12 | H227: =SUMIF('01_BOC_TACH_ONG'!B:B, B227, '01_BOC_TACH_ONG'!K:K) | I227: =SUMIF('02_BOC_TACH_CUA'!B:B, B227, '02_BOC_TACH_CUA'!K:K) | J227: =SUMIF('03_BOC_TACH_VAN'!B:B, B227, '03_BOC_TACH_VAN'!K:K) | K227: =SUM(H227:J227) | L227: =(K227-SUMIFS('03_BOC_TACH_VAN'!K:K, '03_BOC_TACH_VAN'!B:B, B227, '03_BOC_TACH_VAN'!D:D, "ĐỘNG_CƠ_VÀ_CẢM_BIẾN"))*0.25 | M227: =(K227-SUMIFS('03_BOC_TACH_VAN'!K:K, '03_BOC_TACH_VAN'!B:B, B227, '03_BOC_TACH_VAN'!D:D, "ĐỘNG_CƠ_VÀ_CẢM_BIẾN"))*0.10 | N227: =K227+L227+M227 | O227: =IF(G227>0, N227/G227, 0) | P227: 0.18 | Q227: =IF(G227>0, ((N227-SUMIFS('03_BOC_TACH_VAN'!K:K, '03_BOC_TACH_VAN'!B:B, B227, '03_BOC_TACH_VAN'!D:D, "ĐỘNG_CƠ_VÀ_CẢM_BIẾN"))*(1+P227)+SUMIFS('03_BOC_TACH_VAN'!K:K, '03_BOC_TACH_VAN'!B:B, B227, '03_BOC_TACH_VAN'!D:D, "ĐỘNG_CƠ_VÀ_CẢM_BIẾN"))/G227, 0) | R227: =G227*Q227
A228: 227 | B228: SW-ACST-227 | C228: VÁCH NGĂN / HỘP TIÊU ÂM | D228: MIỆNG GIÓ Box gió cấp và box gió hồi máy lạnh kèm tiêu âm dày 25mm 7.1kW | E228: - | F228: Bộ | G228: 12 | H228: =SUMIF('01_BOC_TACH_ONG'!B:B, B228, '01_BOC_TACH_ONG'!K:K) | I228: =SUMIF('02_BOC_TACH_CUA'!B:B, B228, '02_BOC_TACH_CUA'!K:K) | J228: =SUMIF('03_BOC_TACH_VAN'!B:B, B228, '03_BOC_TACH_VAN'!K:K) | K228: =SUM(H228:J228) | L228: =(K228-SUMIFS('03_BOC_TACH_VAN'!K:K, '03_BOC_TACH_VAN'!B:B, B228, '03_BOC_TACH_VAN'!D:D, "ĐỘNG_CƠ_VÀ_CẢM_BIẾN"))*0.25 | M228: =(K228-SUMIFS('03_BOC_TACH_VAN'!K:K, '03_BOC_TACH_VAN'!B:B, B228, '03_BOC_TACH_VAN'!D:D, "ĐỘNG_CƠ_VÀ_CẢM_BIẾN"))*0.10 | N228: =K228+L228+M228 | O228: =IF(G228>0, N228/G228, 0) | P228: 0.18 | Q228: =IF(G228>0, ((N228-SUMIFS('03_BOC_TACH_VAN'!K:K, '03_BOC_TACH_VAN'!B:B, B228, '03_BOC_TACH_VAN'!D:D, "ĐỘNG_CƠ_VÀ_CẢM_BIẾN"))*(1+P228)+SUMIFS('03_BOC_TACH_VAN'!K:K, '03_BOC_TACH_VAN'!B:B, B228, '03_BOC_TACH_VAN'!D:D, "ĐỘNG_CƠ_VÀ_CẢM_BIẾN"))/G228, 0) | R228: =G228*Q228
A229: 228 | B229: SW-ACST-228 | C229: VÁCH NGĂN / HỘP TIÊU ÂM | D229: MIỆNG GIÓ Box gió cấp và box gió hồi máy lạnh kèm tiêu âm dày 25mm 5.6 kW | E229: - | F229: Bộ | G229: 14 | H229: =SUMIF('01_BOC_TACH_ONG'!B:B, B229, '01_BOC_TACH_ONG'!K:K) | I229: =SUMIF('02_BOC_TACH_CUA'!B:B, B229, '02_BOC_TACH_CUA'!K:K) | J229: =SUMIF('03_BOC_TACH_VAN'!B:B, B229, '03_BOC_TACH_VAN'!K:K) | K229: =SUM(H229:J229) | L229: =(K229-SUMIFS('03_BOC_TACH_VAN'!K:K, '03_BOC_TACH_VAN'!B:B, B229, '03_BOC_TACH_VAN'!D:D, "ĐỘNG_CƠ_VÀ_CẢM_BIẾN"))*0.25 | M229: =(K229-SUMIFS('03_BOC_TACH_VAN'!K:K, '03_BOC_TACH_VAN'!B:B, B229, '03_BOC_TACH_VAN'!D:D, "ĐỘNG_CƠ_VÀ_CẢM_BIẾN"))*0.10 | N229: =K229+L229+M229 | O229: =IF(G229>0, N229/G229, 0) | P229: 0.18 | Q229: =IF(G229>0, ((N229-SUMIFS('03_BOC_TACH_VAN'!K:K, '03_BOC_TACH_VAN'!B:B, B229, '03_BOC_TACH_VAN'!D:D, "ĐỘNG_CƠ_VÀ_CẢM_BIẾN"))*(1+P229)+SUMIFS('03_BOC_TACH_VAN'!K:K, '03_BOC_TACH_VAN'!B:B, B229, '03_BOC_TACH_VAN'!D:D, "ĐỘNG_CƠ_VÀ_CẢM_BIẾN"))/G229, 0) | R229: =G229*Q229
A230: 229 | B230: SW-ACST-229 | C230: VÁCH NGĂN / HỘP TIÊU ÂM | D230: MIỆNG GIÓ Box gió cấp và box gió hồi máy lạnh kèm tiêu âm dày 25mm 4.5kW | E230: - | F230: Bộ | G230: 10 | H230: =SUMIF('01_BOC_TACH_ONG'!B:B, B230, '01_BOC_TACH_ONG'!K:K) | I230: =SUMIF('02_BOC_TACH_CUA'!B:B, B230, '02_BOC_TACH_CUA'!K:K) | J230: =SUMIF('03_BOC_TACH_VAN'!B:B, B230, '03_BOC_TACH_VAN'!K:K) | K230: =SUM(H230:J230) | L230: =(K230-SUMIFS('03_BOC_TACH_VAN'!K:K, '03_BOC_TACH_VAN'!B:B, B230, '03_BOC_TACH_VAN'!D:D, "ĐỘNG_CƠ_VÀ_CẢM_BIẾN"))*0.25 | M230: =(K230-SUMIFS('03_BOC_TACH_VAN'!K:K, '03_BOC_TACH_VAN'!B:B, B230, '03_BOC_TACH_VAN'!D:D, "ĐỘNG_CƠ_VÀ_CẢM_BIẾN"))*0.10 | N230: =K230+L230+M230 | O230: =IF(G230>0, N230/G230, 0) | P230: 0.18 | Q230: =IF(G230>0, ((N230-SUMIFS('03_BOC_TACH_VAN'!K:K, '03_BOC_TACH_VAN'!B:B, B230, '03_BOC_TACH_VAN'!D:D, "ĐỘNG_CƠ_VÀ_CẢM_BIẾN"))*(1+P230)+SUMIFS('03_BOC_TACH_VAN'!K:K, '03_BOC_TACH_VAN'!B:B, B230, '03_BOC_TACH_VAN'!D:D, "ĐỘNG_CƠ_VÀ_CẢM_BIẾN"))/G230, 0) | R230: =G230*Q230
A231: 230 | B231: SW-DIFF-230 | C231: CỬA GIÓ | D231: Miệng gió cấp SAG600x600 kèm OBD box miệng gió | E231: 600x600 | F231: Cái | G231: 309 | H231: =SUMIF('01_BOC_TACH_ONG'!B:B, B231, '01_BOC_TACH_ONG'!K:K) | I231: =SUMIF('02_BOC_TACH_CUA'!B:B, B231, '02_BOC_TACH_CUA'!K:K) | J231: =SUMIF('03_BOC_TACH_VAN'!B:B, B231, '03_BOC_TACH_VAN'!K:K) | K231: =SUM(H231:J231) | L231: =(K231-SUMIFS('03_BOC_TACH_VAN'!K:K, '03_BOC_TACH_VAN'!B:B, B231, '03_BOC_TACH_VAN'!D:D, "ĐỘNG_CƠ_VÀ_CẢM_BIẾN"))*0.25 | M231: =(K231-SUMIFS('03_BOC_TACH_VAN'!K:K, '03_BOC_TACH_VAN'!B:B, B231, '03_BOC_TACH_VAN'!D:D, "ĐỘNG_CƠ_VÀ_CẢM_BIẾN"))*0.10 | N231: =K231+L231+M231 | O231: =IF(G231>0, N231/G231, 0) | P231: 0.18 | Q231: =IF(G231>0, ((N231-SUMIFS('03_BOC_TACH_VAN'!K:K, '03_BOC_TACH_VAN'!B:B, B231, '03_BOC_TACH_VAN'!D:D, "ĐỘNG_CƠ_VÀ_CẢM_BIẾN"))*(1+P231)+SUMIFS('03_BOC_TACH_VAN'!K:K, '03_BOC_TACH_VAN'!B:B, B231, '03_BOC_TACH_VAN'!D:D, "ĐỘNG_CƠ_VÀ_CẢM_BIẾN"))/G231, 0) | R231: =G231*Q231
A232: 231 | B232: SW-DIFF-231 | C232: CỬA GIÓ | D232: Miệng gió hồi RAG600x600 kèm OBD box miệng gió | E232: 600x600 | F232: Cái | G232: 195 | H232: =SUMIF('01_BOC_TACH_ONG'!B:B, B232, '01_BOC_TACH_ONG'!K:K) | I232: =SUMIF('02_BOC_TACH_CUA'!B:B, B232, '02_BOC_TACH_CUA'!K:K) | J232: =SUMIF('03_BOC_TACH_VAN'!B:B, B232, '03_BOC_TACH_VAN'!K:K) | K232: =SUM(H232:J232) | L232: =(K232-SUMIFS('03_BOC_TACH_VAN'!K:K, '03_BOC_TACH_VAN'!B:B, B232, '03_BOC_TACH_VAN'!D:D, "ĐỘNG_CƠ_VÀ_CẢM_BIẾN"))*0.25 | M232: =(K232-SUMIFS('03_BOC_TACH_VAN'!K:K, '03_BOC_TACH_VAN'!B:B, B232, '03_BOC_TACH_VAN'!D:D, "ĐỘNG_CƠ_VÀ_CẢM_BIẾN"))*0.10 | N232: =K232+L232+M232 | O232: =IF(G232>0, N232/G232, 0) | P232: 0.18 | Q232: =IF(G232>0, ((N232-SUMIFS('03_BOC_TACH_VAN'!K:K, '03_BOC_TACH_VAN'!B:B, B232, '03_BOC_TACH_VAN'!D:D, "ĐỘNG_CƠ_VÀ_CẢM_BIẾN"))*(1+P232)+SUMIFS('03_BOC_TACH_VAN'!K:K, '03_BOC_TACH_VAN'!B:B, B232, '03_BOC_TACH_VAN'!D:D, "ĐỘNG_CƠ_VÀ_CẢM_BIẾN"))/G232, 0) | R232: =G232*Q232
A233: 232 | B233: SW-TRD-232 | C233: THƯƠNG MẠI | D233: MIỆNG GIÓ Vật tư phụ, phụ kiện | E233: - | F233: Lô | G233: 1 | H233: =SUMIF('01_BOC_TACH_ONG'!B:B, B233, '01_BOC_TACH_ONG'!K:K) | I233: =SUMIF('02_BOC_TACH_CUA'!B:B, B233, '02_BOC_TACH_CUA'!K:K) | J233: =SUMIF('03_BOC_TACH_VAN'!B:B, B233, '03_BOC_TACH_VAN'!K:K) | K233: =SUM(H233:J233) | L233: =(K233-SUMIFS('03_BOC_TACH_VAN'!K:K, '03_BOC_TACH_VAN'!B:B, B233, '03_BOC_TACH_VAN'!D:D, "ĐỘNG_CƠ_VÀ_CẢM_BIẾN"))*0.00 | M233: =(K233-SUMIFS('03_BOC_TACH_VAN'!K:K, '03_BOC_TACH_VAN'!B:B, B233, '03_BOC_TACH_VAN'!D:D, "ĐỘNG_CƠ_VÀ_CẢM_BIẾN"))*0.02 | N233: =K233+L233+M233 | O233: =IF(G233>0, N233/G233, 0) | P233: 0.1 | Q233: =IF(G233>0, ((N233-SUMIFS('03_BOC_TACH_VAN'!K:K, '03_BOC_TACH_VAN'!B:B, B233, '03_BOC_TACH_VAN'!D:D, "ĐỘNG_CƠ_VÀ_CẢM_BIẾN"))*(1+P233)+SUMIFS('03_BOC_TACH_VAN'!K:K, '03_BOC_TACH_VAN'!B:B, B233, '03_BOC_TACH_VAN'!D:D, "ĐỘNG_CƠ_VÀ_CẢM_BIẾN"))/G233, 0) | R233: =G233*Q233 | S233: Hàng thương mại
A234: 233 | B234: SW-DUCT-233 | C234: ỐNG GIÓ | D234: ỐNG GIÓ LẠNH Tole 0.58mm phủ lớp mạ kẽm Z180 | E234: 0.58mm | F234: m2 | G234: 767.5 | H234: =SUMIF('01_BOC_TACH_ONG'!B:B, B234, '01_BOC_TACH_ONG'!K:K) | I234: =SUMIF('02_BOC_TACH_CUA'!B:B, B234, '02_BOC_TACH_CUA'!K:K) | J234: =SUMIF('03_BOC_TACH_VAN'!B:B, B234, '03_BOC_TACH_VAN'!K:K) | K234: =SUM(H234:J234) | L234: =(K234-SUMIFS('03_BOC_TACH_VAN'!K:K, '03_BOC_TACH_VAN'!B:B, B234, '03_BOC_TACH_VAN'!D:D, "ĐỘNG_CƠ_VÀ_CẢM_BIẾN"))*0.25 | M234: =(K234-SUMIFS('03_BOC_TACH_VAN'!K:K, '03_BOC_TACH_VAN'!B:B, B234, '03_BOC_TACH_VAN'!D:D, "ĐỘNG_CƠ_VÀ_CẢM_BIẾN"))*0.10 | N234: =K234+L234+M234 | O234: =IF(G234>0, N234/G234, 0) | P234: 0.18 | Q234: =IF(G234>0, ((N234-SUMIFS('03_BOC_TACH_VAN'!K:K, '03_BOC_TACH_VAN'!B:B, B234, '03_BOC_TACH_VAN'!D:D, "ĐỘNG_CƠ_VÀ_CẢM_BIẾN"))*(1+P234)+SUMIFS('03_BOC_TACH_VAN'!K:K, '03_BOC_TACH_VAN'!B:B, B234, '03_BOC_TACH_VAN'!D:D, "ĐỘNG_CƠ_VÀ_CẢM_BIẾN"))/G234, 0) | R234: =G234*Q234
